Workbook
Name List_海派: 价格快速查询!$V$14:$X$14
Name 仓库列表: 价格快速查询!$S$15:$S$74
Name 海派选项: 价格快速查询!#REF!
Name 海运选项: 价格快速查询!$V$17:$W$17
Name 空派选项: 价格快速查询!$V$18:$AA$18

Sheet 查询首页
A1: =_xlfn.DISPIMG("ID_D6697A225B864C34A678052B48D4E660",1) -> =DISPIMG("ID_D6697A225B864C34A678052B48D4E660",1)

Sheet 美国赔偿标准和免赔声明
A1: =_xlfn.DISPIMG("ID_D6697A225B864C34A678052B48D4E660",1) -> =DISPIMG("ID_D6697A225B864C34A678052B48D4E660",1)
A2: 美国赔偿标准和免赔声明
A3: 一、时效赔付界定：以不同渠道时效说明为准
A4: 二、针对5H查验说明（新增）
A5: 1、散货货物，报价表已含5H查验退运费用，5H退运只包货物退运过程产生的费用，不包时效赔付，店铺绩效等费用。如果客户不接受，可以按表价-0.3/KG，一旦产生5H查验退运，按照实报实销原则，整柜退运产生的全部费用/70CBM，按照柜子里面客户订单的方数占比收取相应的费用； 举例：某个柜子退运产生了RMB140000费用，140000/70CBM=2000/CBM，客户在该柜子的占比是3CBM，则相应承担2000*3=RBM6000. 具体详情如下：关于5H查验，散货货物，使用我司Bond清关，报价包含5H查验退运费用的，5H退运只包货物退运过程产生的费用（如相关仓租、柜租、查验费、退运指定启运港的来回运费、但不包含FBA标签贴标费用、暂存仓租费、内箱SKU换标费且不含改派送地址的派送费，实际派送地址-原先派送地址，差价多退少补。 2.时效延误赔偿说明:凡因5H查验导致的时效延误，我司所有渠道均不承担任何延误赔偿责任，店铺绩效，瑕疵费等费用; 3.发货人责任约定:发货人不得因5H查验相关事宜弃货，亦不得要求我司赔偿货值损失及退运费，需要正常按照合同签署账期支付运费，不得以退运为由不付或少付运费。
A6: 2、整柜货物 a：正常报价，不包查验，如遇查验，所有费用实报实销； b：+1000美金，只包基础查验费（码头拖车费，海关查验，掏箱，装箱等杂费） c.+2000美金：包查验（包含补税，码头拖车费，海关查验，掏箱，装箱等杂费） d:+3800美金：包查验包退运（包含5H查验，包含补税，码头拖车费，海关查验，掏箱，装箱等杂费）
A7: 三、时效免赔说明
A8: 1、船公司船期/航线变更/延迟到港，自然灾害、天气原因，如台风、地震、洪水、冰雹,，暴风雪，雾；政府行为，社会异常事件包括战争，罢工等；
A9: 2、海关查验；
A10: 3、亚马逊拒收或更改预约时间，亚马逊爆仓导致预约困难；
A11: 4、客户FBA ID & 内部编码失误等相关原因；
A12: 5、客户要求扣货后派送或者因客户自身原因导致的延误；
A13: 6、由于疫情，国内仓库无法出货，船公司卸船效率慢，预约困难，拒收等不可抗力导致的延迟交仓,不在赔偿范围,此项如与具体渠道的时效赔付标准有区分，则与具体渠道的标准为准；
... A30: 1、请客户在签收后10个工作日内查询FBA后台是否上架，签收后30天内提供货物未上架后台截图(需带有电脑屏幕右下角当下真实时间)至我司方可进入索赔程序，超过60个工作日不予受理。

Sheet 渠道目录
A1: =_xlfn.DISPIMG("ID_D6697A225B864C34A678052B48D4E660",1) -> =DISPIMG("ID_D6697A225B864C34A678052B48D4E660",1)
A2: 渠道名称 | B2: 链接报价 | C2: 船期/渠道优势说明 | D2: 时效 | E2: 更新提示
A3: FBA渠道 | B3: 进入报价 | C3: 请查看报价表 | D3: 请查看报价表 | E3: 26日达上调0.6/kg
A4: 散货整柜直送 | B4: 进入报价 | C4: 直送渠道，性价比高 | D4: 30个自然日 | E4: 不变
A5: 易·12日达 | B5: 进入报价 | C5: 六截三开，超时赔付 | D5: 30个自然日 | E5: 不变
A6: 易·15日达 | B6: 进入报价 | C6: 六截三开，超时赔付 | D6: 29-31个自然日 | E6: 不变
A7: 易·17日达 | B7: 进入报价 | C7: 超时赔付 | D7: 请查看报价表 | E7: 不变
A8: 易·20日达 | B8: 进入报价 | C8: 中等快线，经济实惠 | D8: 请查看报价表 | E8: 不变
A9: 易·22日达 | B9: 进入报价 | C9: OA普船，舱位稳定，超时赔付 | D9: 请查看报价表 | E9: 不变
A10: 易·25日达 | B10: 进入报价 | C10: 普船统配，性价比高 | D10: 请查看报价表 | E10: 不变
A11: DG海卡 | B11: 进入报价 | C11: 请查看报价表 | D11: 请查看报价表 | E11: 不变
A12: 美西北专线 | B12: 进入报价 | C12: 请查看报价表 | D12: 35-40天 | E12: 不变
A13: 美中专线 | B13: 进入报价 | C13: 请查看报价表 | D13: 35-40天 | E13: 不变
... A27: 欧洲空派 | B27: 进入报价 | C27: 价格波动大，出货前请再确认运费 | D27: 8-10日提取 | E27: 不变
A28: 深圳总部公司地址：广东省深圳市龙华区民治街道民强社区宝山时代大厦2610-2616
A29: 东莞仓库地址（装柜仓库）：东莞市清溪镇九乡村新屋吓一路11号 | E29: 陈主管15118451410
A30: 广州仓库地址（装柜仓库）：广州市白云区太岗公路34号基实(广州)白云空港产业园A1栋4层02单元 | E30: 潘主管 19076062229
A31: 义乌仓库地址（装柜仓库）： 浙江省义乌市稠江街道同和路丰树产业园4G-1库（二楼）。(进大门50米右转，50米左转，直行上坡，二楼 4G-1库） | E31: 邵先生 17280936593
A32: 嘉兴仓库地址（装柜仓库）：嘉兴市嘉善县洪福东路718号丰树（姚庄）科技综合产业园1楼2C-2（进门右转150米） | E32: 李主管 18720007068
A33: 汕头仓库地址（中转仓库）：广东省汕头市澄海区凤翔街道金鸿大道澄海农村信用社南侧190米 | E33: 胡经理 13923475593
A34: 泉州仓库地址（中转仓库）：晋江市磁灶镇西园街道传化公路港k2仓库成翔物流 | E34: 李阿玲 158 6045 1181
A35: 厦门仓库地址（中转仓库）：厦门集美嘉晟物流园1期2栋110 | E35: 李没没 14760028777
A36: 中山仓库地址（中转仓库）：中山市小榄镇北部物流中心 | E36: 薛永波 18659507913

Sheet 美国发货须知
A1: =_xlfn.DISPIMG("ID_D6697A225B864C34A678052B48D4E660",1) -> =DISPIMG("ID_D6697A225B864C34A678052B48D4E660",1)
A2: 美国发货须知
A3: 1. 必须根据实际货物如实申报，货物信息要与发票资料一致，不可瞒报漏报和申报不符，如因申报不符导致海关扣货等后果及产生的所有费用由发货人承担，我司保留追究法律责任的权利.
A4: 2. 不要低价申报，如低价申报导致海关查验，反倾销，扣货，延期，我司不承担任何责任。建议不能低于货值的25%-35%申报。
A5: 3. 纸箱包装需硬朗方正，入亚马逊仓库货件需贴2个以上合格的FBA标签(必须条码字体 清晰、防潮湿耐磨损)，外箱和产品贴有“MADE IN CHINA”标签。如因包装及标签问题导致亚马逊仓库拒收或清关出现问题，所有责任及费用由发货人承担。
A6: 4.使用我司税号清关，税率以预收税率为准，我司不提供关税清单和税费截图；如客户要求清完关后凭税单及发票付关税，我司将收取关税代缴手续费（代缴关税总金额的5%）
A7: 5. 不接仿牌、侵权、反倾销、电子烟、纯电池、食品、药品、书籍、音像制品、带内容的光盘、地图、国旗、管制刀具、液体、粉末、颗粒、强磁、易燃易爆、毒性物质及腐蚀性、古董、货币等国家禁止出口及船司、航空公司、班列禁运物品；其他未列明产品请单询！
A8: 6. 以下情况，我司会协助处理，但不承担任何责任。 A.产品如需要FCC,CE,FDA,TSCA,DOT，CPSC,CPC，EPA等认证而客户无法提供有效证明及文件，导致海关扣货等后果，如因以上情况而产生的退运，销毁，仓租等一切费用，由发货方自行承担 ，例如a.蓝牙，UL，蓝牙类产品要有蓝牙证书，UL灯产品，要有UL证书，FCC,DOT等。 FDA管制的产品需要有MEDICAL DEVICE ID （FDA）: 跟人体接触类产品，医疗器械类需要做FDA申报， 有些产品不仅要FDA申报还需要FDA证书和FDA号码，如太阳镜，急救包，陶瓷制品，美容仪器，理疗产品等。 b.动植物类：产品需要卫生证书； c.木制类：产品和含木质框架的产品需要提供雷斯法案LACEY ACT申报。 d.玩具类：玩具到美国清关都需要提供TESTING REPORT,产品要贴玩具的TRACKING LABEL. 另外还需要做CPC证书 e.电器类，要有FCC认证，产品要贴CE LABEL.否则有可能清不了关，或者被退运。 f.存储类：如涉及知识产权保护法的商品,需提供授权信.如手机,有储存功能的摄录机,MP3，SD卡,HDMI等； g.鞋子/袜子类：请提供FOOTWARE FORM B.产品不符合美国当地法规的，如反倾销，侵权且无法提供有效证及及文件，导致海关扣货等后果
A9: 7. 材质是原木或带有原木的货物要求熏蒸，需要商检的货物：木家私，木制工艺品，木架，竹制品，藤制品，草制品，植物制品，洗发水，化妆品，户外游乐设施等（仅供参考）
A10: 8.每公斤申报价值大于10美金为高货值，10美金-30美金/公斤附加费+1，30美金-50美金/公斤附加费+2，50美金/公斤以上附加费+3。
A11: 9. 电商物流上架险收费标准：（此服务为我司的增值服务，我司代客户购买保险，保险最终解释权按保单说明与保险公司处理结果为准，我司协助客户处理保险事宜）
B12: 保险税率 | C12: 最低收费标准 | D12: 索赔周期
A13: 货值《=1500RMB | C13: RMB50/票 | D13: 预计45天左右
A14: 高货值单询 | B14: / | C14: / | D14: /

Sheet 船期表
A1: =_xlfn.DISPIMG("ID_D6697A225B864C34A678052B48D4E660",1) -> =DISPIMG("ID_D6697A225B864C34A678052B48D4E660",1)
A2: 周次 | B2: 国家 | C2: 渠道 | D2: 预配船司 | E2: 预配船名航次 | F2: ETD | G2: ETA | H2: 航程 | I2: POL | J2: POD | K2: 截单时间&截仓时间
K3: 华南 | S3: 华东
K4: 东莞 | L4: 广州 | M4: 中山 | N4: 汕头 | O4: 厦门 | P4: 泉州 | Q4: 武汉 | R4: 长沙 | S4: 义乌 | T4: 嘉兴
A5: WEEK23 | B5: 美国 | C5: 25日达 | D5: WHL | E5: 统配 | F5: 统配 | G5: 统配 | H5: 18 | I5: SK | J5: LA | K5: 周六 18：00 | L5: 周六 18：00 | M5: 周六18：00 | N5: 周六18：00 | O5: 周六18：00 | P5: 周六18：00 | Q5: 周五18：00 | R5: 周五18：00 | S5: 周六18：00 | T5: 周六18：00
C6: 22日达 | D6: COSCO | E6: OOCL VIOLET/010E | F6: 46205 | G6: 46220 | H6: 15 | I6: YT | J6: LB | K6: 周六 18：00 | L6: 周六 18：00 | M6: 周六 18：00 | N6: 周六 18：00 | O6: 周六 18：00 | P6: 周六 18：00 | Q6: 周五18：00 | R6: 周五18：00 | S6: 周六18：00 | T6: 周六18：00
D7: COSCO | E7: CSCL AUTUMN/073E | F7: 46204 | G7: 46218 | H7: 14 | I7: SH | J7: LA | K7: 周六 18：00 | L7: 周六 18：00 | M7: 周六 18：00 | N7: 周六 18：00 | O7: 周六 18：00 | P7: 周六 18：00 | Q7: 周五18：00 | R7: 周五18：00 | S7: 周六18：00 | T7: 周六18：00
D8: ZIM | E8: Pelican I (ZP1) / 14 / E | F8: 46203 | G8: 46217 | H8: 14 | I8: SH | J8: LA | K8: 周六 18：00 | L8: 周六 18：00 | M8: 周六 18：00 | N8: 周六 18：00 | O8: 周六 18：00 | P8: 周六 18：00 | Q8: 周五18：00 | R8: 周五18：00 | S8: 周六18：00 | T8: 周六18：00
C9: 17-20日达 | D9: ZIM | E9: Nestos (ZY6) / 17 / E | F9: 46204 | G9: 46217 | H9: 13 | I9: YT | J9: LA | K9: 周六 18：00 | L9: 周六 18：00 | M9: 周六 18：00 | N9: 周六 18：00 | O9: 周六 18：00 | P9: 周六 18：00 | Q9: 周五18：00 | R9: 周五18：00 | S9: 周六18：00 | T9: 周六18：00
D10: HEDE | E10: ADAMASTOS/2610E | F10: 46204 | G10: 46218 | H10: 14 | I10: NS | J10: LA | K10: 周六 18：00 | L10: 周六 18：00 | M10: 周六 18：00 | N10: 周六 18：00 | O10: 周六 18：00 | P10: 周六 18：00 | Q10: 周五18：00 | R10: 周五18：00 | S10: 周六18：00 | T10: 周六18：00
D11: HEDE | E11: POSEN /2606E | F11: 46205 | G11: 46218 | H11: 13 | I11: SH | J11: LA | K11: 周六 18：00 | L11: 周六 18：00 | M11: 周六 18：00 | N11: 周六 18：00 | O11: 周六 18：00 | P11: 周六 18：00 | Q11: 周五18：00 | R11: 周五18：00 | S11: 周六18：00 | T11: 周六18：00
C12: 12-15日达 | D12: Maston | E12: LURLINE 101E | F12: 46204 | G12: 46215 | H12: =G12-F12 -> 11 | I12: SH | J12: LB | K12: 周六 18：00 | L12: 周六 18：00 | M12: 周六 18：00 | N12: 周六 18：00 | O12: 周六 18：00 | P12: 周六 18：00 | Q12: 周五18：00 | R12: 周五18：00 | S12: 周六18：00 | T12: 周六18：00
C13: 奥克兰 | D13: EMC | E13: EVER MEMO/1461E | F13: 46209 | G13: 46230 | H13: 21 | I13: YT | J13: OAK | K13: 周六 18：00 | L13: 周六 18：00 | M13: 周六 18：00 | N13: 周六 18：00 | O13: 周六 18：00 | P13: 周六 18：00 | Q13: 周五18：00 | R13: 周五18：00 | S13: 周六18：00 | T13: 周六18：00
D14: COSCO | E14: ERVING/0M708E1MA | F14: 46208 | G14: 46230 | H14: 22 | I14: SH | J14: OAK | K14: 周六 18：00 | L14: 周六 18：00 | M14: 周六 18：00 | N14: 周六 18：00 | O14: 周六 18：00 | P14: 周六 18：00 | Q14: 周五18：00 | R14: 周五18：00 | S14: 周六18：00 | T14: 周六18：00
C15: 西雅图 | D15: COSCO | E15: 暂停 | F15: / | G15: / | H15: / | I15: YT | J15: SEA | K15: 周六 18：00 | L15: 周六 18：00 | M15: 周六 18：00 | N15: 周六 18：00 | O15: 周六 18：00 | P15: 周六 18：00 | Q15: 周五18：00 | R15: 周五18：00 | S15: 周六18：00 | T15: 周六18：00
D16: COSCO | E16: 暂停 | F16: / | G16: / | H16: / | I16: SH | J16: SEA | K16: 周六 18：00 | L16: 周六 18：00 | M16: 周六 18：00 | N16: 周六 18：00 | O16: 周六 18：00 | P16: 周六 18：00 | Q16: 周五18：00 | R16: 周五18：00 | S16: 周六18：00 | T16: 周六18：00
C17: 纽约 | D17: COSCO | E17: OOCL KAPOK/004E | F17: 46208 | G17: 46238 | H17: 30 | I17: YT | J17: NY | K17: 周六 18：00 | L17: 周六 18：00 | M17: 周六 18：00 | N17: 周六 18：00 | O17: 周六 18：00 | P17: 周六 18：00 | Q17: 周五18：00 | R17: 周五18：00 | S17: 周六18：00 | T17: 周六18：00
D18: ZIM | E18: ZIM Mount Fuji (ZF1) / 11 / E | F18: 46207 | G18: 46242 | H18: 35 | I18: YT | J18: NY | K18: 周六 18：00 | L18: 周六 18：00 | M18: 周六 18：00 | N18: 周六 18：00 | O18: 周六 18：00 | P18: 周六 18：00 | Q18: 周五18：00 | R18: 周五18：00 | S18: 周六18：00 | T18: 周六18：00
D19: COSCO | E19: OOCL MAGNOLIA/005E | F19: 46205 | G19: 46231 | H19: 26 | I19: SH | J19: NY | K19: 周六 18：00 | L19: 周六 18：00 | M19: 周六 18：00 | N19: 周六 18：00 | O19: 周六 18：00 | P19: 周六 18：00 | Q19: 周五18：00 | R19: 周五18：00 | S19: 周六18：00 | T19: 周六18：00
C20: 萨凡纳 | D20: COSCO | E20: OOCL KAPOK/004E | F20: 46208 | G20: 46243 | H20: 35 | I20: YT | J20: SAV | K20: 周六 18：00 | L20: 周六 18：00 | M20: 周六 18：00 | N20: 周六 18：00 | O20: 周六 18：00 | P20: 周六 18：00 | Q20: 周五18：00 | R20: 周五18：00 | S20: 周六18：00 | T20: 周六18：00
D21: ZIM | E21: ZIM Mount Fuji (ZF1) / 11 / E | F21: 46207 | G21: 46237 | H21: 30 | I21: YT | J21: SAV | K21: 周六 18：00 | L21: 周六 18：00 | M21: 周六 18：00 | N21: 周六 18：00 | O21: 周六 18：00 | P21: 周六 18：00 | Q21: 周五18：00 | R21: 周五18：00 | S21: 周六18：00 | T21: 周六18：00
D22: COSCO | E22: OOCL MAGNOLIA/005E | F22: 46205 | G22: 46236 | H22: 31 | I22: SH | J22: SAV | K22: 周六 18：00 | L22: 周六 18：00 | M22: 周六 18：00 | N22: 周六 18：00 | O22: 周六 18：00 | P22: 周六 18：00 | Q22: 周五18：00 | R22: 周五18：00 | S22: 周六18：00 | T22: 周六18：00
C23: 休斯顿 | D23: COSCO | E23: OOCL EUROPE/213E | F23: 46208 | G23: 46234 | H23: 26 | I23: YT | J23: HOU | K23: 周六 18：00 | L23: 周六 18：00 | M23: 周六 18：00 | N23: 周六 18：00 | O23: 周六 18：00 | P23: 周六 18：00 | Q23: 周五18：00 | R23: 周五18：00 | S23: 周六18：00 | T23: 周六18：00
D24: ZIM | E24: Rotterdam (ZTD) / 86 / E | F24: 46206 | G24: 46238 | H24: 32 | I24: YT | J24: HOU | K24: 周六 18：00 | L24: 周六 18：00 | M24: 周六 18：00 | N24: 周六 18：00 | O24: 周六 18：00 | P24: 周六 18：00 | Q24: 周五18：00 | R24: 周五18：00 | S24: 周六18：00 | T24: 周六18：00
D25: COSCO | E25: CMA CGM TANCREDI/0PGO3E1MA | F25: 46209 | G25: 46237 | H25: 28 | I25: SH | J25: HOU | K25: 周六 18：00 | L25: 周六 18：00 | M25: 周六 18：00 | N25: 周六 18：00 | O25: 周六 18：00 | P25: 周六 18：00 | Q25: 周五18：00 | R25: 周五18：00 | S25: 周六18：00 | T25: 周六18：00
C26: 芝加哥 | D26: COSCO | E26: OOCL VIOLET/010E | F26: 46205 | G26: 46234 | H26: 29 | I26: YT | J26: CHI | K26: 周六 18：00 | L26: 周六 18：00 | M26: 周六 18：00 | N26: 周六 18：00 | O26: 周六 18：00 | P26: 周六 18：00 | Q26: 周五18：00 | R26: 周五18：00 | S26: 周六18：00 | T26: 周六18：00
D27: COSCO | E27: CSCL AUTUMN/073E | F27: 46204 | G27: 46230 | H27: 26 | I27: SH | J27: CHI | K27: 周六 18：00 | L27: 周六 18：00 | M27: 周六 18：00 | N27: 周六 18：00 | O27: 周六 18：00 | P27: 周六 18：00 | Q27: 周五18：00 | R27: 周五18：00 | S27: 周六18：00 | T27: 周六18：00
B28: 英国 | C28: 英国海派 | D28: COSCO | E28: XIN LIAN YUN GANG 009A | F28: 46202 | G28: 46236 | H28: =_xlfn.DAYS(G28,F28) -> 34 | I28: YT | J28: FEL | K28: 周四18:00 | L28: 周四12:00 | M28: 周四12:00 | N28: 周三18:00 | O28: 周三18:00 | P28: 周三18:00 | Q28: 周二18:00 | R28: 周二18:00 | S28: - | T28: -
D29: COSCO | E29: OOCL ZEEBRUGGE 010W | F29: 46204 | G29: 46243 | H29: =_xlfn.DAYS(G29,F29) -> 39 | I29: NB | J29: FEL | K29: - | L29: - | M29: - | N29: - | O29: - | P29: - | Q29: - | R29: - | S29: 周五17:00 | T29: 周五12:00
B30: 欧洲 | C30: 欧洲海派 | D30: COSCO | E30: EVER ACE 1406-019W | F30: 46201 | G30: 46232 | H30: =_xlfn.DAYS(G30,F30) -> 31 | I30: YT | J30: ROT | K30: 周四12:00 | L30: 周四12:00 | M30: 周四12:00 | N30: 周三12:00 | O30: 周三12:00 | P30: 周三12:00 | Q30: 周二12:00 | R30: 周二12:00 | S30: - | T30: -
D31: COSCO | E31: EVER ART 1407-015W | F31: 46205 | G31: 46239 | H31: =_xlfn.DAYS(G31,F31) -> 34 | I31: NB | J31: ROT | K31: - | L31: - | M31: - | N31: - | O31: - | P31: - | Q31: - | R31: - | S31: 周四12:00 | T31: 周三18:00

Sheet 价格快速查询
A1: =_xlfn.DISPIMG("ID_D6697A225B864C34A678052B48D4E660",1) -> =DISPIMG("ID_D6697A225B864C34A678052B48D4E660",1)
C2: 渠道价格快速查询
C3: 派运方式 | D3: 国内地址 | E3: 仓库代码/地区选择 | F3: 计费标准
C4: 海运 | D4: 东莞/中山/广州 | E4: RDU2 | F4: 12KG+含税
A6: 系列 | B6: 具体渠道 | C6: 渠道单价(KG/CBM) | D6: 参考时效 (开船次日算起) | E6: 理赔时效 (开船次日开始算起) | F6: 送仓方式 | G6: 备选信息 | H6: 备注
A7: FBA渠道 | B7: FBA美西28日达 | C7: {=IF(C4="海运",IFERROR(INDEX(FBA渠道!$B$10:$I$25,MATCH(E4,FBA渠道!$A$10:$A$25,0),MATCH(F4,FBA渠道!$B$9:$I$9,0)+MATCH(D4,FBA渠道!$B$8:$I$8,0)-1),""),"")} | D7: =IF(C7="","",INDEX(FBA渠道!J10:J25,MATCH(E4,FBA渠道!A10:A25,0))) | G7: =IF(C7="","",FBA渠道!A63) | H7: 查看报价
B8: FBA美中南28日达 | C8: {=IF(C4="海运",IFERROR(INDEX(FBA渠道!$B$29:$I$34,MATCH(E4,FBA渠道!$A$29:$A$34,0),MATCH(F4,FBA渠道!$B$28:$I$28,0)+MATCH(D4,FBA渠道!$B$27:$I$27,0)-1),""),"")} | D8: =IF(C8="","",INDEX(FBA渠道!J29:J34,MATCH(E4,FBA渠道!A29:A34,0))) | G8: =IF(C8="","",FBA渠道!A63) | H8: 查看报价
B9: FBA美中北40日达 | C9: {=IF(C4="海运",IFERROR(INDEX(FBA渠道!$B$38:$I$43,MATCH(E4,FBA渠道!$A$38:$A$43,0),MATCH(F4,FBA渠道!$B$37:$I$37,0)+MATCH(D4,FBA渠道!$B$36:$I$36,0)-1),""),"")} | D9: =IF(C9="","",INDEX(FBA渠道!J38:J43,MATCH(E4,FBA渠道!A38:A43,0))) | G9: =IF(C9="","",FBA渠道!A63) | H9: 查看报价
B10: FBA美东南40日达 | C10: {=IF(C4="海运",IFERROR(INDEX(FBA渠道!$B$47:$I$50,MATCH(E4,FBA渠道!$A$47:$A$50,0),MATCH(F4,FBA渠道!$B$46:$I$46,0)+MATCH(D4,FBA渠道!$B$45:$I$45,0)-1),""),"")} -> 5.9 | D10: =IF(C10="","",INDEX(FBA渠道!J47:J50,MATCH(E4,FBA渠道!A47:A50,0))) -> 40-45自然日入仓 | G10: =IF(C10="","",FBA渠道!A63) -> 重货优惠：1：200 -0.2; 1：250 -0.5; 1：300 -0.7; 1：350 -1; 1：500 -1.5 | H10: 查看报价
B11: FBA美东北40日达 | C11: {=IF(C4="海运",IFERROR(INDEX(FBA渠道!$B$55:$I$62,MATCH(E4,FBA渠道!$A$55:$A$62,0),MATCH(F4,FBA渠道!$B$54:$I$54,0)+MATCH(D4,FBA渠道!$B$53:$I$53,0)-1),""),"")} | D11: =IF(C11="","",INDEX(FBA渠道!J55:J62,MATCH(E4,FBA渠道!A55:A62,0))) | G11: =IF(C11="","",FBA渠道!A63) | H11: 查看报价
A12: 美西专仓直送 | B12: 美国整柜直送 | C12: {=IF(C4="海运",IFERROR(INDEX(美西整柜直送!$B$6:$I$21,MATCH(E4,美西整柜直送!$A$6:$A$21,0),MATCH(F4,美西整柜直送!$B$5:$I$5,0)+MATCH(D4,美西整柜直送!$B$4:$I$4,0)-1),""),"")} | D12: =IF(C12="","","28-32") | E12: =IF(C12="","","-") | F12: =IF(C12="","","直送") | G12: =IF(C12="","",美西整柜直送!A22) | H12: 查看报价
A13: 美西22-25日达 | B13: 易·25日达卡派 | C13: {=IF(C4="海运",IFERROR(INDEX('美西22-25日达'!$L$6:$S$104,MATCH(E4,'美西22-25日达'!$A$6:$A$104,0),MATCH(F4,'美西22-25日达'!$L$5:$S$5,0)+MATCH(D4,'美西22-25日达'!$L$4:$S$4,0)-1),""),"")} -> 9.1 | D13: =IF(C13="","",INDEX('美西22-25日达'!T6:T104,MATCH(E4,'美西22-25日达'!A6:A104,0))) -> 28-35 | E13: =IF(C13="","",INDEX('美西22-25日达'!U6:U104,MATCH(E4,'美西22-25日达'!A6:A104,0))) -> - | F13: =IF(C13="","","拆派") -> 拆派 | G13: =IF(C13="","",'美西22-25日达'!A76) -> 重货优惠：1:200 -0.2; 1:250 -0.5，1:300 -1，1:400 -1.5，1:500 -2比重减重后最低1.2/KG。 | H13: 查看报价
B14: 易·22日达卡派 | C14: {=IF(C4="海运",IFERROR(INDEX('美西22-25日达'!$B$6:$I$104,MATCH(E4,'美西22-25日达'!$A$6:$A$104,0),MATCH(F4,'美西22-25日达'!$B$5:$I$5,0)+MATCH(D4,'美西22-25日达'!$B$4:$I$4,0)-1),""),"")} -> 9.5 | D14: =IF(C14="","",INDEX('美西22-25日达'!J6:J104,MATCH(E4,'美西22-25日达'!A6:A104,0))) -> 28-33 | E14: =IF(C14="","",INDEX('美西22-25日达'!K6:K104,MATCH(E4,'美西22-25日达'!A6:A104,0))) -> - | F14: =IF(C14="","","拆派") -> 拆派 | G14: =IF(C14="","",'美西22-25日达'!A76) -> 重货优惠：1:200 -0.2; 1:250 -0.5，1:300 -1，1:400 -1.5，1:500 -2比重减重后最低1.2/KG。 | H14: 查看报价
A15: 美西17-20日达 | B15: 易·20日达卡派 | C15: {=IF(C4="海运",IFERROR(INDEX('美西17-20日达'!$L$6:$S$104,MATCH(E4,'美西17-20日达'!$A$6:$A$104,0),MATCH(F4,'美西17-20日达'!$L$5:$S$5,0)+MATCH(D4,'美西17-20日达'!$L$4:$S$4,0)-1),""),"")} -> 10.3 | D15: {=IF(C15="","",INDEX('美西17-20日达'!T6:T104,MATCH(E4,'美西17-20日达'!A6:A104,0)))} -> 29-32 | E15: {=IF(C15="","",INDEX('美西17-20日达'!U6:U104,MATCH(E4,'美西17-20日达'!A6:A104,0)))} -> - | F15: =IF(C15="","","拆派") -> 拆派 | G15: =IF(C15="","",'美西17-20日达'!A76) -> 重货优惠：1：185-0.2 1：200-0.5 1：250-0.9 1：300-1.5 1.500-2比重减重后最低1.2/KG。 | H15: 查看报价
B16: 易·17日达卡派 | C16: {=IF(C4="海运",IFERROR(INDEX('美西17-20日达'!$B$6:$I$104,MATCH(E4,'美西17-20日达'!$A$6:$A$104,0),MATCH(F4,'美西17-20日达'!$B$5:$I$5,0)+MATCH(D4,'美西17-20日达'!$B$4:$I$4,0)-1),""),"")} -> 10.9 | D16: {=IF(C16="","",INDEX('美西17-20日达'!J7:J104,MATCH(E4,'美西17-20日达'!A7:A104,0)))} -> 27-30 | E16: {=IF(C16="","",INDEX('美西17-20日达'!K7:K104,MATCH(E4,'美西17-20日达'!A7:A104,0)))} -> - | F16: =IF(C16="","","拆派") -> 拆派 | G16: =IF(C16="","",'美西17-20日达'!A76) -> 重货优惠：1：185-0.2 1：200-0.5 1：250-0.9 1：300-1.5 1.500-2比重减重后最低1.2/KG。 | H16: 查看报价
A17: 美西12-15日达 | B17: 易·15日达卡派 | C17: {=IF(C4="海运",IFERROR(INDEX('美西12-15日达'!$H$6:$O$105,MATCH(E4,'美西12-15日达'!$A$6:$A$105,0),MATCH(F4,'美西12-15日达'!$H$5:$O$5,0)+MATCH(D4,'美西12-15日达'!$H$4:$O$4,0)-1),""),"")} -> 14.2 | D17: =IF(C17="","",INDEX('美西12-15日达'!P6:P105,MATCH(E4,'美西12-15日达'!A6:A105,0))) -> 22-27 | E17: =IF(C17="","",INDEX('美西12-15日达'!Q6:Q105,MATCH(E4,'美西12-15日达'!A6:A105,0))) -> - | F17: =IF(C17="","","拆派") -> 拆派 | G17: =IF(C17="","",'美西12-15日达'!A77) -> 重货优惠：1：185-0.2 1：200-0.5 1：250-0.9 1：300-1.5 1.500-2比重减重后最低1.2/KG。 | H17: 查看报价
B18: 易·12日达卡派 | C18: {=IF(C4="海运",IFERROR(INDEX('美西12-15日达'!$B$6:$E$105,MATCH(E4,'美西12-15日达'!$A$6:$A$105,0),MATCH(F4,'美西12-15日达'!$B$5:$E$5,0)+MATCH(D4,'美西12-15日达'!$B$4:$E$4,0)-1),""),"")} -> - | D18: =IF(C18="","",INDEX('美西12-15日达'!F6:F105,MATCH(E4,'美西12-15日达'!A6:A105,0))) -> - | E18: =IF(C18="","",INDEX('美西12-15日达'!G6:G105,MATCH(E4,'美西12-15日达'!A6:A105,0))) -> - | F18: =IF(C18="","","拆派") -> 拆派 | G18: =IF(C18="","",'美西12-15日达'!A77) -> 重货优惠：1：185-0.2 1：200-0.5 1：250-0.9 1：300-1.5 1.500-2比重减重后最低1.2/KG。 | H18: 查看报价
A19: 东部稳速达 | B19: MAX/ZIM带托架/合德快提-东部稳速达 | C19: {=IF(C4="海运",IFERROR(INDEX(FBA渠道!$B$11:$J$37,MATCH(E4,FBA渠道!$A$11:$A$37,0),MATCH(F4,FBA渠道!$B$10:$J$10,0)+MATCH(D4,FBA渠道!$B$9:$J$9,0)-1),""),"")} | D19: =IF(C19="","",INDEX(FBA渠道!#REF!,MATCH(E4,FBA渠道!A11:A37,0))) | E19: =IF(C19="","","-") | F19: =IF(C19="","","拆派") | G19: =IF(C19="","",FBA渠道!A38) | H19: 查看报价
B20: ZIM不带托/合德普提/OA-东部稳速达 | C20: {=IF(C4="海运",IFERROR(INDEX(FBA渠道!$K$11:$N$37,MATCH(E4,FBA渠道!$A$11:$A$37,0),MATCH(F4,FBA渠道!$K$10:$N$10,0)+MATCH(D4,FBA渠道!$K$9:$N$9,0)-1),""),"")} | D20: =IF(C20="","",INDEX(FBA渠道!#REF!,MATCH(E4,FBA渠道!A11:A37,0))) | E20: =IF(C20="","","-") | F20: =IF(C20="","","拆派") | G20: =IF(C20="","",FBA渠道!A38) | H20: 查看报价
B21: OA/MSC/ONE统配-东部稳速达 | C21: {=IF(C4="海运",IFERROR(INDEX(FBA渠道!$O$11:$U$37,MATCH(E4,FBA渠道!$A$11:$A$37,0),MATCH(F4,FBA渠道!$O$10:$U$10,0)+MATCH(D4,FBA渠道!$O$9:$U$9,0)-1),""),"")} | D21: =IF(C21="","",INDEX(FBA渠道!V11:V37,MATCH(E4,FBA渠道!A11:A37,0))) | E21: =IF(C21="","","-") | F21: =IF(C21="","","拆派") | G21: =IF(C21="","",FBA渠道!A38) | H21: 查看报价
A22: 美西北专线 | B22: 易·奥易达卡派 （OA/ONE/MSC/HMM统配) | C22: {=IF(C4="海运",IFERROR(INDEX(美西北专线!$B$6:$I$24,MATCH(E4,美西北专线!$A$6:$A$24,0),MATCH(F4,美西北专线!$B$5:$I$5,0)+MATCH(D4,美西北专线!$B$4:$I$4,0)-1),""),"")} | D22: =IF(C22="","",INDEX(美西北专线!J6:J24,MATCH(E4,美西北专线!A6:A24,0))) | E22: =IF(C22="","","-") | F22: =IF(C22="","","拆派") | G22: =IF(C22="","",美西北专线!A25) | H22: 查看报价
B23: 西雅图专线卡派（暂停） （OA/ONE/MSC/WHL统配） | C23: {=IF(C4="海运",IFERROR(INDEX(美西北专线!$K$6:$R$24,MATCH(E4,美西北专线!$A$6:$A$24,0),MATCH(F4,美西北专线!$K$5:$R$5,0)+MATCH(D4,美西北专线!$K$4:$R$4,0)-1),""),"")} | D23: =IF(C23="","",INDEX(美西北专线!S6:S24,MATCH(E4,美西北专线!A6:A24,0))) | E23: =IF(C23="","","-") | F23: =IF(C23="","","拆派") | G23: =IF(C23="","",美西北专线!A25) | H23: 查看报价
A24: 美中芝加哥卡派 | B24: 芝加哥经济线卡派 （OA/ZIM/MSC统配） | C24: {=IF(C4="海运",IFERROR(INDEX(芝加哥专线!$B$6:$I$33,MATCH(E4,芝加哥专线!$A$6:$A$33,0),MATCH(F4,芝加哥专线!$B$5:$I$5,0)+MATCH(D4,芝加哥专线!$B$4:$I$4,0)-1),""),"")} | D24: {=IF(C24="","",INDEX(芝加哥专线!J6:J33,MATCH(E4,芝加哥专线!A6:A33,0)))} | E24: =IF(C24="","","-") | F24: =IF(C24="","","拆派") | G24: =IF(C24="","",芝加哥专线!A35) | H24: 查看报价
A25: 美中休斯顿卡派 | B25: 休斯顿经济线卡派（OA/ONE/MSC/WHL统配） | C25: {=IF(C4="海运",IFERROR(INDEX(休斯顿专线!$B$6:$I$30,MATCH(E4,休斯顿专线!$A$6:$A$30,0),MATCH(F4,休斯顿专线!$B$5:$I$5,0)+MATCH(D4,休斯顿专线!$B$4:$I$4,0)-1),""),"")} | D25: {=IF(C25="","",INDEX(休斯顿专线!J6:J30,MATCH(E4,休斯顿专线!A6:A30,0)))} | E25: =IF(C25="","","-") | F25: =IF(C25="","","拆派") | G25: =IF(C25="","",休斯顿专线!A31) | H25: 查看报价
A26: 纽约专线 | B26: 美东纽约经济线卡派 (OA/ZIM/MSC统配) | C26: {=IF(C4="海运",IFERROR(INDEX(纽约专线!$B$6:$I$49,MATCH(E4,纽约专线!$A$6:$A$49,0),MATCH(F4,纽约专线!$B$5:$I$5,0)+MATCH(D4,纽约专线!$B$4:$I$4,0)-1),""),"")} -> 7.9 | D26: =IF(C26="","",INDEX(纽约专线!J6:J49,MATCH(E4,纽约专线!A6:A49,0))) -> 40-45 | E26: =IF(C26="","","-") -> - | F26: =IF(C26="","","拆派") -> 拆派 | G26: =IF(C26="","",纽约专线!A50) -> 重货优惠：1:200 -0.2; 1:250 -0.5，1:300 -1，1:400 -1.5，1:500 -2比重减重后最低1.2/KG。 | H26: 查看报价
A27: 萨凡纳专线卡派 | B27: 萨凡纳经济线卡派 (OA/ZIM/MSC/WHL统配) | C27: {=IF(C4="海运",IFERROR(INDEX(萨凡纳专线!$B$6:$I$33,MATCH(E4,萨凡纳专线!$A$6:$A$33,0),MATCH(F4,萨凡纳专线!$B$5:$I$5,0)+MATCH(D4,萨凡纳专线!$B$4:$I$4,0)-1),""),"")} -> 7.3 | D27: {=IF(C27="","",INDEX(萨凡纳专线!J6:J33,MATCH(E4,萨凡纳专线!A6:A33,0)))} -> 40-48 | E27: =IF(C27="","","-") -> - | F27: =IF(C27="","","拆派") -> 拆派 | G27: =IF(C27="","",萨凡纳专线!A34) -> 备注：本报价为人民币报价，价格适用于普货，包含头程运费、进出口买单报关费、文件费（不含出单费）、仓库卸货费、托盘费、目的港清关、派送等费用；不包含保险费、商检费、熏蒸费、因货物问题导致的进出口海关查验费、仓库增值服务费、超期费和仓储费等，如若产生，实报实销。 | H27: 查看报价
A28: 美国海派 | B28: 易·12日达海派 | C28: {=IF($C$4="海派",IFERROR(INDEX(美国海派!$B$6:$I$8,MATCH($E$4,美国海派!$A$6:$A$8,0),MATCH($F$4,美国海派!$B$5:$I$5,0)+MATCH($D$4,美国海派!$B$4:$I$4,0)-1),""),"")} | D28: =IF(C28="","","12-13") | E28: =IF(C28="","","-") | F28: =IF(C28="","","拆派") | G28: =IF(C28="","",美国海派!$A$18) | H28: 查看报价
B29: 易·15日达海派 | C29: {=IF($C$4="海派",IFERROR(INDEX(美国海派!$J$6:$Q$8,MATCH($E$4,美国海派!$A$6:$A$8,0),MATCH($F$4,美国海派!$J$5:$Q$5,0)+MATCH($D$4,美国海派!$J$4:$Q$4,0)-1),""),"")} | D29: =IF(C29="","","13-16") | E29: =IF(C29="","","-") | F29: =IF(C29="","","拆派") | G29: =IF(C29="","",美国海派!$A$18) | H29: 查看报价
B30: 易·17日达海派 | C30: {=IF($C$4="海派",IFERROR(INDEX(美国海派!$R$6:$Y$8,MATCH($E$4,美国海派!$A$6:$A$8,0),MATCH($F$4,美国海派!$R$5:$Y$5,0)+MATCH($D$4,美国海派!$R$4:$Y$4,0)-1),""),"")} | D30: =IF(C30="","","16-19") | E30: =IF(C30="","","-") | F30: =IF(C30="","","拆派") | G30: =IF(C30="","",美国海派!$A$18) | H30: 查看报价
B31: 易·20日达海派 | C31: {=IF($C$4="海派",IFERROR(INDEX(美国海派!$B$14:$I$16,MATCH($E$4,美国海派!$A$14:$A$16,0),MATCH($F$4,美国海派!$B$13:$I$13,0)+MATCH($D$4,美国海派!$B$12:$I$12,0)-1),""),"")} | D31: =IF(C31="","","18-21") | E31: =IF(C31="","","-") | F31: =IF(C31="","","拆派") | G31: =IF(C31="","",美国海派!$A$18) | H31: 查看报价
B32: 易·22日达海派 | C32: {=IF($C$4="海派",IFERROR(INDEX(美国海派!$J$14:$Q$16,MATCH($E$4,美国海派!$A$14:$A$16,0),MATCH($F$4,美国海派!$J$13:$Q$13,0)+MATCH($D$4,美国海派!$J$12:$Q$12,0)-1),""),"")} | D32: =IF(C32="","","20-25") | E32: =IF(C32="","","-") | F32: =IF(C32="","","拆派") | G32: =IF(C32="","",美国海派!$A$18) | H32: 查看报价
B33: 易·25日达海派 | C33: {=IF($C$4="海派",IFERROR(INDEX(美国海派!$R$14:$Y$16,MATCH($E$4,美国海派!$A$14:$A$16,0),MATCH($F$4,美国海派!$R$13:$Y$13,0)+MATCH($D$4,美国海派!$R$12:$Y$12,0)-1),""),"")} | D33: =IF(C33="","","26-30") | E33: =IF(C33="","","-") | F33: =IF(C33="","","拆派") | G33: =IF(C33="","",美国海派!$A$18) | H33: 查看报价

Sheet FBA渠道
A1: =_xlfn.DISPIMG("ID_D6697A225B864C34A678052B48D4E660",1) -> =DISPIMG("ID_D6697A225B864C34A678052B48D4E660",1)
A2: 本渠道有相关的要求和限制，请务必按相关条款执行，未按要求如实申报导致的异常不做任何赔付受理： 1.本渠道只接收亚马逊标准件规格产品，标准件定义：指单件商品（ASIN）尺寸18*14*8英寸（45*35*20CM）以内并且重量低于20磅（9.07KG） 2.本渠道出货前需按我司固定模板填写发票。必须提供详细品名，货件的FBA号，PO号，以及卖家标记信息等相关信息，不然会影响货物上架； 3.本渠道使用真实收货人抬头，可以有效降低5H查验退运风险； 4.本渠道只接FBA仓库货物，沃尔玛，商卡，私人地址不可下单本渠道； 5.同渠道仓库均可合并报关； 6.本渠道直送亚马逊仓库，无法做拦截处理；
A3: FBA全美26日达（OA/ZIM，靠洛杉矶港)
A4: 区域 | B4: 东莞/中山/广州 | D4: 嘉兴/义乌 | F4: 汕头/厦门/泉州 | H4: 武汉/长沙 | J4: 参考时效(开船后)
A5: 仓库代码 | B5: 12KG+含税 | C5: 1CBM+ 不含税 | D5: 12KG+含税 | E5: 1CBM+ 不含税 | F5: 12KG+含税 | G5: 1CBM+ 不含税 | H5: 12KG+含税 | I5: 1CBM+ 不含税
A6: 全美所有FBA仓库均可走本渠道 | B6: 9.1 | C6: =B6*150 -> 1365 | D6: =B6 -> 9.1 | E6: =D6*150 -> 1365 | F6: =B6+0.2 -> 9.3 | G6: =F6*150 -> 1395 | H6: =B6+0.5 -> 9.6 | I6: =H6*150 -> 1440 | J6: 26-28自然日入仓
A7: FBA美西28日达（OA/MSC/WHL统配，靠洛杉矶港)
A8: 区域 | B8: 东莞/中山/广州 | D8: 嘉兴/义乌 | F8: 汕头/厦门/泉州 | H8: 武汉/长沙 | J8: 参考时效(开船后)
A9: 仓库代码 | B9: 12KG+含税 | C9: 1CBM+ 不含税 | D9: 12KG+含税 | E9: 1CBM+ 不含税 | F9: 12KG+含税 | G9: 1CBM+ 不含税 | H9: 12KG+含税 | I9: 1CBM+ 不含税
A10: ONT8 | B10: 5.5 | C10: =B10*150 -> 825 | D10: =B10 -> 5.5 | E10: =D10*150 -> 825 | F10: =B10+0.2 -> 5.7 | G10: =F10*150 -> 855 | H10: =B10+0.5 -> 6 | I10: =H10*150 -> 900 | J10: 25-30自然日入仓
A11: LGB8 | B11: 5.5 | C11: =B11*150 -> 825 | D11: =B11 -> 5.5 | E11: =D11*150 -> 825 | F11: =B11+0.2 -> 5.7 | G11: =F11*150 -> 855 | H11: =B11+0.5 -> 6 | I11: =H11*150 -> 900 | J11: 25-30自然日入仓
A12: SBD1 | B12: 5.5 | C12: =B12*150 -> 825 | D12: =B12 -> 5.5 | E12: =D12*150 -> 825 | F12: =B12+0.2 -> 5.7 | G12: =F12*150 -> 855 | H12: =B12+0.5 -> 6 | I12: =H12*150 -> 900 | J12: 25-30自然日入仓
A13: SMF3 | B13: 5.5 | C13: =B13*150 -> 825 | D13: =B13 -> 5.5 | E13: =D13*150 -> 825 | F13: =B13+0.2 -> 5.7 | G13: =F13*150 -> 855 | H13: =B13+0.5 -> 6 | I13: =H13*150 -> 900 | J13: 25-30自然日入仓
A14: SCK4 | B14: 5.5 | C14: =B14*150 -> 825 | D14: =B14 -> 5.5 | E14: =D14*150 -> 825 | F14: =B14+0.2 -> 5.7 | G14: =F14*150 -> 855 | H14: =B14+0.5 -> 6 | I14: =H14*150 -> 900 | J14: 25-30自然日入仓
A15: MCC1 | B15: 5.5 | C15: =B15*150 -> 825 | D15: =B15 -> 5.5 | E15: =D15*150 -> 825 | F15: =B15+0.2 -> 5.7 | G15: =F15*150 -> 855 | H15: =B15+0.5 -> 6 | I15: =H15*150 -> 900 | J15: 25-30自然日入仓
A16: GEU2 | B16: 5.5 | C16: =B16*150 -> 825 | D16: =B16 -> 5.5 | E16: =D16*150 -> 825 | F16: =B16+0.2 -> 5.7 | G16: =F16*150 -> 855 | H16: =B16+0.5 -> 6 | I16: =H16*150 -> 900 | J16: 25-30自然日入仓
A17: GEU3 | B17: 5.5 | C17: =B17*150 -> 825 | D17: =B17 -> 5.5 | E17: =D17*150 -> 825 | F17: =B17+0.2 -> 5.7 | G17: =F17*150 -> 855 | H17: =B17+0.5 -> 6 | I17: =H17*150 -> 900 | J17: 25-30自然日入仓
A18: ABQ2 | B18: 5.5 | C18: =B18*150 -> 825 | D18: =B18 -> 5.5 | E18: =D18*150 -> 825 | F18: =B18+0.2 -> 5.7 | G18: =F18*150 -> 855 | H18: =B18+0.5 -> 6 | I18: =H18*150 -> 900 | J18: 25-30自然日入仓
A19: PSC2 | B19: 5.5 | C19: =B19*150 -> 825 | D19: =B19 -> 5.5 | E19: =D19*150 -> 825 | F19: =B19+0.2 -> 5.7 | G19: =F19*150 -> 855 | H19: =B19+0.5 -> 6 | I19: =H19*150 -> 900 | J19: 25-30自然日入仓
A20: POC1 | B20: 5.5 | C20: =B20*150 -> 825 | D20: =B20 -> 5.5 | E20: =D20*150 -> 825 | F20: =B20+0.2 -> 5.7 | G20: =F20*150 -> 855 | H20: =B20+0.5 -> 6 | I20: =H20*150 -> 900 | J20: 25-30自然日入仓
A21: POC2 | B21: 5.5 | C21: =B21*150 -> 825 | D21: =B21 -> 5.5 | E21: =D21*150 -> 825 | F21: =B21+0.2 -> 5.7 | G21: =F21*150 -> 855 | H21: =B21+0.5 -> 6 | I21: =H21*150 -> 900 | J21: 25-30自然日入仓
... A25: TCY2 | B25: 5.5 | C25: =B25*150 -> 825 | D25: =B25 -> 5.5 | E25: =D25*150 -> 825 | F25: =B25+0.2 -> 5.7 | G25: =F25*150 -> 855 | H25: =B25+0.5 -> 6 | I25: =H25*150 -> 900 | J25: 25-30自然日入仓
A26: FBA美中南28日达（OA/MSC/WHL统配，靠洛杉矶港)
A27: 区域 | B27: 东莞/中山/广州 | D27: 嘉兴/义乌 | F27: 汕头/厦门/泉州 | H27: 武汉/长沙 | J27: 参考时效(开船后)
A28: 仓库代码/起收量 | B28: 12KG+含税 | C28: 1CBM+ 不含税 | D28: 12KG+含税 | E28: 1CBM+ 不含税 | F28: 12KG+含税 | G28: 1CBM+ 不含税 | H28: 12KG+含税 | I28: 1CBM+ 不含税
A29: LAX9 | B29: 5.9 | C29: =B29*150 -> 885 | D29: =B29 -> 5.9 | E29: =D29*150 -> 885 | F29: =B29+0.2 -> 6.1 | G29: =F29*150 -> 915 | H29: =B29+0.5 -> 6.4 | I29: =H29*150 -> 960 | J29: 25-30自然日入仓
A30: GYR2 | B30: 5.9 | C30: =B30*150 -> 885 | D30: =B30 -> 5.9 | E30: =D30*150 -> 885 | F30: =B30+0.2 -> 6.1 | G30: =F30*150 -> 915 | H30: =B30+0.5 -> 6.4 | I30: =H30*150 -> 960 | J30: 25-30自然日入仓
A31: GYR3 | B31: 5.9 | C31: =B31*150 -> 885 | D31: =B31 -> 5.9 | E31: =D31*150 -> 885 | F31: =B31+0.2 -> 6.1 | G31: =F31*150 -> 915 | H31: =B31+0.5 -> 6.4 | I31: =H31*150 -> 960 | J31: 25-30自然日入仓
A32: PSP3 | B32: 5.9 | C32: =B32*150 -> 885 | D32: =B32 -> 5.9 | E32: =D32*150 -> 885 | F32: =B32+0.2 -> 6.1 | G32: =F32*150 -> 915 | H32: =B32+0.5 -> 6.4 | I32: =H32*150 -> 960 | J32: 25-30自然日入仓
A33: FTW1 | B33: 5.9 | C33: =B33*150 -> 885 | D33: =B33 -> 5.9 | E33: =D33*150 -> 885 | F33: =B33+0.2 -> 6.1 | G33: =F33*150 -> 915 | H33: =B33+0.5 -> 6.4 | I33: =H33*150 -> 960 | J33: 25-30自然日入仓
A34: IAH3 | B34: 5.9 | C34: =B34*150 -> 885 | D34: =B34 -> 5.9 | E34: =D34*150 -> 885 | F34: =B34+0.2 -> 6.1 | G34: =F34*150 -> 915 | H34: =B34+0.5 -> 6.4 | I34: =H34*150 -> 960 | J34: 25-30自然日入仓
A35: FBA美中北40日达（OA/MSC/WHL统配，靠纽约港)
A36: 区域 | B36: 东莞/中山/广州 | D36: 嘉兴/义乌 | F36: 汕头/厦门/泉州 | H36: 武汉/长沙 | J36: 参考时效(开船后)
A37: 仓库代码/起收量 | B37: 12KG+含税 | C37: 1CBM+ 不含税 | D37: 12KG+含税 | E37: 1CBM+ 不含税 | F37: 12KG+含税 | G37: 1CBM+ 不含税 | H37: 12KG+含税 | I37: 1CBM+ 不含税
A38: LAS1 | B38: 6.4 | C38: =B38*150 -> 960 | D38: =B38 -> 6.4 | E38: =D38*150 -> 960 | F38: =B38+0.2 -> 6.6 | G38: =F38*150 -> 990 | H38: =B38+0.5 -> 6.9 | I38: =H38*150 -> 1035 | J38: 40-45自然日入仓
A39: VGT2 | B39: 6.4 | C39: =B39*150 -> 960 | D39: =B39 -> 6.4 | E39: =D39*150 -> 960 | F39: =B39+0.2 -> 6.6 | G39: =F39*150 -> 990 | H39: =B39+0.5 -> 6.9 | I39: =H39*150 -> 1035 | J39: 40-45自然日入仓
A40: FWA4 | B40: 6.4 | C40: =B40*150 -> 960 | D40: =B40 -> 6.4 | E40: =D40*150 -> 960 | F40: =B40+0.2 -> 6.6 | G40: =F40*150 -> 990 | H40: =B40+0.5 -> 6.9 | I40: =H40*150 -> 1035 | J40: 40-45自然日入仓
A41: MDW2 | B41: 6.4 | C41: =B41*150 -> 960 | D41: =B41 -> 6.4 | E41: =D41*150 -> 960 | F41: =B41+0.2 -> 6.6 | G41: =F41*150 -> 990 | H41: =B41+0.5 -> 6.9 | I41: =H41*150 -> 1035 | J41: 40-45自然日入仓
A42: SWF2 | B42: 6.4 | C42: =B42*150 -> 960 | D42: =B42 -> 6.4 | E42: =D42*150 -> 960 | F42: =B42+0.2 -> 6.6 | G42: =F42*150 -> 990 | H42: =B42+0.5 -> 6.9 | I42: =H42*150 -> 1035 | J42: 40-45自然日入仓
A43: RFD2 | B43: 6.4 | C43: =B43*150 -> 960 | D43: =B43 -> 6.4 | E43: =D43*150 -> 960 | F43: =B43+0.2 -> 6.6 | G43: =F43*150 -> 990 | H43: =B43+0.5 -> 6.9 | I43: =H43*150 -> 1035 | J43: 40-45自然日入仓
A44: FBA美东南40日达（OA/ZIM/MSC/WHL统配，靠萨凡纳港)
A45: 区域 | B45: 东莞/中山/广州 | D45: 嘉兴/义乌 | F45: 汕头/厦门/泉州 | H45: 武汉/长沙 | J45: 参考时效(开船后)
A46: 仓库代码/起收量 | B46: 12KG+含税 | C46: 1CBM+ 不含税 | D46: 12KG+含税 | E46: 1CBM+ 不含税 | F46: 12KG+含税 | G46: 1CBM+ 不含税 | H46: 12KG+含税 | I46: 1CBM+ 不含税
A47: IND9 | B47: 5.9 | C47: =B47*150 -> 885 | D47: =B47 -> 5.9 | E47: =D47*150 -> 885 | F47: =B47+0.2 -> 6.1 | G47: =F47*150 -> 915 | H47: =B47+0.5 -> 6.4 | I47: =H47*150 -> 960 | J47: 40-45自然日入仓
A48: MEM1 | B48: 5.9 | C48: =B48*150 -> 885 | D48: =B48 -> 5.9 | E48: =D48*150 -> 885 | F48: =B48+0.2 -> 6.1 | G48: =F48*150 -> 915 | H48: =B48+0.5 -> 6.4 | I48: =H48*150 -> 960 | J48: 40-45自然日入仓
A49: CLT2 | B49: 5.9 | C49: =B49*150 -> 885 | D49: =B49 -> 5.9 | E49: =D49*150 -> 885 | F49: =B49+0.2 -> 6.1 | G49: =F49*150 -> 915 | H49: =B49+0.5 -> 6.4 | I49: =H49*150 -> 960 | J49: 40-45自然日入仓
A50: RDU2 | B50: 5.9 | C50: =B50*150 -> 885 | D50: =B50 -> 5.9 | E50: =D50*150 -> 885 | F50: =B50+0.2 -> 6.1 | G50: =F50*150 -> 915 | H50: =B50+0.5 -> 6.4 | I50: =H50*150 -> 960 | J50: 40-45自然日入仓
A51: MCI4 | B51: 5.9 | C51: =B51*150 -> 885 | D51: =B51 -> 5.9 | E51: =D51*150 -> 885 | F51: =B51+0.2 -> 6.1 | G51: =F51*150 -> 915 | H51: =B51+0.5 -> 6.4 | I51: =H51*150 -> 960 | J51: 40-45自然日入仓
A52: FBA美东北40日达（OA/MSC/WHL统配，靠纽约港)
A53: 区域 | B53: 东莞/中山/广州 | D53: 嘉兴/义乌 | F53: 汕头/厦门/泉州 | H53: 武汉/长沙 | J53: 参考时效(开船后)
A54: 仓库代码/起收量 | B54: 12KG+含税 | C54: 1CBM+ 不含税 | D54: 12KG+含税 | E54: 1CBM+ 不含税 | F54: 12KG+含税 | G54: 1CBM+ 不含税 | H54: 12KG+含税 | I54: 1CBM+ 不含税
A55: ABE8 | B55: 6.4 | C55: =B55*150 -> 960 | D55: =B55 -> 6.4 | E55: =D55*150 -> 960 | F55: =B55+0.2 -> 6.6 | G55: =F55*150 -> 990 | H55: =B55+0.5 -> 6.9 | I55: =H55*150 -> 1035 | J55: 40-45自然日入仓
A56: TEB9 | B56: 6.4 | C56: =B56*150 -> 960 | D56: =B56 -> 6.4 | E56: =D56*150 -> 960 | F56: =B56+0.2 -> 6.6 | G56: =F56*150 -> 990 | H56: =B56+0.5 -> 6.9 | I56: =H56*150 -> 1035 | J56: 40-45自然日入仓
A57: AVP1 | B57: 6.4 | C57: =B57*150 -> 960 | D57: =B57 -> 6.4 | E57: =D57*150 -> 960 | F57: =B57+0.2 -> 6.6 | G57: =F57*150 -> 990 | H57: =B57+0.5 -> 6.9 | I57: =H57*150 -> 1035 | J57: 40-45自然日入仓
A58: ORF2 | B58: 6.4 | C58: =B58*150 -> 960 | D58: =B58 -> 6.4 | E58: =D58*150 -> 960 | F58: =B58+0.2 -> 6.6 | G58: =F58*150 -> 990 | H58: =B58+0.5 -> 6.9 | I58: =H58*150 -> 1035 | J58: 40-45自然日入仓
A59: RMN3 | B59: 6.4 | C59: =B59*150 -> 960 | D59: =B59 -> 6.4 | E59: =D59*150 -> 960 | F59: =B59+0.2 -> 6.6 | G59: =F59*150 -> 990 | H59: =B59+0.5 -> 6.9 | I59: =H59*150 -> 1035 | J59: 40-45自然日入仓
A60: MQJ1 | B60: 6.4 | C60: =B60*150 -> 960 | D60: =B60 -> 6.4 | E60: =D60*150 -> 960 | F60: =B60+0.2 -> 6.6 | G60: =F60*150 -> 990 | H60: =B60+0.5 -> 6.9 | I60: =H60*150 -> 1035 | J60: 40-45自然日入仓
A61: RDU4 | B61: 6.4 | C61: =B61*150 -> 960 | D61: =B61 -> 6.4 | E61: =D61*150 -> 960 | F61: =B61+0.2 -> 6.6 | G61: =F61*150 -> 990 | H61: =B61+0.5 -> 6.9 | I61: =H61*150 -> 1035 | J61: 40-45自然日入仓
A62: TOL3 | B62: 6.4 | C62: =B62*150 -> 960 | D62: =B62 -> 6.4 | E62: =D62*150 -> 960 | F62: =B62+0.2 -> 6.6 | G62: =F62*150 -> 990 | H62: =B62+0.5 -> 6.9 | I62: =H62*150 -> 1035 | J62: 40-45自然日入仓
A63: 重货优惠：1：200 -0.2; 1：250 -0.5; 1：300 -0.7; 1：350 -1; 1：500 -1.5
A64: 计重标准 | B64: 重量转体积：1CBM=300KG; 体积转重量：1CBM=167KG
A65: 报关费&续页费 | B65: 报关费：RMB220, 超6个品名续页费：RMB50/页（即第7个起算，每6个品名一页）
A66: 超品名费 | B66: 每一票单超过五个品名的，收取RMB30/个
A67: 商检费 & 熏蒸费 | B67: 单询
A68: 提单费（如需） | B68: RMB300/BILL
A69: 不含税渠道进口申报要求 | B69: USD280/CBM
A70: 产品附加 | B70: +0.5 | C70: 纺织品,FDA产品,玩具,税率高于30%
B71: 木制品 无单证600/票 单证+RMB800/票
A72: 本渠道拒收产品 | B72: 仿牌、液体、粉末、食品、药品、易燃易爆、古董、货币等国家禁止出口及航空公司禁运物品
B73: 纯电池，移动电源，医疗激光产品，太阳能 （大于10*10），动植物， 化妆品，医疗类产品，铅笔，有医疗作用的牙刷
B74: 侵权产品：蓝牙标及包装有蓝牙字样及标识产品
B75: 反倾销产品：请查看附件
A76: 申报要求 | B76: 如实申报，单货一致；如有需要需如实提供每个产品对应的产品图片和有售价的真实销售链接，如新品链接没有售价，需要提供亚马逊后台定价截图；如因客户低申报或申报不符（海关编码和实物不符，数量不一致等）产生的相关查验费、仓租、调高后的税金、海关罚金需由客户承担；

Sheet 美西整柜直送
A1: =_xlfn.DISPIMG("ID_D6697A225B864C34A678052B48D4E660",1) -> =DISPIMG("ID_D6697A225B864C34A678052B48D4E660",1)
A2: 渠道名称 | B2: 美国整柜直送
A3: 船司 | B3: OA/MSC/ONE/WHL/SML船司，可能需要一周集货时间
A4: 交货仓库 | B4: 东莞/中山/广州 | D4: 嘉兴/义乌 | F4: 汕头/厦门/泉州 | H4: 武汉/长沙 | J4: 参考时效 （开船后自然日） | K4: 备注
A5: 仓库代码 | B5: 12KG+含税 | C5: 0.5CBM+不含税 | D5: 12KG+含税 | E5: 0.5CBM+不含税 | F5: 12KG+含税 | G5: 0.5CBM+不含税 | H5: 12KG+含税 | I5: 0.5CBM+不含税
A6: ONT8 | B6: 5.26 | C6: =B6*150 -> 789 | D6: =B6 -> 5.26 | E6: =D6*150 -> 789 | F6: =B6+0.2 -> 5.46 | G6: =F6*150 -> 819 | H6: =B6+0.5 -> 5.76 | I6: =H6*150 -> 864 | J6: 开船后28-30自然日入仓，无时效赔付） | K6: 此渠道出货后不接受拦截； 直送渠道，单件实重不超22.3KG，尺寸在 63.5*63.5*91厘米之内
A7: LGB8 | B7: 5.26 | C7: =B7*150 -> 789 | D7: =B7 -> 5.26 | E7: =D7*150 -> 789 | F7: =B7+0.2 -> 5.46 | G7: =F7*150 -> 819 | H7: =B7+0.5 -> 5.76 | I7: =H7*150 -> 864
A8: LAX9 | B8: 5.26 | C8: =B8*150 -> 789 | D8: =B8 -> 5.26 | E8: =D8*150 -> 789 | F8: =B8+0.2 -> 5.46 | G8: =F8*150 -> 819 | H8: =B8+0.5 -> 5.76 | I8: =H8*150 -> 864
A9: SBD1 | B9: 5.26 | C9: =B9*150 -> 789 | D9: =B9 -> 5.26 | E9: =D9*150 -> 789 | F9: =B9+0.2 -> 5.46 | G9: =F9*150 -> 819 | H9: =B9+0.5 -> 5.76 | I9: =H9*150 -> 864
A10: POC1 | B10: 5.46 | C10: =B10*150 -> 819 | D10: =B10 -> 5.46 | E10: =D10*150 -> 819 | F10: =B10+0.2 -> 5.66 | G10: =F10*150 -> 849 | H10: =B10+0.5 -> 5.96 | I10: =H10*150 -> 894
A11: POC3 | B11: 5.46 | C11: =B11*150 -> 819 | D11: =B11 -> 5.46 | E11: =D11*150 -> 819 | F11: =B11+0.2 -> 5.66 | G11: =F11*150 -> 849 | H11: =B11+0.5 -> 5.96 | I11: =H11*150 -> 894
A12: LAS1 | B12: 5.86 | C12: =B12*150 -> 879 | D12: =B12 -> 5.86 | E12: =D12*150 -> 879 | F12: =B12+0.2 -> 6.06 | G12: =F12*150 -> 909 | H12: =B12+0.5 -> 6.36 | I12: =H12*150 -> 954
A13: VGT2 | B13: 5.86 | C13: =B13*150 -> 879 | D13: =B13 -> 5.86 | E13: =D13*150 -> 879 | F13: =B13+0.2 -> 6.06 | G13: =F13*150 -> 909 | H13: =B13+0.5 -> 6.36 | I13: =H13*150 -> 954
A14: GYR2 | B14: 5.96 | C14: =B14*150 -> 894 | D14: =B14 -> 5.96 | E14: =D14*150 -> 894 | F14: =B14+0.2 -> 6.16 | G14: =F14*150 -> 924 | H14: =B14+0.5 -> 6.46 | I14: =H14*150 -> 969
A15: GYR3 | B15: 5.96 | C15: =B15*150 -> 894 | D15: =B15 -> 5.96 | E15: =D15*150 -> 894 | F15: =B15+0.2 -> 6.16 | G15: =F15*150 -> 924 | H15: =B15+0.5 -> 6.46 | I15: =H15*150 -> 969
A16: GEU2 | B16: 5.86 | C16: =B16*150 -> 879 | D16: =B16 -> 5.86 | E16: =D16*150 -> 879 | F16: =B16+0.2 -> 6.06 | G16: =F16*150 -> 909 | H16: =B16+0.5 -> 6.36 | I16: =H16*150 -> 954
A17: GEU3 | B17: 5.86 | C17: =B17*150 -> 879 | D17: =B17 -> 5.86 | E17: =D17*150 -> 879 | F17: =B17+0.2 -> 6.06 | G17: =F17*150 -> 909 | H17: =B17+0.5 -> 6.36 | I17: =H17*150 -> 954
A18: SMF3（奥克兰） | B18: 5.86 | C18: =B18*150 -> 879 | D18: =B18 -> 5.86 | E18: =D18*150 -> 879 | F18: =B18+0.2 -> 6.06 | G18: =F18*150 -> 909 | H18: =B18+0.5 -> 6.36 | I18: =H18*150 -> 954
... A20: ABQ2 | B20: 7 | C20: =B20*150 -> 1050 | D20: =B20 -> 7 | E20: =D20*150 -> 1050 | F20: =B20+0.2 -> 7.2 | G20: =F20*150 -> 1080 | H20: =B20+0.5 -> 7.5 | I20: =H20*150 -> 1125
A21: PSC2（西雅图）暂停 | B21: / | C21: / | D21: / | E21: / | F21: / | G21: / | H21: / | I21: /
A22: 重货优惠：1:200 -0.2; 1:250 -0.5，1:300 -1，1:400 -1.2 1:500 -1.5 比重减重后最低1.2/KG。
A23: 备注：本报价为人民币报价，价格适用于普货，包含头程运费、进出口买单报关费、文件费（不含出单费）、仓库卸货费、托盘费、目的港清关、派送等费用；不包含保险费、商检费、熏蒸费、因货物问题导致的进出口海关查验费、仓库增值服务费、超期费和仓储费等，如若产生，实报实销。
A24: 计重标准 | B24: 重量转体积：1CBM=334KG; 体积转重量：1CBM=167KG；托盘，木架，木箱等非纸箱货物出货，计费重需*1.1倍
A25: 报关费&续页费 | B25: 报关费：RMB220, 超6个品名续页费：RMB50/页（即第7个起算，每6个品名一页）
A26: 超品名费 | B26: 每一票单超过五个品名的，收取RMB30/个
A27: 商检费 & 熏蒸费 | B27: 单询
A28: 提单费（如需） | B28: RMB300/BILL
A29: 不含税渠道进口申报要求 | B29: 不含关税渠道，如遇国内和目的港查验，按体积比例承担相应的查验费； 不包税渠道最低申报不低于120USD/CBM；
A30: 产品附加 | B30: 箱包类、行李箱、收纳箱、包包、鞋子、服装等纺织品类、FDA申报类产品+0.5元/KG
B31: 木制品 无单证600/票 单证+RMB800/票
A32: 本渠道拒收产品 | B32: 仿牌、液体、粉末、食品、药品、易燃易爆、古董、货币等国家禁止出口及航空公司禁运物品
B33: 纯电池，移动电源，医疗激光产品，太阳能 （大于10*10），动植物， 化妆品，医疗类产品，铅笔，有医疗作用的牙刷
B34: 侵权产品：蓝牙标及包装有蓝牙字样及标识产品
B35: 反倾销产品：请查看附件
A36: 申报要求 | B36: 如实申报，单货一致；如有需要需如实提供每个产品对应的产品图片和有售价的真实销售链接，如新品链接没有售价，需要提供亚马逊后台定价截图；如因客户低申报或申报不符（海关编码和实物不符，数量不一致等）产生的相关查验费、仓租、调高后的税金、海关罚金需由客户承担.

Sheet 美国海派
A1: =_xlfn.DISPIMG("ID_D6697A225B864C34A678052B48D4E660",1) -> =DISPIMG("ID_D6697A225B864C34A678052B48D4E660",1)
A2: 下单渠道 | B2: 易·12日达海派 | J2: 易·15日达海派 | R2: 易·17日达海派
A3: 使用船司 | B3: 美森正班CLX | J3: 美森正班CLX | R3: EXX/以星带托架/合德快提统配
A4: 交货仓库 | B4: 东莞/中山/广州 | D4: 嘉兴/义乌 | F4: 汕头/厦门/泉州 | H4: 武汉/长沙 | J4: 东莞/中山/广州 | L4: 嘉兴/义乌 | N4: 汕头/厦门/泉州 | P4: 武汉/长沙 | R4: 东莞/中山/广州 | T4: 嘉兴/义乌 | V4: 汕头/厦门/泉州 | X4: 武汉/长沙
A5: 邮编分区/起收量 | B5: 12-50KG | C5: 50KG+ | D5: 12-50KG | E5: 50KG+ | F5: 12-50KG | G5: 50KG+ | H5: 12-50KG | I5: 50KG+ | J5: 12-50KG | K5: 50KG+ | L5: 12-50KG | M5: 50KG+ | N5: 12-50KG | O5: 50KG+ | P5: 12-50KG | Q5: 50KG+ | R5: 12-50KG | S5: 50KG+ | T5: 12-50KG | U5: 50KG+ | V5: 12-50KG | W5: 50KG+ | X5: 12-50KG | Y5: 50KG+
A6: 美国西岸(邮编8,9开头) | B6: 21.1 | C6: 18.1 | D6: 20.6 | E6: 17.6 | F6: 21.3 | G6: 18.3 | H6: 21.6 | I6: 18.6 | J6: 18.1 | K6: 15.1 | L6: 17.6 | M6: 14.6 | N6: 18.3 | O6: 15.3 | P6: 18.6 | Q6: 15.6 | R6: 14.5 | S6: 11.5 | T6: 14.5 | U6: 11.5 | V6: 14.7 | W6: 11.7 | X6: 15 | Y6: 12
A7: 美国中部(邮编4,5,6,7开头) | B7: 22.6 | C7: 19.6 | D7: 22.1 | E7: 19.1 | F7: 22.8 | G7: 19.8 | H7: 23.1 | I7: 20.1 | J7: 19.6 | K7: 16.6 | L7: 19.1 | M7: 16.1 | N7: 19.8 | O7: 16.8 | P7: 20.1 | Q7: 17.1 | R7: 16 | S7: 13 | T7: 16 | U7: 13 | V7: 16.2 | W7: 13.2 | X7: 16.5 | Y7: 13.5
A8: 美国东岸(邮编0,1,2,3开头) | B8: 23.6 | C8: 20.6 | D8: 23.1 | E8: 20.1 | F8: 23.8 | G8: 20.8 | H8: 24.1 | I8: 21.1 | J8: 20.6 | K8: 17.6 | L8: 20.1 | M8: 17.1 | N8: 20.8 | O8: 17.8 | P8: 21.1 | Q8: 18.1 | R8: 17.5 | S8: 14 | T8: 17.5 | U8: 14 | V8: 17.7 | W8: 14.2 | X8: 18 | Y8: 14.5
A9: 参考时效 | B9: 开船后第二天起算12-13天提取，超13天（不含)不提取，每个工作日赔1.5元/KG，时效延误最高赔偿6/KG | J9: 开船后13-16天提取，超过17天不提取，每个工作日赔0.5元/kg，直到运费抵完。 | R9: 开船后16-19天提取，超过20天不提取，每个工作日赔0.5元/kg，直到运费抵完。
A10: 下单渠道 | B10: 易·20日达海派 | J10: 易·22日达海派 | R10: 易·25日达海派
A11: 使用船司 | B11: 以星不带托架/合德普提/SEA3/CEN | J11: COSCO/OA | R11: OA/MSC/ONE/WHL/HMM/TSL普船统配
A12: 交货仓库 | B12: 东莞/中山/广州 | D12: 嘉兴/义乌 | F12: 汕头/厦门/泉州 | H12: 武汉/长沙 | J12: 东莞/中山/广州 | L12: 嘉兴/义乌 | N12: 汕头/厦门/泉州 | P12: 武汉/长沙 | R12: 东莞/中山/广州 | T12: 嘉兴/义乌 | V12: 汕头/厦门/泉州 | X12: 武汉/长沙
A13: 邮编分区/起收量 | B13: 12-50KG | C13: 50KG+ | D13: 12-50KG | E13: 50KG+ | F13: 12-50KG | G13: 50KG+ | H13: 12-50KG | I13: 50KG+ | J13: 12-50KG | K13: 50KG+ | L13: 12-50KG | M13: 50KG+ | N13: 12-50KG | O13: 50KG+ | P13: 12-50KG | Q13: 50KG+ | R13: 12-50KG | S13: 50KG+ | T13: 12-50KG | U13: 50KG+ | V13: 12-50KG | W13: 50KG+ | X13: 12-50KG | Y13: 50KG+
A14: 美国西岸(邮编8,9开头) | B14: 14 | C14: 11 | D14: 14 | E14: 11 | F14: 14.2 | G14: 11.2 | H14: 14.5 | I14: 11.5 | J14: 13 | K14: 10 | L14: 13 | M14: 10 | N14: 13.2 | O14: 10.2 | P14: 13.5 | Q14: 10.5 | R14: 12.6 | S14: 9.6 | T14: 12.8 | U14: 9.8 | V14: 13 | W14: 10 | X14: 13.3 | Y14: 10.3
A15: 美国中部(邮编4,5,6,7开头) | B15: 15.5 | C15: 12.5 | D15: 15.5 | E15: 12.5 | F15: 15.7 | G15: 12.7 | H15: 16 | I15: 13 | J15: 14.5 | K15: 11.5 | L15: 14.5 | M15: 11.5 | N15: 14.7 | O15: 11.7 | P15: 15 | Q15: 12 | R15: 14.1 | S15: 11.1 | T15: 14.3 | U15: 11.3 | V15: 14.5 | W15: 11.5 | X15: 14.8 | Y15: 11.8
A16: 美国东岸(邮编0,1,2,3开头) | B16: 16.5 | C16: 13.5 | D16: 16.5 | E16: 13.5 | F16: 16.7 | G16: 13.7 | H16: 17 | I16: 14 | J16: 15.5 | K16: 12.5 | L16: 15.5 | M16: 12.5 | N16: 15.7 | O16: 12.7 | P16: 16 | Q16: 13 | R16: 15.1 | S16: 12.1 | T16: 15.3 | U16: 12.3 | V16: 15.5 | W16: 12.5 | X16: 15.8 | Y16: 12.8
A17: 参考时效 | B17: 开船后18-21天提取，超过22天不提取，每个工作日赔0.5元/kg，直到运费抵完。 | J17: 开船后20-25天内提取，超过26天不提取，每个工作日赔0.5元/kg，直到运费抵完。 | R17: 开船后26-30天左右提取， 统配渠道无时效赔付
A18: 重货优惠：1:200 -0.2; 1:250 -0.5，1:300 -1，1:400 -1.5，1:500 -2比重减重后最低1.2/KG。
A19: 备注：本报价为人民币报价，价格适用于普货，包含头程运费、进出口买单报关费、文件费（不含出单费）、仓库卸货费、托盘费、目的港清关、派送等费用；不包含保险费、商检费、熏蒸费、因货物问题导致的进出口海关查验费、仓库增值服务费、超期费和仓储费等，如若产生，实报实销。
A20: UPS附加费用如下：
A21: 1.单件计费重量不得低于12KG，单件重量低于12KG按照12KG计费；货物重量的计算方式：长*宽*高CM/6000，实重与材积重取大值为计费重；
A22: 2.单边超120CM，第二长边超76CM，围长需在265CM≤（1长+2宽+2高）范围内 | N22: 加收180元/件，如多项超过需叠加
A23: 3.超长：265CM＜ 长+[2*(宽+高)]≤ 315CM | N23: 加收180元/件
A24: 4.超重：22KG＜实际重量＜40KG | N24: 加收235元/件
A25: 5.单件40KG以上，单边超230CM，或周长超315CM | N25: 拒收
A26: 6.私人地址和商业地址（非亚马逊地址） | N26: 加收1元/KG
A27: 7.私人住宅地址 | N27: 加收50元/箱
A28: 8.UPS偏远地区另需加收偏远费， UPS私人地址:UPS偏远RMB40/件，超偏远45/件。 | N28: 偏远加收40元/箱，超级偏远加45/箱 （如同时为私人地址费用将叠加收取）
A29: 9.提供UPS签收单 | N29: RMB35/件
A30: 10.如我司以打单的情况下更换派送方式以及退货，我司收取删单费 | N30: 1USD/件，最低消费100RMB/票
A31: 11.打单后退货需收操作费，如已装柜不接受退件 | N31: 加收100元/票
A32: 地址派送范围仅限于美国48洲,邮箱BOX,军方地址不收,及各岛屿美国不收、不接收邮编：006-009 PUERTO RICO AND VIRGIN LSLANDS 波多黎各、维尔京群岛，966-969 HAWAIIAND GUAM 夏威夷、关岛 995-999 ALASKA 阿拉斯加等！) | N32: 无服务地址
A33: 超品名费 | N33: 每一票单超过五个品名的，收取RMB30/个
A34: 产品附加 | E34: 箱包类、行李箱、收纳箱、包包、鞋子、服装等纺织品类、FDA申报类产品+0.5元/KG
E35: 木制品 无单证600/票 单证+RMB800/票
A36: 本渠道拒收产品 | E36: 仿牌、液体、粉末、食品、药品、易燃易爆、古董、货币等国家禁止出口及航空公司禁运物品
E37: 纯电池，移动电源，激光产品，太阳能 （大于10*10），动植物， 化妆品，医疗类产品，铅笔，有医疗作用的牙刷
E38: 侵权产品：蓝牙标及包装有蓝牙字样及标识产品
E39: 反倾销产品：请查看附件
A40: 申报要求 | E40: 如实申报，单货一致；如有需要需如实提供每个产品对应的产品图片和有售价的真实销售链接，如新品链接没有售价，需要提供亚马逊后台定价截图；如因客户低申报或申报不符（海关编码和实物不符，数量不一致等）产生的相关查验费、仓租、调高后的税金、海关罚金需由客户承担；

Sheet 美西12-15日达
A1: =_xlfn.DISPIMG("ID_D6697A225B864C34A678052B48D4E660",1) -> =DISPIMG("ID_D6697A225B864C34A678052B48D4E660",1)
A2: 渠道名称 | B2: 易·12日达卡派 | H2: 易·15日达卡派
A3: 使用船司 | B3: 美森正班CLX | H3: 美森正班CLX
A4: 交货仓库 | B4: 东莞/中山/广州 | C4: 嘉兴/义乌 | D4: 汕头/厦门/泉州 | E4: 武汉/长沙 | F4: 参考时效 （开船后自然日） | G4: 理赔时效 以工作日计赔付 1元/kg 最高赔偿5元/KG | H4: 东莞/中山/广州 | J4: 嘉兴/义乌 | L4: 汕头/厦门/泉州 | N4: 武汉/长沙 | P4: 参考时效 （开船后自然日） | Q4: 理赔时效 以工作日计赔付 0.5元/kg
A5: 仓库代码 | B5: 12KG+含税 | C5: 12KG+含税 | D5: 12KG+含税 | E5: 12KG+含税 | H5: 12KG+含税 | I5: 0.5CBM+不含税 | J5: 12KG+含税 | K5: 0.5CBM+不含税 | L5: 12KG+含税 | M5: 0.5CBM+不含税 | N5: 12KG+含税 | O5: 0.5CBM+不含税
A6: 海外仓自提 一件代发头程 | B6: 13.9 | C6: =B6-0.5 -> 13.4 | D6: =B6+0.2 -> 14.1 | E6: =B6+0.5 -> 14.4 | F6: 12自然日 | G6: 超13自然日 | H6: 10.9 | I6: =H6*165 -> 1798.5 | J6: =H6-0.5 -> 10.4 | K6: =J6*165 -> 1716 | L6: =H6+0.2 -> 11.1 | M6: =L6*165 -> 1831.5 | N6: =H6+0.5 -> 11.4 | O6: =N6*165 -> 1881 | P6: 13-15 | Q6: 超16自然日
A7: ONT8 | B7: 13.9 | C7: =B7-0.5 -> 13.4 | D7: =B7+0.2 -> 14.1 | E7: =B7+0.5 -> 14.4 | F7: 12自然日 | G7: 超13自然日 | H7: 10.9 | I7: =H7*165 -> 1798.5 | J7: =H7-0.5 -> 10.4 | K7: =J7*165 -> 1716 | L7: =H7+0.2 -> 11.1 | M7: =L7*165 -> 1831.5 | N7: =H7+0.5 -> 11.4 | O7: =N7*165 -> 1881 | P7: 13-15 | Q7: 超16自然日
A8: LGB8 | B8: 13.9 | C8: =B8-0.5 -> 13.4 | D8: =B8+0.2 -> 14.1 | E8: =B8+0.5 -> 14.4 | F8: 12自然日 | G8: 超13自然日 | H8: 10.9 | I8: =H8*165 -> 1798.5 | J8: =H8-0.5 -> 10.4 | K8: =J8*165 -> 1716 | L8: =H8+0.2 -> 11.1 | M8: =L8*165 -> 1831.5 | N8: =H8+0.5 -> 11.4 | O8: =N8*165 -> 1881 | P8: 13-15 | Q8: 超16自然日
A9: LAX9 | B9: 13.9 | C9: =B9-0.5 -> 13.4 | D9: =B9+0.2 -> 14.1 | E9: =B9+0.5 -> 14.4 | F9: 12自然日 | G9: 超13自然日 | H9: 10.9 | I9: =H9*165 -> 1798.5 | J9: =H9-0.5 -> 10.4 | K9: =J9*165 -> 1716 | L9: =H9+0.2 -> 11.1 | M9: =L9*165 -> 1831.5 | N9: =H9+0.5 -> 11.4 | O9: =N9*165 -> 1881 | P9: 13-15 | Q9: 超16自然日
A10: SBD1 | B10: 13.9 | C10: =B10-0.5 -> 13.4 | D10: =B10+0.2 -> 14.1 | E10: =B10+0.5 -> 14.4 | F10: 12自然日 | G10: 超13自然日 | H10: 10.9 | I10: =H10*165 -> 1798.5 | J10: =H10-0.5 -> 10.4 | K10: =J10*165 -> 1716 | L10: =H10+0.2 -> 11.1 | M10: =L10*165 -> 1831.5 | N10: =H10+0.5 -> 11.4 | O10: =N10*165 -> 1881 | P10: 13-15 | Q10: 超16自然日
A11: PSP3 | B11: - | C11: - | D11: - | E11: - | F11: - | G11: - | H11: 11.2 | I11: =H11*165 -> 1848 | J11: =H11-0.5 -> 10.7 | K11: =J11*165 -> 1765.5 | L11: =H11+0.2 -> 11.4 | M11: =L11*165 -> 1881 | N11: =H11+0.5 -> 11.7 | O11: =N11*165 -> 1930.5 | P11: 14-16 | Q11: -
A12: POC1 | B12: - | C12: - | D12: - | E12: - | F12: - | G12: - | H12: 11.2 | I12: =H12*165 -> 1848 | J12: =H12-0.5 -> 10.7 | K12: =J12*165 -> 1765.5 | L12: =H12+0.2 -> 11.4 | M12: =L12*165 -> 1881 | N12: =H12+0.5 -> 11.7 | O12: =N12*165 -> 1930.5 | P12: 14-16 | Q12: -
A13: POC2 | B13: - | C13: - | D13: - | E13: - | F13: - | G13: - | H13: 11.2 | I13: =H13*165 -> 1848 | J13: =H13-0.5 -> 10.7 | K13: =J13*165 -> 1765.5 | L13: =H13+0.2 -> 11.4 | M13: =L13*165 -> 1881 | N13: =H13+0.5 -> 11.7 | O13: =N13*165 -> 1930.5 | P13: 14-16 | Q13: -
A14: POC3 | B14: - | C14: - | D14: - | E14: - | F14: - | G14: - | H14: 11.2 | I14: =H14*165 -> 1848 | J14: =H14-0.5 -> 10.7 | K14: =J14*165 -> 1765.5 | L14: =H14+0.2 -> 11.4 | M14: =L14*165 -> 1881 | N14: =H14+0.5 -> 11.7 | O14: =N14*165 -> 1930.5 | P14: 14-16 | Q14: -
A15: LAX2T(沃尔玛) | B15: - | C15: - | D15: - | E15: - | F15: - | G15: - | H15: 11.2 | I15: =H15*165 -> 1848 | J15: =H15-0.5 -> 10.7 | K15: =J15*165 -> 1765.5 | L15: =H15+0.2 -> 11.4 | M15: =L15*165 -> 1881 | N15: =H15+0.5 -> 11.7 | O15: =N15*165 -> 1930.5 | P15: 14-16 | Q15: -
A16: IUSP | B16: - | C16: - | D16: - | E16: - | F16: - | G16: - | H16: 11.2 | I16: =H16*165 -> 1848 | J16: =H16-0.5 -> 10.7 | K16: =J16*165 -> 1765.5 | L16: =H16+0.2 -> 11.4 | M16: =L16*165 -> 1881 | N16: =H16+0.5 -> 11.7 | O16: =N16*165 -> 1930.5 | P16: 14-16 | Q16: -
A17: IUSJ | B17: - | C17: - | D17: - | E17: - | F17: - | G17: - | H17: 11.2 | I17: =H17*165 -> 1848 | J17: =H17-0.5 -> 10.7 | K17: =J17*165 -> 1765.5 | L17: =H17+0.2 -> 11.4 | M17: =L17*165 -> 1881 | N17: =H17+0.5 -> 11.7 | O17: =N17*165 -> 1930.5 | P17: 14-16 | Q17: -
A18: IUTI | B18: - | C18: - | D18: - | E18: - | F18: - | G18: - | H18: 11.2 | I18: =H18*165 -> 1848 | J18: =H18-0.5 -> 10.7 | K18: =J18*165 -> 1765.5 | L18: =H18+0.2 -> 11.4 | M18: =L18*165 -> 1881 | N18: =H18+0.5 -> 11.7 | O18: =N18*165 -> 1930.5 | P18: 14-16 | Q18: -
A19: IUSW | B19: - | C19: - | D19: - | E19: - | F19: - | G19: - | H19: 11.2 | I19: =H19*165 -> 1848 | J19: =H19-0.5 -> 10.7 | K19: =J19*165 -> 1765.5 | L19: =H19+0.2 -> 11.4 | M19: =L19*165 -> 1881 | N19: =H19+0.5 -> 11.7 | O19: =N19*165 -> 1930.5 | P19: 14-16 | Q19: -
A20: SNA4 | B20: - | C20: - | D20: - | E20: - | F20: - | G20: - | H20: 11.6 | I20: =H20*165 -> 1914 | J20: =H20-0.5 -> 11.1 | K20: =J20*165 -> 1831.5 | L20: =H20+0.2 -> 11.8 | M20: =L20*165 -> 1947 | N20: =H20+0.5 -> 12.1 | O20: =N20*165 -> 1996.5 | P20: 15-17 | Q20: -
A21: XLX7 | B21: - | C21: - | D21: - | E21: - | F21: - | G21: - | H21: 11.6 | I21: =H21*165 -> 1914 | J21: =H21-0.5 -> 11.1 | K21: =J21*165 -> 1831.5 | L21: =H21+0.2 -> 11.8 | M21: =L21*165 -> 1947 | N21: =H21+0.5 -> 12.1 | O21: =N21*165 -> 1996.5 | P21: 15-17 | Q21: -
A22: LAS1 | B22: - | C22: - | D22: - | E22: - | F22: - | G22: - | H22: 11.6 | I22: =H22*165 -> 1914 | J22: =H22-0.5 -> 11.1 | K22: =J22*165 -> 1831.5 | L22: =H22+0.2 -> 11.8 | M22: =L22*165 -> 1947 | N22: =H22+0.5 -> 12.1 | O22: =N22*165 -> 1996.5 | P22: 15-17 | Q22: -
A23: VGT2 | B23: - | C23: - | D23: - | E23: - | F23: - | G23: - | H23: 11.6 | I23: =H23*165 -> 1914 | J23: =H23-0.5 -> 11.1 | K23: =J23*165 -> 1831.5 | L23: =H23+0.2 -> 11.8 | M23: =L23*165 -> 1947 | N23: =H23+0.5 -> 12.1 | O23: =N23*165 -> 1996.5 | P23: 15-17 | Q23: -
A24: SMF3 | H24: 11.6 | I24: =H24*165 -> 1914 | J24: =H24-0.5 -> 11.1 | K24: =J24*165 -> 1831.5 | L24: =H24+0.2 -> 11.8 | M24: =L24*165 -> 1947 | N24: =H24+0.5 -> 12.1 | O24: =N24*165 -> 1996.5 | P24: 15-17 | Q24: 超21自然日
A25: SCK4 | B25: - | C25: - | D25: - | E25: - | F25: - | G25: - | H25: 11.6 | I25: =H25*165 -> 1914 | J25: =H25-0.5 -> 11.1 | K25: =J25*165 -> 1831.5 | L25: =H25+0.2 -> 11.8 | M25: =L25*165 -> 1947 | N25: =H25+0.5 -> 12.1 | O25: =N25*165 -> 1996.5 | P25: 15-17 | Q25: 超21自然日
A26: GEU2 | B26: - | C26: - | D26: - | E26: - | F26: - | G26: - | H26: 11.6 | I26: =H26*165 -> 1914 | J26: =H26-0.5 -> 11.1 | K26: =J26*165 -> 1831.5 | L26: =H26+0.2 -> 11.8 | M26: =L26*165 -> 1947 | N26: =H26+0.5 -> 12.1 | O26: =N26*165 -> 1996.5 | P26: 15-17 | Q26: 超21自然日
A27: GEU3 | B27: - | C27: - | D27: - | E27: - | F27: - | G27: - | H27: 11.6 | I27: =H27*165 -> 1914 | J27: =H27-0.5 -> 11.1 | K27: =J27*165 -> 1831.5 | L27: =H27+0.2 -> 11.8 | M27: =L27*165 -> 1947 | N27: =H27+0.5 -> 12.1 | O27: =N27*165 -> 1996.5 | P27: 15-17 | Q27: 超21自然日
A28: GYR2 | B28: - | C28: - | D28: - | E28: - | F28: - | G28: - | H28: 11.6 | I28: =H28*165 -> 1914 | J28: =H28-0.5 -> 11.1 | K28: =J28*165 -> 1831.5 | L28: =H28+0.2 -> 11.8 | M28: =L28*165 -> 1947 | N28: =H28+0.5 -> 12.1 | O28: =N28*165 -> 1996.5 | P28: 15-17 | Q28: 超21自然日
A29: GYR3 | B29: - | C29: - | D29: - | E29: - | F29: - | G29: - | H29: 11.6 | I29: =H29*165 -> 1914 | J29: =H29-0.5 -> 11.1 | K29: =J29*165 -> 1831.5 | L29: =H29+0.2 -> 11.8 | M29: =L29*165 -> 1947 | N29: =H29+0.5 -> 12.1 | O29: =N29*165 -> 1996.5 | P29: 15-17 | Q29: 超21自然日
A30: MIT2 | B30: - | C30: - | D30: - | E30: - | F30: - | G30: - | H30: 11.6 | I30: =H30*165 -> 1914 | J30: =H30-0.5 -> 11.1 | K30: =J30*165 -> 1831.5 | L30: =H30+0.2 -> 11.8 | M30: =L30*165 -> 1947 | N30: =H30+0.5 -> 12.1 | O30: =N30*165 -> 1996.5 | P30: 15-18 | Q30: -
A31: QZZ7 | B31: - | C31: - | D31: - | E31: - | F31: - | G31: - | H31: 11.6 | I31: =H31*165 -> 1914 | J31: =H31-0.5 -> 11.1 | K31: =J31*165 -> 1831.5 | L31: =H31+0.2 -> 11.8 | M31: =L31*165 -> 1947 | N31: =H31+0.5 -> 12.1 | O31: =N31*165 -> 1996.5 | P31: 15-18 | Q31: -
A32: TCY1 | B32: - | C32: - | D32: - | E32: - | F32: - | G32: - | H32: 11.9 | I32: =H32*165 -> 1963.5 | J32: =H32-0.5 -> 11.4 | K32: =J32*165 -> 1881 | L32: =H32+0.2 -> 12.1 | M32: =L32*165 -> 1996.5 | N32: =H32+0.5 -> 12.4 | O32: =N32*165 -> 2046 | P32: 15-18 | Q32: -
A33: TCY2 | B33: - | C33: - | D33: - | E33: - | F33: - | G33: - | H33: 11.9 | I33: =H33*165 -> 1963.5 | J33: =H33-0.5 -> 11.4 | K33: =J33*165 -> 1881 | L33: =H33+0.2 -> 12.1 | M33: =L33*165 -> 1996.5 | N33: =H33+0.5 -> 12.4 | O33: =N33*165 -> 2046 | P33: 15-17 | Q33: -
A34: HLI2 | B34: - | C34: - | D34: - | E34: - | F34: - | G34: - | H34: 11.9 | I34: =H34*165 -> 1963.5 | J34: =H34-0.5 -> 11.4 | K34: =J34*165 -> 1881 | L34: =H34+0.2 -> 12.1 | M34: =L34*165 -> 1996.5 | N34: =H34+0.5 -> 12.4 | O34: =N34*165 -> 2046 | P34: 15-18 | Q34: -
A35: QXY8 | B35: - | C35: - | D35: - | E35: - | F35: - | G35: - | H35: 11.9 | I35: =H35*165 -> 1963.5 | J35: =H35-0.5 -> 11.4 | K35: =J35*165 -> 1881 | L35: =H35+0.2 -> 12.1 | M35: =L35*165 -> 1996.5 | N35: =H35+0.5 -> 12.4 | O35: =N35*165 -> 2046 | P35: 15-18 | Q35: -
A36: IUTE | B36: - | C36: - | D36: - | E36: - | F36: - | G36: - | H36: 11.9 | I36: =H36*165 -> 1963.5 | J36: =H36-0.5 -> 11.4 | K36: =J36*165 -> 1881 | L36: =H36+0.2 -> 12.1 | M36: =L36*165 -> 1996.5 | N36: =H36+0.5 -> 12.4 | O36: =N36*165 -> 2046 | P36: 15-18 | Q36: -
... A76: ORF2 | B76: - | C76: - | D76: - | E76: - | F76: - | G76: - | H76: 14.7 | I76: =H76*165 -> 2425.5 | J76: =H76-0.5 -> 14.2 | K76: =J76*165 -> 2343 | L76: =H76+0.2 -> 14.9 | M76: =L76*165 -> 2458.5 | N76: =H76+0.5 -> 15.2 | O76: =N76*165 -> 2508 | P76: 22-27 | Q76: -
A77: 重货优惠：1：185-0.2 1：200-0.5 1：250-0.9 1：300-1.5 1.500-2比重减重后最低1.2/KG。
A78: 备注：本报价为人民币报价，价格适用于普货，包含头程运费、进出口买单报关费、文件费（不含出单费）、仓库卸货费、托盘费、目的港清关、派送等费用；不包含保险费、商检费、熏蒸费、因货物问题导致的进出口海关查验费、仓库增值服务费、超期费和仓储费等，如若产生，实报实销。
A79: 计重标准 | C79: 重量转体积：1CBM=334KG; 体积转重量：1CBM=167KG；托盘，木架，木箱等非纸箱货物出货，计费重需*1.1倍
A80: 报关费&续页费 | C80: 报关费：RMB220, 超6个品名续页费：RMB50/页（即第7个起算，每6个品名一页）
A81: 超长附加费 | C81: 超过120-150CM附加费：+ RMB150/CBM(不含税)OR 1.2/KGS(含税), 超过150-200CM附加费：+ RMB200/CBM(不含税)OR 1.5/KGS(含税), 最长边限2米以内，超过2米以上或超重则需要case by case确认价格
A82: 超品名费 | C82: 每一票单超过五个品名的，收取RMB30/个
A83: 商检费 & 熏蒸费 | C83: 单询
A84: 提单费（如需） | C84: RMB300/BILL
A85: 不含税渠道进口申报要求 | C85: USD180/CBM
A86: 产品附加 | C86: 箱包类、行李箱、收纳箱、包包、鞋子、服装等纺织品类、FDA申报类产品+0.5元/KG
C87: 木制品 无单证600/票 单证+RMB800/票
A88: 本渠道拒收产品 | C88: 仿牌、液体、粉末、食品、药品、易燃易爆、古董、货币等国家禁止出口及航空公司禁运物品
C89: 纯电池，移动电源，医疗激光产品，太阳能 （大于10*10），动植物， 化妆品，医疗类产品，铅笔，有医疗作用的牙刷
C90: 侵权产品：蓝牙标及包装有蓝牙字样及标识产品
C91: 反倾销产品：请查看附件
A92: 申报要求 | C92: 如实申报，单货一致；如有需要需如实提供每个产品对应的产品图片和有售价的真实销售链接，如新品链接没有售价，需要提供亚马逊后台定价截图；如因客户低申报或申报不符（海关编码和实物不符，数量不一致等）产生的相关查验费、仓租、调高后的税金、海关罚金需由客户承担；

Sheet 美西17-20日达
A1: =_xlfn.DISPIMG("ID_D6697A225B864C34A678052B48D4E660",1) -> =DISPIMG("ID_D6697A225B864C34A678052B48D4E660",1)
A2: 渠道名称 | B2: 易·17日达卡派 | L2: 易·20日达卡派
A3: 使用船司 | B3: EXX/以星带托架/合德快提统配（不接受指定船司） | L3: 以星不带托架/合德普提/SEA3定提/CEN（不接受指定船司）
A4: 交货仓库 | B4: 东莞/中山/广州 | D4: 嘉兴/义乌 | F4: 汕头/厦门/泉州 | H4: 武汉/长沙 | J4: 参考时效 （开船后自然日） | K4: 理赔时效 以工作日计赔付 0.5元/kg | L4: 东莞/中山/广州 | N4: 嘉兴/义乌 | P4: 汕头/厦门/泉州 | R4: 武汉/长沙 | T4: 参考时效 （开船后自然日） | U4: 理赔时效 以工作日计赔付 0.5元/kg
A5: 仓库代码 | B5: 12KG+含税 | C5: 0.5CBM+不含税 | D5: 12KG+含税 | E5: 0.5CBM+不含税 | F5: 12KG+含税 | G5: 0.5CBM+不含税 | H5: 12KG+含税 | I5: 0.5CBM+不含税 | L5: 12KG+含税 | M5: 0.5CBM+不含税 | N5: 12KG+含税 | O5: 0.5CBM+不含税 | P5: 12KG+含税 | Q5: 0.5CBM+不含税 | R5: 12KG+含税 | S5: 0.5CBM+不含税
A6: 海外仓自提 一件代发头程 | B6: 7.1 | C6: =B6*165 -> 1171.5 | D6: =B6 -> 7.1 | E6: =D6*165 -> 1171.5 | F6: =B6+0.2 -> 7.3 | G6: =F6*165 -> 1204.5 | H6: =B6+0.5 -> 7.6 | I6: =H6*165 -> 1254 | J6: 15-18 | K6: 超20自然日 | L6: 6.5 | M6: =L6*165 -> 1072.5 | N6: =L6 -> 6.5 | O6: =N6*165 -> 1072.5 | P6: =L6+0.2 -> 6.7 | Q6: =P6*165 -> 1105.5 | R6: =L6+0.5 -> 7 | S6: =R6*165 -> 1155 | T6: 17-20 | U6: 超23自然日
A7: ONT8 | B7: 7.1 | C7: =B7*165 -> 1171.5 | D7: =B7 -> 7.1 | E7: =D7*165 -> 1171.5 | F7: =B7+0.2 -> 7.3 | G7: =F7*165 -> 1204.5 | H7: =B7+0.5 -> 7.6 | I7: =H7*165 -> 1254 | J7: 15-18 | K7: 超20自然日 | L7: 6.5 | M7: =L7*165 -> 1072.5 | N7: =L7 -> 6.5 | O7: =N7*165 -> 1072.5 | P7: =L7+0.2 -> 6.7 | Q7: =P7*165 -> 1105.5 | R7: =L7+0.5 -> 7 | S7: =R7*165 -> 1155 | T7: 17-20 | U7: 超23自然日
A8: LGB8 | B8: 7.1 | C8: =B8*165 -> 1171.5 | D8: =B8 -> 7.1 | E8: =D8*165 -> 1171.5 | F8: =B8+0.2 -> 7.3 | G8: =F8*165 -> 1204.5 | H8: =B8+0.5 -> 7.6 | I8: =H8*165 -> 1254 | J8: 15-18 | K8: 超20自然日 | L8: 6.5 | M8: =L8*165 -> 1072.5 | N8: =L8 -> 6.5 | O8: =N8*165 -> 1072.5 | P8: =L8+0.2 -> 6.7 | Q8: =P8*165 -> 1105.5 | R8: =L8+0.5 -> 7 | S8: =R8*165 -> 1155 | T8: 17-20 | U8: 超23自然日
A9: LAX9 | B9: 7.1 | C9: =B9*165 -> 1171.5 | D9: =B9 -> 7.1 | E9: =D9*165 -> 1171.5 | F9: =B9+0.2 -> 7.3 | G9: =F9*165 -> 1204.5 | H9: =B9+0.5 -> 7.6 | I9: =H9*165 -> 1254 | J9: 15-18 | K9: 超20自然日 | L9: 6.5 | M9: =L9*165 -> 1072.5 | N9: =L9 -> 6.5 | O9: =N9*165 -> 1072.5 | P9: =L9+0.2 -> 6.7 | Q9: =P9*165 -> 1105.5 | R9: =L9+0.5 -> 7 | S9: =R9*165 -> 1155 | T9: 17-20 | U9: 超23自然日
A10: SBD1 | B10: 7.1 | C10: =B10*165 -> 1171.5 | D10: =B10 -> 7.1 | E10: =D10*165 -> 1171.5 | F10: =B10+0.2 -> 7.3 | G10: =F10*165 -> 1204.5 | H10: =B10+0.5 -> 7.6 | I10: =H10*165 -> 1254 | J10: 15-18 | K10: 超20自然日 | L10: 6.5 | M10: =L10*165 -> 1072.5 | N10: =L10 -> 6.5 | O10: =N10*165 -> 1072.5 | P10: =L10+0.2 -> 6.7 | Q10: =P10*165 -> 1105.5 | R10: =L10+0.5 -> 7 | S10: =R10*165 -> 1155 | T10: 17-20 | U10: 超23自然日
A11: PSP3 | B11: 7.1 | C11: =B11*165 -> 1171.5 | D11: =B11 -> 7.1 | E11: =D11*165 -> 1171.5 | F11: =B11+0.2 -> 7.3 | G11: =F11*165 -> 1204.5 | H11: =B11+0.5 -> 7.6 | I11: =H11*165 -> 1254 | J11: 15-18 | K11: - | L11: 6.5 | M11: =L11*165 -> 1072.5 | N11: =L11 -> 6.5 | O11: =N11*165 -> 1072.5 | P11: =L11+0.2 -> 6.7 | Q11: =P11*165 -> 1105.5 | R11: =L11+0.5 -> 7 | S11: =R11*165 -> 1155 | T11: 17-20 | U11: -
A12: POC1 | B12: 7.1 | C12: =B12*165 -> 1171.5 | D12: =B12 -> 7.1 | E12: =D12*165 -> 1171.5 | F12: =B12+0.2 -> 7.3 | G12: =F12*165 -> 1204.5 | H12: =B12+0.5 -> 7.6 | I12: =H12*165 -> 1254 | J12: 15-18 | K12: - | L12: 6.5 | M12: =L12*165 -> 1072.5 | N12: =L12 -> 6.5 | O12: =N12*165 -> 1072.5 | P12: =L12+0.2 -> 6.7 | Q12: =P12*165 -> 1105.5 | R12: =L12+0.5 -> 7 | S12: =R12*165 -> 1155 | T12: 17-20 | U12: -
A13: POC2 | B13: 7.1 | C13: =B13*165 -> 1171.5 | D13: =B13 -> 7.1 | E13: =D13*165 -> 1171.5 | F13: =B13+0.2 -> 7.3 | G13: =F13*165 -> 1204.5 | H13: =B13+0.5 -> 7.6 | I13: =H13*165 -> 1254 | J13: 15-18 | K13: - | L13: 6.5 | M13: =L13*165 -> 1072.5 | N13: =L13 -> 6.5 | O13: =N13*165 -> 1072.5 | P13: =L13+0.2 -> 6.7 | Q13: =P13*165 -> 1105.5 | R13: =L13+0.5 -> 7 | S13: =R13*165 -> 1155 | T13: 17-20 | U13: -
A14: POC3 | B14: 7.1 | C14: =B14*165 -> 1171.5 | D14: =B14 -> 7.1 | E14: =D14*165 -> 1171.5 | F14: =B14+0.2 -> 7.3 | G14: =F14*165 -> 1204.5 | H14: =B14+0.5 -> 7.6 | I14: =H14*165 -> 1254 | J14: 15-18 | K14: - | L14: 6.5 | M14: =L14*165 -> 1072.5 | N14: =L14 -> 6.5 | O14: =N14*165 -> 1072.5 | P14: =L14+0.2 -> 6.7 | Q14: =P14*165 -> 1105.5 | R14: =L14+0.5 -> 7 | S14: =R14*165 -> 1155 | T14: 17-20 | U14: -
A15: LAX2T(沃尔玛) | B15: 7.1 | C15: =B15*165 -> 1171.5 | D15: =B15 -> 7.1 | E15: =D15*165 -> 1171.5 | F15: =B15+0.2 -> 7.3 | G15: =F15*165 -> 1204.5 | H15: =B15+0.5 -> 7.6 | I15: =H15*165 -> 1254 | J15: 15-18 | K15: - | L15: 6.5 | M15: =L15*165 -> 1072.5 | N15: =L15 -> 6.5 | O15: =N15*165 -> 1072.5 | P15: =L15+0.2 -> 6.7 | Q15: =P15*165 -> 1105.5 | R15: =L15+0.5 -> 7 | S15: =R15*165 -> 1155 | T15: 17-20 | U15: -
A16: IUSP | B16: 7.3 | C16: =B16*165 -> 1204.5 | D16: =B16 -> 7.3 | E16: =D16*165 -> 1204.5 | F16: =B16+0.2 -> 7.5 | G16: =F16*165 -> 1237.5 | H16: =B16+0.5 -> 7.8 | I16: =H16*165 -> 1287 | J16: 15-18 | K16: - | L16: 6.7 | M16: =L16*165 -> 1105.5 | N16: =L16 -> 6.7 | O16: =N16*165 -> 1105.5 | P16: =L16+0.2 -> 6.9 | Q16: =P16*165 -> 1138.5 | R16: =L16+0.5 -> 7.2 | S16: =R16*165 -> 1188 | T16: 17-20 | U16: -
A17: IUSJ | B17: 7.3 | C17: =B17*165 -> 1204.5 | D17: =B17 -> 7.3 | E17: =D17*165 -> 1204.5 | F17: =B17+0.2 -> 7.5 | G17: =F17*165 -> 1237.5 | H17: =B17+0.5 -> 7.8 | I17: =H17*165 -> 1287 | J17: 15-18 | K17: - | L17: 6.7 | M17: =L17*165 -> 1105.5 | N17: =L17 -> 6.7 | O17: =N17*165 -> 1105.5 | P17: =L17+0.2 -> 6.9 | Q17: =P17*165 -> 1138.5 | R17: =L17+0.5 -> 7.2 | S17: =R17*165 -> 1188 | T17: 17-20 | U17: -
... A49: IAH3 | B49: 9.2 | C49: =B49*165 -> 1518 | D49: =B49 -> 9.2 | E49: =D49*165 -> 1518 | F49: =B49+0.2 -> 9.4 | G49: =F49*165 -> 1551 | H49: =B49+0.5 -> 9.7 | I49: =H49*165 -> 1600.5 | J49: 22-26 | K49: - | L49: 8.6 | M49: =L49*165 -> 1419 | N49: =L49 -> 8.6 | O49: =N49*165 -> 1419 | P49: =L49+0.2 -> 8.8 | Q49: =P49*165 -> 1452 | R49: =L49+0.5 -> 9.1 | S49: =R49*165 -> 1501.5 | T49: 24-28 | U49: -
A50: SAT1 | B50: 9.2 | C50: =B50*165 -> 1518 | D50: =B50 -> 9.2 | E50: =D50*165 -> 1518 | F50: =B50+0.2 -> 9.4 | G50: =F50*165 -> 1551 | H50: =B50+0.5 -> 9.7 | I50: =H50*165 -> 1600.5 | J50: 22-26 | L50: 8.6 | M50: =L50*165 -> 1419 | N50: =L50 -> 8.6 | O50: =N50*165 -> 1419 | P50: =L50+0.2 -> 8.8 | Q50: =P50*165 -> 1452 | R50: =L50+0.5 -> 9.1 | S50: =R50*165 -> 1501.5 | T50: 24-28 | U50: -
A51: SAT4 | B51: 9.2 | C51: =B51*165 -> 1518 | D51: =B51 -> 9.2 | E51: =D51*165 -> 1518 | F51: =B51+0.2 -> 9.4 | G51: =F51*165 -> 1551 | H51: =B51+0.5 -> 9.7 | I51: =H51*165 -> 1600.5 | J51: 22-26 | K51: - | L51: 8.6 | M51: =L51*165 -> 1419 | N51: =L51 -> 8.6 | O51: =N51*165 -> 1419 | P51: =L51+0.2 -> 8.8 | Q51: =P51*165 -> 1452 | R51: =L51+0.5 -> 9.1 | S51: =R51*165 -> 1501.5 | T51: 24-28 | U51: -
A52: IUSF | B52: 9.2 | C52: =B52*165 -> 1518 | D52: =B52 -> 9.2 | E52: =D52*165 -> 1518 | F52: =B52+0.2 -> 9.4 | G52: =F52*165 -> 1551 | H52: =B52+0.5 -> 9.7 | I52: =H52*165 -> 1600.5 | J52: 22-26 | K52: - | L52: 8.6 | M52: =L52*165 -> 1419 | N52: =L52 -> 8.6 | O52: =N52*165 -> 1419 | P52: =L52+0.2 -> 8.8 | Q52: =P52*165 -> 1452 | R52: =L52+0.5 -> 9.1 | S52: =R52*165 -> 1501.5 | T52: 24-28 | U52: -
A53: IUTH | B53: 9.2 | C53: =B53*165 -> 1518 | D53: =B53 -> 9.2 | E53: =D53*165 -> 1518 | F53: =B53+0.2 -> 9.4 | G53: =F53*165 -> 1551 | H53: =B53+0.5 -> 9.7 | I53: =H53*165 -> 1600.5 | J53: 22-26 | K53: - | L53: 8.6 | M53: =L53*165 -> 1419 | N53: =L53 -> 8.6 | O53: =N53*165 -> 1419 | P53: =L53+0.2 -> 8.8 | Q53: =P53*165 -> 1452 | R53: =L53+0.5 -> 9.1 | S53: =R53*165 -> 1501.5 | T53: 24-28 | U53: -
A54: STL3 | B54: 9.4 | C54: =B54*165 -> 1551 | D54: =B54 -> 9.4 | E54: =D54*165 -> 1551 | F54: =B54+0.2 -> 9.6 | G54: =F54*165 -> 1584 | H54: =B54+0.5 -> 9.9 | I54: =H54*165 -> 1633.5 | J54: 25-28 | K54: - | L54: 8.8 | M54: =L54*165 -> 1452 | N54: =L54 -> 8.8 | O54: =N54*165 -> 1452 | P54: =L54+0.2 -> 9 | Q54: =P54*165 -> 1485 | R54: =L54+0.5 -> 9.3 | S54: =R54*165 -> 1534.5 | T54: 27-30 | U54: -
A55: STL4 | B55: 9.4 | C55: =B55*165 -> 1551 | D55: =B55 -> 9.4 | E55: =D55*165 -> 1551 | F55: =B55+0.2 -> 9.6 | G55: =F55*165 -> 1584 | H55: =B55+0.5 -> 9.9 | I55: =H55*165 -> 1633.5 | J55: 25-28 | K55: - | L55: 8.8 | M55: =L55*165 -> 1452 | N55: =L55 -> 8.8 | O55: =N55*165 -> 1452 | P55: =L55+0.2 -> 9 | Q55: =P55*165 -> 1485 | R55: =L55+0.5 -> 9.3 | S55: =R55*165 -> 1534.5 | T55: 27-30 | U55: -
A56: PSC2 | B56: 9.4 | C56: =B56*165 -> 1551 | D56: =B56 -> 9.4 | E56: =D56*165 -> 1551 | F56: =B56+0.2 -> 9.6 | G56: =F56*165 -> 1584 | H56: =B56+0.5 -> 9.9 | I56: =H56*165 -> 1633.5 | J56: 25-28 | K56: - | L56: 8.8 | M56: =L56*165 -> 1452 | N56: =L56 -> 8.8 | O56: =N56*165 -> 1452 | P56: =L56+0.2 -> 9 | Q56: =P56*165 -> 1485 | R56: =L56+0.5 -> 9.3 | S56: =R56*165 -> 1534.5 | T56: 27-30 | U56: -
A57: PDX7 | B57: 9.4 | C57: =B57*165 -> 1551 | D57: =B57 -> 9.4 | E57: =D57*165 -> 1551 | F57: =B57+0.2 -> 9.6 | G57: =F57*165 -> 1584 | H57: =B57+0.5 -> 9.9 | I57: =H57*165 -> 1633.5 | J57: 25-28 | K57: - | L57: 8.8 | M57: =L57*165 -> 1452 | N57: =L57 -> 8.8 | O57: =N57*165 -> 1452 | P57: =L57+0.2 -> 9 | Q57: =P57*165 -> 1485 | R57: =L57+0.5 -> 9.3 | S57: =R57*165 -> 1534.5 | T57: 27-30 | U57: -
A58: BFI3 | B58: 9.4 | C58: =B58*165 -> 1551 | D58: =B58 -> 9.4 | E58: =D58*165 -> 1551 | F58: =B58+0.2 -> 9.6 | G58: =F58*165 -> 1584 | H58: =B58+0.5 -> 9.9 | I58: =H58*165 -> 1633.5 | J58: 25-28 | K58: - | L58: 8.8 | M58: =L58*165 -> 1452 | N58: =L58 -> 8.8 | O58: =N58*165 -> 1452 | P58: =L58+0.2 -> 9 | Q58: =P58*165 -> 1485 | R58: =L58+0.5 -> 9.3 | S58: =R58*165 -> 1534.5 | T58: 27-30 | U58: -
A59: DEN8 | B59: 9.4 | C59: =B59*165 -> 1551 | D59: =B59 -> 9.4 | E59: =D59*165 -> 1551 | F59: =B59+0.2 -> 9.6 | G59: =F59*165 -> 1584 | H59: =B59+0.5 -> 9.9 | I59: =H59*165 -> 1633.5 | J59: 25-28 | K59: - | L59: 8.8 | M59: =L59*165 -> 1452 | N59: =L59 -> 8.8 | O59: =N59*165 -> 1452 | P59: =L59+0.2 -> 9 | Q59: =P59*165 -> 1485 | R59: =L59+0.5 -> 9.3 | S59: =R59*165 -> 1534.5 | T59: 27-30 | U59: -
A60: IND9 | B60: 9.8 | C60: =B60*165 -> 1617 | D60: =B60 -> 9.8 | E60: =D60*165 -> 1617 | F60: =B60+0.2 -> 10 | G60: =F60*165 -> 1650 | H60: =B60+0.5 -> 10.3 | I60: =H60*165 -> 1699.5 | J60: 25-28 | K60: 超31自然日 | L60: 9.3 | M60: =L60*165 -> 1534.5 | N60: =L60 -> 9.3 | O60: =N60*165 -> 1534.5 | P60: =L60+0.2 -> 9.5 | Q60: =P60*165 -> 1567.5 | R60: =L60+0.5 -> 9.8 | S60: =R60*165 -> 1617 | T60: 27-30 | U60: 超33自然日
A61: MDW2 | B61: 9.8 | C61: =B61*165 -> 1617 | D61: =B61 -> 9.8 | E61: =D61*165 -> 1617 | F61: =B61+0.2 -> 10 | G61: =F61*165 -> 1650 | H61: =B61+0.5 -> 10.3 | I61: =H61*165 -> 1699.5 | J61: 25-28 | K61: 超31自然日 | L61: 9.3 | M61: =L61*165 -> 1534.5 | N61: =L61 -> 9.3 | O61: =N61*165 -> 1534.5 | P61: =L61+0.2 -> 9.5 | Q61: =P61*165 -> 1567.5 | R61: =L61+0.5 -> 9.8 | S61: =R61*165 -> 1617 | T61: 27-30 | U61: 超33自然日
A62: FWA4 | B62: 9.8 | C62: =B62*165 -> 1617 | D62: =B62 -> 9.8 | E62: =D62*165 -> 1617 | F62: =B62+0.2 -> 10 | G62: =F62*165 -> 1650 | H62: =B62+0.5 -> 10.3 | I62: =H62*165 -> 1699.5 | J62: 25-28 | K62: 超31自然日 | L62: 9.3 | M62: =L62*165 -> 1534.5 | N62: =L62 -> 9.3 | O62: =N62*165 -> 1534.5 | P62: =L62+0.2 -> 9.5 | Q62: =P62*165 -> 1567.5 | R62: =L62+0.5 -> 9.8 | S62: =R62*165 -> 1617 | T62: 27-30 | U62: 超33自然日
... A75: ORF2 | B75: 11.4 | C75: =B75*165 -> 1881 | D75: =B75 -> 11.4 | E75: =D75*165 -> 1881 | F75: =B75+0.2 -> 11.6 | G75: =F75*165 -> 1914 | H75: =B75+0.5 -> 11.9 | I75: =H75*165 -> 1963.5 | J75: 27-30 | K75: - | L75: 10.8 | M75: =L75*165 -> 1782 | N75: =L75 -> 10.8 | O75: =N75*165 -> 1782 | P75: =L75+0.2 -> 11 | Q75: =P75*165 -> 1815 | R75: =L75+0.5 -> 11.3 | S75: =R75*165 -> 1864.5 | T75: 29-32 | U75: -
A76: 重货优惠：1：185-0.2 1：200-0.5 1：250-0.9 1：300-1.5 1.500-2比重减重后最低1.2/KG。
A77: 备注：本报价为人民币报价，价格适用于普货，包含头程运费、进出口买单报关费、文件费（不含出单费）、仓库卸货费、托盘费、目的港清关、派送等费用；不包含保险费、商检费、熏蒸费、因货物问题导致的进出口海关查验费、仓库增值服务费、超期费和仓储费等，如若产生，实报实销。
A78: 计重标准 | C78: 重量转体积：1CBM=334KG; 体积转重量：1CBM=167KG；托盘，木架，木箱等非纸箱货物出货，计费重需*1.1倍
A79: 报关费&续页费 | C79: 报关费：RMB220, 超6个品名续页费：RMB50/页（即第7个起算，每6个品名一页）
A80: 超长附加费 | C80: 超过120-150CM附加费：+ RMB150/CBM(不含税)OR 1.2/KGS(含税), 超过150-200CM附加费：+ RMB200/CBM(不含税)OR 1.5/KGS(含税), 最长边限2米以内，超过2米以上或超重则需要case by case确认价格
A81: 超品名费 | C81: 每一票单超过五个品名的，收取RMB30/个
A82: 商检费 & 熏蒸费 | C82: 单询
A83: 提单费（如需） | C83: RMB300/BILL
A84: 不含税渠道进口申报要求 | C84: USD180/CBM
A85: 产品附加 | C85: 箱包类、行李箱、收纳箱、包包、鞋子、服装等纺织品类、FDA申报类产品+0.5元/KG
C86: 木制品 无单证600/票 单证+RMB800/票
A87: 本渠道拒收产品 | C87: 仿牌、液体、粉末、食品、药品、易燃易爆、古董、货币等国家禁止出口及航空公司禁运物品
C88: 纯电池，移动电源，医疗激光产品，太阳能 （大于10*10），动植物， 化妆品，医疗类产品，铅笔，有医疗作用的牙刷
C89: 侵权产品：蓝牙标及包装有蓝牙字样及标识产品
C90: 反倾销产品：请查看附件
A91: 申报要求 | C91: 如实申报，单货一致；如有需要需如实提供每个产品对应的产品图片和有售价的真实销售链接，如新品链接没有售价，需要提供亚马逊后台定价截图；如因客户低申报或申报不符（海关编码和实物不符，数量不一致等）产生的相关查验费、仓租、调高后的税金、海关罚金需由客户承担；

Sheet 美西22-25日达
A1: =_xlfn.DISPIMG("ID_D6697A225B864C34A678052B48D4E660",1) -> =DISPIMG("ID_D6697A225B864C34A678052B48D4E660",1)
A2: 渠道名称 | B2: 易·22日达卡派 | L2: 易·25日达卡派
A3: 使用船司 | B3: COSCO/OA | L3: OA/MSC/ONE/WHL/HMM/TSL统配
A4: 交货仓库 | B4: 东莞/中山/广州 | D4: 嘉兴/义乌 | F4: 汕头/厦门/泉州 | H4: 武汉/长沙 | J4: 参考时效 （开船后自然日） | K4: 理赔时效 以工作日计赔付 0.5元/kg | L4: 东莞/中山/广州 | N4: 嘉兴/义乌 | P4: 汕头/厦门/泉州 | R4: 武汉/长沙 | T4: 参考时效 （开船后自然日） | U4: 本渠道 无时效赔付
A5: 仓库代码 | B5: 12KG+含税 | C5: 0.5CBM+不含税 | D5: 12KG+含税 | E5: 0.5CBM+不含税 | F5: 12KG+含税 | G5: 0.5CBM+不含税 | H5: 12KG+含税 | I5: 0.5CBM+不含税 | L5: 12KG+含税 | M5: 0.5CBM+不含税 | N5: 12KG+含税 | O5: 0.5CBM+不含税 | P5: 12KG+含税 | Q5: 0.5CBM+不含税 | R5: 12KG+含税 | S5: 0.5CBM+不含税
A6: 海外仓自提 一件代发头程 | B6: 6 | C6: =B6*165 -> 990 | D6: =B6 -> 6 | E6: =D6*165 -> 990 | F6: =B6+0.2 -> 6.2 | G6: =F6*165 -> 1023 | H6: =B6+0.5 -> 6.5 | I6: =H6*165 -> 1072.5 | J6: 18-25 | K6: 超28自然日 | L6: 5.6 | M6: =L6*165 -> 924 | N6: =L6 -> 5.6 | O6: =N6*165 -> 924 | P6: =L6+0.2 -> 5.8 | Q6: =P6*165 -> 957 | R6: =L6+0.5 -> 6.1 | S6: =R6*165 -> 1006.5 | T6: 22-28 | U6: -
A7: ONT8 | B7: 6 | C7: =B7*165 -> 990 | D7: =B7 -> 6 | E7: =D7*165 -> 990 | F7: =B7+0.2 -> 6.2 | G7: =F7*165 -> 1023 | H7: =B7+0.5 -> 6.5 | I7: =H7*165 -> 1072.5 | J7: 18-25 | K7: 超28自然日 | L7: 5.6 | M7: =L7*165 -> 924 | N7: =L7 -> 5.6 | O7: =N7*165 -> 924 | P7: =L7+0.2 -> 5.8 | Q7: =P7*165 -> 957 | R7: =L7+0.5 -> 6.1 | S7: =R7*165 -> 1006.5 | T7: 22-28 | U7: -
A8: LGB8 | B8: 6 | C8: =B8*165 -> 990 | D8: =B8 -> 6 | E8: =D8*165 -> 990 | F8: =B8+0.2 -> 6.2 | G8: =F8*165 -> 1023 | H8: =B8+0.5 -> 6.5 | I8: =H8*165 -> 1072.5 | J8: 18-25 | K8: 超28自然日 | L8: 5.6 | M8: =L8*165 -> 924 | N8: =L8 -> 5.6 | O8: =N8*165 -> 924 | P8: =L8+0.2 -> 5.8 | Q8: =P8*165 -> 957 | R8: =L8+0.5 -> 6.1 | S8: =R8*165 -> 1006.5 | T8: 22-28 | U8: -
A9: LAX9 | B9: 6 | C9: =B9*165 -> 990 | D9: =B9 -> 6 | E9: =D9*165 -> 990 | F9: =B9+0.2 -> 6.2 | G9: =F9*165 -> 1023 | H9: =B9+0.5 -> 6.5 | I9: =H9*165 -> 1072.5 | J9: 18-25 | K9: 超28自然日 | L9: 5.6 | M9: =L9*165 -> 924 | N9: =L9 -> 5.6 | O9: =N9*165 -> 924 | P9: =L9+0.2 -> 5.8 | Q9: =P9*165 -> 957 | R9: =L9+0.5 -> 6.1 | S9: =R9*165 -> 1006.5 | T9: 22-28 | U9: -
A10: SBD1 | B10: 6 | C10: =B10*165 -> 990 | D10: =B10 -> 6 | E10: =D10*165 -> 990 | F10: =B10+0.2 -> 6.2 | G10: =F10*165 -> 1023 | H10: =B10+0.5 -> 6.5 | I10: =H10*165 -> 1072.5 | J10: 18-25 | K10: 超28自然日 | L10: 5.6 | M10: =L10*165 -> 924 | N10: =L10 -> 5.6 | O10: =N10*165 -> 924 | P10: =L10+0.2 -> 5.8 | Q10: =P10*165 -> 957 | R10: =L10+0.5 -> 6.1 | S10: =R10*165 -> 1006.5 | T10: 22-28 | U10: -
A11: PSP3 | B11: 6 | C11: =B11*165 -> 990 | D11: =B11 -> 6 | E11: =D11*165 -> 990 | F11: =B11+0.2 -> 6.2 | G11: =F11*165 -> 1023 | H11: =B11+0.5 -> 6.5 | I11: =H11*165 -> 1072.5 | J11: 18-25 | K11: - | L11: 5.6 | M11: =L11*165 -> 924 | N11: =L11 -> 5.6 | O11: =N11*165 -> 924 | P11: =L11+0.2 -> 5.8 | Q11: =P11*165 -> 957 | R11: =L11+0.5 -> 6.1 | S11: =R11*165 -> 1006.5 | T11: 22-28 | U11: -
A12: POC1 | B12: 6 | C12: =B12*165 -> 990 | D12: =B12 -> 6 | E12: =D12*165 -> 990 | F12: =B12+0.2 -> 6.2 | G12: =F12*165 -> 1023 | H12: =B12+0.5 -> 6.5 | I12: =H12*165 -> 1072.5 | J12: 18-25 | K12: - | L12: 5.6 | M12: =L12*165 -> 924 | N12: =L12 -> 5.6 | O12: =N12*165 -> 924 | P12: =L12+0.2 -> 5.8 | Q12: =P12*165 -> 957 | R12: =L12+0.5 -> 6.1 | S12: =R12*165 -> 1006.5 | T12: 22-28 | U12: -
A13: POC2 | B13: 6 | C13: =B13*165 -> 990 | D13: =B13 -> 6 | E13: =D13*165 -> 990 | F13: =B13+0.2 -> 6.2 | G13: =F13*165 -> 1023 | H13: =B13+0.5 -> 6.5 | I13: =H13*165 -> 1072.5 | J13: 18-25 | K13: - | L13: 5.6 | M13: =L13*165 -> 924 | N13: =L13 -> 5.6 | O13: =N13*165 -> 924 | P13: =L13+0.2 -> 5.8 | Q13: =P13*165 -> 957 | R13: =L13+0.5 -> 6.1 | S13: =R13*165 -> 1006.5 | T13: 22-28 | U13: -
A14: POC3 | B14: 6 | C14: =B14*165 -> 990 | D14: =B14 -> 6 | E14: =D14*165 -> 990 | F14: =B14+0.2 -> 6.2 | G14: =F14*165 -> 1023 | H14: =B14+0.5 -> 6.5 | I14: =H14*165 -> 1072.5 | J14: 18-25 | K14: - | L14: 5.6 | M14: =L14*165 -> 924 | N14: =L14 -> 5.6 | O14: =N14*165 -> 924 | P14: =L14+0.2 -> 5.8 | Q14: =P14*165 -> 957 | R14: =L14+0.5 -> 6.1 | S14: =R14*165 -> 1006.5 | T14: 22-28 | U14: -
A15: LAX2T(沃尔玛) | B15: 6 | C15: =B15*165 -> 990 | D15: =B15 -> 6 | E15: =D15*165 -> 990 | F15: =B15+0.2 -> 6.2 | G15: =F15*165 -> 1023 | H15: =B15+0.5 -> 6.5 | I15: =H15*165 -> 1072.5 | J15: 18-25 | K15: - | L15: 5.6 | M15: =L15*165 -> 924 | N15: =L15 -> 5.6 | O15: =N15*165 -> 924 | P15: =L15+0.2 -> 5.8 | Q15: =P15*165 -> 957 | R15: =L15+0.5 -> 6.1 | S15: =R15*165 -> 1006.5 | T15: 22-28 | U15: -
A16: IUSP | B16: 6.2 | C16: =B16*165 -> 1023 | D16: =B16 -> 6.2 | E16: =D16*165 -> 1023 | F16: =B16+0.2 -> 6.4 | G16: =F16*165 -> 1056 | H16: =B16+0.5 -> 6.7 | I16: =H16*165 -> 1105.5 | J16: 18-25 | K16: - | L16: 5.8 | M16: =L16*165 -> 957 | N16: =L16 -> 5.8 | O16: =N16*165 -> 957 | P16: =L16+0.2 -> 6 | Q16: =P16*165 -> 990 | R16: =L16+0.5 -> 6.3 | S16: =R16*165 -> 1039.5 | T16: 22-28 | U16: -
A17: IUSJ | B17: 6.2 | C17: =B17*165 -> 1023 | D17: =B17 -> 6.2 | E17: =D17*165 -> 1023 | F17: =B17+0.2 -> 6.4 | G17: =F17*165 -> 1056 | H17: =B17+0.5 -> 6.7 | I17: =H17*165 -> 1105.5 | J17: 18-25 | K17: - | L17: 5.8 | M17: =L17*165 -> 957 | N17: =L17 -> 5.8 | O17: =N17*165 -> 957 | P17: =L17+0.2 -> 6 | Q17: =P17*165 -> 990 | R17: =L17+0.5 -> 6.3 | S17: =R17*165 -> 1039.5 | T17: 22-28 | U17: -
... A49: IAH3 | B49: 8 | C49: =B49*165 -> 1320 | D49: =B49 -> 8 | E49: =D49*165 -> 1320 | F49: =B49+0.2 -> 8.2 | G49: =F49*165 -> 1353 | H49: =B49+0.5 -> 8.5 | I49: =H49*165 -> 1402.5 | J49: 25-30 | K49: - | L49: 7.6 | M49: =L49*165 -> 1254 | N49: =L49 -> 7.6 | O49: =N49*165 -> 1254 | P49: =L49+0.2 -> 7.8 | Q49: =P49*165 -> 1287 | R49: =L49+0.5 -> 8.1 | S49: =R49*165 -> 1336.5 | T49: 27-32 | U49: -
A50: SAT1 | B50: 8 | C50: =B50*165 -> 1320 | D50: =B50 -> 8 | E50: =D50*165 -> 1320 | F50: =B50+0.2 -> 8.2 | G50: =F50*165 -> 1353 | H50: =B50+0.5 -> 8.5 | I50: =H50*165 -> 1402.5 | J50: 25-30 | L50: 7.6 | M50: =L50*165 -> 1254 | N50: =L50 -> 7.6 | O50: =N50*165 -> 1254 | P50: =L50+0.2 -> 7.8 | Q50: =P50*165 -> 1287 | R50: =L50+0.5 -> 8.1 | S50: =R50*165 -> 1336.5 | T50: 27-32 | U50: -
A51: SAT4 | B51: 8 | C51: =B51*165 -> 1320 | D51: =B51 -> 8 | E51: =D51*165 -> 1320 | F51: =B51+0.2 -> 8.2 | G51: =F51*165 -> 1353 | H51: =B51+0.5 -> 8.5 | I51: =H51*165 -> 1402.5 | J51: 25-30 | K51: - | L51: 7.6 | M51: =L51*165 -> 1254 | N51: =L51 -> 7.6 | O51: =N51*165 -> 1254 | P51: =L51+0.2 -> 7.8 | Q51: =P51*165 -> 1287 | R51: =L51+0.5 -> 8.1 | S51: =R51*165 -> 1336.5 | T51: 27-32 | U51: -
A52: IUSF | B52: 8 | C52: =B52*165 -> 1320 | D52: =B52 -> 8 | E52: =D52*165 -> 1320 | F52: =B52+0.2 -> 8.2 | G52: =F52*165 -> 1353 | H52: =B52+0.5 -> 8.5 | I52: =H52*165 -> 1402.5 | J52: 25-30 | K52: - | L52: 7.6 | M52: =L52*165 -> 1254 | N52: =L52 -> 7.6 | O52: =N52*165 -> 1254 | P52: =L52+0.2 -> 7.8 | Q52: =P52*165 -> 1287 | R52: =L52+0.5 -> 8.1 | S52: =R52*165 -> 1336.5 | T52: 27-32 | U52: -
A53: IUTH | B53: 8 | C53: =B53*165 -> 1320 | D53: =B53 -> 8 | E53: =D53*165 -> 1320 | F53: =B53+0.2 -> 8.2 | G53: =F53*165 -> 1353 | H53: =B53+0.5 -> 8.5 | I53: =H53*165 -> 1402.5 | J53: 25-30 | K53: - | L53: 7.6 | M53: =L53*165 -> 1254 | N53: =L53 -> 7.6 | O53: =N53*165 -> 1254 | P53: =L53+0.2 -> 7.8 | Q53: =P53*165 -> 1287 | R53: =L53+0.5 -> 8.1 | S53: =R53*165 -> 1336.5 | T53: 27-32 | U53: -
A54: STL3 | B54: 8.2 | C54: =B54*165 -> 1353 | D54: =B54 -> 8.2 | E54: =D54*165 -> 1353 | F54: =B54+0.2 -> 8.4 | G54: =F54*165 -> 1386 | H54: =B54+0.5 -> 8.7 | I54: =H54*165 -> 1435.5 | J54: 25-30 | K54: - | L54: 7.8 | M54: =L54*165 -> 1287 | N54: =L54 -> 7.8 | O54: =N54*165 -> 1287 | P54: =L54+0.2 -> 8 | Q54: =P54*165 -> 1320 | R54: =L54+0.5 -> 8.3 | S54: =R54*165 -> 1369.5 | T54: 27-32 | U54: -
A55: STL4 | B55: 8.2 | C55: =B55*165 -> 1353 | D55: =B55 -> 8.2 | E55: =D55*165 -> 1353 | F55: =B55+0.2 -> 8.4 | G55: =F55*165 -> 1386 | H55: =B55+0.5 -> 8.7 | I55: =H55*165 -> 1435.5 | J55: 25-30 | K55: - | L55: 7.8 | M55: =L55*165 -> 1287 | N55: =L55 -> 7.8 | O55: =N55*165 -> 1287 | P55: =L55+0.2 -> 8 | Q55: =P55*165 -> 1320 | R55: =L55+0.5 -> 8.3 | S55: =R55*165 -> 1369.5 | T55: 27-32 | U55: -
A56: PSC2 | B56: 8.2 | C56: =B56*165 -> 1353 | D56: =B56 -> 8.2 | E56: =D56*165 -> 1353 | F56: =B56+0.2 -> 8.4 | G56: =F56*165 -> 1386 | H56: =B56+0.5 -> 8.7 | I56: =H56*165 -> 1435.5 | J56: 25-30 | K56: - | L56: 7.8 | M56: =L56*165 -> 1287 | N56: =L56 -> 7.8 | O56: =N56*165 -> 1287 | P56: =L56+0.2 -> 8 | Q56: =P56*165 -> 1320 | R56: =L56+0.5 -> 8.3 | S56: =R56*165 -> 1369.5 | T56: 27-32 | U56: -
A57: PDX7 | B57: 8.2 | C57: =B57*165 -> 1353 | D57: =B57 -> 8.2 | E57: =D57*165 -> 1353 | F57: =B57+0.2 -> 8.4 | G57: =F57*165 -> 1386 | H57: =B57+0.5 -> 8.7 | I57: =H57*165 -> 1435.5 | J57: 28-33 | K57: - | L57: 7.8 | M57: =L57*165 -> 1287 | N57: =L57 -> 7.8 | O57: =N57*165 -> 1287 | P57: =L57+0.2 -> 8 | Q57: =P57*165 -> 1320 | R57: =L57+0.5 -> 8.3 | S57: =R57*165 -> 1369.5 | T57: 28-35 | U57: -
A58: BFI3 | B58: 8.2 | C58: =B58*165 -> 1353 | D58: =B58 -> 8.2 | E58: =D58*165 -> 1353 | F58: =B58+0.2 -> 8.4 | G58: =F58*165 -> 1386 | H58: =B58+0.5 -> 8.7 | I58: =H58*165 -> 1435.5 | J58: 28-33 | K58: - | L58: 7.8 | M58: =L58*165 -> 1287 | N58: =L58 -> 7.8 | O58: =N58*165 -> 1287 | P58: =L58+0.2 -> 8 | Q58: =P58*165 -> 1320 | R58: =L58+0.5 -> 8.3 | S58: =R58*165 -> 1369.5 | T58: 28-35 | U58: -
A59: DEN8 | B59: 8.2 | C59: =B59*165 -> 1353 | D59: =B59 -> 8.2 | E59: =D59*165 -> 1353 | F59: =B59+0.2 -> 8.4 | G59: =F59*165 -> 1386 | H59: =B59+0.5 -> 8.7 | I59: =H59*165 -> 1435.5 | J59: 28-33 | K59: - | L59: 7.8 | M59: =L59*165 -> 1287 | N59: =L59 -> 7.8 | O59: =N59*165 -> 1287 | P59: =L59+0.2 -> 8 | Q59: =P59*165 -> 1320 | R59: =L59+0.5 -> 8.3 | S59: =R59*165 -> 1369.5 | T59: 28-35 | U59: -
A60: IND9 | B60: 8.6 | C60: =B60*165 -> 1419 | D60: =B60 -> 8.6 | E60: =D60*165 -> 1419 | F60: =B60+0.2 -> 8.8 | G60: =F60*165 -> 1452 | H60: =B60+0.5 -> 9.1 | I60: =H60*165 -> 1501.5 | J60: 28-33 | K60: 超38自然日 | L60: 8.2 | M60: =L60*165 -> 1353 | N60: =L60 -> 8.2 | O60: =N60*165 -> 1353 | P60: =L60+0.2 -> 8.4 | Q60: =P60*165 -> 1386 | R60: =L60+0.5 -> 8.7 | S60: =R60*165 -> 1435.5 | T60: 28-35 | U60: -
A61: MDW2 | B61: 8.6 | C61: =B61*165 -> 1419 | D61: =B61 -> 8.6 | E61: =D61*165 -> 1419 | F61: =B61+0.2 -> 8.8 | G61: =F61*165 -> 1452 | H61: =B61+0.5 -> 9.1 | I61: =H61*165 -> 1501.5 | J61: 28-33 | K61: 超38自然日 | L61: 8.2 | M61: =L61*165 -> 1353 | N61: =L61 -> 8.2 | O61: =N61*165 -> 1353 | P61: =L61+0.2 -> 8.4 | Q61: =P61*165 -> 1386 | R61: =L61+0.5 -> 8.7 | S61: =R61*165 -> 1435.5 | T61: 28-35 | U61: -
A62: FWA4 | B62: 8.6 | C62: =B62*165 -> 1419 | D62: =B62 -> 8.6 | E62: =D62*165 -> 1419 | F62: =B62+0.2 -> 8.8 | G62: =F62*165 -> 1452 | H62: =B62+0.5 -> 9.1 | I62: =H62*165 -> 1501.5 | J62: 28-33 | K62: 超38自然日 | L62: 8.2 | M62: =L62*165 -> 1353 | N62: =L62 -> 8.2 | O62: =N62*165 -> 1353 | P62: =L62+0.2 -> 8.4 | Q62: =P62*165 -> 1386 | R62: =L62+0.5 -> 8.7 | S62: =R62*165 -> 1435.5 | T62: 28-35 | U62: -
... A64: MQJ1 | B64: 8.6 | C64: =B64*165 -> 1419 | D64: =B64 -> 8.6 | E64: =D64*165 -> 1419 | F64: =B64+0.2 -> 8.8 | G64: =F64*165 -> 1452 | H64: =B64+0.5 -> 9.1 | I64: =H64*165 -> 1501.5 | J64: 28-33 | K64: 超38自然日 | L64: 8.2 | M64: =L64*165 -> 1353 | N64: =L64 -> 8.2 | O64: =N64*165 -> 1353 | P64: =L64+0.2 -> 8.4 | Q64: =P64*165 -> 1386 | R64: =L64+0.5 -> 8.7 | S64: =R64*165 -> 1435.5 | T64: 28-35 | U64: -
A65: GEG2 | B65: 8.6 | C65: =B65*165 -> 1419 | D65: =B65 -> 8.6 | E65: =D65*165 -> 1419 | F65: =B65+0.2 -> 8.8 | G65: =F65*165 -> 1452 | H65: =B65+0.5 -> 9.1 | I65: =H65*165 -> 1501.5 | J65: 28-33 | L65: 8.2 | M65: =L65*165 -> 1353 | N65: =L65 -> 8.2 | O65: =N65*165 -> 1353 | P65: =L65+0.2 -> 8.4 | Q65: =P65*165 -> 1386 | R65: =L65+0.5 -> 8.7 | S65: =R65*165 -> 1435.5 | T65: 28-35 | U65: -
A66: RFD2 | B66: 8.6 | C66: =B66*165 -> 1419 | D66: =B66 -> 8.6 | E66: =D66*165 -> 1419 | F66: =B66+0.2 -> 8.8 | G66: =F66*165 -> 1452 | H66: =B66+0.5 -> 9.1 | I66: =H66*165 -> 1501.5 | J66: 28-33 | K66: - | L66: 8.2 | M66: =L66*165 -> 1353 | N66: =L66 -> 8.2 | O66: =N66*165 -> 1353 | P66: =L66+0.2 -> 8.4 | Q66: =P66*165 -> 1386 | R66: =L66+0.5 -> 8.7 | S66: =R66*165 -> 1435.5 | T66: 28-35 | U66: -
A67: CLT2 | B67: 9.5 | C67: =B67*165 -> 1567.5 | D67: =B67 -> 9.5 | E67: =D67*165 -> 1567.5 | F67: =B67+0.2 -> 9.7 | G67: =F67*165 -> 1600.5 | H67: =B67+0.5 -> 10 | I67: =H67*165 -> 1650 | J67: 28-33 | K67: - | L67: 9.1 | M67: =L67*165 -> 1501.5 | N67: =L67 -> 9.1 | O67: =N67*165 -> 1501.5 | P67: =L67+0.2 -> 9.3 | Q67: =P67*165 -> 1534.5 | R67: =L67+0.5 -> 9.6 | S67: =R67*165 -> 1584 | T67: 28-35 | U67: -
A68: RDU2 | B68: 9.5 | C68: =B68*165 -> 1567.5 | D68: =B68 -> 9.5 | E68: =D68*165 -> 1567.5 | F68: =B68+0.2 -> 9.7 | G68: =F68*165 -> 1600.5 | H68: =B68+0.5 -> 10 | I68: =H68*165 -> 1650 | J68: 28-33 | K68: - | L68: 9.1 | M68: =L68*165 -> 1501.5 | N68: =L68 -> 9.1 | O68: =N68*165 -> 1501.5 | P68: =L68+0.2 -> 9.3 | Q68: =P68*165 -> 1534.5 | R68: =L68+0.5 -> 9.6 | S68: =R68*165 -> 1584 | T68: 28-35 | U68: -
A69: TOL3 | B69: 9.5 | C69: =B69*165 -> 1567.5 | D69: =B69 -> 9.5 | E69: =D69*165 -> 1567.5 | F69: =B69+0.2 -> 9.7 | G69: =F69*165 -> 1600.5 | H69: =B69+0.5 -> 10 | I69: =H69*165 -> 1650 | J69: 28-33 | K69: - | L69: 9.1 | M69: =L69*165 -> 1501.5 | N69: =L69 -> 9.1 | O69: =N69*165 -> 1501.5 | P69: =L69+0.2 -> 9.3 | Q69: =P69*165 -> 1534.5 | R69: =L69+0.5 -> 9.6 | S69: =R69*165 -> 1584 | T69: 28-35 | U69: -
A70: ABE8 | B70: 10 | C70: =B70*165 -> 1650 | D70: =B70 -> 10 | E70: =D70*165 -> 1650 | F70: =B70+0.2 -> 10.2 | G70: =F70*165 -> 1683 | H70: =B70+0.5 -> 10.5 | I70: =H70*165 -> 1732.5 | J70: 28-33 | K70: - | L70: 9.6 | M70: =L70*165 -> 1584 | N70: =L70 -> 9.6 | O70: =N70*165 -> 1584 | P70: =L70+0.2 -> 9.8 | Q70: =P70*165 -> 1617 | R70: =L70+0.5 -> 10.1 | S70: =R70*165 -> 1666.5 | T70: 28-35 | U70: -
A71: RMN3 | B71: 10 | C71: =B71*165 -> 1650 | D71: =B71 -> 10 | E71: =D71*165 -> 1650 | F71: =B71+0.2 -> 10.2 | G71: =F71*165 -> 1683 | H71: =B71+0.5 -> 10.5 | I71: =H71*165 -> 1732.5 | J71: 28-33 | K71: - | L71: 9.6 | M71: =L71*165 -> 1584 | N71: =L71 -> 9.6 | O71: =N71*165 -> 1584 | P71: =L71+0.2 -> 9.8 | Q71: =P71*165 -> 1617 | R71: =L71+0.5 -> 10.1 | S71: =R71*165 -> 1666.5 | T71: 28-35 | U71: -
A72: AVP1 | B72: 10 | C72: =B72*165 -> 1650 | D72: =B72 -> 10 | E72: =D72*165 -> 1650 | F72: =B72+0.2 -> 10.2 | G72: =F72*165 -> 1683 | H72: =B72+0.5 -> 10.5 | I72: =H72*165 -> 1732.5 | J72: 28-33 | K72: - | L72: 9.6 | M72: =L72*165 -> 1584 | N72: =L72 -> 9.6 | O72: =N72*165 -> 1584 | P72: =L72+0.2 -> 9.8 | Q72: =P72*165 -> 1617 | R72: =L72+0.5 -> 10.1 | S72: =R72*165 -> 1666.5 | T72: 28-35 | U72: -
A73: SWF2 | B73: 10 | C73: =B73*165 -> 1650 | D73: =B73 -> 10 | E73: =D73*165 -> 1650 | F73: =B73+0.2 -> 10.2 | G73: =F73*165 -> 1683 | H73: =B73+0.5 -> 10.5 | I73: =H73*165 -> 1732.5 | J73: 28-33 | K73: - | L73: 9.6 | M73: =L73*165 -> 1584 | N73: =L73 -> 9.6 | O73: =N73*165 -> 1584 | P73: =L73+0.2 -> 9.8 | Q73: =P73*165 -> 1617 | R73: =L73+0.5 -> 10.1 | S73: =R73*165 -> 1666.5 | T73: 28-35 | U73: -
A74: TEB9 | B74: 10 | C74: =B74*165 -> 1650 | D74: =B74 -> 10 | E74: =D74*165 -> 1650 | F74: =B74+0.2 -> 10.2 | G74: =F74*165 -> 1683 | H74: =B74+0.5 -> 10.5 | I74: =H74*165 -> 1732.5 | J74: 28-33 | K74: - | L74: 9.6 | M74: =L74*165 -> 1584 | N74: =L74 -> 9.6 | O74: =N74*165 -> 1584 | P74: =L74+0.2 -> 9.8 | Q74: =P74*165 -> 1617 | R74: =L74+0.5 -> 10.1 | S74: =R74*165 -> 1666.5 | T74: 28-35 | U74: -
A75: ORF2 | B75: 10 | C75: =B75*165 -> 1650 | D75: =B75 -> 10 | E75: =D75*165 -> 1650 | F75: =B75+0.2 -> 10.2 | G75: =F75*165 -> 1683 | H75: =B75+0.5 -> 10.5 | I75: =H75*165 -> 1732.5 | J75: 28-33 | K75: - | L75: 9.6 | M75: =L75*165 -> 1584 | N75: =L75 -> 9.6 | O75: =N75*165 -> 1584 | P75: =L75+0.2 -> 9.8 | Q75: =P75*165 -> 1617 | R75: =L75+0.5 -> 10.1 | S75: =R75*165 -> 1666.5 | T75: 28-35 | U75: -
A76: 重货优惠：1:200 -0.2; 1:250 -0.5，1:300 -1，1:400 -1.5，1:500 -2比重减重后最低1.2/KG。
A77: 备注：本报价为人民币报价，价格适用于普货，包含头程运费、进出口买单报关费、文件费（不含出单费）、仓库卸货费、托盘费、目的港清关、派送等费用；不包含保险费、商检费、熏蒸费、因货物问题导致的进出口海关查验费、仓库增值服务费、超期费和仓储费等，如若产生，实报实销。
A78: 计重标准 | C78: 重量转体积：1CBM=334KG; 体积转重量：1CBM=167KG；托盘，木架，木箱等非纸箱货物出货，计费重需*1.1倍
A79: 报关费&续页费 | C79: 报关费：RMB220, 超6个品名续页费：RMB50/页（即第7个起算，每6个品名一页）
A80: 超长附加费 | C80: 超过120-150CM附加费：+ RMB150/CBM(不含税)OR 1.2/KGS(含税), 超过150-200CM附加费：+ RMB200/CBM(不含税)OR 1.5/KGS(含税), 最长边限2米以内，超过2米以上或超重则需要case by case确认价格
A81: 超品名费 | C81: 每一票单超过五个品名的，收取RMB30/个
A82: 商检费 & 熏蒸费 | C82: 单询
A83: 提单费（如需） | C83: RMB300/BILL
A84: 不含税渠道进口申报要求 | C84: USD180/CBM
A85: 产品附加 | C85: 箱包类、行李箱、收纳箱、包包、鞋子、服装等纺织品类、FDA申报类产品+0.5元/KG
C86: 木制品 无单证600/票 单证+RMB800/票
A87: 本渠道拒收产品 | C87: 仿牌、液体、粉末、食品、药品、易燃易爆、古董、货币等国家禁止出口及航空公司禁运物品
C88: 纯电池，移动电源，医疗激光产品，太阳能 （大于10*10），动植物， 化妆品，医疗类产品，铅笔，有医疗作用的牙刷
C89: 侵权产品：蓝牙标及包装有蓝牙字样及标识产品
C90: 反倾销产品：请查看附件
A91: 申报要求 | C91: 如实申报，单货一致；如有需要需如实提供每个产品对应的产品图片和有售价的真实销售链接，如新品链接没有售价，需要提供亚马逊后台定价截图；如因客户低申报或申报不符（海关编码和实物不符，数量不一致等）产生的相关查验费、仓租、调高后的税金、海关罚金需由客户承担；

Sheet DG海卡
A1: =_xlfn.DISPIMG("ID_D6697A225B864C34A678052B48D4E660",1) -> =DISPIMG("ID_D6697A225B864C34A678052B48D4E660",1)
A2: 渠道名称 | B2: DG海卡
A3: 使用船司 | B3: COSCO/OA
A4: 交货仓库 | B4: 东莞/中山/广州 | C4: 嘉兴/义乌 | D4: 汕头/厦门/泉州 | E4: 武汉/长沙 | F4: 参考时效 （开船后自然日） | G4: 本渠道 无时效赔付
A5: 仓库代码 | B5: 12KG+含税 | C5: 12KG+含税 | D5: 12KG+含税 | E5: 12KG+含税
A6: 海外仓自提 一件代发头程 | B6: 8 | C6: =B6+0.2 -> 8.2 | D6: =B6+0.2 -> 8.2 | E6: =B6+0.5 -> 8.5 | F6: 18-25 | G6: -
A7: ONT8 | B7: 8 | C7: =B7+0.2 -> 8.2 | D7: =B7+0.2 -> 8.2 | E7: =B7+0.5 -> 8.5 | F7: 18-25 | G7: -
A8: LGB8 | B8: 8 | C8: =B8+0.2 -> 8.2 | D8: =B8+0.2 -> 8.2 | E8: =B8+0.5 -> 8.5 | F8: 18-25 | G8: -
A9: LAX9 | B9: 8 | C9: =B9+0.2 -> 8.2 | D9: =B9+0.2 -> 8.2 | E9: =B9+0.5 -> 8.5 | F9: 18-25 | G9: -
A10: SBD1 | B10: 8 | C10: =B10+0.2 -> 8.2 | D10: =B10+0.2 -> 8.2 | E10: =B10+0.5 -> 8.5 | F10: 18-25 | G10: -
A11: POC1 | B11: 8.3 | C11: =B11+0.2 -> 8.5 | D11: =B11+0.2 -> 8.5 | E11: =B11+0.5 -> 8.8 | F11: 18-25 | G11: -
A12: POC2 | B12: 8.3 | C12: =B12+0.2 -> 8.5 | D12: =B12+0.2 -> 8.5 | E12: =B12+0.5 -> 8.8 | F12: 18-25 | G12: -
A13: POC3 | B13: 8.3 | C13: =B13+0.2 -> 8.5 | D13: =B13+0.2 -> 8.5 | E13: =B13+0.5 -> 8.8 | F13: 18-25 | G13: -
A14: IUSP | B14: 8.5 | C14: =B14+0.2 -> 8.7 | D14: =B14+0.2 -> 8.7 | E14: =B14+0.5 -> 9 | F14: 18-25 | G14: -
A15: IUSJ | B15: 8.5 | C15: =B15+0.2 -> 8.7 | D15: =B15+0.2 -> 8.7 | E15: =B15+0.5 -> 9 | F15: 18-25 | G15: -
A16: IUTI | B16: 8.5 | C16: =B16+0.2 -> 8.7 | D16: =B16+0.2 -> 8.7 | E16: =B16+0.5 -> 9 | F16: 18-25 | G16: -
A17: IUSW | B17: 8.5 | C17: =B17+0.2 -> 8.7 | D17: =B17+0.2 -> 8.7 | E17: =B17+0.5 -> 9 | F17: 18-25 | G17: -
... A64: ORF2 | B64: 12.9 | C64: =B64+0.2 -> 13.1 | D64: =B64+0.2 -> 13.1 | E64: =B64+0.5 -> 13.4 | F64: 28-33 | G64: -
A65: 无重货优惠
A66: 备注：本报价为人民币报价，价格适用于普货，包含头程运费、进出口买单报关费、文件费（不含出单费）、仓库卸货费、托盘费、目的港清关、派送等费用；不包含保险费、商检费、熏蒸费、因货物问题导致的进出口海关查验费、仓库增值服务费、超期费和仓储费等，如若产生，实报实销。
A67: 注意： 1、DG电池渠道需提供货证相符且有效的UN38.3/MSDS/1.2米跌落测试报告/货物运输安全鉴定报告证书/危包证，发货前请提供资料审核； 2、因美国海关对电动自行车，电动滑板车类产品不再进行关税豁免，此类产品需要按表价+1/KG 3、注意事项：实际货物跟买单、出口报关资料、电池及产品相关证书以及危包证信息必须一致，若海关查验，因信息不符造成的一切费用及责任概由客户承担
A68: 计重标准 | C68: 重量转体积：1CBM=334KG; 体积转重量：1CBM=167KG；托盘，木架，木箱等非纸箱货物出货，计费重需*1.1倍
A69: 报关费&续页费 | C69: 报关费：RMB220, 超6个品名续页费：RMB50/页（即第7个起算，每6个品名一页）
A70: 超品名费 | C70: 每一票单超过五个品名的，收取RMB30/个
A71: 提单费（如需） | C71: RMB300/BILL
A72: 申报要求 | C72: 如实申报，单货一致；如有需要需如实提供每个产品对应的产品图片和有售价的真实销售链接，如新品链接没有售价，需要提供亚马逊后台定价截图；如因客户低申报或申报不符（海关编码和实物不符，数量不一致等）产生的相关查验费、仓租、调高后的税金、海关罚金需由客户承担；
A73: 包装要求：
A74: 1、DG电池产品需加贴9类危险品电池标签（尺寸100*100MM)以及UN标签（尺寸120*110MM)(此两种标签各贴3张，分别贴在外箱正面、侧面及上面,请见右图），以防止货物运输过程中磨损，影响出运或海外无法派送等。另外需贴两面我司提供的系统分货唛头，便于货物入仓及时分货，海外派送；标签材质必须是不干胶纸;
A75: 2、锂电池标签、危险品类别标签需使用不干胶纸贴制，UN串号需丝印在纸箱上；锂电池的危包箱需要II级包装，包装箱上的字母是X或Y才能满足要求。
A76: 3、标签要求：FBA地址请严格按照亚马逊要求加贴相应标签，根据亚马逊仓规定，如单件重量若超过15KG，在外箱贴上“Heavy Package"(超重标签）。如单件重量在22.5-30KG，在外箱贴上“Team Lift"标签。
A77: 4、发货人需对电池货物做好绝缘、防静电、防震等安全措施
A78: 5、海关严查产地标识，外箱和每个产品上必须贴“MADE IN CHINA”。

Sheet 美西北专线
A1: =_xlfn.DISPIMG("ID_D6697A225B864C34A678052B48D4E660",1) -> =DISPIMG("ID_D6697A225B864C34A678052B48D4E660",1)
A2: 渠道名称 | B2: 易·奥易达卡派 | K2: 西雅图卡派（暂停）
A3: 使用船司 | B3: OA/ONE/MSC/HMM统配
A4: 交货仓库 | B4: 东莞/中山/广州 | D4: 嘉兴/义乌 | F4: 汕头/厦门/泉州 | H4: 武汉/长沙 | J4: 参考时效 （开船后自然日） | K4: 东莞/中山/广州 | M4: 嘉兴/义乌 | O4: 汕头/厦门/泉州 | Q4: 武汉/长沙 | S4: 参考时效 （开船后自然日）
A5: 仓库代码 | B5: 12KG+含税 | C5: 0.5CBM+不含税 | D5: 12KG+含税 | E5: 0.5CBM+不含税 | F5: 12KG+含税 | G5: 0.5CBM+不含税 | H5: 12KG+含税 | I5: 0.5CBM+不含税 | K5: 12KG+含税 | L5: 0.5CBM+不含税 | M5: 12KG+含税 | N5: 0.5CBM+不含税 | O5: 12KG+含税 | P5: 0.5CBM+不含税 | Q5: 12KG+含税 | R5: 0.5CBM+不含税
A6: SMF3 | B6: 6.3 | C6: =(B6*165)+0 -> 1039.5 | D6: =((B6+0.1))+0 -> 6.4 | E6: =(D6*165)+0 -> 1056 | F6: =(B6+0.2)+0 -> 6.5 | G6: =(F6*165)+0 -> 1072.5 | H6: =B6+0.5 -> 6.8 | I6: =H6*165 -> 1122 | J6: 25-30 | K6: - | L6: =K6 -> - | M6: - | N6: - | O6: - | P6: - | Q6: - | R6: - | S6: -
A7: SCK4 | B7: 6.3 | C7: =(B7*165)+0 -> 1039.5 | D7: =((B7+0.1))+0 -> 6.4 | E7: =(D7*165)+0 -> 1056 | F7: =(B7+0.2)+0 -> 6.5 | G7: =(F7*165)+0 -> 1072.5 | H7: =B7+0.5 -> 6.8 | I7: =H7*165 -> 1122 | J7: 25-30 | K7: - | L7: =K7 -> - | M7: - | N7: - | O7: - | P7: - | Q7: - | R7: - | S7: -
A8: SCK8 | B8: 6.3 | C8: =(B8*165)+0 -> 1039.5 | D8: =((B8+0.1))+0 -> 6.4 | E8: =(D8*165)+0 -> 1056 | F8: =(B8+0.2)+0 -> 6.5 | G8: =(F8*165)+0 -> 1072.5 | H8: =B8+0.5 -> 6.8 | I8: =H8*165 -> 1122 | J8: 25-30 | K8: - | L8: =K8 -> - | M8: - | N8: - | O8: - | P8: - | Q8: - | R8: - | S8: -
A9: SCK1 | B9: 6.3 | C9: =(B9*165)+0 -> 1039.5 | D9: =((B9+0.1))+0 -> 6.4 | E9: =(D9*165)+0 -> 1056 | F9: =(B9+0.2)+0 -> 6.5 | G9: =(F9*165)+0 -> 1072.5 | H9: =B9+0.5 -> 6.8 | I9: =H9*165 -> 1122 | J9: 25-30 | K9: - | L9: =K9 -> - | M9: - | N9: - | O9: - | P9: - | Q9: - | R9: - | S9: -
A10: TCY1 | B10: 6.3 | C10: =(B10*165)+0 -> 1039.5 | D10: =((B10+0.1))+0 -> 6.4 | E10: =(D10*165)+0 -> 1056 | F10: =(B10+0.2)+0 -> 6.5 | G10: =(F10*165)+0 -> 1072.5 | H10: =B10+0.5 -> 6.8 | I10: =H10*165 -> 1122 | J10: 28-32 | K10: - | L10: - | M10: - | N10: - | O10: - | P10: - | Q10: - | R10: - | S10: -
A11: TCY2 | B11: 6.3 | C11: =(B11*165)+0 -> 1039.5 | D11: =((B11+0.1))+0 -> 6.4 | E11: =(D11*165)+0 -> 1056 | F11: =(B11+0.2)+0 -> 6.5 | G11: =(F11*165)+0 -> 1072.5 | H11: =B11+0.5 -> 6.8 | I11: =H11*165 -> 1122 | J11: 28-32 | K11: - | L11: - | M11: - | N11: - | O11: - | P11: - | Q11: - | R11: - | S11: -
A12: OAK3 | B12: 6.3 | C12: =(B12*165)+0 -> 1039.5 | D12: =((B12+0.1))+0 -> 6.4 | E12: =(D12*165)+0 -> 1056 | F12: =(B12+0.2)+0 -> 6.5 | G12: =(F12*165)+0 -> 1072.5 | H12: =B12+0.5 -> 6.8 | I12: =H12*165 -> 1122 | J12: 30-35 | K12: - | L12: - | M12: - | N12: - | O12: - | P12: - | Q12: - | R12: - | S12: -
A13: MCE1 | B13: 6.7 | C13: =(B13*165)+0 -> 1105.5 | D13: =((B13+0.1))+0 -> 6.8 | E13: =(D13*165)+0 -> 1122 | F13: =(B13+0.2)+0 -> 6.9 | G13: =(F13*165)+0 -> 1138.5 | H13: =B13+0.5 -> 7.2 | I13: =H13*165 -> 1188 | J13: 30-35 | K13: - | L13: - | M13: - | N13: - | O13: - | P13: - | Q13: - | R13: - | S13: -
A14: SMF6 | B14: 6.7 | C14: =(B14*165)+0 -> 1105.5 | D14: =((B14+0.1))+0 -> 6.8 | E14: =(D14*165)+0 -> 1122 | F14: =(B14+0.2)+0 -> 6.9 | G14: =(F14*165)+0 -> 1138.5 | H14: =B14+0.5 -> 7.2 | I14: =H14*165 -> 1188 | J14: 30-35 | K14: - | L14: - | M14: - | N14: - | O14: - | P14: - | Q14: - | R14: - | S14: -
A15: SMF7 | B15: 6.7 | C15: =(B15*165)+0 -> 1105.5 | D15: =((B15+0.1))+0 -> 6.8 | E15: =(D15*165)+0 -> 1122 | F15: =(B15+0.2)+0 -> 6.9 | G15: =(F15*165)+0 -> 1138.5 | H15: =B15+0.5 -> 7.2 | I15: =H15*165 -> 1188 | J15: 30-35 | K15: - | L15: - | M15: - | N15: - | O15: - | P15: - | Q15: - | R15: - | S15: -
A16: HLI2 | B16: 6.7 | C16: =(B16*165)+0 -> 1105.5 | D16: =((B16+0.1))+0 -> 6.8 | E16: =(D16*165)+0 -> 1122 | F16: =(B16+0.2)+0 -> 6.9 | G16: =(F16*165)+0 -> 1138.5 | H16: =B16+0.5 -> 7.2 | I16: =H16*165 -> 1188 | J16: 30-35 | K16: - | L16: - | M16: - | N16: - | O16: - | P16: - | Q16: - | R16: - | S16: -
A17: FAT2 | B17: 6.8 | C17: =(B17*165)+0 -> 1122 | D17: =((B17+0.1))+0 -> 6.9 | E17: =(D17*165)+0 -> 1138.5 | F17: =(B17+0.2)+0 -> 7 | G17: =(F17*165)+0 -> 1155 | H17: =B17+0.5 -> 7.3 | I17: =H17*165 -> 1204.5 | J17: 30-35 | K17: - | L17: - | M17: - | N17: - | O17: - | P17: - | Q17: - | R17: - | S17: -
A18: RNO4 | B18: 6.8 | C18: =(B18*165)+0 -> 1122 | D18: =((B18+0.1))+0 -> 6.9 | E18: =(D18*165)+0 -> 1138.5 | F18: =(B18+0.2)+0 -> 7 | G18: =(F18*165)+0 -> 1155 | H18: =B18+0.5 -> 7.3 | I18: =H18*165 -> 1204.5 | J18: 30-35 | K18: - | L18: - | M18: - | N18: - | O18: - | P18: - | Q18: - | R18: - | S18: -
A19: BFI3 | B19: - | C19: =B19 -> - | D19: - | E19: - | F19: - | G19: - | H19: - | I19: - | K19: 5.9 | L19: =K19*165 -> 973.5 | M19: =(K19+0.1) -> 6 | N19: =M19*165 -> 990 | O19: =K19+0.2 -> 6.1 | P19: =O19*165 -> 1006.5 | Q19: =K19+0.5 -> 6.4 | R19: =Q19*165 -> 1056 | S19: 25-30
A20: BFI7 | B20: - | C20: =B20 -> - | D20: - | E20: - | F20: - | G20: - | H20: - | I20: - | K20: 5.9 | L20: =K20*165 -> 973.5 | M20: =(K20+0.1) -> 6 | N20: =M20*165 -> 990 | O20: =K20+0.2 -> 6.1 | P20: =O20*165 -> 1006.5 | Q20: =K20+0.5 -> 6.4 | R20: =Q20*165 -> 1056 | S20: 25-30
A21: PDX6 | B21: - | C21: =B21 -> - | D21: - | E21: - | F21: - | G21: - | H21: - | I21: - | K21: 6.1 | L21: =K21*165 -> 1006.5 | M21: =(K21+0.1) -> 6.2 | N21: =M21*165 -> 1023 | O21: =K21+0.2 -> 6.3 | P21: =O21*165 -> 1039.5 | Q21: =K21+0.5 -> 6.6 | R21: =Q21*165 -> 1089 | S21: 25-30
A22: PDX7 | B22: - | C22: =B22 -> - | D22: - | E22: - | F22: - | G22: - | H22: - | I22: - | K22: 6.1 | L22: =K22*165 -> 1006.5 | M22: =(K22+0.1) -> 6.2 | N22: =M22*165 -> 1023 | O22: =K22+0.2 -> 6.3 | P22: =O22*165 -> 1039.5 | Q22: =K22+0.5 -> 6.6 | R22: =Q22*165 -> 1089 | S22: 28-32
A23: PSC2 | B23: - | C23: =B23 -> - | D23: =C23 -> - | E23: =D23 -> - | F23: =E23 -> - | G23: =F23 -> - | H23: =G23 -> - | I23: =H23 -> - | K23: 6 | L23: =K23*165 -> 990 | M23: =(K23+0.1) -> 6.1 | N23: =M23*165 -> 1006.5 | O23: =K23+0.2 -> 6.2 | P23: =O23*165 -> 1023 | Q23: =K23+0.5 -> 6.5 | R23: =Q23*165 -> 1072.5 | S23: 28-32
A24: GEG2 | B24: - | C24: =B24 -> - | D24: - | E24: - | F24: - | G24: - | H24: - | I24: - | K24: 6 | L24: =K24*165 -> 990 | M24: =(K24+0.1) -> 6.1 | N24: =M24*165 -> 1006.5 | O24: =K24+0.2 -> 6.2 | P24: =O24*165 -> 1023 | Q24: =K24+0.5 -> 6.5 | R24: =Q24*165 -> 1072.5 | S24: 29-35
A25: 重货优惠：1:200 -0.2; 1:250 -0.5，1:300 -1，1:400 -1.5，1:500 -2比重减重后最低1.2/KG。
A26: 备注：本报价为人民币报价，价格适用于普货，包含头程运费、进出口买单报关费、文件费（不含出单费）、仓库卸货费、托盘费、目的港清关、派送等费用；不包含保险费、商检费、熏蒸费、因货物问题导致的进出口海关查验费、仓库增值服务费、超期费和仓储费等，如若产生，实报实销。
A27: 计重标准 | C27: 重量转体积：1CBM=334KG; 体积转重量：1CBM=167KG；托盘，木架，木箱等非纸箱货物出货，计费重需*1.1倍
A28: 报关费&续页费 | C28: 报关费：RMB220, 超6个品名续页费：RMB50/页（即第7个起算，每6个品名一页）
A29: 超长附加费 | C29: 超过120-150CM附加费：+ RMB150/CBM(不含税)OR 1.2/KGS(含税), 超过150-200CM附加费：+ RMB200/CBM(不含税)OR 1.5/KGS(含税), 最长边限2米以内，超过2米以上或超重则需要case by case确认价格
A30: 超品名费 | C30: 每一票单超过五个品名的，收取RMB30/个
A31: 商检费 & 熏蒸费 | C31: 单询
A32: 提单费（如需） | C32: RMB300/BILL
A33: 不含税渠道进口申报要求 | C33: USD180/CBM
A34: 产品附加 | C34: 箱包类、行李箱、收纳箱、包包、鞋子、服装等纺织品类、FDA申报类产品+0.5元/KG
C35: 木制品 无单证600/票 单证+RMB800/票
A36: 本渠道拒收产品 | C36: 仿牌、液体、粉末、食品、药品、易燃易爆、古董、货币等国家禁止出口及航空公司禁运物品
C37: 纯电池，移动电源，医疗激光产品，太阳能 （大于10*10），动植物， 化妆品，医疗类产品，铅笔，有医疗作用的牙刷
C38: 侵权产品：蓝牙标及包装有蓝牙字样及标识产品
C39: 反倾销产品：请查看附件
A40: 申报要求 | C40: 如实申报，单货一致；如有需要需如实提供每个产品对应的产品图片和有售价的真实销售链接，如新品链接没有售价，需要提供亚马逊后台定价截图；如因客户低申报或申报不符（海关编码和实物不符，数量不一致等）产生的相关查验费、仓租、调高后的税金、海关罚金需由客户承担；

Sheet 芝加哥专线
A1: =_xlfn.DISPIMG("ID_D6697A225B864C34A678052B48D4E660",1) -> =DISPIMG("ID_D6697A225B864C34A678052B48D4E660",1)
A2: 渠道名称 | B2: 美中芝加哥卡派
A3: 使用船司 | B3: OA/ZIM/MSC统配
A4: 交货仓库 | B4: 东莞/中山/广州 | D4: 嘉兴/义乌 | F4: 汕头/厦门/泉州 | H4: 武汉/长沙 | J4: 参考时效 （开船后自然日）
A5: 仓库代码 | B5: 12KG+含税 | C5: 0.5CBM+不含税 | D5: 12KG+含税 | E5: 0.5CBM+不含税 | F5: 12KG+含税 | G5: 0.5CBM+不含税 | H5: 12KG+含税 | I5: 0.5CBM+不含税
A6: MDW2 | B6: 8.1 | C6: =B6*165 -> 1336.5 | D6: =(B6+0.1) -> 8.2 | E6: =D6*165 -> 1353 | F6: =B6+0.2 -> 8.3 | G6: =F6*165 -> 1369.5 | H6: =B6+0.5 -> 8.6 | I6: =H6*165 -> 1419 | J6: 32-40
A7: ORD2 | B7: 8.1 | C7: =B7*165 -> 1336.5 | D7: =(B7+0.1) -> 8.2 | E7: =D7*165 -> 1353 | F7: =B7+0.2 -> 8.3 | G7: =F7*165 -> 1369.5 | H7: =B7+0.5 -> 8.6 | I7: =H7*165 -> 1419 | J7: 32-40
A8: IGQ2 | B8: 8.1 | C8: =B8*165 -> 1336.5 | D8: =(B8+0.1) -> 8.2 | E8: =D8*165 -> 1353 | F8: =B8+0.2 -> 8.3 | G8: =F8*165 -> 1369.5 | H8: =B8+0.5 -> 8.6 | I8: =H8*165 -> 1419 | J8: 32-40
A9: MDW6 | B9: 8.1 | C9: =B9*165 -> 1336.5 | D9: =(B9+0.1) -> 8.2 | E9: =D9*165 -> 1353 | F9: =B9+0.2 -> 8.3 | G9: =F9*165 -> 1369.5 | H9: =B9+0.5 -> 8.6 | I9: =H9*165 -> 1419 | J9: 32-40
A10: MDW9 | B10: 8.1 | C10: =B10*165 -> 1336.5 | D10: =(B10+0.1) -> 8.2 | E10: =D10*165 -> 1353 | F10: =B10+0.2 -> 8.3 | G10: =F10*165 -> 1369.5 | H10: =B10+0.5 -> 8.6 | I10: =H10*165 -> 1419 | J10: 32-40
A11: RFD2 | B11: 8.1 | C11: =B11*165 -> 1336.5 | D11: =(B11+0.1) -> 8.2 | E11: =D11*165 -> 1353 | F11: =B11+0.2 -> 8.3 | G11: =F11*165 -> 1369.5 | H11: =B11+0.5 -> 8.6 | I11: =H11*165 -> 1419 | J11: 32-40
A12: RFD4 | B12: 8.1 | C12: =B12*165 -> 1336.5 | D12: =(B12+0.1) -> 8.2 | E12: =D12*165 -> 1353 | F12: =B12+0.2 -> 8.3 | G12: =F12*165 -> 1369.5 | H12: =B12+0.5 -> 8.6 | I12: =H12*165 -> 1419 | J12: 32-40
A13: JVL1 | B13: 8.1 | C13: =B13*165 -> 1336.5 | D13: =(B13+0.1) -> 8.2 | E13: =D13*165 -> 1353 | F13: =B13+0.2 -> 8.3 | G13: =F13*165 -> 1369.5 | H13: =B13+0.5 -> 8.6 | I13: =H13*165 -> 1419 | J13: 32-40
A14: 沃尔玛---ORD1S | B14: 8.1 | C14: =B14*165 -> 1336.5 | D14: =(B14+0.1) -> 8.2 | E14: =D14*165 -> 1353 | F14: =B14+0.2 -> 8.3 | G14: =F14*165 -> 1369.5 | H14: =B14+0.5 -> 8.6 | I14: =H14*165 -> 1419 | J14: 32-40
A15: IND9 | B15: 8.5 | C15: =B15*165 -> 1402.5 | D15: =(B15+0.1) -> 8.6 | E15: =D15*165 -> 1419 | F15: =B15+0.2 -> 8.7 | G15: =F15*165 -> 1435.5 | H15: =B15+0.5 -> 9 | I15: =H15*165 -> 1485 | J15: 32-40
A16: FWA4 | B16: 8.5 | C16: =B16*165 -> 1402.5 | D16: =(B16+0.1) -> 8.6 | E16: =D16*165 -> 1419 | F16: =B16+0.2 -> 8.7 | G16: =F16*165 -> 1435.5 | H16: =B16+0.5 -> 9 | I16: =H16*165 -> 1485 | J16: 32-40
A17: MQJ1 | B17: 8.5 | C17: =B17*165 -> 1402.5 | D17: =(B17+0.1) -> 8.6 | E17: =D17*165 -> 1419 | F17: =B17+0.2 -> 8.7 | G17: =F17*165 -> 1435.5 | H17: =B17+0.5 -> 9 | I17: =H17*165 -> 1485 | J17: 32-40
... A34: MCI4 | B34: 9.2 | C34: =B34*165 -> 1518 | D34: =(B34+0.1) -> 9.3 | E34: =D34*165 -> 1534.5 | F34: =B34+0.2 -> 9.4 | G34: =F34*165 -> 1551 | H34: =B34+0.5 -> 9.7 | I34: =H34*165 -> 1600.5 | J34: 32-40
A35: 重货优惠：1:200 -0.2; 1:250 -0.5，1:300 -1，1:400 -1.5，1:500 -2比重减重后最低1.2/KG。
A36: 备注：本报价为人民币报价，价格适用于普货，包含头程运费、进出口买单报关费、文件费（不含出单费）、仓库卸货费、托盘费、目的港清关、派送等费用；不包含保险费、商检费、熏蒸费、因货物问题导致的进出口海关查验费、仓库增值服务费、超期费和仓储费等，如若产生，实报实销。
A37: 计重标准 | C37: 重量转体积：1CBM=334KG; 体积转重量：1CBM=167KG；托盘，木架，木箱等非纸箱货物出货，计费重需*1.1倍
A38: 报关费&续页费 | C38: 报关费：RMB220, 超6个品名续页费：RMB50/页（即第7个起算，每6个品名一页）
A39: 超长附加费 | C39: 超过120-150CM附加费：+ RMB150/CBM(不含税)OR 1.2/KGS(含税), 超过150-200CM附加费：+ RMB200/CBM(不含税)OR 1.5/KGS(含税), 最长边限2米以内，超过2米以上或超重则需要case by case确认价格
A40: 超品名费 | C40: 每一票单超过五个品名的，收取RMB30/个
A41: 商检费 & 熏蒸费 | C41: 单询
A42: 提单费（如需） | C42: RMB300/BILL
A43: 不含税渠道进口申报要求 | C43: USD180/CBM
A44: 产品附加 | C44: 箱包类、行李箱、收纳箱、包包、鞋子、服装等纺织品类、FDA申报类产品+0.5元/KG
C45: 木制品 无单证600/票 单证+RMB800/票
A46: 本渠道拒收产品 | C46: 仿牌、液体、粉末、食品、药品、易燃易爆、古董、货币等国家禁止出口及航空公司禁运物品
C47: 纯电池，移动电源，医疗激光产品，太阳能 （大于10*10），动植物， 化妆品，医疗类产品，铅笔，有医疗作用的牙刷
C48: 侵权产品：蓝牙标及包装有蓝牙字样及标识产品
C49: 反倾销产品：请查看附件
A50: 申报要求 | C50: 如实申报，单货一致；如有需要需如实提供每个产品对应的产品图片和有售价的真实销售链接，如新品链接没有售价，需要提供亚马逊后台定价截图；如因客户低申报或申报不符（海关编码和实物不符，数量不一致等）产生的相关查验费、仓租、调高后的税金、海关罚金需由客户承担；

Sheet 休斯顿专线
A1: =_xlfn.DISPIMG("ID_D6697A225B864C34A678052B48D4E660",1) -> =DISPIMG("ID_D6697A225B864C34A678052B48D4E660",1)
A2: 渠道名称 | B2: 美中休斯顿卡派
A3: 使用船司 | B3: OA/ONE/MSC/WHL统配
A4: 交货仓库 | B4: 东莞/中山/广州 | D4: 嘉兴/义乌 | F4: 汕头/厦门/泉州 | H4: 武汉/长沙 | J4: 参考时效 （开船后自然日）
A5: 仓库代码 | B5: 12KG+含税 | C5: 0.5CBM+不含税 | D5: 12KG+含税 | E5: 0.5CBM+不含税 | F5: 12KG+含税 | G5: 0.5CBM+不含税 | H5: 12KG+含税 | I5: 0.5CBM+不含税
A6: HOU1 | B6: 7 | C6: =B6*165 -> 1155 | D6: =(B6+0.1) -> 7.1 | E6: =D6*165 -> 1171.5 | F6: =B6+0.2 -> 7.2 | G6: =F6*165 -> 1188 | H6: =B6+0.5 -> 7.5 | I6: =H6*165 -> 1237.5 | J6: 35-40
A7: HOU2 | B7: 7 | C7: =B7*165 -> 1155 | D7: =(B7+0.1) -> 7.1 | E7: =D7*165 -> 1171.5 | F7: =B7+0.2 -> 7.2 | G7: =F7*165 -> 1188 | H7: =B7+0.5 -> 7.5 | I7: =H7*165 -> 1237.5 | J7: 35-40
A8: HOU3 | B8: 7 | C8: =B8*165 -> 1155 | D8: =(B8+0.1) -> 7.1 | E8: =D8*165 -> 1171.5 | F8: =B8+0.2 -> 7.2 | G8: =F8*165 -> 1188 | H8: =B8+0.5 -> 7.5 | I8: =H8*165 -> 1237.5 | J8: 35-40
A9: HOU7 | B9: 7 | C9: =B9*165 -> 1155 | D9: =(B9+0.1) -> 7.1 | E9: =D9*165 -> 1171.5 | F9: =B9+0.2 -> 7.2 | G9: =F9*165 -> 1188 | H9: =B9+0.5 -> 7.5 | I9: =H9*165 -> 1237.5 | J9: 35-40
A10: HOU8 | B10: 7 | C10: =B10*165 -> 1155 | D10: =(B10+0.1) -> 7.1 | E10: =D10*165 -> 1171.5 | F10: =B10+0.2 -> 7.2 | G10: =F10*165 -> 1188 | H10: =B10+0.5 -> 7.5 | I10: =H10*165 -> 1237.5 | J10: 35-40
A11: IAH3 | B11: 7 | C11: =B11*165 -> 1155 | D11: =(B11+0.1) -> 7.1 | E11: =D11*165 -> 1171.5 | F11: =B11+0.2 -> 7.2 | G11: =F11*165 -> 1188 | H11: =B11+0.5 -> 7.5 | I11: =H11*165 -> 1237.5 | J11: 35-40
A12: FTW1 | B12: 7.6 | C12: =B12*165 -> 1254 | D12: =(B12+0.1) -> 7.7 | E12: =D12*165 -> 1270.5 | F12: =B12+0.2 -> 7.8 | G12: =F12*165 -> 1287 | H12: =B12+0.5 -> 8.1 | I12: =H12*165 -> 1336.5 | J12: 35-40
A13: FTW2 | B13: 7.6 | C13: =B13*165 -> 1254 | D13: =(B13+0.1) -> 7.7 | E13: =D13*165 -> 1270.5 | F13: =B13+0.2 -> 7.8 | G13: =F13*165 -> 1287 | H13: =B13+0.5 -> 8.1 | I13: =H13*165 -> 1336.5 | J13: 35-40
A14: FTW3 | B14: 7.6 | C14: =B14*165 -> 1254 | D14: =(B14+0.1) -> 7.7 | E14: =D14*165 -> 1270.5 | F14: =B14+0.2 -> 7.8 | G14: =F14*165 -> 1287 | H14: =B14+0.5 -> 8.1 | I14: =H14*165 -> 1336.5 | J14: 35-40
A15: FTW5 | B15: 7.6 | C15: =B15*165 -> 1254 | D15: =(B15+0.1) -> 7.7 | E15: =D15*165 -> 1270.5 | F15: =B15+0.2 -> 7.8 | G15: =F15*165 -> 1287 | H15: =B15+0.5 -> 8.1 | I15: =H15*165 -> 1336.5 | J15: 35-40
A16: FTW9 | B16: 7.6 | C16: =B16*165 -> 1254 | D16: =(B16+0.1) -> 7.7 | E16: =D16*165 -> 1270.5 | F16: =B16+0.2 -> 7.8 | G16: =F16*165 -> 1287 | H16: =B16+0.5 -> 8.1 | I16: =H16*165 -> 1336.5 | J16: 35-40
A17: IUTH | B17: 7.6 | C17: =B17*165 -> 1254 | D17: =(B17+0.1) -> 7.7 | E17: =D17*165 -> 1270.5 | F17: =B17+0.2 -> 7.8 | G17: =F17*165 -> 1287 | H17: =B17+0.5 -> 8.1 | I17: =H17*165 -> 1336.5 | J17: 35-40
... A30: FOE1 | B30: 8.2 | C30: =B30*165 -> 1353 | D30: =(B30+0.1) -> 8.3 | E30: =D30*165 -> 1369.5 | F30: =B30+0.2 -> 8.4 | G30: =F30*165 -> 1386 | H30: =B30+0.5 -> 8.7 | I30: =H30*165 -> 1435.5 | J30: 35-40
A31: 重货优惠：1:200 -0.2; 1:250 -0.5，1:300 -1，1:400 -1.5，1:500 -2比重减重后最低1.2/KG。
A32: 备注：本报价为人民币报价，价格适用于普货，包含头程运费、进出口买单报关费、文件费（不含出单费）、仓库卸货费、托盘费、目的港清关、派送等费用；不包含保险费、商检费、熏蒸费、因货物问题导致的进出口海关查验费、仓库增值服务费、超期费和仓储费等，如若产生，实报实销。
A33: 计重标准 | C33: 重量转体积：1CBM=334KG; 体积转重量：1CBM=167KG；托盘，木架，木箱等非纸箱货物出货，计费重需*1.1倍
A34: 报关费&续页费 | C34: 报关费：RMB220, 超6个品名续页费：RMB50/页（即第7个起算，每6个品名一页）
A35: 超长附加费 | C35: 超过120-150CM附加费：+ RMB150/CBM(不含税)OR 1.2/KGS(含税), 超过150-200CM附加费：+ RMB200/CBM(不含税)OR 1.5/KGS(含税), 最长边限2米以内，超过2米以上或超重则需要case by case确认价格
A36: 超品名费 | C36: 每一票单超过五个品名的，收取RMB30/个
A37: 商检费 & 熏蒸费 | C37: 单询
A38: 提单费（如需） | C38: RMB300/BILL
A39: 不含税渠道进口申报要求 | C39: USD180/CBM
A40: 产品附加 | C40: 箱包类、行李箱、收纳箱、包包、鞋子、服装等纺织品类、FDA申报类产品+0.5元/KG
C41: 木制品 无单证600/票 单证+RMB800/票
A42: 本渠道拒收产品 | C42: 仿牌、液体、粉末、食品、药品、易燃易爆、古董、货币等国家禁止出口及航空公司禁运物品
C43: 纯电池，移动电源，医疗激光产品，太阳能 （大于10*10），动植物， 化妆品，医疗类产品，铅笔，有医疗作用的牙刷
C44: 侵权产品：蓝牙标及包装有蓝牙字样及标识产品
C45: 反倾销产品：请查看附件
A46: 申报要求 | C46: 如实申报，单货一致；如有需要需如实提供每个产品对应的产品图片和有售价的真实销售链接，如新品链接没有售价，需要提供亚马逊后台定价截图；如因客户低申报或申报不符（海关编码和实物不符，数量不一致等）产生的相关查验费、仓租、调高后的税金、海关罚金需由客户承担；

Sheet 纽约专线
A1: =_xlfn.DISPIMG("ID_D6697A225B864C34A678052B48D4E660",1) -> =DISPIMG("ID_D6697A225B864C34A678052B48D4E660",1)
A2: 渠道名称 | B2: 美东纽约卡派
A3: 使用船司 | B3: OA/ZIM/MSC/WHL统配
A4: 交货仓库 | B4: 东莞/中山/广州 | D4: 嘉兴/义乌 | F4: 汕头/厦门/泉州 | H4: 武汉/长沙 | J4: 参考时效 （开船后自然日）
A5: 仓库代码 | B5: 12KG+含税 | C5: 0.5CBM+不含税 | D5: 12KG+含税 | E5: 0.5CBM+不含税 | F5: 12KG+含税 | G5: 0.5CBM+不含税 | H5: 12KG+含税 | I5: 0.5CBM+不含税
A6: 海外仓自提 一件代发头程 | B6: 6.7 | C6: =B6*165 -> 1105.5 | D6: =B6+0.1 -> 6.8 | E6: =D6*165 -> 1122 | F6: =B6+0.2 -> 6.9 | G6: =F6*165 -> 1138.5 | H6: =B6+0.5 -> 7.2 | I6: =H6*165 -> 1188 | J6: 37-42
A7: ACY2 | B7: 6.7 | C7: =B7*165 -> 1105.5 | D7: =B7+0.1 -> 6.8 | E7: =D7*165 -> 1122 | F7: =B7+0.2 -> 6.9 | G7: =F7*165 -> 1138.5 | H7: =B7+0.5 -> 7.2 | I7: =H7*165 -> 1188 | J7: 37-42
A8: TTN2 | B8: 6.7 | C8: =B8*165 -> 1105.5 | D8: =B8+0.1 -> 6.8 | E8: =D8*165 -> 1122 | F8: =B8+0.2 -> 6.9 | G8: =F8*165 -> 1138.5 | H8: =B8+0.5 -> 7.2 | I8: =H8*165 -> 1188 | J8: 37-42
A9: ABE8 | B9: 6.7 | C9: =B9*165 -> 1105.5 | D9: =B9+0.1 -> 6.8 | E9: =D9*165 -> 1122 | F9: =B9+0.2 -> 6.9 | G9: =F9*165 -> 1138.5 | H9: =B9+0.5 -> 7.2 | I9: =H9*165 -> 1188 | J9: 37-42
A10: TEB9 | B10: 6.7 | C10: =B10*165 -> 1105.5 | D10: =B10+0.1 -> 6.8 | E10: =D10*165 -> 1122 | F10: =B10+0.2 -> 6.9 | G10: =F10*165 -> 1138.5 | H10: =B10+0.5 -> 7.2 | I10: =H10*165 -> 1188 | J10: 37-42
A11: TEB6 | B11: 6.7 | C11: =B11*165 -> 1105.5 | D11: =B11+0.1 -> 6.8 | E11: =D11*165 -> 1122 | F11: =B11+0.2 -> 6.9 | G11: =F11*165 -> 1138.5 | H11: =B11+0.5 -> 7.2 | I11: =H11*165 -> 1188 | J11: 37-42
A12: TEB3 | B12: 6.7 | C12: =B12*165 -> 1105.5 | D12: =B12+0.1 -> 6.8 | E12: =D12*165 -> 1122 | F12: =B12+0.2 -> 6.9 | G12: =F12*165 -> 1138.5 | H12: =B12+0.5 -> 7.2 | I12: =H12*165 -> 1188 | J12: 37-42
A13: TEB4 | B13: 6.7 | C13: =B13*165 -> 1105.5 | D13: =B13+0.1 -> 6.8 | E13: =D13*165 -> 1122 | F13: =B13+0.2 -> 6.9 | G13: =F13*165 -> 1138.5 | H13: =B13+0.5 -> 7.2 | I13: =H13*165 -> 1188 | J13: 37-42
A14: XEW5 | B14: 6.7 | C14: =B14*165 -> 1105.5 | D14: =B14+0.1 -> 6.8 | E14: =D14*165 -> 1122 | F14: =B14+0.2 -> 6.9 | G14: =F14*165 -> 1138.5 | H14: =B14+0.5 -> 7.2 | I14: =H14*165 -> 1188 | J14: 37-42
A15: ABE4 | B15: 7 | C15: =B15*165 -> 1155 | D15: =B15+0.1 -> 7.1 | E15: =D15*165 -> 1171.5 | F15: =B15+0.2 -> 7.2 | G15: =F15*165 -> 1188 | H15: =B15+0.5 -> 7.5 | I15: =H15*165 -> 1237.5 | J15: 37-42
A16: AVP1 | B16: 7 | C16: =B16*165 -> 1155 | D16: =B16+0.1 -> 7.1 | E16: =D16*165 -> 1171.5 | F16: =B16+0.2 -> 7.2 | G16: =F16*165 -> 1188 | H16: =B16+0.5 -> 7.5 | I16: =H16*165 -> 1237.5 | J16: 40-45
A17: AVP9 | B17: 7 | C17: =B17*165 -> 1155 | D17: =B17+0.1 -> 7.1 | E17: =D17*165 -> 1171.5 | F17: =B17+0.2 -> 7.2 | G17: =F17*165 -> 1188 | H17: =B17+0.5 -> 7.5 | I17: =H17*165 -> 1237.5 | J17: 40-45
... A49: IUST | B49: 7.9 | C49: =B49*165 -> 1303.5 | D49: =B49+0.1 -> 8 | E49: =D49*165 -> 1320 | F49: =B49+0.2 -> 8.1 | G49: =F49*165 -> 1336.5 | H49: =B49+0.5 -> 8.4 | I49: =H49*165 -> 1386 | J49: 40-45
A50: 重货优惠：1:200 -0.2; 1:250 -0.5，1:300 -1，1:400 -1.5，1:500 -2比重减重后最低1.2/KG。
A51: 备注：本报价为人民币报价，价格适用于普货，包含头程运费、进出口买单报关费、文件费（不含出单费）、仓库卸货费、托盘费、目的港清关、派送等费用；不包含保险费、商检费、熏蒸费、因货物问题导致的进出口海关查验费、仓库增值服务费、超期费和仓储费等，如若产生，实报实销。
A52: 计重标准 | C52: 重量转体积：1CBM=334KG; 体积转重量：1CBM=167KG；托盘，木架，木箱等非纸箱货物出货，计费重需*1.1倍
A53: 报关费&续页费 | C53: 报关费：RMB220, 超6个品名续页费：RMB50/页（即第7个起算，每6个品名一页）
A54: 超长附加费 | C54: 超过120-150CM附加费：+ RMB150/CBM(不含税)OR 1.2/KGS(含税), 超过150-200CM附加费：+ RMB200/CBM(不含税)OR 1.5/KGS(含税), 最长边限2米以内，超过2米以上或超重则需要case by case确认价格
A55: 超品名费 | C55: 每一票单超过五个品名的，收取RMB30/个
A56: 商检费 & 熏蒸费 | C56: 单询
A57: 提单费（如需） | C57: RMB300/BILL
A58: 不含税渠道进口申报要求 | C58: USD180/CBM
A59: 产品附加 | C59: 箱包类、行李箱、收纳箱、包包、鞋子、服装等纺织品类、FDA申报类产品+0.5元/KG
C60: 木制品 无单证600/票 单证+RMB800/票
A61: 本渠道拒收产品 | C61: 仿牌、液体、粉末、食品、药品、易燃易爆、古董、货币等国家禁止出口及航空公司禁运物品
C62: 纯电池，移动电源，医疗激光产品，太阳能 （大于10*10），动植物， 化妆品，医疗类产品，铅笔，有医疗作用的牙刷
C63: 侵权产品：蓝牙标及包装有蓝牙字样及标识产品
C64: 反倾销产品：请查看附件
A65: 申报要求 | C65: 如实申报，单货一致；如有需要需如实提供每个产品对应的产品图片和有售价的真实销售链接，如新品链接没有售价，需要提供亚马逊后台定价截图；如因客户低申报或申报不符（海关编码和实物不符，数量不一致等）产生的相关查验费、仓租、调高后的税金、海关罚金需由客户承担；

Sheet 萨凡纳专线
A1: =_xlfn.DISPIMG("ID_D6697A225B864C34A678052B48D4E660",1) -> =DISPIMG("ID_D6697A225B864C34A678052B48D4E660",1)
A2: 渠道名称 | B2: 萨凡纳专线卡派
A3: 使用船司 | B3: OA/ZIM/MSC/WHL统配
A4: 交货仓库 | B4: 东莞/中山/广州 | D4: 嘉兴/义乌 | F4: 汕头/厦门/泉州 | H4: 武汉/长沙 | J4: 参考时效 （开船后自然日）
A5: 仓库代码 | B5: 12KG+含税 | C5: 0.5CBM+不含税 | D5: 12KG+含税 | E5: 0.5CBM+不含税 | F5: 12KG+含税 | G5: 0.5CBM+不含税 | H5: 12KG+含税 | I5: 0.5CBM+不含税
A6: MGE1 | B6: 7 | C6: =B6*165 -> 1155 | D6: =B6+0.1 -> 7.1 | E6: =D6*165 -> 1171.5 | F6: =B6+0.2 -> 7.2 | G6: =F6*165 -> 1188 | H6: =B6+0.5 -> 7.5 | I6: =H6*165 -> 1237.5 | J6: 40-48
A7: MGE3 | B7: 7 | C7: =B7*165 -> 1155 | D7: =B7+0.1 -> 7.1 | E7: =D7*165 -> 1171.5 | F7: =B7+0.2 -> 7.2 | G7: =F7*165 -> 1188 | H7: =B7+0.5 -> 7.5 | I7: =H7*165 -> 1237.5 | J7: 40-48
A8: JAX3 | B8: 7 | C8: =B8*165 -> 1155 | D8: =B8+0.1 -> 7.1 | E8: =D8*165 -> 1171.5 | F8: =B8+0.2 -> 7.2 | G8: =F8*165 -> 1188 | H8: =B8+0.5 -> 7.5 | I8: =H8*165 -> 1237.5 | J8: 40-48
A9: WAL-ATL1 | B9: 7 | C9: =B9*165 -> 1155 | D9: =B9+0.1 -> 7.1 | E9: =D9*165 -> 1171.5 | F9: =B9+0.2 -> 7.2 | G9: =F9*165 -> 1188 | H9: =B9+0.5 -> 7.5 | I9: =H9*165 -> 1237.5 | J9: 40-48
A10: XLX6 | B10: 7.3 | C10: =B10*165 -> 1204.5 | D10: =B10+0.1 -> 7.4 | E10: =D10*165 -> 1221 | F10: =B10+0.2 -> 7.5 | G10: =F10*165 -> 1237.5 | H10: =B10+0.5 -> 7.8 | I10: =H10*165 -> 1287 | J10: 40-48
A11: XPB2 | B11: 7.3 | C11: =B11*165 -> 1204.5 | D11: =B11+0.1 -> 7.4 | E11: =D11*165 -> 1221 | F11: =B11+0.2 -> 7.5 | G11: =F11*165 -> 1237.5 | H11: =B11+0.5 -> 7.8 | I11: =H11*165 -> 1287 | J11: 40-48
A12: CLT2 | B12: 7.3 | C12: =B12*165 -> 1204.5 | D12: =B12+0.1 -> 7.4 | E12: =D12*165 -> 1221 | F12: =B12+0.2 -> 7.5 | G12: =F12*165 -> 1237.5 | H12: =B12+0.5 -> 7.8 | I12: =H12*165 -> 1287 | J12: 40-48
A13: CLT3 | B13: 7.3 | C13: =B13*165 -> 1204.5 | D13: =B13+0.1 -> 7.4 | E13: =D13*165 -> 1221 | F13: =B13+0.2 -> 7.5 | G13: =F13*165 -> 1237.5 | H13: =B13+0.5 -> 7.8 | I13: =H13*165 -> 1287 | J13: 40-48
A14: RYY2 | B14: 7.3 | C14: =B14*165 -> 1204.5 | D14: =B14+0.1 -> 7.4 | E14: =D14*165 -> 1221 | F14: =B14+0.2 -> 7.5 | G14: =F14*165 -> 1237.5 | H14: =B14+0.5 -> 7.8 | I14: =H14*165 -> 1287 | J14: 40-48
A15: RDU2 | B15: 7.3 | C15: =B15*165 -> 1204.5 | D15: =B15+0.1 -> 7.4 | E15: =D15*165 -> 1221 | F15: =B15+0.2 -> 7.5 | G15: =F15*165 -> 1237.5 | H15: =B15+0.5 -> 7.8 | I15: =H15*165 -> 1287 | J15: 40-48
A16: GSO1 | B16: 7.3 | C16: =B16*165 -> 1204.5 | D16: =B16+0.1 -> 7.4 | E16: =D16*165 -> 1221 | F16: =B16+0.2 -> 7.5 | G16: =F16*165 -> 1237.5 | H16: =B16+0.5 -> 7.8 | I16: =H16*165 -> 1287 | J16: 40-48
A17: GSP1 | B17: 7.3 | C17: =B17*165 -> 1204.5 | D17: =B17+0.1 -> 7.4 | E17: =D17*165 -> 1221 | F17: =B17+0.2 -> 7.5 | G17: =F17*165 -> 1237.5 | H17: =B17+0.5 -> 7.8 | I17: =H17*165 -> 1287 | J17: 40-61
... A32: TMB8 | B32: 8 | C32: =B32*165 -> 1320 | D32: =B32+0.1 -> 8.1 | E32: =D32*165 -> 1336.5 | F32: =B32+0.2 -> 8.2 | G32: =F32*165 -> 1353 | H32: =B32+0.5 -> 8.5 | I32: =H32*165 -> 1402.5 | J32: 43-51
A33: 重货优惠：1:200 -0.2; 1:250 -0.5，1:300 -1，1:400 -1.5，1:500 -2比重减重后最低1.2/KG。
A34: 备注：本报价为人民币报价，价格适用于普货，包含头程运费、进出口买单报关费、文件费（不含出单费）、仓库卸货费、托盘费、目的港清关、派送等费用；不包含保险费、商检费、熏蒸费、因货物问题导致的进出口海关查验费、仓库增值服务费、超期费和仓储费等，如若产生，实报实销。
A35: 计重标准 | C35: 重量转体积：1CBM=334KG; 体积转重量：1CBM=167KG；托盘，木架，木箱等非纸箱货物出货，计费重需*1.1倍
A36: 报关费&续页费 | C36: 报关费：RMB220, 超6个品名续页费：RMB50/页（即第7个起算，每6个品名一页）
A37: 超长附加费 | C37: 超过120-150CM附加费：+ RMB150/CBM(不含税)OR 1.2/KGS(含税), 超过150-200CM附加费：+ RMB200/CBM(不含税)OR 1.5/KGS(含税), 最长边限2米以内，超过2米以上或超重则需要case by case确认价格
A38: 超品名费 | C38: 每一票单超过五个品名的，收取RMB30/个
A39: 商检费 & 熏蒸费 | C39: 单询
A40: 提单费（如需） | C40: RMB300/BILL
A41: 不含税渠道进口申报要求 | C41: USD180/CBM
A42: 产品附加 | C42: 箱包类、行李箱、收纳箱、包包、鞋子、服装等纺织品类、FDA申报类产品+0.5元/KG
C43: 木制品 无单证600/票 单证+RMB800/票
A44: 本渠道拒收产品 | C44: 仿牌、液体、粉末、食品、药品、易燃易爆、古董、货币等国家禁止出口及航空公司禁运物品
C45: 纯电池，移动电源，医疗激光产品，太阳能 （大于10*10），动植物， 化妆品，医疗类产品，铅笔，有医疗作用的牙刷
C46: 侵权产品：蓝牙标及包装有蓝牙字样及标识产品
C47: 反倾销产品：请查看附件
A48: 申报要求 | C48: 如实申报，单货一致；如有需要需如实提供每个产品对应的产品图片和有售价的真实销售链接，如新品链接没有售价，需要提供亚马逊后台定价截图；如因客户低申报或申报不符（海关编码和实物不符，数量不一致等）产生的相关查验费、仓租、调高后的税金、海关罚金需由客户承担；

Sheet 美西私人地址
A1: =_xlfn.DISPIMG("ID_D6697A225B864C34A678052B48D4E660",1) -> =DISPIMG("ID_D6697A225B864C34A678052B48D4E660",1)
A2: 美西90-92邮编商业地址及私人地址报价
A3: 地址 | D3: 易·15日达卡派（CLX） | I3: 易·17日达卡派 EXX/以星带托架/合德快提统配 | N3: 易·20日达卡派 以星不带托架/合德普提/SEA3定提/CEN | S3: 易·22日达卡派 （OA/COSCO） | X3: 易·25日达卡派 (（OA/MSC/ONE/WHL/HMM/TSL统配）) | AC3: 注意事项
A4: 目的港 | B4: 低消 | D4: 低消300KG， 300KG-1500KG，+1/KG | I4: 低消300KG， 300KG-1500KG，+1/KG | N4: 低消300KG， 300KG-1500KG，+1/KG | S4: 低消300KG， 300KG-1500KG，+1/KG | X4: 低消300KG， 300KG-1500KG，+1/KG
B5: 区域 | D5: 东莞/中山/广州 | E5: 嘉兴/义乌 | F5: 汕头/厦门/泉州 | G5: 武汉/长沙 | H5: 参考时效(开船后) | I5: 东莞/中山/广州 | J5: 嘉兴/义乌 | K5: 汕头/厦门/泉州 | L5: 武汉/长沙 | M5: 参考时效(开船后) | N5: 东莞/中山/广州 | O5: 嘉兴/义乌 | P5: 汕头/厦门/泉州 | Q5: 武汉/长沙 | R5: 参考时效(开船后) | S5: 东莞/中山/广州 | T5: 嘉兴/义乌 | U5: 汕头/厦门/泉州 | V5: 武汉/长沙 | W5: 参考时效(开船后) | X5: 东莞/中山/广州 | Y5: 嘉兴/义乌 | Z5: 汕头/厦门/泉州 | AA5: 武汉/长沙 | AB5: 参考时效(开船后)
B6: 仓库代码 | C6: 邮编 | D6: 1500KG+ | E6: 1500KG+ | F6: 1500KG+ | G6: 1500KG+ | I6: 1500KG+ | J6: 1500KG+ | K6: 1500KG+ | L6: 1500KG+ | N6: 1500KG+ | O6: 1500KG+ | P6: 1500KG+ | Q6: 1500KG+ | S6: 1500KG+ | T6: 1500KG+ | U6: 1500KG+ | V6: 1500KG+ | X6: 1500KG+ | Y6: 1500KG+ | Z6: 1500KG+ | AA6: 1500KG+
A7: LA/LB | B7: 京东仓92337 | C7: 92337 | D7: 11.9 | E7: =D7-0.5 -> 11.4 | F7: =D7+0.2 -> 12.1 | G7: =D7+0.5 -> 12.4 | H7: 14-18天 | I7: 8 | J7: =I7 -> 8 | K7: =I7+0.2 -> 8.2 | L7: =I7+0.5 -> 8.5 | M7: 16-20天 | N7: 7.3 | O7: =N7 -> 7.3 | P7: =N7+0.2 -> 7.5 | Q7: =N7+0.5 -> 7.8 | R7: 18-22天 | S7: 6.4 | T7: S7 | U7: =S7+0.2 -> 6.6 | V7: =S7+0.5 -> 6.9 | W7: 22-25天 | X7: 6 | Y7: =X7 -> 6 | Z7: =X7+0.2 -> 6.2 | AA7: =X7+0.5 -> 6.5 | AB7: 25-28天 | AC7: 1、标准打板限制: 1000磅/板，卡板尺寸（单位：IN）40x48"x72"，1.8CBM/板。注：超尺寸/超重按实际超板情况计费。 2、附加费：超尺寸、超重按实际超板情况计费（超尺寸，超大件货物请单独确认成本）。 3、升降机费用：如需拖车带尾板/升降机服务，需额外加收50/票。(超大件$250/票） 4、空跑费：按$200/次收取。注：因客户原因拒收/无人签收货物等情况产生。 5、卸货等候费：按 $80/时。卸货时间超一小时，开始计算。 6、本报价不含卸货费，如需卸货，按$200/票收取。 7、低消：单票收费重不足300KG，按照300KG计费。 8、邮编必须和城市一致，才能用此渠道价格，不一致请单独询价。 9、海外货物签收时，请收货人先检查外包装是否破损和及时清点收货件数，如有异常请拒收货物，如正常签收后反馈货物损坏，将无法进行货物理赔。
B8: 易达云 92337 | C8: 92337 | D8: 11.9 | E8: =D8-0.5 -> 11.4 | F8: =D8+0.2 -> 12.1 | G8: =D8+0.5 -> 12.4 | H8: 14-18天 | I8: 8 | J8: =I8 -> 8 | K8: =I8+0.2 -> 8.2 | L8: =I8+0.5 -> 8.5 | M8: 16-20天 | N8: 7.3 | O8: =N8 -> 7.3 | P8: =N8+0.2 -> 7.5 | Q8: =N8+0.5 -> 7.8 | R8: 18-22天 | S8: 6.4 | T8: =S8 -> 6.4 | U8: =S8+0.2 -> 6.6 | V8: =S8+0.5 -> 6.9 | W8: 22-25天 | X8: 6 | Y8: =X8 -> 6 | Z8: =X8+0.2 -> 6.2 | AA8: =X8+0.5 -> 6.5 | AB8: 25-28天
B9: 易达云 91761 | C9: 91761 | D9: 11.9 | E9: =D9-0.5 -> 11.4 | F9: =D9+0.2 -> 12.1 | G9: =D9+0.5 -> 12.4 | H9: 14-18天 | I9: 8 | J9: =I9 -> 8 | K9: =I9+0.2 -> 8.2 | L9: =I9+0.5 -> 8.5 | M9: 16-20天 | N9: 7.3 | O9: =N9 -> 7.3 | P9: =N9+0.2 -> 7.5 | Q9: =N9+0.5 -> 7.8 | R9: 18-22天 | S9: 6.4 | T9: =S9 -> 6.4 | U9: =S9+0.2 -> 6.6 | V9: =S9+0.5 -> 6.9 | W9: 22-25天 | X9: 6 | Y9: =X9 -> 6 | Z9: =X9+0.2 -> 6.2 | AA9: =X9+0.5 -> 6.5 | AB9: 25-28天
B10: 谷仓 | C10: 91710 / 92336 / 91761 / 91762 | D10: 11.9 | E10: =D10-0.5 -> 11.4 | F10: =D10+0.2 -> 12.1 | G10: =D10+0.5 -> 12.4 | H10: 14-18天 | I10: 8 | J10: =I10 -> 8 | K10: =I10+0.2 -> 8.2 | L10: =I10+0.5 -> 8.5 | M10: 16-20天 | N10: 7.3 | O10: =N10 -> 7.3 | P10: =N10+0.2 -> 7.5 | Q10: =N10+0.5 -> 7.8 | R10: 18-22天 | S10: 6.4 | T10: =S10 -> 6.4 | U10: =S10+0.2 -> 6.6 | V10: =S10+0.5 -> 6.9 | W10: 22-25天 | X10: 6 | Y10: =X10 -> 6 | Z10: =X10+0.2 -> 6.2 | AA10: =X10+0.5 -> 6.5 | AB10: 25-28天
B11: 4PX | C11: 91730 / 90022 | D11: 12.1 | E11: =D11-0.5 -> 11.6 | F11: =D11+0.2 -> 12.3 | G11: =D11+0.5 -> 12.6 | H11: 14-18天 | I11: 8.5 | J11: =I11 -> 8.5 | K11: =I11+0.2 -> 8.7 | L11: =I11+0.5 -> 9 | M11: 16-20天 | N11: 7.7 | O11: =N11 -> 7.7 | P11: =N11+0.2 -> 7.9 | Q11: =N11+0.5 -> 8.2 | R11: 18-22天 | S11: 6.8 | T11: =S11 -> 6.8 | U11: =S11+0.2 -> 7 | V11: =S11+0.5 -> 7.3 | W11: 22-25天 | X11: 6.4 | Y11: =X11 -> 6.4 | Z11: =X11+0.2 -> 6.6 | AA11: =X11+0.5 -> 6.9 | AB11: 25-28天
B12: 万邑通 | C12: 91789 | D12: 12.1 | E12: =D12-0.5 -> 11.6 | F12: =D12+0.2 -> 12.3 | G12: =D12+0.5 -> 12.6 | H12: 14-18天 | I12: 8.2 | J12: =I12 -> 8.2 | K12: =I12+0.2 -> 8.4 | L12: =I12+0.5 -> 8.7 | M12: 16-20天 | N12: 7.5 | O12: =N12 -> 7.5 | P12: =N12+0.2 -> 7.7 | Q12: =N12+0.5 -> 8 | R12: 18-22天 | S12: 6.8 | T12: =S12 -> 6.8 | U12: =S12+0.2 -> 7 | V12: =S12+0.5 -> 7.3 | W12: 22-25天 | X12: 6.4 | Y12: =X12 -> 6.4 | Z12: =X12+0.2 -> 6.6 | AA12: =X12+0.5 -> 6.9 | AB12: 25-28天
B13: FONTANA | C13: 9233X | D13: 12.1 | E13: =D13-0.5 -> 11.6 | F13: =D13+0.2 -> 12.3 | G13: =D13+0.5 -> 12.6 | H13: 14-18天 | I13: 8 | J13: =I13 -> 8 | K13: =I13+0.2 -> 8.2 | L13: =I13+0.5 -> 8.5 | M13: 16-20天 | N13: 7.3 | O13: =N13 -> 7.3 | P13: =N13+0.2 -> 7.5 | Q13: =N13+0.5 -> 7.8 | R13: 18-22天 | S13: 6.4 | T13: =S13 -> 6.4 | U13: =S13+0.2 -> 6.6 | V13: =S13+0.5 -> 6.9 | W13: 22-25天 | X13: 6 | Y13: =X13 -> 6 | Z13: =X13+0.2 -> 6.2 | AA13: =X13+0.5 -> 6.5 | AB13: 25-28天
B14: ONTARIO | C14: 9176X | D14: 12.1 | E14: =D14-0.5 -> 11.6 | F14: =D14+0.2 -> 12.3 | G14: =D14+0.5 -> 12.6 | H14: 14-18天 | I14: 8 | J14: =I14 -> 8 | K14: =I14+0.2 -> 8.2 | L14: =I14+0.5 -> 8.5 | M14: 16-20天 | N14: 7.3 | O14: =N14 -> 7.3 | P14: =N14+0.2 -> 7.5 | Q14: =N14+0.5 -> 7.8 | R14: 18-22天 | S14: 6.4 | T14: =S14 -> 6.4 | U14: =S14+0.2 -> 6.6 | V14: =S14+0.5 -> 6.9 | W14: 22-25天 | X14: 6 | Y14: =X14 -> 6 | Z14: =X14+0.2 -> 6.2 | AA14: =X14+0.5 -> 6.5 | AB14: 25-28天
B15: CHINO | C15: 9171X | D15: 12.1 | E15: =D15-0.5 -> 11.6 | F15: =D15+0.2 -> 12.3 | G15: =D15+0.5 -> 12.6 | H15: 14-18天 | I15: 8 | J15: =I15 -> 8 | K15: =I15+0.2 -> 8.2 | L15: =I15+0.5 -> 8.5 | M15: 16-20天 | N15: 7.3 | O15: =N15 -> 7.3 | P15: =N15+0.2 -> 7.5 | Q15: =N15+0.5 -> 7.8 | R15: 18-22天 | S15: 6.4 | T15: =S15 -> 6.4 | U15: =S15+0.2 -> 6.6 | V15: =S15+0.5 -> 6.9 | W15: 22-25天 | X15: 6 | Y15: =X15 -> 6 | Z15: =X15+0.2 -> 6.2 | AA15: =X15+0.5 -> 6.5 | AB15: 25-28天
B16: DIAMOND BAR | C16: 9176X | D16: 12.3 | E16: =D16-0.5 -> 11.8 | F16: =D16+0.2 -> 12.5 | G16: =D16+0.5 -> 12.8 | H16: 14-18天 | I16: 8.2 | J16: =I16 -> 8.2 | K16: =I16+0.2 -> 8.4 | L16: =I16+0.5 -> 8.7 | M16: 16-20天 | N16: 7.5 | O16: =N16 -> 7.5 | P16: =N16+0.2 -> 7.7 | Q16: =N16+0.5 -> 8 | R16: 18-22天 | S16: 6.6 | T16: =S16 -> 6.6 | U16: =S16+0.2 -> 6.8 | V16: =S16+0.5 -> 7.1 | W16: 22-25天 | X16: 6.2 | Y16: =X16 -> 6.2 | Z16: =X16+0.2 -> 6.4 | AA16: =X16+0.5 -> 6.7 | AB16: 25-28天
B17: POMONA | C17: 9176X | D17: 12.3 | E17: =D17-0.5 -> 11.8 | F17: =D17+0.2 -> 12.5 | G17: =D17+0.5 -> 12.8 | H17: 14-18天 | I17: 8.2 | J17: =I17 -> 8.2 | K17: =I17+0.2 -> 8.4 | L17: =I17+0.5 -> 8.7 | M17: 16-20天 | N17: 7.5 | O17: =N17 -> 7.5 | P17: =N17+0.2 -> 7.7 | Q17: =N17+0.5 -> 8 | R17: 18-22天 | S17: 6.6 | T17: =S17 -> 6.6 | U17: =S17+0.2 -> 6.8 | V17: =S17+0.5 -> 7.1 | W17: 22-25天 | X17: 6.2 | Y17: =X17 -> 6.2 | Z17: =X17+0.2 -> 6.4 | AA17: =X17+0.5 -> 6.7 | AB17: 25-28天
B18: AZUSA | C18: 9170X | D18: 12.3 | E18: =D18-0.5 -> 11.8 | F18: =D18+0.2 -> 12.5 | G18: =D18+0.5 -> 12.8 | H18: 14-18天 | I18: 8.2 | J18: =I18 -> 8.2 | K18: =I18+0.2 -> 8.4 | L18: =I18+0.5 -> 8.7 | M18: 16-20天 | N18: 7.5 | O18: =N18 -> 7.5 | P18: =N18+0.2 -> 7.7 | Q18: =N18+0.5 -> 8 | R18: 18-22天 | S18: 6.6 | T18: =S18 -> 6.6 | U18: =S18+0.2 -> 6.8 | V18: =S18+0.5 -> 7.1 | W18: 22-25天 | X18: 6.2 | Y18: =X18 -> 6.2 | Z18: =X18+0.2 -> 6.4 | AA18: =X18+0.5 -> 6.7 | AB18: 25-28天
B19: SAN DIMAS | C19: 9177X | D19: 12.3 | E19: =D19-0.5 -> 11.8 | F19: =D19+0.2 -> 12.5 | G19: =D19+0.5 -> 12.8 | H19: 14-18天 | I19: 8.2 | J19: =I19 -> 8.2 | K19: =I19+0.2 -> 8.4 | L19: =I19+0.5 -> 8.7 | M19: 16-20天 | N19: 7.5 | O19: =N19 -> 7.5 | P19: =N19+0.2 -> 7.7 | Q19: =N19+0.5 -> 8 | R19: 18-22天 | S19: 6.6 | T19: =S19 -> 6.6 | U19: =S19+0.2 -> 6.8 | V19: =S19+0.5 -> 7.1 | W19: 22-25天 | X19: 6.2 | Y19: =X19 -> 6.2 | Z19: =X19+0.2 -> 6.4 | AA19: =X19+0.5 -> 6.7 | AB19: 25-28天
B20: SAN BERNARDINO | C20: 9240X | D20: 12.3 | E20: =D20-0.5 -> 11.8 | F20: =D20+0.2 -> 12.5 | G20: =D20+0.5 -> 12.8 | H20: 14-18天 | I20: 8.2 | J20: =I20 -> 8.2 | K20: =I20+0.2 -> 8.4 | L20: =I20+0.5 -> 8.7 | M20: 16-20天 | N20: 7.5 | O20: =N20 -> 7.5 | P20: =N20+0.2 -> 7.7 | Q20: =N20+0.5 -> 8 | R20: 18-22天 | S20: 6.6 | T20: =S20 -> 6.6 | U20: =S20+0.2 -> 6.8 | V20: =S20+0.5 -> 7.1 | W20: 22-25天 | X20: 6.2 | Y20: =X20 -> 6.2 | Z20: =X20+0.2 -> 6.4 | AA20: =X20+0.5 -> 6.7 | AB20: 25-28天
B21: RIVERSIDE | C21: 9250X | D21: 12.3 | E21: =D21-0.5 -> 11.8 | F21: =D21+0.2 -> 12.5 | G21: =D21+0.5 -> 12.8 | H21: 14-18天 | I21: 8.2 | J21: =I21 -> 8.2 | K21: =I21+0.2 -> 8.4 | L21: =I21+0.5 -> 8.7 | M21: 16-20天 | N21: 7.5 | O21: =N21 -> 7.5 | P21: =N21+0.2 -> 7.7 | Q21: =N21+0.5 -> 8 | R21: 18-22天 | S21: 6.6 | T21: =S21 -> 6.6 | U21: =S21+0.2 -> 6.8 | V21: =S21+0.5 -> 7.1 | W21: 22-25天 | X21: 6.2 | Y21: =X21 -> 6.2 | Z21: =X21+0.2 -> 6.4 | AA21: =X21+0.5 -> 6.7 | AB21: 25-28天
B22: COLTON | C22: 9232X | D22: 12.3 | E22: =D22-0.5 -> 11.8 | F22: =D22+0.2 -> 12.5 | G22: =D22+0.5 -> 12.8 | H22: 14-18天 | I22: 8.2 | J22: =I22 -> 8.2 | K22: =I22+0.2 -> 8.4 | L22: =I22+0.5 -> 8.7 | M22: 16-20天 | N22: 7.5 | O22: =N22 -> 7.5 | P22: =N22+0.2 -> 7.7 | Q22: =N22+0.5 -> 8 | R22: 18-22天 | S22: 6.6 | T22: =S22 -> 6.6 | U22: =S22+0.2 -> 6.8 | V22: =S22+0.5 -> 7.1 | W22: 22-25天 | X22: 6.2 | Y22: =X22 -> 6.2 | Z22: =X22+0.2 -> 6.4 | AA22: =X22+0.5 -> 6.7 | AB22: 25-28天
B23: ANAHEIM | C23: 9280X | D23: 12.3 | E23: =D23-0.5 -> 11.8 | F23: =D23+0.2 -> 12.5 | G23: =D23+0.5 -> 12.8 | H23: 14-18天 | I23: 8.2 | J23: =I23 -> 8.2 | K23: =I23+0.2 -> 8.4 | L23: =I23+0.5 -> 8.7 | M23: 16-20天 | N23: 7.5 | O23: =N23 -> 7.5 | P23: =N23+0.2 -> 7.7 | Q23: =N23+0.5 -> 8 | R23: 18-22天 | S23: 6.6 | T23: =S23 -> 6.6 | U23: =S23+0.2 -> 6.8 | V23: =S23+0.5 -> 7.1 | W23: 22-25天 | X23: 6.2 | Y23: =X23 -> 6.2 | Z23: =X23+0.2 -> 6.4 | AA23: =X23+0.5 -> 6.7 | AB23: 25-28天
B24: SANTA FE SPRINGS | C24: 9067X | D24: 12.3 | E24: =D24-0.5 -> 11.8 | F24: =D24+0.2 -> 12.5 | G24: =D24+0.5 -> 12.8 | H24: 14-18天 | I24: 8.2 | J24: =I24 -> 8.2 | K24: =I24+0.2 -> 8.4 | L24: =I24+0.5 -> 8.7 | M24: 16-20天 | N24: 7.5 | O24: =N24 -> 7.5 | P24: =N24+0.2 -> 7.7 | Q24: =N24+0.5 -> 8 | R24: 18-22天 | S24: 6.6 | T24: =S24 -> 6.6 | U24: =S24+0.2 -> 6.8 | V24: =S24+0.5 -> 7.1 | W24: 22-25天 | X24: 6.2 | Y24: =X24 -> 6.2 | Z24: =X24+0.2 -> 6.4 | AA24: =X24+0.5 -> 6.7 | AB24: 25-28天
... B41: ALHAMBRA | C41: 9180X | D41: 12.5 | E41: =D41-0.5 -> 12 | F41: =D41+0.2 -> 12.7 | G41: =D41+0.5 -> 13 | H41: 14-18天 | I41: 8.5 | J41: =I41 -> 8.5 | K41: =I41+0.2 -> 8.7 | L41: =I41+0.5 -> 9 | M41: 16-20天 | N41: 7.7 | O41: =N41 -> 7.7 | P41: =N41+0.2 -> 7.9 | Q41: =N41+0.5 -> 8.2 | R41: 18-22天 | S41: 7 | T41: =S41 -> 7 | U41: =S41+0.2 -> 7.2 | V41: =S41+0.5 -> 7.5 | W41: 22-25天 | X41: 6.6 | Y41: =X41 -> 6.6 | Z41: =X41+0.2 -> 6.8 | AA41: =X41+0.5 -> 7.1 | AB41: 25-28天
A42: 重货优惠：1:200 -0.2; 1:250 -0.5，1:300 -1，1:400 -1.5，1:500 -2比重减重后最低1.2/KG。
A43: 备注：本报价为人民币报价，价格适用于普货，包含头程运费、进出口买单报关费、文件费（不含出单费）、仓库卸货费、托盘费、目的港清关、派送等费用；不包含保险费、商检费、熏蒸费、因货物问题导致的进出口海关查验费、仓库增值服务费、超期费和仓储费等，如若产生，实报实销。
A44: 报关费&续页费 | C44: 报关费：RMB220, 超6个品名续页费：RMB50/页（即第7个起算，每6个品名一页）
A45: 计重标准 | B45: 重量转体积：1CBM=334KG; 体积转重量：1CBM=167KG；托盘，木架，木箱等非纸箱货物出货，计费重需*1.1倍
A46: 超长附加费 | C46: 超过120-150CM附加费：+ RMB150/CBM(不含税)OR 1.2/KGS(含税),超过150-200CM附加费：+ RMB200/CBM(不含税)OR 1.5/KGS(含税),最长边限2米以内，超过2米以上或超重则需要case by case确认价格
A47: 超品名费 | C47: 每一票单超过五个品名的，收取RMB30/个
A48: 商检费 & 熏蒸费 | C48: 单询
A49: 提单费（如需） | C49: RMB300/BILL
A50: 产品附加 | C50: 箱包类、行李箱、收纳箱、包包、鞋子、服装等纺织品类、FDA申报类产品+0.5元/KG
C51: 木制品 无单证600/票 单证+RMB800/票
A52: 本渠道拒收产品 | B52: 仿牌、液体、粉末、食品、药品、易燃易爆、古董、货币等国家禁止出口及航空公司禁运物品
B53: 纯电池，移动电源，医疗激光产品，太阳能 （大于10*10），动植物， 化妆品，医疗类产品，铅笔，有医疗作用的牙刷
B54: 侵权产品：蓝牙标及包装有蓝牙字样及标识产品
B55: 反倾销产品：请查看附件
A56: 申报要求 | B56: 如实申报，单货一致；如有需要需如实提供每个产品对应的产品图片和有售价的真实销售链接，如新品链接没有售价，需要提供亚马逊后台定价截图；如因客户低申报或申报不符（海关编码和实物不符，数量不一致等）产生的相关查验费、仓租、调高后的税金、海关罚金需由客户承担；

Sheet 欧海通
A1: =_xlfn.DISPIMG("ID_D6697A225B864C34A678052B48D4E660",1) -> =DISPIMG("ID_D6697A225B864C34A678052B48D4E660",1)
A2: 欧洲海派包税（UPS/DPD/GLS派送）
A3: 仓库代码（直送/卡派） | B3: 100KG+ | F3: 备注
A4: 44145(DTM2) DTM1 | B4: 7.1 | F4: 无重货优惠，拒收纺织品和多品名产品，尺寸限制不超亚马逊标准即可，实重不超30KG；开船后45-50天签收 | G4: 0.2
A5: 38350(HAJ1)/BER8/KSF7/DTM9/MHG9/ | B5: 7.4
A6: 06126(WRO5) | B6: 7.6
A7: 国家 | B7: 30KG+ | C7: 61KG+ | E7: 100KG+ | F7: 备注
A8: 德国 | B8: 10.6 | C8: 9.1 | E8: 8.1 | F8: 开船后45自然日 东欧、希腊清关 UPS/DPD/OLL派送
A9: 法国、波兰、捷克、匈牙利、斯洛伐克、奥地利、比利时、荷兰 | B9: 12.7 | C9: 11.2 | E9: 10.2
A10: 保加利亚、丹麦、爱沙尼亚、拉脱维亚、卢森堡、摩纳哥、斯洛文尼亚 | B10: 13.2 | C10: 11.7 | E10: 10.7
A11: 西班牙、意大利、克罗地亚、 瑞典 | B11: 13.7 | C11: 12.2 | E11: 11.2
A12: 芬兰、爱尔兰、葡萄牙、希腊 | B12: 14.5 | C12: 13 | E12: 12
A13: 重货优惠：货型1:250以上（实重除以体积），单价减0.5/KG(单箱平均重量满足15公斤以上) 1：300 减1，1：400 减1.5 ，1：500减2
A14: 一、注意事项
A15: 1、以上价格人民币报价，私人地址+1元/KG，低消100元/票；木制品商检费300元/品名；一般贸易报关件木制品商检800元/品名。
A16: 2、欧洲快船线路：深圳盐田→鹿特丹(荷兰)→东欧（清关） 快递提取（全程45-55天）
A17: 3、报关：一般贸易报关费: RMB350元/票报关费，续页费RMB80元/页；一达通报关费：RMB500/票，续页费RMB80/页报关口岸
A18: 4、单件计费重量不得低于12KG，单件低于12KG请自行做好并件处理，不足12KG部分按12KG每件收费处理；货物重量的计算方式：长*宽*高CM/6000,实重与材积重取大值为计费重；
A19: 5、单票品名超5个，第6个品名开始加收RMB30/个。
A20: 6、交货前需提交货清单与发票，货物品名和价值需要如实申报，资料标明是否带电，是否为一般贸易报关；
A21: 7、偏远地址加收RMB5/KG,最低单票收费RMB240。注意亚马逊货也可能产生住宅地址及杂费，如产生账单半年有效实报实销,欲知您所发货物目的地是否属偏远地区请上UPS网查询,我司出货时不另行通知，以UPS帐单产生为准。亚马逊仓邮编66050 45340也属于偏远！
A22: 以上为人民币报价：包括运费、清关费、税费、国外派送费等，不含上门提货费，查验费，罚金及仓租等费用，这些费用如有发生，实报实销，汇率按我司每次公布的汇率为准。所有报价均不含税，若开票有税点，税费需客户承担。
A23: 二、包装要求说明
A24: 1.只接受方正硬朗无破损纸箱包装，单件计费重量不得低于13KG，单件低于13KG请自行做好并件处理，2件起收，单件实重小于等于31KGS，材积6000计算
... A26: 3.不接受金属，木箱，不规则包装，压缩包，编织袋以及打包带包装。
A27: 派送方式 | B27: 类型 | C27: 费用解释说明 | F27: 附加费（件）
A28: DE_UPS | B28: 不规则 | C28: 1.金属或木制外包装箱 2.不规则包裹（不是长/正方体） 3.最长边≥100cm 或次长边≥76cm 4.实重≥25kg | F28: 22.25
B29: 大包裹 | C29: 周长大于300cm，小于400cm；2*(高+宽)+长 | F29: 95.55
B30: 超大件 | C30: 1.实重≥70kg 2.最长边≥274cm 3.最长边+2*(宽+高）≥400cm （大包裹费及所有其他适用的费用照收） | F30: 217
A31: DE_DHL | B31: 大包裹 | C31: 包裹超31.5kg； 宽度超过60cm,或高度超过60cm,或长度超120cm,长度不超200cm;围长不超过300cm; 2*(高+宽)+长 | F31: 不接
A32: DE_GLS | B32: 大包裹 | C32: 包裹超30kg,不超40kg; 宽度超过70cm,或高度超过60cm,或长度超120cm,长度不超200cm;围长不超过300cm; 2*(高+宽)+长 | F32: 10
A33: DE_DPD | B33: 超尺寸 | C33: 长度超过120cm,小于175cm; 或宽度或高度超过60cm; 或单位体积超过0.15立方米（长*宽*高÷1000000） | F33: 9
B34: 大包裹 | C34: 包裹超过31.5kg; 或单边长超过175cm; 或2*(高+宽)+长 大于300cm | F34: 40
B35: 超大件 | C35: 包裹超40kg; 或单边长超250cm; 或2*(高+宽)+长 大于330cm | F35: 60
A36: 三、后端派送说明
A37: 1货物在国内出仓后，如有需要请在到港前及时提出扣货，换标等需求，我司将尽早告知海外同事处理。
A38: 2、快递派送过程中，若因收件人地址和收件人原因造成货物被退回我司海外办事处，因此在当地产生其他费用皆由客户自行承担，费用以我司账单为准（不提供快递账单）；若客户需要二次重派，则需收取RMB150/票的重派操作费，二次重派费用实报实销（不提供UPS账单），具体以我司账单金额为准，请先和我司业务确认预估重派费用，需先收取操作费用再进行安排重派；私人地址与商业地址如果货物已经提取，由于客户原因（收件方拒收、产品本身原因、资料错误原因等）导致退回，我司会协助重派工作，但是不作后续任何赔偿，请务必和平台收件人以及发货人提前沟通这点！
A40: 3、退件费：当天打单须退件加收RMB100/票，如已装柜不接受退件。暂扣件及改派地址业务，我司不承诺百分百成功，如有此失误我司不承担任何赔偿
A41: 四、免责声明与赔偿条款声明
A42: 免责声明：
A43: 1.我司无法保证可以逐一审核查验所有货物及其发票箱单和外箱包装等, 如因货物本身及发票箱单、包装等问题导致海关扣货、收件人拒收或退回，所产生的一切费用及责任由发件方承担。
A44: 2.不符合目的地国家进口要求的货物不能寄运！出口货物需要办理审批、检验、认证等手续的，发件方应当将办理完有关手续的证明文件提交我司，但我司无鉴别货物出口所需授权、检验、认证等资料文件真实性的能力，发件方所提供的相关文件，我司默认其真实有效。如因产品授权，认证等相关资料缺失或者无效导致货物退运、查没、扣留、销毁等产生的所有责任和相关费用将由发件方承担，给我司或第三人造成经济损失的，发件方应承担相对应责任
A45: 3.目的地海关认定货物是品牌货物，或者是CE、蓝牙、HDMI、FDA、FCC、Lacey Act、DOT等认证和授权的问题，或者货物属于当地反倾销货物或不符合目的地国家进口要求的货物，客人需要提供相应授权书和认证报告，（如下货物需要CE认证或产品上有CE标志：包括电子产品、电器、灯具、玩具类、机械类、带电产品。其中玩具因为涉及儿童健康，还需要ENT1标准测试报告，主要涉及无毒无害证明，玩具上还要有具体吊牌商标适合年龄段等等详细的说明）。
A46: 4.因不可抗拒因素造成的延误和丢件，我司不承担赔偿责任。（不可抗抗拒因素包括但不限于地震、泥石流、洪涝灾害；台风、暴雨雪、雾霾等恶劣天气；罢工、恐怖事件、意外交通事故、法规政策的修改、政府、海关等司法机关的行为、决定或命令；抢劫、飞车抢夺等暴力犯罪；船司或班列的甩柜等不可控因素；疫情原因造成的在港口和堆场滞留，目的地车站海关查验、派送承运商造成的延误等。）
A47: 5.发往亚马逊货物请自行贴好入仓FBA标签贴纸，每件外箱包装上须粘贴2个以上合格的FBA标签贴纸并用透明胶布覆盖(必须达到条码字体清晰、防潮湿耐磨损)，我司不再对包装做任何审核
A48: 6.托寄物可能获得的收益、利润、实际用途、商业机会、商业价值等任何间接损失，我司不承担赔偿责任。
... A57: 特别提示：如客户一旦在我司交货，默认为客户已详细阅读过此价格表备注内容，并接受和享受各条款。

Sheet 欧铁通
A1: =_xlfn.DISPIMG("ID_D6697A225B864C34A678052B48D4E660",1) -> =DISPIMG("ID_D6697A225B864C34A678052B48D4E660",1)
A2: 欧洲铁路包税-亚马逊专线-卡派
A3: 德国FBA仓库 | B3: 45KG+ | C3: 100KG+ | D3: 卡派 | E3: 备注
A4: 06126（WRO5)/HAJ1/DTM2 | B4: 12.3 | C4: 10.3 | D4: 开班列后预计35-38天左右提取 | E4: 亚马逊直送，无需预约 免打托、丢件率低、每票都有手签POD
A5: 尺寸计费要求： 单件不足12KG按12kg计重 德国WRO5、HAJ1、DTM2、无超尺寸附加费 以上单箱货物实重超31.5KG，收取6欧/箱超重费，单箱超40kg单询 其他仓最长边超120CM，次边超60CM，单箱体积超0.15方，加收费2.5欧/箱。周长大于300CM，加收6欧/箱，周长大于330CM单询 专线货物拦截包裹：10欧/箱。拦截结果反馈后，5天免仓期，超过后按周收取，下达操作指令后停止计费，5欧/周/箱。
A6: 专线无重货优惠
A7: DHL/DPD/UPS/GLS派送 指定快递派送+1/KG
A8: 国家 | B8: 45KG+ | C8: 75KG+ | D8: 100KG+ | E8: 时效(快递提取)
A9: 德国(FBA DHL/UPS) | B9: 12.89 | C9: 11.89 | D9: 10.89 | E9: 开班列后预计35-38天左右提取
A10: 德国(非FBA UPS派送) | B10: 14.29 | C10: 13.29 | D10: 12.29 | E10: 开班列后预计35-38天左右提取
A11: 法国(UPS) | B11: 14.5 | C11: 13.5 | D11: 12.5 | E11: 开班列后预计35-38天左右提取
A12: 西班牙、意大利(UPS) | B12: 14.99 | C12: 13.99 | D12: 12.99 | E12: 开班列后预计35-38天左右提取
A13: 波兰、比利时、荷兰、奥地利(UPS) | B13: 15.5 | C13: 14.5 | D13: 13.5 | E13: 开班列后预计35-38天左右提取
A14: 捷克、芬兰、瑞典、斯洛伐克、斯洛文尼亚、丹麦、卢森堡、葡萄牙、希腊、爱尔兰、爱沙尼亚、克罗地亚、匈牙利、保加利亚、立陶宛、拉脱维亚(UPS) | B14: 15.89 | C14: 14.89 | D14: 13.89 | E14: 开班列后预计35-38天左右提取
A15: 1:250优惠0.5/KG；1:350优惠1/KG。
A16: 路线： 深圳装柜---重庆/成都/郑州---阿拉山口---哈萨克斯坦---俄罗斯--- 白俄罗斯--- 波兰 /杜堡
A17: CE类产品：要求客户运输包装上印刷CE标志，并在海关查验时提供合格的CE证书，否则由此引起的责任由客户自行承担。
A18: 加收产品：品名超过5个，加收35RMB/个 ，木制品需要做商检，商检费用800-1000不等,1箱货不超过5品名，1票货不超过8个品名，超过不接
A19: 拒收产品 | B19: 敏感货、粉末液体、膏体、反倾销类产品（自行车、电动自行车、大型太阳能光伏产品、汽车轮毂等）
A20: 其他产品 | B20: 如果货物为高货值商品（海关核价后单价超过20欧元）我们将出示海关完税单，并额外收取费用，费用=货值1欧元=1元人民币(如海关核价于20欧元一件，我司就加收20RMB/个产品单个产品为100欧，我司就加收100RMB/个产品，)
A21: 单独报关 | B21: 可接受单独报关件，加收350元/票；报关件一票金额超过5万需加500元/票，超10万需加1300元/票,超20万以上报不了（请分票报关），请知悉！
A22: 郑重声明 | B22: 如遇查柜，无赔偿，我司会尽量处理，请耐心等待，如需提供相关文件清关，请客户配合处理，因真实文件缺失导致的扣货或没收我司概不负责，请严格按照真实品名申报，不得谎报漏报品名，一旦查出，退件费200RMB/票，需谎报漏报品名重出费：RMB50/个
A23: 报价说明
A24: A | B24: 销售价格：A、以上价格仅包含报关费、铁路运费、清关费、税金、派送费等，不包含查验费及仓租等费用；B、单件货物（计费重：实重或者材积有一个需满足）不能低于12kg，不足12KG按照12KG收费；C、如果地址错误产生UPS改地址和扣件费用，将按每票100RMB收取；D、偏远地址加收4.5*U元/KG，最低收费220*U元/票，请自行查偏远地区，UPS偏远费3个月内收取；E、暂扣件及改派地址业务，我司不承诺百分百成功，如有此问题我司不承担任何赔偿。
A25: B | B25: 其他费用：若客户使用自出单出口报关，则每票加收CNY500。
A26: C | B26: 跟人体直接接触的相关产品，必须具备欧洲相关资质认证以及相关证书，提前提交我司，审核通过之后才能安排出货，否则我司概不承接此类货物。常见人体直接接触的产品：奶瓶，磨牙棒，儿童玩具类等幼儿用品；杯子，刀叉，碗筷跟口腔直接接触类产品；粉底，精油，眼影等化妆品。
A27: D | B27: 计费重量：计费重量按体积重量和实际重量相比，二者取其大者；体积重量=长*宽*高/6000CM；计费重量以我司国内仓包裹测量的体积为准；
A28: E | B28: UPS 特殊收费明细 一、以下情况会产生额外附加费：35欧/箱， 1）最长边 ＞100CM 或者 次长边＞ 76CM； 2）30KG＞实际重量（非体积重）＞ 25KG； 二、以下情况会产生大型包裹附加费：180欧/件 1）如果单个包裹的体积周长大于 300CM，并且小于 400CM，须加收包裹的超大件费用。 2）体积周长：= 长＋2×（宽＋高）（CM） 3）70KG＞实际重量（非体积重）＞ 30KG； 收取大型包裹附加费时，不收取额外处理费。 三、以下情况的的货物UPS会拒收： 1）不规则包装(例如：木箱包装、软包装、非方形包装等)； 2）最长边超过274CM； 3）体积周长 ＞ 400CM； 4）包裹重量 ＞ 70KG； 四、地址更正:10欧/箱 如果地址有误，我们将尽一切合理的努力找到正确的地址，并在同一 目的地国家内交付货物。我们 将向发货人收取额外费用。 DHL 特殊收费明细,超过以下标准手续25欧每箱 1、最大尺寸限制：长边≤120cm，且宽边≤60cm，且高度≤60cm, 或长＋2*（宽＋高）≤300cm 2、最小尺寸限制：长边≥15cm，且宽边≥11cm，且高度≥1cm。 3、重量限制：包裹净重≤30kg。超过拒收 非正常包装 异型包裹、非纸箱包裹：如圆柱体，麻袋等 形状包裹 收取35欧/箱 （1）发往亚马逊货物请自行贴好入仓FBA标签贴纸，单件超过15公斤，请按照Amazon FBA的规定，贴上“Team Lift"标签，每件外箱包装上须粘贴2个以上合格的FBA标签贴 纸并用透明胶布覆盖(必须达到条码字体清晰、防潮湿耐磨损)，如因FBA标签不能被识 别导致无法派送入亚玛逊仓库所带来的后果将由发件人自行承担！ （2）带电产品，清单需备注。
A29: F | B29: CE类产品：要求客户运输包装上印刷CE标志，并在海关查验时提供合格的CE证书，否则由此引起的责任由客户自行承担。
A30: G | B30: 货物资料：如实提供完整详细的货品描述，包括材质、用途、产品价值等信息，因提供信息与实际不符带来的风险由客户自行承担。
A31: H | B31: 后程派送： （1）后端为UPS派送模式，一站式服务，装柜后不接受扣件服务； （2）若因发件人的失误造成派件地址错误产生ＵＰＳ改地址和扣件费用，收件人拒收等原因造成的二次派送的，产生的费用由客户承担； （3）偏远地址请自行查询，若偏远请提前通知我司跟单同事，若未及时通知所产生的偏远费用由发件人承担，此费用6个月内收取有效； （4）暂扣件及改派地址业务，我司不承诺百分百成功，如有此问题我司不承担任何赔偿。 （5）如亚马逊拒收货件，产生的退回运费以及其他任何额外费用，发件人自理，我司概不承担任何责任！
A32: I | B32: 免责声明： （1）因不可抗力因素（罢工、战争、自然灾害、海关因素、政府行为等）或由于客户提供的资料不全、不清晰、有误或由于提供的货物不符合海关进出口要求而造成的延误、损毁、丢失，甚至被海关扣查、没收或罚款造成损失的，我司不承担责任，由客户承担由此产生的风险与责任。 （2）发票申报与货物必须一致,否则造成延误或丢失以及扣关我司一概不负责。当地海关认定货物是品牌货物，或者如CE、蓝牙、HDMI、FDA、FCC、Lacey Act、DOT（不限于以上列举）等等认证的问题，或者货物属于当地反倾销货物或不符合当地进口要求的货物，发件人应于发货前提供相应授权书或认证报告，如未提供导致货物扣关甚至退运而产生的，所有责任和相关费用将由发件人承担。
A33: J | B33: 赔偿条款：在运输过程中如货物整票丢失或者扣关，并在寄件日起2个月内无法寻回，我司赔偿运费的2倍每公斤（不退运费），如客户申报不全或产品侵权等问题将不适此项条款。 特别申明以下情况不受理赔偿： （1）如因侵权问题，我司不承担任何责任并且保留追究发件人因此带来对我司的损失的赔偿； （2）如货物没有按照实际价值申报、侵犯知识产权、产品配件不符合欧盟国家的要求、当地禁止进口等原因而导致的海关扣货，此情况不在赔偿范围之内，我司只是协助发件人提供清关文件； （3）如因客户货物本身质量问题以及涉及到具体的认证问题等，均不受理赔偿； （4）如遇战争，自然灾害等不可抗力因素除导致货物破坏或灭失，不受理赔偿； （5）在运输过程中如遇到航班延误/清关延误等引起的总体时效延误，均不受理赔偿。 （6）UPS提取转运后丢失按照UPS赔偿标准每票最高不超过100USD，以UPS赔偿账单为准. （7）易碎产品：只接受原包装出货，如发现有改包装的一律不接，易碎品不接受任何损坏赔偿! （8）产品数量缺少、部份丢失/损坏不受理赔偿。一旦交付货物即默认本条款规则。 （9） 一般贸易漏报关赔偿：3倍报关费，请慎接报关件，不接受赔偿标准的不要发！！发货即为默认！ （10）货物未收到的情况下，请在发货后14天内告知我司提供调查表开查，超过这个查询时间国外将不再受理开查、索赔等事宜！
A34: K | B34: 产品限制：此线路不接收以下货物：仿牌、手机、手表、平板电脑、魔方、陀螺、电视购物类货品、原产为中国以外的货、自行车及配件、纯电、液体、粉末、食品、药品、易燃易爆危险品、古董、仿古董、胶状物、书籍、货币、密封性包装等国家禁止出口及铁路公司禁运物品；如有发现冲货或者带电不备注行为没收货物并罚款RMB20000RMB/票 。
A35: L | B35: 货物入仓后，因客户原因需要退仓，收取最低100MRB/票退件费 个别电子产品，如有CE、蓝牙、HDMI、FDA、FCC、Lacey Act、DOT等标识，或属于当地反倾销货物，或不符合目的地国家进口要求的货物，请提供相对资料协助清关；如果不能及时提供或提供不了导致货物扣关、退回，届时所产生一切责任和费用将由发件人承担；UPS提取后，包裹最后一条扫描日期45天内未反馈，国外不再受理开查，也无法赔偿。货物未提取，需在发货日期14天内开启调查，如超过时间反馈国外不再受理，也无法索赔。
... A42: L | B42: 货物入仓后，因客户原因需要退仓，收取最低100MRB/票退件费 个别电子产品，如有CE、蓝牙、HDMI、FDA、FCC、Lacey Act、DOT等标识，或属于当地反倾销货物，或不符合目的地国家进口要求的货物，请提供相对资料协助清关；如果不能及时提供或提供不了导致货物扣关、退回，届时所产生一切责任和费用将由发件人承担；UPS提取后，包裹最后一条扫描日期45天内未反馈，国外不再受理开查，也无法赔偿。货物未提取，需在发货日期14天内开启调查，如超过时间反馈国外不再受理，也无法索赔。

Sheet 欧卡通
A1: =_xlfn.DISPIMG("ID_D6697A225B864C34A678052B48D4E660",1) -> =DISPIMG("ID_D6697A225B864C34A678052B48D4E660",1)
A2: 欧洲卡航专线--交华南
A3: 国家/重量 | C3: 21KG+ | E3: 101KG+ | G3: 派送方式 | H3: 备注
A4: 德国 | C4: =((E4+1.5)+1)+1 -> 18.5 | E4: 15 | G4: DHL/DPD派送 | H4: 1、单件计费重不足12KG按12KG计费 2、天天装，收满即装，每周至少5-6班次，正常时效18-22天提取 3、德国/捷克清关 （德国DPD派送)
A5: 法国，荷兰，波兰，比利时，奥地利，卢森堡，捷克 | C5: =((E5+1.5)+1)+1 -> 20.5 | E5: 17 | G5: DPD派送
A6: 西班牙，意大利，斯洛伐克，匈牙利 | C6: =((E6+1.5)+1)+1 -> 22 | E6: 18.5
A7: 葡萄牙，立陶宛 | C7: =((E7+1.5)+1)+1 -> 25 | E7: 21.5
A8: 爱尔兰 | C8: =((E8+1.5)+1)+1 -> 32 | E8: 28.5
A9: 希腊 | C9: =((E9+1.5)+1)+1 -> 37 | E9: 33.5
A10: 欧洲卡航递延专线（针对亚马逊和海外仓）--交华南
A11: 国家/重量 | C11: 101KG+ | E11: 派送方式 | F11: 清关费 | H11: 提取时效（开车后起算）
A12: 德国 | C12: 14.5 | E12: DHL/DPD派送 | F12: 300元/票 | H12: 约25-30天提取，此时效仅供参考，若实际因不可抗力因素或异常情况影响会稍有延迟变动。
A13: 法国，波兰 | C13: 16.5 | E13: DPD派送
A14: 西班牙，意大利 | C14: 17.5
A15: 欧洲自主VAT税号查验费用： 查验费150RMB/方，不足1立方按1立方计算，单票查验低消1500RMB/票；如整柜查验则收取1200EUR/柜。 另外会产生分拣费450欧+装卸费850欧 监管仓2天免仓租（从提货当天起算），10EUR/方/天。不足1立方按1立方计算。 查验产生的其他费用如税金、海关罚款、销毁、退运、压车费等费用均实报实销。
A16: 如欧盟有需要贴CE标的产品客户发货时自行贴好CE标，如未贴CE标或产品实际无CE证书被海关罚没，需自行承担。
A17: 欧洲卡航线路：广深装柜-巴克图-哈萨克斯坦-俄罗斯-白俄-白俄边境-立陶宛-波兰--德国-比利时清关-德国交仓
A18: 注意事项：
A19: 1.亚马逊单件重量12KG以上,非亚马逊13KG以上,不足12/KG&13/KG,加收1/KG；如单件重量低于10KG，单价+1/KG+超轻费30RMB/件；
A20: 2.非亚马逊地址+1/kg，岛屿不接，偏远地址+250/件，具体是否偏远可提供地址查询。因客户地址不详细，派送收件人不在，或拒收等原因产生的二次派送费费用实报实销。
A21: 3.品名第6个起（包含第6个），需加收20RMB/个
A22: 4.单票单件单个派送地址，欧洲派送费+50RMB/件。
A23: 5.UPS常规尺寸 重量＜24.5（实重） 材积重＜20KG 最长边＜98，次长边＜74CM，围长＜298CM 【UPS超尺寸费用】 1）、实重≥24.5KG （>24.5KG-39KG为超重） 2）、最长边≥98CM 或次长边≥74CM（>98CM-160CM为超边) 3）、材积重≥20KG （>20KG-35KG为超材积） 4）、方数≥0.14CMB（>0.14CMB为超方数） 5）、整票材积取平均值≥20KG或整票实重取平均值≥24.5KG，则整票每件均收取超尺寸费用，同时产生时不叠加。 以上（1至5点）超尺寸附加费：【超实重和超边/超材积/超方数叠加收费】：德国+250RMB/件、非德国+280RMB/件 6）、≥298cm 周长<398cm（周长=最长边+2*高+2*宽） 超周长费用+850RMB/件（不区分国家） 周长与其他尺寸同时产生时不叠加，按最高费用收取。 注：以上如遇UPS收取旺季附加费，我司则实销实报收取UPS旺季附加费
A24: DHL派送超长/超重附加： 欧洲：1.单件尺寸最长边不超120CM，第二边超60CM，或单件方数超0.14m³，或材积超24KG，派送费+40RMB/件； 2.如材积超31.5KG，派送费+35欧元/件 3.单件尺寸最长边超120CM但不超175CM，派送费+40RMB/件 4.周长超300CM--319CM内，或单件实重大于30KG但小于40KG，派送费+50欧元/件； 5.周长超320CM--350CM内，派送费+60欧元/件。 如周长超300CM/实重超30KG/最长边超120CM，这3者其中2者同时出现则附加费叠加 （以上尺寸数据均是等于大于） 超大件包裹费用长期有效，如因超大件导致拒收/退回等情况，费用均实报实销(无DHL账单，均以我司账单为准）
A25: 6.报关费：国内报关件350RMB/票（限5个品名，超过5个品名，续页费50/页）
A26: 7.欧代：近期英国/欧洲海关TS部门(Trading Standards)查获频繁，请确认产品附有英代/欧代及生产商信息。如若查到产品无英代/欧代信息和生产商信息，不仅要补充这些信息，还可能面临高额罚款，不然不予放行，费用将实报。请知悉【不单单针对CE产品，所有产品】
... A28: 特别声明：如客户一旦同意接受我公司服务，即认为客户已详细阅读过此价格表备注内容以及我司托运条款，并接受各条款的约束。

Sheet 英卡通 
A1: =_xlfn.DISPIMG("ID_D6697A225B864C34A678052B48D4E660",1) -> =DISPIMG("ID_D6697A225B864C34A678052B48D4E660",1)
A2: 英国卡航专线
A3: 国家 | C3: 21-100KG | E3: 101KG+ | G3: 备注
A4: 英国-不包税（自主VAT/递延PVA） | C4: 16.5 | E4: 14 | G4: 1、不固定班次，收满即装，每周至少3-4班次 2、正常时效20-22天提取，此时效仅供参考，若实际因不可抗力因素或异常情况影响会稍有延迟变动。 3、自税递延清关费200/票
A5: 英国包税 | C5: 19.5 | E5: 17
A6: 英国卡航陆运线路：广深装柜-巴克图-哈萨克斯坦-俄罗斯-白俄-白俄边境-立陶宛-波兰-德国-比利时-法国登船-英国清关，英国提取
A7: 自有VAT说明：
A8: 清关方式：1：客户提供自主VAT税号，关税实报实销，清关目的国（英国）。 查验费用：2：自主VAT税号查验费用实报，监管仓3天免租（从提货当天起算）15英镑/CBM/天，如有其他费用均实报实销。
A9: 费用说明：英磅汇率以当天账单汇率为准，关税需预付申报金额的30%，需要垫付关税加收费用3%手续费。预付不需要手续费，因低申报和产品安检问题超过24小时仓储费实报实销（税费由发货人支付，不向收货人收取）。 税费计算方式：VAT=【DUTY+申报价值（CIF价）+海关调价】*20%，DUTY=（申报价值（CIF价）)*税率（关税预付30%）
A10: 注意事项：
A11: 1.FBA地址单件不足12kg按12kg计费；非亚马逊地址单件重量8-10KG收超轻费30RMB/件，10-13KG收超轻费20RMB/件，或直接按平均13KG计费；
A12: 2.非亚马逊地址+1/kg，岛屿不接，偏远地址+250/件，具体是否偏远可提供地址查询。因客户地址不详细，派送收件人不在，或拒收等原因产生的二次派送费费用实报实销。
A13: 3.品名第6个起（包含第6个），需加收20RMB/个
A14: 4.单票单件单个派送地址，英国派送费+40RMB/件。
A15: 5.超长/超重附加： 1.单件尺寸最长边超100CM，不超150CM，或周长超300CM，派送费+40GBP/件； 2.单件尺寸最长边不超100CM，第二边超70CM，或第三边超60CM，派送费+40RMB/件 （第1.2同时产生，不叠加收费，按最高收费标准（40GBP/件)收费） 3.单件尺寸在150*70*60cm以内，重量大于30KG，但小于40KG，派送费40GBP+超出部分+1GBP/KG； （超尺寸费用和超重量费用分开收费，同时产生需叠加收费）（以上尺寸数据均是等于大于）； 超大件包裹费用长期有效，如因超大件导致拒收/退回等情况，费用均实报实销(无DPD账单，均以我司账单为准）
A16: 6.报关费：国内报关件350RMB/票（限5个品名，超过5个品名，续页费50/页）
A17: 7.自有VAT查验费用标准： 1）.查验分货费50GBP+查验费40GBP/票。 2）.监管仓3天免仓租（从提货当天起算）15GBP/立方/天，不足1立方按1立方计算。 3）.查验产生的其他费用如税金、海关罚款、销毁、退运等费用均实报实销。
... A20: 特别声明：如客户一旦同意接受我公司服务，即认为客户已详细阅读过此价格表备注内容以及我司托运条款，并接受各条款的约束。

Sheet 英国海运
A1: =_xlfn.DISPIMG("ID_D6697A225B864C34A678052B48D4E660",1) -> =DISPIMG("ID_D6697A225B864C34A678052B48D4E660",1)
A2: 英国海运
A3: 英国FBA-海派专线
A4: 渠道 | B4: 仓库代码 | C4: 21KG+ | D4: 100KG+ | E4: 时效 | F4: 船期 | G4: 备注
A5: 英国海派-自有VAT （不包税） | B5: 英国全区FBA地址 | C5: 7.1 | D5: 6.1 | E5: 开船后40-45天左右提取 （参考时效不含因查验、天气原因、码头塞港、疫情、节假日等影响） | F5: 四截一开 33-35个自然日左右到港 | G5: 如需做递延需提前告知；DPD派送 必须提供有效英国本地VAT税号和EORI号用于清关；
A6: 英国海派-包税 | C6: 10.5 | D6: 8 | G6: DPD派送 （运费不含产品附加费，需根据具体产品确认是否有产品附加费）
A7: 备注： 费用组成 : 运费+清关费+VAT/关税实报实销+3%垫付关税手续费（税金单出来一周内支付，超过付款期限的收3%手续费；关税预付的情况下无需垫付手续费）;
A8: 英国FBA-海卡专线（自有VAT）
A9: 渠道 | B9: 仓库代码 | C9: 100KG+ | E9: 时效 | F9: 船期 | G9: 备注
A10: 英国海卡自税（KG) | B10: BHX4 / LBA4 | C10: 5 | E10: 开船后40-45天左右提取 （参考时效不含因查验、天气原因、码头塞港、疫情、节假日等影响） | F10: 四截一开 33-35个自然日左右到港 | G10: 1、英国标准托盘尺寸是1.2*1米；FBA地址如果最长边超过120cm，周长不超300cm，加收10元/箱，单箱重量超过30kg，加收10元/箱，既超长又超重，费用叠加收取，收20元/箱； 2、BHX4 / LBA4特价仓不允许和其他卡派仓库合并报关或清关，如需合并，运价跟其他FBA仓库同价
B11: 其他FBA仓 | C11: 5.2
B12: 大型海外仓：4PX(LU5)，Orange橙仓(B6,LE19,CV21)，Winit万邑通(B78,LE3)，Goodcang谷仓(WR4,WS11,ST15) | C12: 5.5
A13: 渠道 | B13: 仓库代码 | C13: 1CBM+ | E13: 时效 | F13: 船期
A14: 英国海卡自税（CBM) | B14: BHX4 / LBA4 | C14: 930 | E14: 开船后40-45天左右提取 （参考时效不含因查验、天气原因、码头塞港、疫情、节假日等影响） | F14: 四截一开 33-35个自然日左右到港
B15: 其他FBA仓 | C15: 960
A16: 注意事项
A17: 附加费 | B17: 报关费 | C17: RMB350/票 （报关退税收取，买单报关不收），续页费50元/页
B18: 清关费 | C18: RMB300/VAT（不包税收取），限5个品名，超过第6个起每个品名加收RMB20/品名
B19: 非亚马逊地址 | C19: 非亚马逊地址，快递派送+1/kg，低消100/票。 偏远地址+300RMB/箱；部分偏远地址开头邮编（BT FK17-21 GY HS1-9 IM IV1-56 IV63 JE KA27-28 KW1-17 AB36-38 PA20-49 PA60-80 PH19-26 PH30-44 PH49-50 TR21-25 ZE1-3 )，出货前咨询。
B20: 税金结算 | C20: 汇率按照C88文件上日期当天的中行现钞卖出价加0.3结算（暂时只接受人民币付款），超过3个工作日未支付税金，将产生3%的关税垫付手续费。
B21: 关税&增值税 | C21: 关税和VAT税计算方式：duty=申报货值*关税税率，vat=(申报货值+duty)*20%，最终以海关C88税金单为准，实报实销。
B22: 木制品及竹制品 | C22: 木制及竹制品 退税报关件商检客户自行安排，买单件+1RMB /KG，最高800/票。
A23: 申报要求 | B23: 申报 | C23: 由于英国严查低申报，不包税渠道清关发票申报金额不得低于亚马逊售价的20%，递延货物如申报低于20%，不可做递延。
A24: 监管仓拦截收费标准 | B24: 拦截费 | C24: 拦截费 150英镑/票；不保证百分百拦截成功，未拦截成功，不收拦截费
B25: 操作费 | C25: 5英镑/箱（需要换外箱标签，包含入库上架，唛头，出库）；如无需换标，只暂存，后续直接出库的操作费收2英镑/箱；
B26: 分货费 | C26: 1.5英镑/箱（如需根据外箱标签分货）；
B27: 开箱操作费 | C27: 2英镑/箱（如需换SKU标签时收取，只换外箱标签不收此费用）；
B28: SKU标签费 | C28: 0.8英镑/张（如需换SKU标签）；
B29: 仓租 | C29: 0.3英镑/箱/天（前7天免费，第8天开始收取）；
B30: 纸箱耗材费 | C30: 6英镑/箱（如需换纸箱）；
A31: 其他收费项目 | B31: DPD退件 | C31: 1. 退回7.5英镑/箱； 2.重派4.5英镑/箱； 3.操作费3.5英镑/箱（含海外仓入库费，重新打单贴标，出库费），如产生仓租实报；
A32: 亚马逊入仓标准 | B32: 1，快递派送单箱尺寸限制100*70*60cm，单箱最长边不超过100cm，最大重量不超过30KG。亚马逊规定，最长边不超过63.5CM，单件货物重量不超过23公斤，超尺寸超重货物需跟亚马逊确认是否可以接收。
B33: 2. 单箱超过15KG，请按照Amazon FBA的规定贴上“Team Lift"标签。
A34: 特别声明 | B34: 1，以上报价不包含保险费、商检费、熏蒸费、海关查验费、查验仓储费、仓库增值服务费等；
B35: 2.入仓需贴我司系统唛头，且对应FBA号，尽量不要混贴；
B36: 3.由于目的港清关需要提供任何相关的清关文件，请客户积极配合并提供；如若提供不到，产生的责任和后果由客人自行承担；
B37: 4.一票仅支持一个VAT及一个地址，若一个VAT有多个派送地址，需分多票，且每个地址都满足起收标准；
B38: 5.退件费说明：当天打单退件需收取100元/票，如已装柜，不接受退件；
B39: 6.DPD 要求货箱必须可以过自动分拣机，如:不规则外箱，外箱缠胶带，外箱缠泡沫，打木架，纸箱质量过软 等因素可能会导致货箱无法过机，如无法过机需要人工手动扫描的，会收取 handling 费用8镑/箱.
B40: 7.箱单发票申报务必准确，下单渠道及发票中品名、品牌、材质、申报要素、产品属性等请与实际货物保持一致，否则因申报不符或渠道错误导致中国海关或国外海关产生罚款或扣货我司概不负责！另因瞒报、漏报、冲货查到仿牌/侵权罚款最低2000元人民币每票，上不封顶！
A41: 特别提示：如客户一旦同意接受我司服务，我司将默认为客户已详细阅读过此价格表所有备注内容，并接受各条款的约束，严格按照备注内容执行。

Sheet 美转墨准时达
A1: =_xlfn.DISPIMG("ID_D6697A225B864C34A678052B48D4E660",1) -> =DISPIMG("ID_D6697A225B864C34A678052B48D4E660",1)
A2: 美转墨准时达--华南交货
A3: 区域 | B3: 1CBM+ | D3: 10CBM+ | F3: 时效
A4: A，塑料产品（非电子类） | B4: 3500 | D4: 3500 | F4: 开船30天内到仓（不含清关查验或其它不可控因素）
A5: B，电子产品类 | B5: 3600 | D5: 3600
A6: C，纺织产品类 | B6: 3700 | D6: 3700
A7: A类：吸管/刮痧板/指南针/健身锤/硅胶瑜伽垫/冰滚轮/按摩锤/记事本/手机钢化膜（含酒精包）/潜水面罩/保护壳/纯塑料制品/数据线/塑料玩具/反光板/橡皮泥/流沙画/贴纸/梳子/木制品（+800元/票）/螺丝/一次性餐具/PCB线路板/陶瓷产品/手机周边配件/人造石/硅胶制品/水杯水壶/保护膜/纸箱/纸盒/墙纸/五金扳手钳子/五金配件/不锈钢厨房用品/球类/镜子/水晶泥/橡皮泥/瓷砖/木地板/纹身贴/海绵等； B类：认证电子产品(需要NOM.蓝牙、HDMI、FDA、FCC、Lacey Act、DOT等认证的产品)灯具/充电器/收音机行车记录仪/音箱/检测设备/服装辅料/模组/除碳机/跑步机/激光机/打印机/焊接机/折弯机/定型机/抛光打磨机/包装机/食品机/压榨机/摄影或电影摄像机/乐器/汽车配件/电压表/电钻/门铃/报警器/网卡/温度计/望远镜/录音笔/探测仪/检测仪/U盘/内存卡/路由器/手表/智能手环/车载DVD播放器/烫画机/加热器/智能门锁/行车记录仪/麦克风/电锯/电子打火机/硒鼓墨盒/训狗器/GPS定位器/摄像头/太阳能产品/VR眼镜/天文望远镜/蒸脸仪/洁面刷仪/黑头仪/脱毛仪/对讲机/电子元器件/投影仪/相机/打印机/平板电脑/显微镜/显示屏/手机屏/光驱/主板/机顶盒/电子狗/机器人/相机/电动剃须刀/咖啡机/修剪器/剃毛器/按摩仪/冲牙器/吸奶器/马克笔/铅笔/毛刷/厨房刀/汽车配件/烧水壶/电磁炉/电饭煲/射钉器（不含火药钉）/按摩仪等； C类：纺织品/鞋垫/鞋带/衣服/裤子/袜子/麻袋/毛巾/毛毯/内衣内裤/枕头/枕套/背带/帽子/护膝/被子/包包类/皮革类/钱包/箱包/假发/行李箱/活性炭/竹炭包/头盔/按摩床/皮具/假发/等；
A8: 注意事项：
A9: 1.以上价格免费派送在墨西哥城的所有平台仓库（亚马逊，美客多，Felabella等）； 2,Mercado美客多，货到当地后要由发件人预约入仓时间后再安排派送；由于电商仓爆仓造成货物不能入仓以及产品销售链接失效以及后续问题，我司概不负责；由于美客多的预约问题与我们物流商无关，如Mercado美客多货物到仓后我司进行预约派送7天后仍无法预约，我司会提供截图给交货方，需要卖家与美客多客户经理进行协助争取白名单，以便更好早点预约成功； 3.墨西哥其它外州平台仓库只能快递送仓，没有签收单，派送费：RMB120/箱。快递派送：最长边不大于100，次长边不大于70，除5000小于30； 4.按立方计费：体重比1:363，单票最低1CBM 5.单独报关件收费：RMB350/票，续页50RMB/页。木制品需提供商检，无法提供商检的需要单询操作员落实商检费。 6.美妆产品商检费3000元/票，木制品商检费800元/票。
A10: 赔偿说明：
A11: 1.不买保险：货物运输过程中如出现因乙方原因造成的货物丢失或海关扣货问题的，由甲方提供采购价格证明文件，乙方按照采购价格进行赔偿（如实际采购价格超出运费的，则仅按运费进行赔偿），并退还相应运费。（货物完成派送我司提供签收单,如出现箱内产品数量缺少、损坏不受理赔偿。） 2.高货值产品（比如手机、平板等）、易碎品（比如灯具、显示器、玻璃制品等）客户需自行购买保险，在运输过程中如果损坏原则上我司不赔偿（保丢不保损）。 3.运输途中如遇抢劫导致丢件，退运费且补偿一倍运费作为赔偿。 4.我司接受购买保险，保费按照承保金额5.5%（箱内丢失免责，整箱丢件/扣关按照购买保额赔付）
A12: 特别注意：出货前请仔细阅读我司理赔标准，我司默认已阅读并已同意此赔偿方案。不另做争议。
A13: 注意：交货之前请认真阅读各渠道条款，交货我司，代表认同我司报价表上之条款，并接受各条款的约束，此价格表最终解释权属我司。
A14: 墨西哥仓库代码
A15: 国家 | B15: 所属平台 | C15: 仓库代码 / 编号 | D15: 仓库邮编 | E15: 仓库区域 | F15: 仓库详细地址 | G15: 配送收费标准
A16: 墨西哥 | B16: 美客多仓库 | C16: ML E1 | D16: 54715 | E16: 墨西哥州 | F16: Domicilio de la bodega O′Donnell Mercado Libre Parque Industrial O′Donnell Puente México, (Edificio 1) Av. Ayotl SN, Colonia Axotlan, Cuautitlan Izcalli, Estado De México. CP 54715 | G16: 免费派送
C17: MXRC02 | D17: 54607 | E17: 墨西哥州 | F17: Pral. Av, de la industria SN, Las Animas 6, SN, Topatzcllan, Estado De méxico. 54616 | G17: 免费派送
C18: ML E3 | D18: 54616 | E18: 墨西哥州 | F18: Megapark Mercado Libre Prol. Av. de la industria S/N, Las Animas Nave 6, Tepotzotlan, Estado De México. ZIP CODE: 54616. | G18: 免费派送
C19: ML E4 | D19: 54010 | E19: 墨西哥州 | F19: Av. Gustavo Baz Prada, Col. San Pedro Barrientos km 12.5, Tlalnepantla de Baz, Estado De México. ZIP CODE: 54010. | G19: 免费派送
C20: MXCD05 | D20: 54800 | E20: 墨西哥州 | F20: Av. Lic. Arturo Montiel Rojas, entre esquina el terremolo y hacienda las arboledas S/N, San Juan, Cuautitlan, Estado De Mexico CP.54800 | G20: 免费派送
C21: MXCD06 | D21: 54803 | E21: 墨西哥州 | F21: Carretera Cuautitlan -Tultepec lote B no. 2 y lote C 1, Colonia Terremoto, Cuautitlan, Estado De México. 54803 | G21: 免费派送
C22: MXRC03 | D22: 54800 | E22: 墨西哥州 | F22: Vialidad Cola de Caballo S/N, Rancho Nuevo la Virgen, Cuautitlan, Estado De México. ZIP CODE: 54800 | G22: 免费派送
C23: 瓜仓 | D23: 45694 | E23: 外州 | F23: Vesta Park Guadalajara I Mercado Libre Carretera Guadalajara - El Salto vía El Verde 1900, Colonia Potrero El Salitre, El Salto, Jalisco. ZIP CODE: 45694. | G23: 快递派送
C24: 蒙特雷仓 | D24: 66648 | E24: 外州 | F24: Mercado Libre Nexxus MTY Parque Nexxus autopista al aeropuerto KM 3+800, Apodaca, Nuevo León. ZIP CODE: 66648. | G24: 快递派送
B25: 亚马逊仓库 | C25: MEX1 | D25: 54715 | E25: 墨西哥州 | F25: Cuautitlán Izcalli,Estado de México,MX（ZIP）：54715 | G25: 免费派送
C26: MEX2 | D26: 54769 | E26: 墨西哥州 | F26: Cuautitlán Izcalli,MX,（ZIP）：54769 | G26: 免费派送
C27: MEX3 | D27: 54607 | E27: 墨西哥州 | F27: Amazon MEX3 Prologis Park Grande Libramiento Norte No. 87 Lote A Tepotzotlan, Estado de Mexico 54607 | G27: 免费派送
C28: MEX6 | D28: 54607 | E28: 墨西哥州 | F28: Camino a XOYOACAC，Fracc B Nav Jerusalem， TEPOTZOTLAN, MEXICO 54607 | G28: 免费派送
C29: GDL1 | D29: 45672 | E29: 外州 | F29: Guadalajara-Chapala Highway #9999 Building 5 Zapote del Valle, JALISCO 45672 | G29: 快递派送
C30: GDL2 | D30: 45680 | E30: 外州 | F30: Carretera El Salto 273 Flex Park 45680 | G30: 快递派送
C31: MTY1 | D31: 66627 | E31: 外州 | F31: BLVD GUADALUPE No.403 Interior B012 APODACA, NUEVO LEON 66627 | G31: 快递派送
C32: TIJ1 | D32: 22465 | E32: 外州 | F32: Camino Vecinal #20652, Nave 4 Colonia Murua Oriente 22465 - Tijuana, BAJA CALIFORNIA - Mexico | G32: 快递派送
C33: HMO3 | D33: 83297 | E33: 外州 | F33: Av. Mercury, Polígono B1-2, II Etapa, al Sur de la Carretera a la Colorada Parque Industrial Dynatech Sur Segunda Etapa 83297 - Hermosillo, Sonora - Mexico | G33: 快递派送
C34: MID1 | D34: 97246 | E34: 外州 | F34: 431, de la Calle 19, Umán, YUCATAN, MX, 97246 | G34: 快递派送
C35: BJX1 | D35: 37680 | E35: 外州 | F35: Calle Oliver Evans number 107 Carretera a Santa Ana del Conde, Km 4.5 Parque Industrial Bajío (PILBA) León, Guanajuato 37680 | G35: 快递派送

Sheet UPS红单
A1: =_xlfn.DISPIMG("ID_D6697A225B864C34A678052B48D4E660",1) -> =DISPIMG("ID_D6697A225B864C34A678052B48D4E660",1)
A2: 香港UPS红单/5000
A3: 国家地区 | B3: 23-100KG | E3: 101-200KG | H3: 201-290KG
A4: 美国含税 | B4: 61.5+150/票 | E4: 61.5+150/票 | H4: 200KG以上请分票 | K4: https://www.ups.com/cn/zh/support/shipping-support/shipping-costs-rates/fuel-surcharges.page
A5: 香港UPS红单/6000
A6: 国家地区 | B6: 23-100KG | E6: 101-200KG | H6: 201-290KG
A7: 美国含税 | B7: 63+150/票 | E7: 63+150/票 | H7: 200KG以上请分票
A8: 一票货物只有单箱的请单询价格
A9: 一般贸易报关：报关费350 另加中港1RMB/KG(低消50RMB)
A10: 实重不达标23KG 体积按照25KG 起步计费 实重达标23KG 以实际测量为准 一票多件货物 单件不足8kg 按照8KG计费 包税渠道 25KG 起步计费
A11: 包税渠道进口处理费 | B11: 18元/票
A12: 账号性质： | B12: 香港UPS 红单服务 UPS WORLDWIDE EXPRESS SAVER
A14: 取件地： | B14: 香港 长沙湾 CHUANG SHA WAN
A16: 中港截止时间： | B16: 每天中午 14.30
A18: 当天下港交货截止时间： | B18: 每天中午13.30
A20: 产品限制： | B20: 液体、粉末、枪支弹药等航空禁运物品
A22: UPS附加费说明： | B22: 一、附加费以UPS实际账单通知为准收取，3年内补收均为有效。（包括:偏远费，国外退件费，关税费，住宅费，更改地址费，违禁品，危险品费 ，查验费，清关费等杂费） 二、超出UPS服务范围的偏远地区，需加收偏远附加费，标准为RMB3.7元/KG*燃油，或者最低消费RMB175元*燃油，取两者较大者为收费标准；请自行查偏远地区，UPS偏远费3个月内收取有效。 1)亚马逊有备用仓的情况，后期是有可能会产生改派地址费，UPS账单出来是需要额外收取的，亚马逊如果有备用地址的，UPS在派送时会按亚马逊仓的要求改派到备用仓的地址去，这种改派UPS也是要额外收费，且UPS是不会向发件人发起问题的，不通知 2) 右侧亚马逊备用地址偏远更新EXCEL 即打单地址不管是哪个地址，ups都会下偏远账单，请知悉） 三、附加手续服务费:UPS为RMB143元每件，需乘燃油，客户托运以下任何一款包裹时，UPS将会对每件包裹向客户加收此附加费: 1)木箱包装/塑料箱包装/金属包装/缠绕膜包装 2)任何未有以瓦楞纸完包裹好的圆柱形物件，如圆桶、鼓、提桶或轮胎等 3) 任何最长一边之长度超过及包含120厘米或第二最长边的长度超过74厘米的包裹。 4)任何单件货物实重超过24公斤(不含24公斤)或者每票单件货物平均超过24公斤，收取附加费143*U/件 四、重量和尺寸的限制要求如下:(以下几种情况最大尺寸或者重量超过会加收1938元乘燃油/件) 1)任何包裹的最长一边(长度)超过及包含270厘米: 2)任何包裹的三围之和(即:(宽+高)*2+长)超过390厘米; 3)任何包裹的实重超过及包含67公斤。 说明:UPS不承运超过以上三个条件的包裹，被UPS操作人员一经发现会拒收，如果因透漏发现而被安排出口的此美货件，UPS会完成此派送服务，并自动会向发件客户收取此附加费
A23: 附加费： 包税渠道 | B23: 1类产品：鞋子类、纺织品、笔类、手机屏、带磁性产品、摄像头、车载收音机DVD、行车记录仪、加收1元/公斤； 2类产品：电子烟、指尖陀螺、自行车配件、U盘、对讲机、智能手环、中型播放器、机顶盒、数码相机、强磁性产品、剃须刀等部分刀具产品、假发、成人用品、加收3元/公斤； 3类产品：平板、手表、相机、大型玩具、安防/监控设备、空气净化器、录像机/摄像机、电子元器件、功放、显微镜、投影仪、显示屏、汽车用品及配件、云台、天文望远镜、无线电通讯设备、美容护肤器、大型工具包、等高货值产品：加收4元/公斤； 手机/无人机 其他产品单询。所有产品附加费最低收费30RMB/票；
A24: 税金 | B24: 关税账单长期有效，其他附加费原账单，一律半年内能够提供给代理的均为有效
A26: 此价格特别声明：如非货物本身问题，货物清关被卡导致无法清关，我司按货值赔偿，但最高不超40RMB/KG，并退运费。货物已交承运商中转发生丢失、损坏、是承运商责任的以承运商的赔偿金额为准，按申报价值赔偿，但最高赔偿金额不超过USD100。高价值货物请自行购买保险；如若接受此价格走货，代表默认此条款！

Sheet 美国空派
A1: =_xlfn.DISPIMG("ID_D6697A225B864C34A678052B48D4E660",1) -> =DISPIMG("ID_D6697A225B864C34A678052B48D4E660",1)
A2: 美国空派-普货
A3: 目的地国家 | B3: 12KG+ | C3: 71KG+ | D3: 101KG+ | E3: 提取时效
A4: 美国西岸 (邮编8-9) | B4: 70 | C4: 64 | D4: 62 | E4: 6-8天左右提取 一票多件，单件货物实际重量要求12KG以上，不得超22KG
A5: 美国中岸 (邮编4-7) | B5: 71 | C5: 65 | D5: 63
A6: 美国东岸 (邮编0-3) | B6: 72 | C6: 66 | D6: 64
A7: 此渠道不接液体 粉末 木竹制品 带电产品(带磁/马达/电机/泵需做磁检鉴定），如有瞒报一经查出罚款3000-5000元，产生退库延误损失由客户承担
A8: 美国空派-带电
A9: 目的地国家 | B9: 12KG+ | C9: 71KG+ | D9: 101KG+ | E9: 提取时效
A10: 美国西岸 (邮编8-9) | B10: 71 | C10: 65 | D10: 63 | E10: 10-12天左右提取 一票多件，单件货物实际重量要求12KG以上，不得超22KG
A11: 美国中岸 (邮编4-7) | B11: 72 | C11: 66 | D11: 64
A12: 美国东岸 (邮编0-3) | B12: 73 | C12: 67 | D12: 65
A13: 产品说明
A14: 温馨提示：出货需每箱贴"MADE IN CHINA"的标签，产品上也需要贴MADE IN CHINA 如产品未贴有中国制造的标签导致货物被扣，我司概不负责！
A15: ◇普货渠道在国内起飞,非普货渠道主要在韩国起飞；主要飞LAX/ORD/JFK三个机场清关派送,一般情况下，美中美东货物优先安排飞ORD/JFK；如有其他特殊需求，可安排定制化方案服务； ◇末端派送方式有专车派送、LTL卡派（可以接托盘、木箱等大件货）卡派价格可以单询、FEDEX/UPS快递派送（只接受坚硬厚纸箱包装，过度地缠胶带、外包装缠膜等行为导致快递派送产生额外的包装费用实报实销） ◇我司可提供美国仓库仓储以及退换货服务.详情可咨询业务专员 ◇ 接报关件/报关费350RMB/票，续页费50RMB/续页；5项品名为一页； 发票上需注明FBA号。单票货物限制5个品名，超出部分加收50RMB/个。
A16: ◇单箱货物12KG 起计费，计费重不足12KG按12KG收费。货物重量的计算方式：长cm X 宽cm X 高cm /6000，实重和材积重取较大者 ◇系统下单必须提供真实齐全详细产品申报信息（品名、产品数量、品牌、型号等）,如我司仓库检查不符,罚款RMB2000/票起；带电、带磁、带液体粉末等产品瞒报，如被机场安检查验，罚款RMB3000/票起；以上原因导致海关查验或查验不符,罚款RMB5000/票起,其他额外费用实报实销 ；并且发件人将承担产生的退货费、机场分箱费、国外理货操作费、空运操作费等 因冲货产生的其他费用实报实销； ◇如果地址错误产生UPS/FedEx更改地址和扣件费用的，所产生的具体费用需要单独咨询我司客服.
A17: ◇末端派送服务仅限于美国本土48个州,不接收邮局邮箱,军方地址：APO 、FPO 、DPO等；岛屿(不接邮编：006-009 波多黎各、维尔京群岛,967-969 HI 夏威夷、关岛 995-999 AK 阿拉斯加等！)；亚马逊卫星仓（仓库IU代码开头）无法使用快递派送，卡派价格请单询
A18: 详参产品附加费表格
A19: 拒收产品目录： 1.枪支弹药、毒品、白色粉末、爆炸易燃危险品、毒性物质、化学腐蚀品、侵权仿牌产品、书籍、古董、货币、石墨，外箱贴有九类危险标识的货物 2.未有品牌授权的手机、电子产品（不限于以上列举）等产品；反倾销、涉及政治、宗教、侵犯知识产权、美国禁止进口货物、国家禁止出口及航空公司禁运物品 3.婴幼儿产品、原木制品、电子烟、医疗器械、食品、药品、化妆品（包括光疗仪、酒精棉）、干燥剂、汽车轮胎产品 4.不具备CE/UKCA认证或未贴CE/UKCA标签等原因导致海关查验扣关。（如CE、UKCA、蓝牙、HDMI、FDA、FCC、Lacey Act、DOT（不限于以上列举）等产品 5.移动电源、管制刀具、捆绑件、安全锤、手推车、钢钉、登山杖、折叠型金属桌椅、激光类产品 6、国家管制的稀有金属：钆、钇、铈、钕、铒、镱、铂、钋、镭、锕、钍、铀、钚、锔、锎、锿、锂、铼、镓、铟、锗、钛、锆、铪、钽、钨、钼、铼、碲铋、铟、锑、钐、铽、镝、镨、钪、铍、铌、钍、镍、锰等
A20: 末端快递派送
A21: 美国空派未指定快递派送 默认UPS和FEDEX,计泡系数6000 一、接收货物要求：单件实重不得大于或者等于50KGS；最长边不得超过260cm;周长=长+[（2 x宽+2 x高）]不得超过380cm 二、包装要求： 1.未完全装入瓦楞纸板运输集装箱的任何物品，包括轮胎 2.任何外部装有非瓦楞纸板集装箱的包装，包括 但不限于帆布、皮革、金属、木材、硬塑料、软塑料（如塑料袋）或发泡聚苯乙烯泡沫（例如，聚苯乙烯泡沫塑料）。" 3.用收缩包装或拉伸包装覆盖外部运输集装箱的任何包装 4.任何用金属、塑料或布带捆扎的包裹，或有轮子、脚轮、把手的包裹或捆扎带（包括外表面松散包裹或内容物伸出容器表面） 5.任何圆柱形类似物品，包括但不限于桶、桶、罐、桶、邮寄管或者桶。 6.货箱外箱包装需使用透明胶带，不得缠过多的胶带、绑扎带，钉子、蛇皮袋，黄色胶带拉伸膜等过度包装 三、普通偏远地区产生的附加费单件25元/件；偏远扩展地区产生的附加费单件30元/件；超级偏远地区产生的附加费单件15美元/件；私人地址+2RMB/Kg 四、附加费规则： 1、单件实重大于或者等于22.5KG加收RMB245/件 2、单边长大于或者等于1.2M或者任意两边大于或者等于75cm 加收RMB185/件 3、周长=长+（宽+高）*2 大于266cm ，每件收185RMB/件附加费，周长超300cm 超大附加费单询或者实报实销 4、未按照包装要求或快递服务商在中转货物过程出现纸箱破损，额外产生不规则包装费每件收185RMB/件 5、其他特殊尺寸重量，附加费请单询 5.1超大包裹附加费标准 最长边超过96英寸=243cm（超过260cm 拒收） 周长=长+（宽+高）*2 超过130英寸：长+[（2 x宽+2 x高）]大于等于300 小于等于390 （超过380拒收） 重量大于等于40.9KGS=90LBS 小于等于 50KGS (超过50KGS 拒收) 6.地址修正费：因下单地址或其他信息不完整，不正确，导致快递公司产生地址修正费USD 28/箱；因收件人拒收产生的退件费和二次派送费,实报实销 温馨提示:UPS/FEDEX针对超标件在旺季期间将会额外收取旺季附加费，我司会根据快递账单实报实销
A23: 赔偿标准
A24: 在运输过程中如货物丢失，最高不超过RMB40/KG赔偿，退运费.已交UPS/FedEx后丢失的不退运费,按申报价值赔偿(最高不超100USD/票).高货值产品请买保险，找业务代买保险 特殊产品单询 特别申明以下情况不受理赔偿： 1）如因侵权问题，我司不承担任何责任并且保留追究发件人因此带来对我司的损失的赔偿； 2）如货物没有按照实际价值申报、侵犯知识产权、当地禁止进口等原因而导致的海关扣货，此情况不在赔偿范围之内，我司只协助发件人提供清关文件； 3）如因客户货物本身质量问题以及涉及到具体的认证问题等，均不受理赔偿； 4）如遇战争，自然灾害等不可抗力因素除导致货物破坏或灭失，不受理赔偿； 5）在运输过程中如遇到航班延误/清关延误等引起的总体时效延误，均不受理赔偿. 6）产品包装不合格问题、数量缺少、损坏不受理赔偿. 7）易碎品不接受任何损坏赔偿. 8）若亚马逊仓库因包装问题、标签问题产生拒收等原因，不受理赔偿； 9）我司无法保证可以逐一审核查验所有货物及其发票箱单和外箱包装等, 如因货物本身及发票箱单、包装等问题导致海关扣货、收件人拒收或退回，所产生的一切费用不受理赔偿； 10）箱单发票申报务必准确，下单渠道及发票中品名、品牌、材质、申报要素、产品属性等请与实际货物保持一致，否则因申报不符或渠道错误导致中国海关或国外海关产生罚款或扣货。我司概不负责且不受理赔偿！

Sheet 欧洲空派
A1: =_xlfn.DISPIMG("ID_D6697A225B864C34A678052B48D4E660",1) -> =DISPIMG("ID_D6697A225B864C34A678052B48D4E660",1)
A2: 欧洲(GLS/DHL/UPS安特卫普清专线 (可递延，泡分50%)普货
A3: 国家 | B3: 21KG+ | C3: 71KG+ | D3: 100KG+ | E3: 备注
A4: 德国 | B4: 49 | C4: 47 | D4: 45 | E4: 时效约8-10个自然日提取
A5: 法国/意大利10000以上邮编 | B5: 50 | C5: 48 | D5: 46 | E5: 时效约8-10个自然日提取
A6: 捷克/波兰/荷兰/西班牙/意大利10000以下/匈牙利/瑞典/奥地利/丹麦/希腊/葡萄牙/立陶宛/卢森堡/爱尔兰 | B6: 50.5 | C6: 48.5 | D6: 46.5 | E6: 时效约8-10个自然日提取
A7: 欧洲(GLS/DHL/UPS)安特卫普清专线 (可递延，泡分50%)带电
A8: 国家 | B8: 21KG+ | C8: 71KG+ | D8: 100KG+ | E8: 备注
A9: 德国 | B9: 52.5 | C9: 50.5 | D9: 48.5 | E9: 时效约8-12个自然日提取
A10: 法国/意大利10000以上邮编 | B10: 53.5 | C10: 51.5 | D10: 49.5 | E10: 时效约8-12个自然日提取
A11: 捷克/波兰/荷兰/西班牙/意大利10000以下/匈牙利/瑞典/奥地利/丹麦/希腊/葡萄牙/立陶宛/卢森堡/爱尔兰 | B11: 54 | C11: 52 | D11: 50 | E11: 时效约8-12个自然日提取
A12: 注意事项！在递延资料审核通过后，亚马逊货物如需做递延，需满足以下基本要求！ 1、产品销售链接税号必须要与清关税号一致，新品/断货/不再售的产品需提供产品的后台售价截图和同清关税号一致的店铺链接； 2、申报单价不得低于销售价格的35%，如不符合海关系统同类产品平均最低申报标准，将按海关的最低标准申报（出货前可让单证客服协助确认税金，如不同意按此标准申报，无法做递延，请走包税）； 3、派送（收件对应）国家要求：清关VAT号所属国家需和派送国家一致； 4、其他能提供销售链接显示的税号与VAT税号一致的海外仓和平台可以接，例如：EBAY、法国CD，速卖通及其他大型海外仓等，出货前请提供货物发票单询客服； 5、因海关定期查税，递延货物在清关后必须提供“VAT申报金额确认函”及“申报回执单”给到清关行备案，以便海关不定期核查，为保障递延申报与清关一致并及时提供，我司在出货前确认申报货值时，并预收VAT保证金费用（=清关资料上的申报货值*21%），具体内容及要求可咨询客服； 6、货物一旦安排出货后，不得更改渠道，否则所产生的运单处理费 ，审单费等自行承担； 7、欧洲递延价格为价格表减1.5/KG+RMB400/VAT号清关费； 8、递延货物如遇查验产生查验费、国外仓储等费用实报实销，不接受请勿安排！
A13: 渠道说明
A14: 1）整票货的单件计费重需12KG计费，单箱不足12KG按12KG计费。UPS必须2件起步派送 ，1件的话要补20欧派送费。
A15: 2）可接私人地址/商业地址/海外仓单询！
A16: 3）异地交仓货物下单前确认价格和交仓时间，请知悉！
A17: 4）非我司原因货物退仓，产生退货费用：RMB2/件，最低50RMB/票！
A18: 5）可接报关件，报关费350RMB/票。（如因报关货物/资料问题导致查验产生费用需客人全权承担！）
A19: 6）木制品涉及商检需加收2/KG，需与产品附加费用叠加！
A20: 7）常见产品加收： 欧洲空运附加费： 1）纯纺织品类、鞋类产品+8/KG！磁性+2/KG！ 2）手机壳、手表壳、钢化膜、手链、项链、戒指、数据线、钢化膜、插座、表带、掏耳器、电器元器件、钥匙扣、计时器、温度计、汽车配件、夹子、一次性产品、气球等产品+4/KG；混合纺织品、皮革制品、箱包、所有灯具、纯金属制产品，笔、血压计、机顶盒、导航仪、眼镜、太阳镜、蓝牙产品、太阳能产品、相机、行车记录仪、车载DVD、对讲机、手机屏、功放、显微镜、投影仪、3D打印机、手推车、打印机、摄像机（头）等产品+2/KG！ 3）产品单箱装箱平均100pcs以下不需要附加，100-150pcs+1.5/KG，200pcs+2.5/KG，300pcs+3.5/KG，400pcs+5.5/KG，500pcs+7.5/KG，超600pcs以上+9.5/KG，封顶附加费+9.5/KG 4）如2.3点均符合，附加费哪个高取哪个；产品附加包含但不限于以上明细，如价表无体现，请在出货前留意单询并确认附加费再交货，一经出货默认同意附加！
A21: 8）欧洲UPS包装要求： 1）超重收费：标准包裹实重大于25kg小于30KG德国加收160人民币/箱 非德国加收人民币200/箱，超过30KG拒收。 2）超长收费：最长边＜100cm，第二长边＜70cm，任意一边超长德国加收人民币160/箱 非德国加收人民币200/箱（任意边长超出160cm包裹拒收） 。 3）超材积收费：/6000后 材积超20.5KG德国加收160人民币/箱 非德国加收人民币200/箱。 4）超周长收费：长+2*宽+2*高=周长＜3米，如超出3米小于3.9米加收人民币650/件，超过3.9米拒收。 5）非规则包裹收费：外箱蛇皮袋/缠满黄色胶纸 德国加收人民币160/箱 非德国加收200人民币/箱。 6）/6000后 材积超35KG拒收。 欧洲GLS包装要求： 1）超重收费：标准包裹不大于30kg，＞30KG每个包裹加收400人民币 （≥40KG包裹拒收） 2）超长收费：最长边＜110cm，第二长边＜70cm，任意一边超长每个包裹加收150人民币（任意边长超出160cm包裹拒收） 3）超周长限制：长+2*宽+2*高=周长＜3米，如周长超出3m包裹拒收；或可接受周长超出3m且＜390cm的包裹账单实报实销，否则拒收。 4）超体积费用：标准包裹不大于150升（0.15m³），超过每个包裹加收20人民币；
A22: 赔偿说明
A23: 1）丢件赔偿：未上架经核实丢件，最高补偿RMB40/KG不退运费；上网后提取未签收，按照快递标准最高赔偿USD100/票不退运费。（补充说明：高货值请发货人自行购买保险，或委托我司购买，具体请单询）
... A35: 特别声明：如客户一旦交付货物并接受我司服务，我司默认客户已详细阅读过此价格表声明内容并接受各条款约束。

Sheet 英国空派
A1: =_xlfn.DISPIMG("ID_D6697A225B864C34A678052B48D4E660",1) -> =DISPIMG("ID_D6697A225B864C34A678052B48D4E660",1)
A2: 英国空派
A3: 国家 | B3: 21KG+ | C3: 51KG+ | D3: 101KG+ | E3: 备注
A4: 英国UK（包税） | B4: 51 | C4: 49 | D4: 47 | E4: 时效约7-9个自然日提取
A5: 英国UK（自税） | B5: 46 | C5: 44 | D5: 42 | E5: 时效约7-9个自然日提取
A6: 英国UK（包税）-带电 | B6: 54 | C6: 52 | D6: 50 | E6: 时效约9-11个自然日提取
A7: 英国UK（自税）-带电 | B7: 49 | C7: 47 | D7: 45 | E7: 时效约9-11个自然日提取
A8: 温馨提示： 请注意！在递延资料审核通过后，亚马逊货物如需做递延，需满足以下基本要求！ 1、递延税号必须与申报税号一致，产品销售链接可以不与税号对应，但是需要提供店铺链接（清关税号必须与店铺一致） 2、递延产品申报单价不得低于市场销售价格的15%-20%（自税10%-15%左右），具体申报以实际产品为准（一般电子类产品申报较高） 3、海外仓递延货物具体请查看递延资料中的说明，也可在出货前咨询客服 4、不包税货物如遇查验产生查验费、国外仓储等费用实报实销，不接受请勿安排！ 5、海外仓递延货物要求具体咨询客服
A9: 渠道说明
A10: 1）非亚马逊单询！可收超大件，单询！递延及不包税 查验产生的费用实报实销！
A11: 2）清关费：RMB150/票，整票货的单件计费重需12KG计费，单箱不足12KG按12KG计费。可接私人地址/商业地址/海外仓，加收1/KG！
A12: 3）异地交仓货物下单前确认价格和交仓时间，请知悉！
A13: 4）非我司原因货物退仓，产生退货费用：RMB2/件，最低50RMB/票！国内贴标费1元/张，纸箱费15元/箱
A14: 5）可接报关件，报关费350RMB/票。（如因报关货物/资料问题导致查验产生费用需客人全权承担！）
A15: 6） 木制品涉及商检需加收2/KG，需与产品附加费用叠加！
A16: 7）超5个品名加收15RMB/个！（第6个品名开始加收）
A17: 8）常见产品加收： 1）纯纺织品类+2/kg，鞋类+4/kg！售价超50英镑产品附加费需单询！ 2）混合纺织品、皮革制品、箱包、纯金属制产品，笔、血压计、机顶盒、导航仪、眼镜、太阳镜、蓝牙产品、太阳能产品、相机、行车记录仪、车载DVD、对讲机、手机屏、功放、显微镜、投影仪、3D打印机、手推车、打印机、摄像机（头）等产品+2/KG！ 3）如价表无体现，请在出货前留意单询并确认附加费再交货，一经出货默认同意附加！
A18: 9）英国DPD包装要求： 1）超重收费：标准包裹不大于30kg，＞30KG每个包裹加收300人民币 （≥40KG包裹拒收） 2）超长收费：最长边＜100cm，第二边长＜70cm，第三边长＜60cm，任意一边超长每个包裹加收300人民币（任意边长超出160cm包裹拒收） 3）超周长限制：长+宽+高=周长＜2.3米，如周长超出2.3m包裹拒收；或可接受周长超出2.3m且＜3m的包裹账单实报实销，否则拒收。
A19: 赔偿说明
... A32: 特别声明：如客户一旦交付货物并接受我司服务，我司默认客户已详细阅读过此价格表声明内容并接受各条款约束。

Sheet 海外仓服务
A1: =_xlfn.DISPIMG("ID_D6697A225B864C34A678052B48D4E660",1) -> =DISPIMG("ID_D6697A225B864C34A678052B48D4E660",1)
A2: 美国海外存储及拦截服务收费标准
A3: 序号 | B3: 收费项目 | D3: 价格 | E3: 说明
A4: 1 | B4: 散货拦截费（整柜直送不可拦截） | D4: USD120/票 | E4: 拦截成功收取
A5: 2 | B5: 入库费 | C5: 纸箱入库 | D5: USD1/箱，纸箱最低收费USD50/票 | E5: 非用我司头程入仓则收取该费用
A6: 3 | B6: 仓储费（低消1托，1.8CBM/托） | C6: 不足0.5CBM，按0.5CBM计算 不足7天，按7天计费 | D6: ￥0/CBM | E6: 1-7天，免仓租
C7: 8-60天 | D7: USD1/托/天 | E7: 8天-60天，每半个月结算一次仓租，不足1周，按1周计费
C8: 61-90天 | D8: USD1.5/托/天 | E8: 61-90天，每半个月结算一次仓租，不足1周，按1周计费
C9: 91-119 | D9: USD2/托/天 | E9: 91天，每半个月结算一次仓租，不足1周，按1周计费
C10: 120天以上 | D10: USD3/托/天 | E10: 120天，每半个月结算一次仓租，不足1周，按1周计费
A11: 4 | B11: 分货费 | C11: 纸箱仓库内分货 | D11: USD1/箱，最低收费USD15/票 | E11: 按整柜对应仓点总件数收费
A12: 5 | B12: 打托费 | C12: 按亚马逊入仓标准 | D12: USD15/托 | E12: 适用于纸箱散货入仓，打托出仓；含托盘及拉伸膜等材料和人工
A13: 6 | B13: 贴标签 | C13: FBA标签 | D13: USD0.5/张 | E13: 每箱至少两张
A14: 7 | B14: 贴标签 | C14: SKU标签 | D14: USD0.5/张 | E14: 2.5“ x 1" 贴纸，包括贴纸打印
A15: 8 | B15: 贴标签 | C15: UPS标签 | D15: USD0.5/张 | E15: 每箱至少两张
A16: 9 | B16: 对应贴标费 | C16: 标签 | D16: USD1/张 | E16: 要求指定箱号贴标或覆盖外箱原有旧标签时产生
A17: 10 | B17: 出库费 | C17: 纸箱出仓 | D17: USD1/箱，最低收费USD15/票 | E17: 快递出库收取该费用
A18: 11 | B18: 自提费 | C18: 托盘出仓 | D18: USD15/托 | E18: 按托盘收费
A19: 增值服务费（如产生）
A20: 1 | B20: 清点费 | C20: 清点产品数量 | D20: USD0.5/PCS，低消USD15/箱 | E20: 原箱如需拆箱分拣、清点、封箱，则收取此费用
A21: 2 | B21: 开箱操作费 | C21: 重新整理 | D21: USD5/箱 | E21: 原箱如需拆箱分拣、清点、重新整理装箱，则收取此费用
A22: 3 | B22: 打托费 | C22: 按亚马逊入仓标准 | D22: USD15/托 | E22: 适用于纸箱散货入仓，打托出仓；含托盘及拉伸膜等材料和人工
A23: 4 | B23: 拍照费 | C23: 标签、货件等外观 | D23: USD1/张 | E23: 如需拆箱拍产品照，需额外收取重新打包或打托费
A24: 5 | B24: 抽卡费 | C24: 抽取卡片 | D24: USD1/张 | E24: 移除留评卡，礼品卡
A25: 6 | B25: 派送费 | C25: 二次派送费 | D25: 单询 | E25: 根据拦截后更新的仓库进行核算
A26: 7 | B26: 销毁费 | C26: 库内销毁 | D26: USD0.5/PCS | E26: 拦截或者留仓货物需要海外仓进行销毁处理
A27: 重要说明
A28: 1、以上价格适用于“FBA中转补仓服务”；从中国以整柜或散货的形式进入海外仓，以纸箱或托盘为最小处理单位，按需分批发往FBA； 2、易通海外仓有权拒收未预先告知入库、私人地址退件或者无客户ID的货物，且不承担由此造成的后果； 3、货物到仓后，海外仓按照客户提供的货运清单，以纸箱或托盘为最小清点单位，向客户反馈到仓情况；不对箱内产品数量进行清点且不负责； 4、仓库不接收一切仿牌、违禁、易燃易爆、违反美国法律法规等货物；仓库对每一批到仓货物都会进行抽检，一旦发现此类产品，将立即通知客户，作下架并销毁的处理； 海外仓概不负责； 5、收费构成： ①整柜散货入仓、按箱出仓：入仓费（按柜型）+订单处理费（纸箱）+ 仓租； ②整柜散货入仓、按托出仓：入仓费（按柜型）+订单处理费（纸箱）+ 打托费 + 仓租； ③散货纸箱入仓、按箱出仓：入仓费（纸箱）+订单处理费（纸箱） + 仓租； ④散货纸箱入仓、按托出仓：入仓费（纸箱）+订单处理费（纸箱）+ 打托费 + 仓租； 6、以上收费标准及服务政策，最终解释权归易通所有；确认合作后，即表示客户已阅读、理解并认同以上价格和内容，双方已达成共识。

Sheet 易通国内仓服务
A1: =_xlfn.DISPIMG("ID_D6697A225B864C34A678052B48D4E660",1) -> =DISPIMG("ID_D6697A225B864C34A678052B48D4E660",1)
A2: 仓库增值服务价格表
A3: 项目 | B3: 价格 | C3: 备注
A4: 入仓费 | B4: 22/CBM | C4: 货物送达我司仓库，收取RMB22/CBM，包含卸货，测量数据，登记入库等动作。
A5: 仓租 | B5: 请看备注 | C5: 1.存放一个星期(含7天)免费 (如客户需中转或退回的：需收取退仓费+仓储费，仓储费按RMB2.5/CBM/天收取) 2.超出7天一个月(第8-30天)之内按照RMB2.5/CBM/天收取存储费； 3.第二个月(第31天到60天)按照RMB5/CBM/天收取存储费，同时客服提前7天邮件通知客户是否继续续费存储； 4.对未缴纳存储费的客户，客服邮件提醒通知客户，存储周期为二个月(60天)未交费，定义客户自动弃货，我公司有权自行处理；
A6: 装柜费 | B6: 请看备注 | C6: 整柜装柜按RMB1000/柜收取费用
A7: 加班费 | B7: 请看备注 | C7: 周一至周五 20:01—23:00 RMB20元/小时/人 23:00后停止收货 周六18:00以后收货算加班，加班费30元/小时/人
A8: 贴标费 | B8: 请看备注 | C8: 1.进仓必须有我司唛头，未贴唛头或FBA标签，标贴破损，更换外箱标贴等不符合标准入仓货物需重新贴标，按照1元/张收取贴标费(另:我司可免费提供标签给客户/司机或业务自贴)最低消费10元/票； 2.内箱未贴中国制造、SKU的货物，按照0.6元/张收取(如有特殊操作要求需单询)最低消费30元/票； 3.撕黄色胶纸，收5元/箱(包重新贴透明胶纸)； 4.翻箱检查费(如:开箱核对SKU)5元/箱，最低消费50元/票。
A9: 换箱（我司提供纸箱） | B9: RMB20/箱 | C9: 含纸箱、两张FBA标签、唛头
A10: 换箱(客户提供纸箱) | B10: RMB10/箱 | C10: 含两张FBA标签、唛头
A11: 退仓费 | B11: RMB25/CBM | C11: 非我司原因导致的退仓：如产品不符合进出口要求、卖家账号异常等。最低收费RMB50/次。
A12: 打印费 | B12: 请看备注 | C12: 2元/张(入仓需入仓单，一式两份）（直客有唛头无需入仓单）
A13: 国内仓库地址及工作时间
A14: 收货时间： 1） 周一至周五 10:00-12:30 14:00-20:00 2） 周六 10:00-23:00 深圳总部公司地址：广东省深圳市龙华区民治街道民强社区宝山时代大厦2610-2616 东莞仓库地址（装柜仓库）：东莞市清溪镇九乡村新屋吓一路11号 陈主管15118451410 广州仓库地址（装柜仓库）：广州市白云区太岗公路34号基实(广州)白云空港产业园A1栋4层02单元 潘主管 19076062229 义乌仓库地址（装柜仓库）： 金华市金东区金港大道988号中外运仓库4号库1.2号门 王小姐 18158397350 嘉兴仓库地址（装柜仓库）：嘉兴市嘉善县洪福东路718号丰树（姚庄）科技综合产业园1B-3 李主管 18720007068 汕头仓库地址（中转仓库）：汕头市澄海区莱美工业区凤翔路逸诚汽车维修向前一到三间 胡经理 13923475593 泉州仓库地址（中转仓库）：晋江市磁灶镇西园街道传化公路港k2仓库成翔物流 李阿玲 158 6045 1181 厦门仓库地址（中转仓库）：厦门集美嘉晟物流园1期2栋110 李没没 14760028777 中山仓库地址（中转仓库）：中山市小榄镇北部物流中心 薛永波 18659507913
A15: 特别提示:此价格表一经发送，如客户一旦交货至我司，我司默认客户已仔细阅读此价格表的所有内容并接受各条款。

Sheet FBA偏远仓
A1: =_xlfn.DISPIMG("ID_D6697A225B864C34A678052B48D4E660",1) -> =DISPIMG("ID_D6697A225B864C34A678052B48D4E660",1)
A2: 顺序 | B2: FBA Code | C2: 地址 | D2: State | E2: Zip | F2: 是否偏远UPS/FEDEX
A3: 1 | B3: MCE1 | C3: 3200 Fulkerth Road TURLOCK,(MCE1) | D3: CA | E3: 95380 | F3: 偏远
A4: 2 | B4: SCK1 | C4: 4532 NEWCASTLE RD STOCKTON CA 95215-9465(SCK1) | D4: CA | E4: 95215 | F4: 偏远
A5: 3 | B5: SCK4 | C5: SCK4 - 6001 S AUSTIN RD 95215-8354 - STOCKTON, CA - United States(SCK4) | D5: CA | E5: 95215 | F5: 偏远
A6: 4 | B6: SCK8 | C6: 4700 WILBUR AVE 94561-2677 - OAKLEY，CA United states | D6: CA | E6: 94561 | F6: 偏远
A7: 5 | B7: FTW5 | C7: 1475 AKRON WAY FORNEY FORNEY TX 75126-3566 US(FTW5) | D7: TX | E7: 75126 | F7: 偏远
A8: 6 | B8: MKC4 | C8: Amazon.com.ksdc LLC 19645 Waverly Rd Edgerton, KS 66021-9588 US (MKC4) | D8: KS | E8: 66021 | F8: 超级偏远
A9: 7 | B9: ORD2 | C9: 23714 W Amoco Rd CHANNAHON, IL 60410-8758 US (ORD2) | D9: IL | E9: 60410 | F9: 偏远
A10: 8 | B10: IND4 | C10: Amazon.com.indc LLC 710 S Girls School Rd Indianapolis, IN 46231-1132 US(IND4) | D10: IN | E10: 46231 | F10: 偏远
A11: 9 | B11: MEM8 | C11: 850 GATEWAY GLOBAL DR BYHALIA, MS 38611-6040 US (MEM8) | D11: MS | E11: 38611 | F11: 超级偏远
A12: 10 | B12: MEM2 | C12: 191 NORFOLK SOUTHERN WAY BYHALIA, MS 38611-2306 US (MEM2) | D12: MS | E12: 38611 | F12: 超级偏远
A13: 11 | B13: IUSL | C13: 600 PRINCIPIO PKWY W 21901-2914 - NORTH EAST, MD - United States | D13: MD | E13: 21901 | F13: 偏远
A14: 12 | B14: RDG1 | C14: 3563 Mountain Road HAMBURG, PA 19526-7947 US (RDG1) | D14: PA | E14: 19526 | F14: 偏远
... A56: 54 | B56: LAS1 | C56: LAS1=12300 Bermuda RoadHENDERSON, NV 89044-8746 US | D56: NV | E56: 89044 | F56: 偏远

Sheet 美国偏远地址邮编
B8: Effective June 1, 2025
B10: US 48 ZIP Codes
B12: 1002 | C12: 1380 | D12: 1741 | E12: 2114 | F12: 2662 | G12: 3033 | H12: 3469 | I12: 3907 | J12: 4270 | K12: 4690 | L12: 5158 | M12: 5740 | N12: 6094 | O12: 6383 | P12: 6712
B13: 1007 | C13: 1420 | D13: 1754 | E13: 2116 | F13: 2668 | G13: 3034 | H13: 3470 | I13: 3908 | J13: 4271 | K13: 4738 | L13: 5159 | M13: 5753 | N13: 6230 | O13: 6387 | P13: 6716
B14: 1010 | C14: 1430 | D14: 1770 | E14: 2127 | F14: 2669 | G14: 3036 | H14: 3570 | I14: 4002 | J14: 4274 | K14: 4740 | L14: 5201 | M14: 5765 | N14: 6231 | O14: 6388 | P14: 6749
B15: 1029 | C15: 1431 | D15: 1773 | E15: 2203 | F15: 2670 | G15: 3040 | H15: 3575 | I15: 4021 | J15: 4280 | K15: 4742 | L15: 5253 | M15: 5768 | N15: 6232 | O15: 6401 | P15: 6751
B16: 1032 | C16: 1432 | D16: 1775 | E16: 2210 | F16: 2671 | G16: 3045 | H16: 3581 | I16: 4030 | J16: 4281 | K16: 4751 | L16: 5254 | M16: 5819 | N16: 6237 | O16: 6403 | P16: 6759
B17: 1033 | C17: 1436 | D17: 1826 | E17: 2269 | F17: 2675 | G17: 3046 | H17: 3584 | I17: 4033 | J17: 4282 | K17: 4843 | L17: 5255 | M17: 5823 | N17: 6238 | O17: 6404 | P17: 6762
B18: 1036 | C18: 1438 | D18: 1827 | E18: 2330 | F18: 2702 | G18: 3048 | H18: 3585 | I18: 4038 | J18: 4284 | K18: 4849 | L18: 5301 | M18: 5829 | N18: 6239 | O18: 6409 | P18: 6776
B19: 1038 | C19: 1450 | D19: 1830 | E19: 2332 | F19: 2715 | G19: 3049 | H19: 3598 | I19: 4039 | J19: 4286 | K19: 4850 | L19: 5302 | M19: 5830 | N19: 6243 | O19: 6412 | P19: 6778
B20: 1039 | C20: 1451 | D20: 1832 | E20: 2338 | F20: 2717 | G20: 3055 | H20: 3608 | I20: 4042 | J20: 4291 | K20: 4854 | L20: 5303 | M20: 5848 | N20: 6246 | O20: 6414 | P20: 6779
B21: 1056 | C21: 1462 | D21: 1833 | E21: 2341 | F21: 2722 | G21: 3057 | H21: 3741 | I21: 4046 | J21: 4341 | K21: 4856 | L21: 5304 | M21: 5850 | N21: 6248 | O21: 6415 | P21: 6782
B22: 1057 | C22: 1463 | D22: 1860 | E22: 2347 | F22: 2739 | G22: 3070 | H22: 3743 | I22: 4054 | J22: 4343 | K22: 4861 | L22: 5346 | M22: 5851 | N22: 6249 | O22: 6417 | P22: 6786
B23: 1069 | C23: 1464 | D23: 1879 | E23: 2364 | F23: 2743 | G23: 3084 | H23: 3748 | I23: 4061 | J23: 4345 | K23: 4865 | L23: 5354 | M23: 5855 | N23: 6250 | O23: 6419 | P23: 6787
... B52: 1376 | C52: 1720 | D52: 2113 | E52: 2660 | F52: 3032 | G52: 3467 | H52: 3905 | I52: 4268 | J52: 4675 | K52: 5156 | L52: 5736 | M52: 6093 | N52: 6378 | O52: 6704 | P52: 7710
B62: =B8 -> Effective June 1, 2025
B64: US 48 ZIP Codes
B66: 7716 | C66: 8011 | D66: 8240 | E66: 8533 | F66: 10001 | G66: 10123 | H66: 10505 | I66: 11212 | J66: 12019 | K66: 12414 | L66: 12545 | M66: 12820 | N66: 13064 | O66: 13326 | P66: 13636
B67: 7717 | C67: 8014 | D67: 8241 | E67: 8535 | F67: 10002 | G67: 10150 | H67: 10506 | I67: 11221 | J67: 12020 | K67: 12417 | L67: 12547 | M67: 12821 | N67: 13065 | O67: 13328 | P67: 13638
B68: 7719 | C68: 8015 | D68: 8242 | E68: 8551 | F68: 10003 | G68: 10151 | H68: 10509 | I68: 11226 | J68: 12027 | K68: 12419 | L68: 12548 | M68: 12831 | N68: 13068 | O68: 13335 | P68: 13640
B69: 7720 | C69: 8022 | D69: 8243 | E69: 8553 | F69: 10004 | G69: 10152 | H69: 10516 | I69: 11239 | J69: 12033 | K69: 12420 | L69: 12561 | M69: 12833 | N69: 13069 | O69: 13337 | P69: 13642
B70: 7722 | C70: 8025 | D70: 8245 | E70: 8554 | F70: 10005 | G70: 10153 | H70: 10518 | I70: 11569 | J70: 12041 | K70: 12423 | L70: 12563 | M70: 12834 | N70: 13073 | O70: 13346 | P70: 13645
B71: 7727 | C71: 8037 | D71: 8247 | E71: 8555 | F71: 10006 | G71: 10154 | H71: 10519 | I71: 11792 | J71: 12043 | K71: 12431 | L71: 12564 | M71: 12839 | N71: 13074 | O71: 13352 | P71: 13647
B72: 7732 | C72: 8038 | D72: 8248 | E72: 8556 | F72: 10007 | G72: 10155 | H72: 10524 | I72: 11930 | J72: 12050 | K72: 12432 | L72: 12565 | M72: 12845 | N72: 13076 | O72: 13354 | P72: 13649
B73: 7738 | C73: 8042 | D73: 8251 | E73: 8560 | F73: 10008 | G73: 10158 | H73: 10526 | I73: 11932 | J73: 12059 | K73: 12433 | L73: 12566 | M73: 12848 | N73: 13078 | O73: 13357 | P73: 13651
B74: 7762 | C74: 8050 | D74: 8260 | E74: 8562 | F74: 10009 | G74: 10165 | H74: 10536 | I74: 11933 | J74: 12063 | K74: 12436 | L74: 12568 | M74: 12854 | N74: 13080 | O74: 13363 | P74: 13657
B75: 7803 | C75: 8067 | D75: 8302 | E75: 8721 | F75: 10010 | G75: 10166 | H75: 10541 | I75: 11935 | J75: 12067 | K75: 12440 | L75: 12569 | M75: 12863 | N75: 13082 | O75: 13364 | P75: 13676
B76: 7821 | C76: 8068 | D76: 8310 | E76: 8731 | F76: 10011 | G76: 10167 | H76: 10542 | I76: 11937 | J76: 12069 | K76: 12443 | L76: 12570 | M76: 12884 | N76: 13084 | O76: 13401 | P76: 13677
B77: 7822 | C77: 8069 | D77: 8312 | E77: 8732 | F77: 10012 | G77: 10168 | H77: 10552 | I77: 11939 | J77: 12073 | K77: 12451 | L77: 12571 | M77: 12886 | N77: 13093 | O77: 13402 | P77: 13685
... B106: 8008 | C106: 8232 | D106: 8530 | E106: 8889 | F106: 10122 | G106: 10475 | H106: 10998 | I106: 12018 | J106: 12407 | K106: 12544 | L106: 12804 | M106: 13062 | N106: 13314 | O106: 13634 | P106: 14025
B116: =B8 -> Effective June 1, 2025
B118: US 48 ZIP Codes
B120: 14027 | C120: 14428 | D120: 14555 | E120: 14864 | F120: 15325 | G120: 15449 | H120: 15618 | I120: 15777 | J120: 16030 | K120: 16229 | L120: 16430 | M120: 16848 | N120: 17236 | O120: 17506 | P120: 17810
B121: 14029 | C121: 14429 | D121: 14556 | E121: 14865 | F121: 15327 | G121: 15450 | H121: 15622 | I121: 15783 | J121: 16033 | K121: 16232 | L121: 16432 | M121: 16851 | N121: 17237 | O121: 17507 | P121: 17820
B122: 14030 | C122: 14432 | D122: 14557 | E122: 14867 | F122: 15330 | G122: 15454 | H122: 15627 | I122: 15823 | J122: 16037 | K122: 16246 | L122: 16433 | M122: 16870 | N122: 17241 | O122: 17516 | P122: 17827
B123: 14033 | C123: 14437 | D123: 14563 | E123: 14869 | F123: 15331 | G123: 15458 | H123: 15628 | I123: 15824 | J123: 16038 | K123: 16250 | L123: 16438 | M123: 16873 | N123: 17249 | O123: 17519 | P123: 17832
B124: 14036 | C124: 14443 | D124: 14568 | E124: 14871 | F124: 15332 | G124: 15460 | H124: 15630 | I124: 15825 | J124: 16039 | K124: 16253 | L124: 16440 | M124: 16876 | N124: 17252 | O124: 17528 | P124: 17833
B125: 14041 | C125: 14449 | D125: 14569 | E125: 14872 | F125: 15334 | G125: 15461 | H125: 15641 | I125: 15827 | J125: 16048 | K125: 16254 | L125: 16441 | M125: 16877 | N125: 17253 | O125: 17529 | P125: 17834
B126: 14057 | C126: 14452 | D126: 14572 | E126: 14876 | F126: 15340 | G126: 15462 | H126: 15646 | I126: 15840 | J126: 16051 | K126: 16262 | L126: 16443 | M126: 16879 | N126: 17256 | O126: 17532 | P126: 17835
B127: 14061 | C127: 14454 | D127: 14589 | E127: 14881 | F127: 15344 | G127: 15463 | H127: 15656 | I127: 15841 | J127: 16052 | K127: 16301 | L127: 16475 | M127: 16901 | N127: 17257 | O127: 17534 | P127: 17840
B128: 14063 | C128: 14456 | D128: 14592 | E128: 14882 | F128: 15346 | G128: 15466 | H128: 15658 | I128: 15845 | J128: 16053 | K128: 16311 | L128: 16613 | M128: 16910 | N128: 17261 | O128: 17535 | P128: 17842
B129: 14070 | C129: 14464 | D129: 14701 | E129: 14886 | F129: 15347 | G129: 15468 | H129: 15670 | I129: 15846 | J129: 16055 | K129: 16314 | L129: 16614 | M129: 16920 | N129: 17266 | O129: 17562 | P129: 17844
B130: 14080 | C130: 14468 | D130: 14707 | E130: 14887 | F130: 15348 | G130: 15469 | H130: 15671 | I130: 15851 | J130: 16056 | K130: 16316 | L130: 16620 | M130: 16933 | N130: 17270 | O130: 17565 | P130: 17846
B131: 14081 | C131: 14469 | D131: 14710 | E131: 14891 | F131: 15351 | G131: 15473 | H131: 15679 | I131: 15853 | J131: 16057 | K131: 16319 | L131: 16624 | M131: 17007 | N131: 17301 | O131: 17566 | P131: 17847
... B160: 14424 | C160: 14551 | D160: 14863 | E160: 15324 | F160: 15447 | G160: 15617 | H160: 15776 | I160: 16027 | J160: 16223 | K160: 16428 | L160: 16847 | M160: 17235 | N160: 17505 | O160: 17801 | P160: 17951
B170: =B8 -> Effective June 1, 2025
B172: US 48 ZIP Codes
B174: 17959 | C174: 18244 | D174: 18444 | E174: 18934 | F174: 19530 | G174: 19956 | H174: 20620 | I174: 20770 | J174: 21156 | K174: 21715 | L174: 21862 | M174: 22660 | N174: 23001 | O174: 23847 | P174: 24266
B175: 17963 | C175: 18247 | D175: 18447 | E175: 18938 | F175: 19534 | G175: 19960 | H175: 20622 | I175: 20776 | J175: 21157 | K175: 21716 | L175: 21874 | M175: 22663 | N175: 23014 | O175: 23851 | P175: 24273
B176: 17966 | C176: 18250 | D176: 18451 | E176: 18942 | F176: 19535 | G176: 19962 | H176: 20623 | I176: 20777 | J176: 21158 | K176: 21719 | L176: 21875 | M176: 22664 | N176: 23043 | O176: 23860 | P176: 24277
B177: 17967 | C177: 18251 | D177: 18459 | E177: 18944 | F177: 19536 | G177: 19963 | H177: 20627 | I177: 20778 | J177: 21163 | K177: 21720 | L177: 21890 | M177: 22701 | N177: 23061 | O177: 23870 | P177: 24290
B178: 17974 | C178: 18252 | D178: 18463 | E178: 18947 | F178: 19539 | G178: 19968 | H178: 20629 | I178: 20779 | J178: 21522 | K178: 21721 | L178: 21901 | M178: 22712 | N178: 23064 | O178: 23884 | P178: 24293
B179: 17976 | C179: 18254 | D179: 18472 | E179: 18949 | F179: 19540 | G179: 19977 | H179: 20632 | I179: 20833 | J179: 21529 | K179: 21722 | L179: 21903 | M179: 22720 | N179: 23066 | O179: 23891 | P179: 24301
B180: 17978 | C180: 18255 | D180: 18503 | E180: 18951 | F180: 19541 | G180: 19979 | H180: 20634 | I180: 20841 | J180: 21532 | K180: 21723 | L180: 21904 | M180: 22722 | N180: 23069 | O180: 23899 | P180: 24311
B181: 17980 | C181: 18256 | D181: 18601 | E181: 18953 | F181: 19543 | G181: 20106 | H181: 20635 | I181: 20860 | J181: 21539 | K181: 21727 | L181: 21911 | M181: 22724 | N181: 23072 | O181: 23901 | P181: 24316
B182: 17981 | C182: 18301 | D182: 18603 | E182: 18963 | F182: 19545 | G182: 20107 | H182: 20636 | I182: 20861 | J182: 21541 | K182: 21733 | L182: 21917 | M182: 22725 | N182: 23092 | O182: 23909 | P182: 24333
B183: 18012 | C183: 18302 | D183: 18610 | E183: 18972 | F183: 19547 | G183: 20112 | H183: 20637 | I183: 20862 | J183: 21542 | K183: 21737 | L183: 21921 | M183: 22728 | N183: 23102 | O183: 23919 | P183: 24354
B184: 18013 | C184: 18320 | D184: 18612 | E184: 18981 | F184: 19548 | G184: 20119 | H184: 20640 | I184: 20872 | J184: 21545 | K184: 21738 | L184: 21922 | M184: 22731 | N184: 23103 | O184: 23939 | P184: 24382
B185: 18038 | C185: 18326 | D185: 18615 | E185: 18991 | F185: 19549 | G185: 20124 | H185: 20643 | I185: 20882 | J185: 21550 | K185: 21746 | L185: 22037 | M185: 22734 | N185: 23120 | O185: 23950 | P185: 24412
... B214: 18240 | C214: 18440 | D214: 18930 | E214: 19526 | F214: 19954 | G214: 20617 | H214: 20765 | I214: 21155 | J214: 21713 | K214: 21851 | L214: 22657 | M214: 22989 | N214: 23842 | O214: 24218 | P214: 24637
B224: =B8 -> Effective June 1, 2025
B226: US 48 ZIP Codes
B228: 24641 | C228: 25186 | D228: 25690 | E228: 26292 | F228: 27006 | G228: 27317 | H228: 27597 | I228: 27966 | J228: 28327 | K228: 28472 | L228: 28678 | M228: 28903 | N228: 29461 | O228: 29682 | P228: 30107
B229: 24701 | C229: 25202 | D229: 25810 | E229: 26346 | F229: 27009 | G229: 27320 | H229: 27801 | I229: 27981 | J229: 28328 | K229: 28479 | L229: 28680 | M229: 29006 | N229: 29486 | O229: 29688 | P229: 30110
B230: 24712 | C230: 25213 | D230: 25813 | E230: 26347 | F230: 27018 | G230: 27321 | H230: 27802 | I230: 27982 | J230: 28329 | K230: 28502 | L230: 28681 | M230: 29020 | N230: 29487 | O230: 29689 | P230: 30114
B231: 24724 | C231: 25260 | D231: 25823 | E231: 26366 | F231: 27019 | G231: 27323 | H231: 27803 | I231: 27986 | J231: 28330 | K231: 28503 | L231: 28682 | M231: 29021 | N231: 29488 | O231: 29690 | P231: 30116
B232: 24731 | C232: 25262 | D232: 25826 | E232: 26369 | F232: 27021 | G232: 27330 | H232: 27807 | I232: 28001 | J232: 28333 | K232: 28513 | L232: 28688 | M232: 29044 | N232: 29493 | O232: 29691 | P232: 30117
B233: 24737 | C233: 25264 | D233: 25840 | E233: 26378 | F233: 27025 | G233: 27331 | H233: 27809 | I233: 28002 | J233: 28334 | K233: 28519 | L233: 28691 | M233: 29046 | N233: 29511 | O233: 29693 | P233: 30120
B234: 24738 | C234: 25306 | D234: 25849 | E234: 26386 | F234: 27028 | G234: 27350 | H234: 27813 | I234: 28009 | J234: 28335 | K234: 28522 | L234: 28694 | M234: 29053 | N234: 29519 | O234: 29695 | P234: 30125
B235: 24739 | C235: 25311 | D235: 25853 | E235: 26404 | F235: 27030 | G235: 27351 | H235: 27819 | I235: 28016 | J235: 28339 | K235: 28529 | L235: 28697 | M235: 29054 | N235: 29520 | O235: 29697 | P235: 30129
B236: 24740 | C236: 25315 | D236: 25855 | E236: 26422 | F236: 27041 | G236: 27357 | H236: 27823 | I236: 28017 | J236: 28343 | K236: 28530 | L236: 28701 | M236: 29070 | N236: 29527 | O236: 29702 | P236: 30132
B237: 24751 | C237: 25404 | D237: 25873 | E237: 26424 | F237: 27042 | G237: 27358 | H237: 27825 | I237: 28021 | J237: 28345 | K237: 28532 | L237: 28711 | M237: 29074 | N237: 29532 | O237: 29704 | P237: 30140
B238: 24829 | C238: 25410 | D238: 25878 | E238: 26431 | F238: 27043 | G238: 27359 | H238: 27828 | I238: 28023 | J238: 28349 | K238: 28540 | L238: 28715 | M238: 29075 | N238: 29536 | O238: 29710 | P238: 30143
B239: 24843 | C239: 25414 | D239: 25901 | E239: 26438 | F239: 27045 | G239: 27370 | H239: 27837 | I239: 28024 | J239: 28352 | K239: 28544 | L239: 28716 | M239: 29079 | N239: 29541 | O239: 29714 | P239: 30145
... B268: 25185 | C268: 25667 | D268: 26275 | E268: 26855 | F268: 27313 | G268: 27596 | H268: 27964 | I268: 28326 | J268: 28467 | K268: 28673 | L268: 28901 | M268: 29433 | N268: 29678 | O268: 30094 | P268: 30281
B278: =B8 -> Effective June 1, 2025
B280: US 48 ZIP Codes
B282: 30290 | C282: 30655 | D282: 31084 | E282: 31757 | F282: 32168 | G282: 32643 | H282: 33139 | I282: 33870 | J282: 34430 | K282: 34762 | L282: 35127 | M282: 35760 | N282: 36275 | O282: 36576 | P282: 37143
B283: 30298 | C283: 30656 | D283: 31211 | E283: 31760 | F283: 32177 | G283: 32655 | H283: 33149 | I283: 33872 | J283: 34431 | K283: 34771 | L283: 35128 | M283: 35761 | N283: 36277 | O283: 36578 | P283: 37146
B284: 30337 | C284: 30665 | D284: 31220 | E284: 31763 | F284: 32178 | G284: 32658 | H284: 33187 | I284: 33873 | J284: 34432 | K284: 34772 | L284: 35135 | M284: 35768 | N284: 36301 | O284: 36580 | P284: 37148
B285: 30401 | C285: 30666 | D285: 31301 | E285: 31768 | F285: 32193 | G285: 32664 | H285: 33327 | I285: 33877 | J285: 34434 | K285: 34785 | L285: 35139 | M285: 35773 | N285: 36305 | O285: 36587 | P285: 37153
B286: 30414 | C286: 30671 | D286: 31302 | E286: 31769 | F286: 32195 | G286: 32669 | H286: 33455 | I286: 33917 | J286: 34441 | K286: 34797 | L286: 35146 | M286: 35901 | N286: 36312 | O286: 36612 | P286: 37160
B287: 30415 | C287: 30677 | D287: 31307 | E287: 31776 | F287: 32305 | G287: 32696 | H287: 33470 | I287: 33920 | J287: 34442 | K287: 34946 | L287: 35147 | M287: 35904 | N287: 36321 | O287: 36613 | P287: 37166
B288: 30417 | C288: 30701 | D288: 31308 | E288: 31782 | F288: 32310 | G288: 32697 | H288: 33475 | I288: 33921 | J288: 34445 | K288: 34947 | L288: 35148 | M288: 35905 | N288: 36322 | O288: 36633 | P288: 37172
B289: 30429 | C289: 30705 | D289: 31310 | E289: 31788 | F289: 32326 | G289: 32713 | H289: 33513 | I289: 33922 | J289: 34446 | K289: 34949 | L289: 35149 | M289: 35906 | N289: 36330 | O289: 36701 | P289: 37179
B290: 30436 | C290: 30710 | D290: 31312 | E290: 31791 | F290: 32327 | G290: 32720 | H290: 33521 | I290: 33936 | J290: 34447 | K290: 34951 | L290: 35150 | M290: 35950 | N290: 36340 | O290: 36702 | P290: 37180
B291: 30461 | C291: 30725 | D291: 31313 | E291: 31792 | F291: 32330 | G291: 32724 | H291: 33525 | I291: 33945 | J291: 34448 | K291: 34957 | L291: 35160 | M291: 35951 | N291: 36345 | O291: 36703 | P291: 37187
B292: 30464 | C292: 30728 | D292: 31315 | E292: 31794 | F292: 32332 | G292: 32744 | H292: 33526 | I292: 33947 | J292: 34450 | K292: 34987 | L292: 35161 | M292: 35954 | N292: 36349 | O292: 36732 | P292: 37188
B293: 30474 | C293: 30732 | D293: 31318 | E293: 31804 | F293: 32333 | G293: 32745 | H293: 33527 | I293: 33955 | J293: 34451 | K293: 34990 | L293: 35176 | M293: 35956 | N293: 36350 | O293: 36741 | P293: 37189
... B322: 30650 | C322: 31069 | D322: 31729 | E322: 32137 | F322: 32634 | G322: 33132 | H322: 33868 | I322: 34429 | J322: 34759 | K322: 35126 | L322: 35759 | M322: 36271 | N322: 36574 | O322: 37111 | P322: 37656
B332: =B8 -> Effective June 1, 2025
B334: US 48 ZIP Codes
B336: 37659 | C336: 38004 | D336: 38478 | E336: 38865 | F336: 39520 | G336: 40117 | H336: 40965 | I336: 41651 | J336: 42347 | K336: 43058 | L336: 43402 | M336: 43725 | N336: 44003 | O336: 44411 | P336: 44654
B337: 37690 | C337: 38006 | D337: 38483 | E337: 38866 | F337: 39521 | G337: 40121 | H337: 41001 | I337: 41653 | J337: 42354 | K337: 43067 | L337: 43410 | M337: 43731 | N337: 44010 | O337: 44412 | P337: 44657
B338: 37692 | C338: 38011 | D338: 38558 | E338: 38869 | F338: 39553 | G338: 40165 | H338: 41030 | I338: 41659 | J338: 42367 | K338: 43070 | L338: 43416 | M338: 43733 | N338: 44021 | O338: 44413 | P338: 44659
B339: 37694 | C339: 38019 | D339: 38559 | E339: 38880 | F339: 39556 | G339: 40310 | H339: 41031 | I339: 41666 | J339: 42370 | K339: 43074 | L339: 43420 | M339: 43735 | N339: 44030 | O339: 44415 | P339: 44660
B340: 37709 | C340: 38024 | D340: 38570 | E340: 38915 | F340: 39558 | G340: 40317 | H340: 41035 | I340: 41669 | J340: 42374 | K340: 43076 | L340: 43430 | M340: 43738 | N340: 44041 | O340: 44418 | P340: 44662
B341: 37711 | C341: 38025 | D341: 38571 | E341: 38926 | F341: 39561 | G341: 40320 | H341: 41056 | I341: 41701 | J341: 42402 | K341: 43077 | L341: 43431 | M341: 43740 | N341: 44044 | O341: 44423 | P341: 44666
B342: 37719 | C342: 38028 | D342: 38578 | E342: 38947 | F342: 39563 | G342: 40339 | H342: 41059 | I342: 41739 | J342: 42413 | K342: 43078 | L342: 43432 | M342: 43752 | N342: 44047 | O342: 44424 | P342: 44669
B343: 37725 | C343: 38036 | D343: 38583 | E343: 38957 | F343: 39571 | G343: 40342 | H343: 41080 | I343: 41778 | J343: 42420 | K343: 43101 | L343: 43433 | M343: 43759 | N343: 44048 | O343: 44431 | P343: 44670
...

Sheet 美国超偏远地址邮编
B8: Effective June 1, 2025
B10: US 48 DAS Extended ZIP Codes
B12: 1005 | C12: 1340 | D12: 2874 | E12: 3268 | F12: 3605 | G12: 3882 | H12: 4076 | I12: 4411 | J12: 4488 | K12: 4629 | L12: 4734 | M12: 4910 | N12: 5034 | O12: 5151 | P12: 5462
B13: 1008 | C13: 1341 | D13: 2875 | E13: 3269 | F13: 3607 | G13: 3883 | H13: 4077 | I13: 4414 | J13: 4489 | K13: 4631 | L13: 4735 | M13: 4912 | N13: 5035 | O13: 5152 | P13: 5463
B14: 1011 | C14: 1343 | D14: 2883 | E14: 3272 | F14: 3609 | G14: 3884 | H14: 4078 | I14: 4418 | J14: 4491 | K14: 4634 | L14: 4736 | M14: 4920 | N14: 5036 | O14: 5153 | P14: 5464
B15: 1012 | C15: 1344 | D15: 2892 | E15: 3273 | F15: 3740 | G15: 3886 | H15: 4079 | I15: 4420 | J15: 4493 | K15: 4635 | L15: 4737 | M15: 4921 | N15: 5037 | O15: 5155 | P15: 5466
B16: 1031 | C16: 1346 | D16: 2894 | E16: 3278 | F16: 3745 | G16: 3887 | H16: 4088 | I16: 4421 | J16: 4497 | K16: 4640 | L16: 4739 | M16: 4922 | N16: 5038 | O16: 5161 | P16: 5470
B17: 1034 | C17: 1350 | D17: 3037 | E17: 3279 | F17: 3746 | G17: 3890 | H17: 4091 | I17: 4422 | J17: 4535 | K17: 4642 | L17: 4741 | M17: 4923 | N17: 5039 | O17: 5250 | P17: 5471
B18: 1037 | C18: 1355 | D18: 3043 | E18: 3282 | F18: 3750 | G18: 3894 | H18: 4095 | I18: 4423 | J18: 4539 | K18: 4643 | L18: 4744 | M18: 4925 | N18: 5040 | O18: 5251 | P18: 5472
B19: 1050 | C19: 1360 | D19: 3044 | E19: 3284 | F19: 3751 | G19: 3896 | H19: 4109 | I19: 4424 | J19: 4544 | K19: 4644 | L19: 4745 | M19: 4926 | N19: 5041 | O19: 5252 | P19: 5474
B20: 1054 | C20: 1366 | D20: 3047 | E20: 3285 | F20: 3752 | G20: 3897 | H20: 4216 | I20: 4427 | J20: 4547 | K20: 4646 | L20: 4747 | M20: 4928 | N20: 5042 | O20: 5257 | P20: 5476
B21: 1066 | C21: 1367 | D21: 3071 | E21: 3287 | F21: 3765 | G21: 4001 | H21: 4217 | I21: 4428 | J21: 4551 | K21: 4648 | L21: 4750 | M21: 4929 | N21: 5043 | O21: 5260 | P21: 5481
B22: 1068 | C22: 1370 | D22: 3082 | E22: 3290 | F22: 3768 | G22: 4003 | H22: 4219 | I22: 4429 | J22: 4552 | K22: 4649 | L22: 4756 | M22: 4930 | N22: 5045 | O22: 5261 | P22: 5486
B23: 1070 | C23: 1378 | D23: 3215 | E23: 3307 | F23: 3777 | G23: 4008 | H23: 4220 | I23: 4430 | J23: 4555 | K23: 4650 | L23: 4757 | M23: 4932 | N23: 5046 | O23: 5262 | P23: 5488
... B52: 1339 | C52: 2872 | D52: 3266 | E52: 3603 | F52: 3875 | G52: 4075 | H52: 4410 | I52: 4485 | J52: 4628 | K52: 4733 | L52: 4864 | M52: 5032 | N52: 5149 | O52: 5460 | P52: 5735
B62: =B8 -> Effective June 1, 2025
B64: US 48 DAS Extended ZIP Codes
B66: 5737 | C66: 5837 | D66: 6242 | E66: 7851 | F66: 12024 | G66: 12136 | H66: 12430 | I66: 12517 | J66: 12777 | K66: 12856 | L66: 12957 | M66: 13102 | N66: 13342 | O66: 13489 | P66: 13672
B67: 5738 | C67: 5839 | D67: 6244 | E67: 7863 | F67: 12025 | G67: 12137 | H67: 12434 | I67: 12521 | J67: 12778 | K67: 12857 | L67: 12959 | M67: 13110 | N67: 13343 | O67: 13491 | P67: 13673
B68: 5739 | C68: 5841 | D68: 6247 | E68: 7865 | F68: 12028 | G68: 12138 | H68: 12435 | I68: 12522 | J68: 12780 | K68: 12859 | L68: 12960 | M68: 13111 | N68: 13345 | O68: 13493 | P68: 13674
B69: 5741 | C69: 5842 | D69: 6258 | E69: 7875 | F69: 12029 | G69: 12139 | H69: 12438 | I69: 12523 | J69: 12782 | K69: 12860 | L69: 12961 | M69: 13114 | N69: 13348 | O69: 13494 | P69: 13675
B70: 5742 | C70: 5843 | D70: 6259 | E70: 7880 | F70: 12031 | G70: 12147 | H70: 12439 | I70: 12526 | J70: 12783 | K70: 12865 | L70: 12964 | M70: 13118 | N70: 13353 | O70: 13602 | P70: 13678
B71: 5743 | C71: 5846 | D71: 6278 | E71: 7890 | F71: 12032 | G71: 12149 | H71: 12441 | I71: 12529 | J71: 12784 | K71: 12870 | L71: 12965 | M71: 13122 | N71: 13360 | O71: 13608 | P71: 13679
B72: 5744 | C72: 5847 | D72: 6281 | E72: 7931 | F72: 12035 | G72: 12153 | H72: 12442 | I72: 12546 | J72: 12786 | K72: 12871 | L72: 12966 | M72: 13123 | N72: 13361 | O72: 13613 | P72: 13680
B73: 5745 | C73: 5849 | D73: 6282 | E73: 8006 | F73: 12036 | G73: 12155 | H73: 12444 | I73: 12567 | J73: 12788 | K73: 12873 | L73: 12967 | M73: 13124 | N73: 13365 | O73: 13614 | P73: 13681
B74: 5746 | C74: 5857 | D74: 6334 | E74: 8019 | F74: 12037 | G74: 12156 | H74: 12446 | I74: 12581 | J74: 12789 | K74: 12874 | L74: 12969 | M74: 13136 | N74: 13367 | O74: 13618 | P74: 13682
B75: 5747 | C75: 5858 | D75: 6336 | E75: 8041 | F75: 12040 | G75: 12157 | H75: 12448 | I75: 12583 | J75: 12790 | K75: 12878 | L75: 12970 | M75: 13140 | N75: 13368 | O75: 13620 | P75: 13684
B76: 5748 | C76: 5859 | D76: 6350 | E76: 8064 | F76: 12042 | G76: 12160 | H76: 12450 | I76: 12588 | J76: 12791 | K76: 12879 | L76: 12973 | M76: 13141 | N76: 13406 | O76: 13621 | P76: 13687
B77: 5750 | C77: 5860 | D77: 6359 | E77: 8219 | F77: 12046 | G77: 12164 | H77: 12452 | I77: 12719 | J77: 12792 | K77: 12883 | L77: 12974 | M77: 13143 | N77: 13411 | O77: 13622 | P77: 13690
... B106: 5836 | C106: 6235 | D106: 7844 | E106: 12023 | F106: 12134 | G106: 12428 | H106: 12516 | I106: 12776 | J106: 12855 | K106: 12956 | L106: 13101 | M106: 13339 | N106: 13488 | O106: 13671 | P106: 13783
B116: =B8 -> Effective June 1, 2025
B118: US 48 DAS Extended ZIP Codes
B120: 13786 | C120: 14055 | D120: 14536 | E120: 14754 | F120: 14860 | G120: 15411 | H120: 15713 | I120: 15864 | J120: 16224 | K120: 16374 | L120: 16678 | M120: 16839 | N120: 16943 | O120: 17219 | P120: 17765
B121: 13787 | C121: 14058 | D121: 14539 | E121: 14755 | F121: 14861 | G121: 15412 | H121: 15716 | I121: 15868 | J121: 16226 | K121: 16402 | L121: 16679 | M121: 16841 | N121: 16945 | O121: 17220 | P121: 17771
B122: 13788 | C122: 14060 | D122: 14541 | E122: 14758 | F122: 14873 | G122: 15424 | H122: 15724 | I122: 15870 | J122: 16230 | K122: 16404 | L122: 16680 | M122: 16845 | N122: 16946 | O122: 17222 | P122: 17774
B123: 13796 | C123: 14062 | D123: 14547 | E123: 14767 | F123: 14874 | G123: 15433 | H123: 15725 | I123: 15923 | J123: 16233 | K123: 16405 | L123: 16683 | M123: 16849 | N123: 16947 | O123: 17224 | P123: 17776
B124: 13797 | C124: 14065 | D124: 14549 | E124: 14769 | F124: 14877 | G124: 15440 | H124: 15727 | I124: 15924 | J124: 16234 | K124: 16406 | L124: 16685 | M124: 16852 | N124: 16948 | O124: 17228 | P124: 17812
B125: 13801 | C125: 14066 | D125: 14550 | E125: 14770 | F125: 14878 | G125: 15451 | H125: 15729 | I125: 15926 | J125: 16235 | K125: 16420 | L125: 16689 | M125: 16854 | N125: 17002 | O125: 17229 | P125: 17813
B126: 13803 | C126: 14067 | D126: 14560 | E126: 14772 | F126: 14879 | G126: 15459 | H126: 15732 | I126: 15929 | J126: 16236 | K126: 16434 | L126: 16691 | M126: 16855 | N126: 17004 | O126: 17238 | P126: 17814
B127: 13806 | C127: 14069 | D127: 14561 | E127: 14774 | F127: 14880 | G127: 15464 | H127: 15736 | I127: 15936 | J127: 16239 | K127: 16435 | L127: 16692 | M127: 16856 | N127: 17006 | O127: 17239 | P127: 17821
B128: 13807 | C128: 14082 | D128: 14571 | E128: 14775 | F128: 14883 | G128: 15467 | H128: 15737 | I128: 15940 | J128: 16240 | K128: 16436 | L128: 16693 | M128: 16858 | N128: 17017 | O128: 17240 | P128: 17823
B129: 13808 | C129: 14083 | D129: 14590 | E129: 14777 | F129: 14884 | G129: 15470 | H129: 15742 | I129: 15942 | J129: 16242 | K129: 16442 | L129: 16694 | M129: 16859 | N129: 17021 | O129: 17243 | P129: 17824
B130: 13809 | C130: 14091 | D130: 14591 | E130: 14779 | F130: 14885 | G130: 15485 | H130: 15745 | I130: 15944 | J130: 16244 | K130: 16611 | L130: 16695 | M130: 16860 | N130: 17029 | O130: 17244 | P130: 17825
B131: 13810 | C131: 14098 | D131: 14706 | E131: 14781 | F131: 14889 | G131: 15486 | H131: 15746 | I131: 15955 | J131: 16245 | K131: 16616 | L131: 16698 | M131: 16861 | N131: 17030 | O131: 17246 | P131: 17828
... B160: 14054 | C160: 14525 | D160: 14753 | E160: 14859 | F160: 15410 | G160: 15711 | H160: 15863 | I160: 16222 | J160: 16373 | K160: 16677 | L160: 16838 | M160: 16941 | N160: 17217 | O160: 17764 | P160: 18065
B170: =B8 -> Effective June 1, 2025
B172: US 48 DAS Extended ZIP Codes
B174: 18066 | C174: 18456 | D174: 18844 | E174: 20656 | F174: 21636 | G174: 21856 | H174: 22530 | I174: 22733 | J174: 22973 | K174: 23115 | L174: 23401 | M174: 23867 | N174: 23976 | O174: 24246 | P174: 24380
B175: 18220 | C175: 18457 | D175: 18845 | E175: 20662 | F175: 21640 | G175: 21857 | H175: 22534 | I175: 22735 | J175: 22976 | K175: 23117 | L175: 23404 | M175: 23868 | N175: 24054 | O175: 24248 | P175: 24381
B176: 18241 | C176: 18458 | D176: 18846 | E176: 20664 | F176: 21641 | G176: 21861 | H176: 22535 | I176: 22736 | J176: 23002 | K176: 23119 | L176: 23405 | M176: 23874 | N176: 24055 | O176: 24251 | P176: 24413
B177: 18242 | C177: 18460 | D177: 18850 | E177: 20670 | F177: 21644 | G177: 21863 | H177: 22539 | I177: 22737 | J177: 23003 | K177: 23126 | L177: 23408 | M177: 23876 | N177: 24059 | O177: 24256 | P177: 24421
B178: 18243 | C178: 18461 | D178: 18851 | E178: 20674 | F178: 21645 | G178: 21864 | H178: 22542 | I178: 22738 | J178: 23004 | K178: 23128 | L178: 23410 | M178: 23878 | N178: 24065 | O178: 24258 | P178: 24422
B179: 18246 | C179: 18462 | D179: 18853 | E179: 20680 | F179: 21648 | G179: 21865 | H179: 22546 | I179: 22740 | J179: 23009 | K179: 23130 | L179: 23412 | M179: 23879 | N179: 24066 | O179: 24260 | P179: 24426
B180: 18248 | C180: 18464 | D180: 18854 | E180: 20682 | F180: 21650 | G180: 21869 | H180: 22548 | I180: 22741 | J180: 23011 | K180: 23138 | L180: 23415 | M180: 23882 | N180: 24069 | O180: 24269 | P180: 24430
B181: 18249 | C181: 18465 | D181: 18920 | E181: 20685 | F181: 21657 | G181: 21871 | H181: 22558 | I181: 22743 | J181: 23015 | K181: 23140 | L181: 23416 | M181: 23883 | N181: 24070 | O181: 24270 | P181: 24432
B182: 18323 | C182: 18466 | D182: 18928 | E182: 20687 | F182: 21658 | G182: 21872 | H182: 22565 | I182: 22746 | J182: 23021 | K182: 23148 | L182: 23417 | M182: 23885 | N182: 24072 | O182: 24271 | P182: 24433
B183: 18324 | C183: 18469 | D183: 18933 | E183: 20692 | F183: 21659 | G183: 21912 | H183: 22567 | I183: 22747 | J183: 23022 | K183: 23149 | L183: 23419 | M183: 23887 | N183: 24079 | O183: 24279 | P183: 24435
B184: 18325 | C184: 18470 | D184: 19052 | E184: 20837 | F184: 21661 | G184: 21913 | H184: 22570 | I184: 22749 | J184: 23023 | K184: 23153 | L184: 23421 | M184: 23888 | N184: 24082 | O184: 24280 | P184: 24439
B185: 18327 | C185: 18473 | D185: 19507 | E185: 20838 | F185: 21662 | G185: 21915 | H185: 22572 | I185: 22810 | J185: 23024 | K185: 23154 | L185: 23422 | M185: 23889 | N185: 24085 | O185: 24281 | P185: 24445
... B214: 18454 | C214: 18842 | D214: 20645 | E214: 21634 | F214: 21853 | G214: 22529 | H214: 22732 | I214: 22972 | J214: 23110 | K214: 23399 | L214: 23866 | M214: 23974 | N214: 24237 | O214: 24378 | P214: 24557
B224: =B8 -> Effective June 1, 2025
B226: US 48 DAS Extended ZIP Codes
B228: 24558 | C228: 24714 | D228: 24878 | E228: 25003 | F228: 25121 | G228: 25251 | H228: 25635 | I228: 25857 | J228: 26047 | K228: 26285 | L228: 26572 | M228: 27013 | N228: 27521 | O228: 27849 | P228: 27943
B229: 24562 | C229: 24715 | D229: 24879 | E229: 25004 | F229: 25122 | G229: 25258 | H229: 25636 | I229: 25862 | J229: 26056 | K229: 26287 | L229: 26575 | M229: 27017 | N229: 27524 | O229: 27850 | P229: 27946
B230: 24563 | C230: 24716 | D230: 24880 | E230: 25005 | F230: 25124 | G230: 25261 | H230: 25637 | I230: 25864 | J230: 26070 | K230: 26289 | L230: 26586 | M230: 27020 | N230: 27541 | O230: 27851 | P230: 27949
B231: 24566 | C231: 24719 | D231: 24882 | E231: 25007 | F231: 25126 | G231: 25276 | H231: 25638 | I231: 25865 | J231: 26121 | K231: 26291 | L231: 26589 | M231: 27022 | N231: 27544 | O231: 27852 | P231: 27950
B232: 24569 | C232: 24733 | D232: 24883 | E232: 25008 | F232: 25130 | G232: 25279 | H232: 25644 | I232: 25866 | J232: 26135 | K232: 26293 | L232: 26590 | M232: 27024 | N232: 27549 | O232: 27853 | P232: 27953
B233: 24571 | C233: 24801 | D233: 24887 | E233: 25010 | F233: 25132 | G233: 25281 | H233: 25645 | I233: 25868 | J233: 26136 | K233: 26298 | L233: 26624 | M233: 27027 | N233: 27551 | O233: 27857 | P233: 27954
B234: 24574 | C234: 24808 | D234: 24888 | E234: 25018 | F234: 25134 | G234: 25283 | H234: 25646 | I234: 25870 | J234: 26137 | K234: 26327 | L234: 26629 | M234: 27046 | N234: 27553 | O234: 27860 | P234: 27956
B235: 24576 | C235: 24813 | D235: 24892 | E235: 25019 | F235: 25136 | G235: 25285 | H235: 25647 | I235: 25875 | J235: 26138 | K235: 26328 | L235: 26634 | M235: 27047 | N235: 27557 | O235: 27861 | P235: 27957
B236: 24577 | C236: 24818 | D236: 24894 | E236: 25021 | F236: 25140 | G236: 25312 | H236: 25649 | I236: 25876 | J236: 26142 | K236: 26332 | L236: 26639 | M236: 27048 | N236: 27559 | O236: 27862 | P236: 27959
B237: 24578 | C237: 24821 | D237: 24895 | E237: 25022 | F237: 25141 | G237: 25320 | H237: 25650 | I237: 25879 | J237: 26143 | K237: 26334 | L237: 26641 | M237: 27052 | N237: 27563 | O237: 27869 | P237: 27960
B238: 24579 | C238: 24822 | D238: 24898 | E238: 25025 | F238: 25142 | G238: 25411 | H238: 25651 | I238: 25880 | J238: 26146 | K238: 26337 | L238: 26651 | M238: 27053 | N238: 27565 | O238: 27871 | P238: 27962
B239: 24585 | C239: 24823 | D239: 24899 | E239: 25028 | F239: 25148 | G239: 25413 | H239: 25661 | I239: 25882 | J239: 26147 | K239: 26348 | L239: 26656 | M239: 27054 | N239: 27569 | O239: 27872 | P239: 27965
... B268: 24658 | C268: 24877 | D268: 25002 | E268: 25119 | F268: 25250 | G268: 25634 | H268: 25856 | I268: 26036 | J268: 26283 | K268: 26571 | L268: 27011 | M268: 27507 | N268: 27847 | O268: 27942 | P268: 28125
B278: =B8 -> Effective June 1, 2025
B280: US 48 DAS Extended ZIP Codes
B282: 28127 | C282: 28398 | D282: 28512 | E282: 28636 | F282: 28768 | G282: 29080 | H282: 29372 | I282: 29544 | J282: 29728 | K282: 30056 | L282: 30293 | M282: 30533 | N282: 30678 | O282: 31035 | P282: 31331
B283: 28128 | C283: 28399 | D283: 28515 | E283: 28640 | F283: 28771 | G283: 29081 | H283: 29373 | I283: 29545 | J283: 29729 | K283: 30103 | L283: 30295 | M283: 30534 | N283: 30683 | O283: 31036 | P283: 31510
B284: 28129 | C284: 28420 | D284: 28516 | E284: 28646 | F284: 28774 | G284: 29082 | H284: 29374 | I284: 29547 | J284: 29741 | K284: 30104 | L284: 30410 | M284: 30537 | N284: 30707 | O284: 31037 | P284: 31512
B285: 28133 | C285: 28421 | D285: 28520 | E285: 28651 | F285: 28775 | G285: 29101 | H285: 29377 | I285: 29555 | J285: 29743 | K285: 30105 | L285: 30411 | M285: 30540 | N285: 30708 | O285: 31041 | P285: 31513
B286: 28135 | C286: 28423 | D286: 28521 | E286: 28654 | F286: 28777 | G286: 29104 | H286: 29379 | I286: 29556 | J286: 29810 | K286: 30108 | L286: 30412 | M286: 30545 | N286: 30711 | O286: 31042 | P286: 31515
B287: 28139 | C287: 28424 | D287: 28523 | E287: 28660 | F287: 28782 | G287: 29105 | H287: 29384 | I287: 29565 | J287: 29812 | K287: 30113 | L287: 30413 | M287: 30547 | N287: 30724 | O287: 31044 | P287: 31518
B288: 28163 | C288: 28430 | D288: 28524 | E288: 28663 | F288: 28784 | G288: 29107 | H288: 29429 | I288: 29567 | J288: 29813 | K288: 30124 | L288: 30420 | M288: 30554 | N288: 30735 | O288: 31050 | P288: 31519
B289: 28167 | C289: 28431 | D289: 28525 | E289: 28664 | F289: 28785 | G289: 29111 | H289: 29431 | I289: 29570 | J289: 29817 | K289: 30139 | L289: 30421 | M289: 30557 | N289: 30746 | O289: 31051 | P289: 31527
B290: 28168 | C290: 28432 | D290: 28526 | E290: 28665 | F290: 28789 | G290: 29112 | H290: 29432 | I290: 29574 | J290: 29819 | K290: 30147 | L290: 30424 | M290: 30558 | N290: 30747 | O290: 31054 | P290: 31532
B291: 28170 | C291: 28433 | D291: 28527 | E291: 28669 | F291: 28904 | G291: 29113 | H291: 29434 | I291: 29581 | J291: 29821 | K291: 30148 | L291: 30425 | M291: 30564 | N291: 30752 | O291: 31055 | P291: 31533
B292: 28315 | C292: 28434 | D292: 28528 | E292: 28670 | F292: 28905 | G292: 29114 | H292: 29435 | I292: 29583 | J292: 29822 | K292: 30151 | L292: 30426 | M292: 30567 | N292: 30802 | O292: 31057 | P292: 31537
B293: 28318 | C293: 28435 | D293: 28537 | E293: 28672 | F293: 28906 | G293: 29124 | H293: 29436 | I293: 29584 | J293: 29824 | K293: 30170 | L293: 30427 | M293: 30568 | N293: 30803 | O293: 31058 | P293: 31539
... B322: 28396 | C322: 28511 | D322: 28634 | E322: 28765 | F322: 29078 | G322: 29370 | H322: 29540 | I322: 29727 | J322: 30055 | K322: 30292 | L322: 30529 | M322: 30673 | N322: 31033 | O322: 31329 | P322: 31637
B332: =B8 -> Effective June 1, 2025
B334: US 48 DAS Extended ZIP Codes
B336: 31638 | C336: 31752 | D336: 31826 | E336: 32180 | F336: 32438 | G336: 32736 | H336: 33960 | I336: 35060 | J336: 35474 | K336: 35622 | L336: 35979 | M336: 36264 | N336: 36475 | O336: 36782 | P336: 37049
B337: 31639 | C337: 31754 | D337: 31827 | E337: 32181 | F337: 32442 | G337: 32764 | H337: 33975 | I337: 35063 | J337: 35480 | K337: 35633 | L337: 35980 | M337: 36267 | N337: 36477 | O337: 36783 | P337: 37050
B338: 31641 | C338: 31756 | D338: 31830 | E338: 32182 | F338: 32445 | G338: 32767 | H338: 33982 | I338: 35072 | J338: 35481 | K338: 35643 | L338: 35981 | M338: 36270 | N338: 36483 | O338: 36784 | P338: 37051
B339: 31642 | C339: 31759 | D339: 31832 | E339: 32183 | F339: 32449 | G339: 32775 | H339: 34138 | I339: 35074 | J339: 35490 | K339: 35645 | L339: 35983 | M339: 36272 | N339: 36505 | O339: 36790 | P339: 37052
B340: 31643 | C340: 31761 | D340: 31836 | E340: 32185 | F340: 32452 | G340: 32833 | H340: 34139 | I340: 35077 | J340: 35503 | K340: 35646 | L340: 35984 | M340: 36274 | N340: 36507 | O340: 36792 | P340: 37057
B341: 31645 | C341: 31762 | D341: 32009 | E341: 32187 | F341: 32462 | G341: 32834 | H341: 34141 | I341: 35078 | J341: 35540 | K341: 35647 | L341: 35988 | M341: 36276 | N341: 36511 | O341: 36850 | P341: 37059
B342: 31646 | C342: 31765 | D342: 32013 | E342: 32189 | F342: 32465 | G342: 32948 | H342: 34142 | I342: 35079 | J342: 35541 | K342: 35648 | L342: 35989 | M342: 36278 | N342: 36515 | O342: 36851 | P342: 37060
B343: 31647 | C343: 31766 | D343: 32033 | E343: 32190 | F343: 32466 | G343: 33001 | H343: 34143 | I343: 35083 | J343: 35542 | K343: 35652 | L343: 35990 | M343: 36279 | N343: 36521 | O343: 36852 | P343: 37061
...
