Workbook
Name _Loc1: [1]Request!$M$125
Name Testing: [2]欧洲UPS偏远表!#REF!
Name 美国: '[3]美国海运查询表 (2)'!$P$2:$P$1048576
Name 美国: '[3]美国海运查询表 (2)'!$P$2:$P$1048576
Name 美国: '美国海运查询表 (2)'!$P$2:$P$1048576
Name 英国: '[3]美国海运查询表 (2)'!$R$2:$R$1048576
Name 英国: '[3]美国海运查询表 (2)'!$R$2:$R$1048576
Name 英国: '美国海运查询表 (2)'!$R$2:$R$1048576

Sheet 价格查询表
D1: 天图通逊供应链有限公司 立志打造一家具有社会价值的百年跨境物流企业 | M1: {=_xlfn.LET(_xlpm.X,IFERROR(_wpsfn.REGEXP(_xlfn._xlws.FILTER(_xlfn.VSTACK(_xlfn.UNIQUE(INDIRECT("美西直送系列!A7:A"&COUNTA(美西直送系列!A:A)+6-1)),_xlfn.UNIQUE(INDIRECT("'美西-美森(12-17)'!A7:A"&COUNTA('美西-美森(12-17)'!A7:A130)+6-1)),_xlfn.UNIQUE(INDIRECT("'美西-以星&普船(17-26)'!A7:A"&COUNTA('美西-以星&普船(17-26)'!A:A)+6-1)),_xlfn.UNIQUE(INDIRECT("美西北!A7:A"&COUNTA(美西北!A:A)+6-1)),_xlfn.UNIQUE(INDIRECT("'美东-海铁系列'!A7:A"&COUNTA('美东-海铁系列'!A:A)+6-1)),_xlfn.UNIQUE(INDIRECT("美东南直航系列!A7:A"&COUNTA(美东南直航系列!A:A)+6-1)),_xlfn.UNIQUE(INDIRECT("'美中-休斯顿'!A7:A"&COUNTA('美中-休斯顿'!A:A)+6-1)),_xlfn.UNIQUE(INDIRECT("'美中-芝加哥'!A7:A"&COUNTA('美中-芝加哥'!A:A)+6-1)),_xlfn.UNIQUE(INDIRECT("美东南海陆系列!A7:A"&COUNTA(美东南海陆系列!A:A)+6-1))),IF(ISNUMBER(FIND("-直送特价",_xlfn.VSTACK(_xlfn.UNIQUE(INDIRECT("美西直送系列!A7:A"&COUNTA(美西直送系列!A:A)+6-1)),_xlfn.UNIQUE(INDIRECT("'美西-美森(12-17)'!A7:A"&COUNTA('美西-美森(12-17)'!A7:A130)+6-1)),_xlfn.UNIQUE(INDIRECT("'美西-以星&普船(17-26)'!A7:A"&COUNTA('美西-以星&普船(17-26)'!A:A)+6-1)),_xlfn.UNIQUE(INDIRECT("美西北!A7:A"&COUNTA(美西北!A:A)+6-1)),_xlfn.UNIQUE(INDIRECT("'美东-海铁&海陆系列'!A7:A"&COUNTA('美东-海铁系列'!A:A)+6-1)),_xlfn.UNIQUE(INDIRECT("美东南直航系列!A7:A"&COUNTA(美东南直航系列!A:A)+6-1)),_xlfn.UNIQUE(INDIRECT("'美中-休斯顿'!A7:A"&COUNTA('美中-休斯顿'!A:A)+6-1)),_xlfn.UNIQUE(INDIRECT("'美中-芝加哥'!A7:A"&COUNTA('美中-芝加哥'!A:A)+6-1)),_xlfn.UNIQUE(INDIRECT("'美东南海陆系列'!A7:A"&COUNTA(美东南海陆系列!A:A)+6-1))),1))=FALSE,TRUE,FALSE)),"[^一-龟]+"),""),_xlfn._xlws.FILTER(_xlpm.X,(_xlpm.X<>"0")*(_xlpm.X<>"")*(_xlpm.X<>CHAR(10)&"(")*(_xlpm.X<>CHAR(10))))} -> #VALUE! | N1: {=_xlfn.UNIQUE(_xlfn.VSTACK(INDIRECT("'美转加-普船系列'!A7:A"&COUNTA(#REF!)),INDIRECT("'美转加-合德系列'!A7:A"&COUNTA(#REF!)),INDIRECT("'美转加-EXX美森系列'!A7:A"&COUNTA(#REF!)),INDIRECT("'美转加-美森MAX系列'!A7:A"&COUNTA(#REF!)),INDIRECT("'美转加-美森CLX系列'!A7:A"&COUNTA(#REF!)),INDIRECT("'加拿大直航-普船系列'!A7:A"&COUNTA(#REF!))))} -> #REF! | P1: 其它 | Q1: 12KG+ | R1: 深圳 | S1: 华南
P2: {=_xlfn.UNIQUE(INDIRECT("'英国海运-卡派(23-40) '!A7:A"&COUNTA(#REF!)))} -> #REF! | Q2: 71KG+ | R2: 广州 | S2: 华南
D3: =IF(D6="加拿大","加拿大价格查询表",IF(D6="英国","英国价格查询表","美国海运价格查询表")) -> 加拿大价格查询表 | Q3: 100KG+ | R3: 中山 | S3: 华南
H4: 华南：深圳、广州、中山、东莞南城、惠州 华东：义乌、上海、宁波、苏州、杭州、绍兴 | Q4: 300KG+ | R4: 泉州 | S4: 厦门/泉州
D5: 国家 | E5: 目的仓 | F5: 国内仓 | G5: =IF(D3="英国价格查询表","公斤段","") | Q5: 15CBM+ | R5: 厦门 | S5: 厦门/泉州
D6: 加拿大 | E6: YYZ2 | F6: 义乌 | G6: 300KG+ | R6: 义乌 | S6: 华东
D7: 备注：（美国空运、快递派不在本查询中，具体详情请看报价表）；请根据你所查询的国家/仓库进行切换；非对应国家仓库价格不可参考；查询表仅供参考，实际以对应渠道报价为准！ | R7: 上海 | S7: 华东
B8: {=IF(D3="美国海运价格查询表",'价格查询表-间接版'!A7:$G$43,IF(D3="英国价格查询表",'价格查询表-间接版'!I7:O22,'价格查询表-间接版'!Q7:W35))} -> 默认送仓方式 | C8: 渠道类型 | D8: 包税 (100KG+) | E8: 不包税 (1CBM+) | F8: 签收时效 开船后-入仓时效 | G8: 延时赔付 开船后-不入仓时效 | H8: 备注 | I8: 偏远邮编查询 | R8: 福州 | S8: 厦门/泉州
B9: 直航 | C9: 加拿大加东直航30日达-卡派 | D9: - | E9: - | F9: - | G9: - | H9: 包税21-49KG:+1.5元/KG；50-99KG:+1元/KG | I9: 请输入邮编码： | J9: 21840 | R9: 汕头 | S9: 汕头
B10: 直航 | C10: 加拿大加东直航30日达-UPS派 | D10: - | E10: - | F10: - | G10: - | H10: 包税21-49KG:+1.5元/KG；50-99KG:+1元/KG | R10: 东莞南城 | S10: 华南
B11: 直航 | C11: 加拿大加西直航30日达-卡派 | D11: - | E11: - | F11: - | G11: - | H11: 包税21-49KG:+1.5元/KG；50-99KG:+1元/KG | I11: UPS | J11: =IFERROR(VLOOKUP(J9,偏远邮编库!B:C,2,0),"单询") -> 超偏远 | R11: 宁波 | S11: 华东
B12: 直航 | C12: 加拿大加西直航30日达-UPS派 | D12: - | E12: - | F12: - | G12: - | H12: 包税21-49KG:+1.5元/KG；50-99KG:+1元/KG | R12: 青岛 | S12: 青岛
B13: 直航 | C13: 加拿大加东直航33日达-卡派 | D13: - | E13: - | F13: - | G13: - | H13: 包税21-49KG:+1.5元/KG；50-99KG:+1元/KG | I13: Fedex | J13: =IFERROR(VLOOKUP(J9,偏远邮编库!F:G,2,0),"单询") -> 超偏远 | R13: 武汉 | S13: 武汉
B14: 直航 | C14: 加拿大加东直航33日达-UPS派 | D14: - | E14: - | F14: - | G14: - | H14: 包税21-49KG:+1.5元/KG；50-99KG:+1元/KG | R14: 长沙 | S14: 武汉
B15: 直航 | C15: 加拿大加西直航33日达-卡派 | D15: - | E15: - | F15: - | G15: - | H15: 包税21-49KG:+1.5元/KG；50-99KG:+1元/KG | R15: 郑州 | S15: 青岛
B16: 直航 | C16: 加拿大加西直航33日达-UPS派 | D16: - | E16: - | F16: - | G16: - | H16: 包税21-49KG:+1.5元/KG；50-99KG:+1元/KG | R16: 苏州 | S16: 华东
B17: 美转加 | C17: 美转加加东25日达-卡派（OA） | D17: - | E17: - | F17: - | G17: - | H17: 包税21-49KG:+1.5元/KG；50-99KG:+1元/KG | R17: 杭州仓 | S17: 华东
B18: 美转加 | C18: 美转加加东25日达-UPS派（OA） | D18: - | E18: - | F18: - | G18: - | H18: 包税21-49KG:+1.5元/KG；50-99KG:+1元/KG | R18: 绍兴 | S18: 华东
B19: 美转加 | C19: 美转加加西25日达-卡派（OA） | D19: - | E19: - | F19: - | G19: - | H19: 包税21-49KG:+1.5元/KG；50-99KG:+1元/KG | R19: 连云港 | S19: 青岛
B20: 美转加 | C20: 美转加加西25日达-UPS派（OA） | D20: - | E20: - | F20: - | G20: - | H20: 包税21-49KG:+1.5元/KG；50-99KG:+1元/KG | R20: 温州 | S20: 青岛
B21: 美转加 | C21: 美转加加东20日达-卡派（HD） | D21: - | E21: - | F21: - | G21: - | H21: 包税21-49KG:+1.5元/KG；50-99KG:+1元/KG | R21: 台州 | S21: 青岛
B22: 美转加 | C22: 美转加加东20日达-UPS派（HD） | D22: - | E22: - | F22: - | G22: - | H22: 包税21-49KG:+1.5元/KG；50-99KG:+1元/KG | R22: 重庆 | S22: 重庆
B23: 美转加 | C23: 美转加加西20日达-卡派（HD） | D23: - | E23: - | F23: - | G23: - | H23: 包税21-49KG:+1.5元/KG；50-99KG:+1元/KG | R23: 成都 | S23: 武汉
B24: 美转加 | C24: 美转加加西20日达-UPS派（HD） | D24: - | E24: - | F24: - | G24: - | H24: 包税21-49KG:+1.5元/KG；50-99KG:+1元/KG | R24: 天津 | S24: 天津/南昌/石家庄
B25: 美转加 | C25: 美转加加东19日达-卡派（EXX） | D25: - | E25: - | F25: - | G25: - | H25: 包税21-49KG:+1.5元/KG；50-99KG:+1元/KG | R25: 南昌 | S25: 天津/南昌/石家庄
... B33: 美转加 | C33: 美转加CLX加东16日达-卡派 | D33: - | E33: - | F33: 20-24日 | G33: 超26日 | H33: 快递派包税21-99KG:+1元/KG； | R33: 潍坊 | S33: 济南/潍坊
B34: 美转加 | C34: 美转加CLX加东16日达-UPS派 | D34: - | E34: - | F34: 18-22日 | G34: 超24日 | H34: 快递派包税21-99KG:+1元/KG；
B35: 美转加 | C35: 美转加CLX加西16日达-卡派 | D35: - | E35: - | F35: - | G35: - | H35: 快递派包税21-99KG:+1元/KG；
B36: 美转加 | C36: 美转加CLX加西16日达-UPS派 | D36: - | E36: - | F36: - | G36: - | H36: 快递派包税21-99KG:+1元/KG；

Sheet 价格查询表-间接版
A1: 天图通逊供应链有限公司 立志打造一家具有社会价值的百年跨境物流企业
A3: 美国海运价格快速查询栏 | I3: 英国价格快速查询栏 | Q3: 加拿大价格快速查询栏
A4: 备注： “英国”&“快递派”&“空运”渠道不在本快速查找范围，请查询报价表内页详情。 | C4: 目的仓 | D4: 国内仓 | E4: 注意事项如下 | G4: =TODAY() -> 46202 | I4: 备注： “美国”渠道不在本快速查找范围，请查询报价表内页详情。 | K4: 目的仓 | L4: 国内仓 | M4: 公斤段 | N4: 注意事项如下 | Q4: 备注： “英国”&“快递派”&“空运”渠道不在本快速查找范围，请查询报价表内页详情。 | S4: 目的仓 | T4: 国内仓 | U4: 注意事项如下 | AC4: 青岛 | AD4: 青岛/郑州/绍兴/苏州/杭州仓/连云港/温州/台州/南京/合肥
C5: =价格查询表!E6 -> YYZ2 | D5: =VLOOKUP(价格查询表!F6,价格查询表!R:S,2,0) -> 华东 | K5: =价格查询表!E6 -> YYZ2 | L5: =价格查询表!F6 -> 义乌 | M5: =价格查询表!G6 -> 300KG+ | S5: =价格查询表!E6 -> YYZ2 | T5: =VLOOKUP(价格查询表!F6,价格查询表!R:S,2,0) -> 华东 | AC5: 郑州 | AD5: 青岛/郑州/绍兴/苏州/杭州仓/连云港/温州/台州/南京/合肥
AC6: 绍兴 | AD6: 青岛/郑州/绍兴/苏州/杭州仓/连云港/温州/台州/南京/合肥
A7: 默认送仓方式 | B7: 渠道类型 | C7: =IF(LEFT(C5,3)="WM-","包税"&CHAR(10)&"(100kg+）","包税"&CHAR(10)&"(50kg+）") -> 包税 (50kg+） | D7: 不包税 (1CBM+) | E7: 签收时效 开船后-入仓时效 | F7: 延时赔付 开船后-不入仓时效 | G7: 备注 | I7: 运输方式 | J7: 渠道类型 | K7: 包税 | L7: 不包税 | M7: 签收时效 | N7: 延时赔付 | O7: 备注 | Q7: 默认送仓方式 | R7: 渠道类型 | S7: 包税 (100KG+) | T7: 不包税 (1CBM+) | U7: 签收时效 开船后-入仓时效 | V7: 延时赔付 开船后-不入仓时效 | W7: 备注 | AC7: 苏州 | AD7: 青岛/郑州/绍兴/苏州/杭州仓/连云港/温州/台州/南京/合肥
A8: 直送专线 | B8: 洛杉矶普船28日达直送 | C8: {=IFERROR(VLOOKUP($C$5,美西直送系列!$A:$DT,INDEX(定位!$A:$W,MATCH($B8,定位!$A:$A,0),MATCH("*"&$D$5&"*"&"-BS",定位!$1:$1,0)),FALSE),"-")} -> - | D8: {=IFERROR(VLOOKUP($C$5,美西直送系列!$A:$DT,INDEX(定位!$A:$W,MATCH($B8,定位!$A:$A,0),MATCH("*"&$D$5&"*"&"-NBS",定位!$1:$1,0)),FALSE),"-")} -> - | E8: =IFERROR(VLOOKUP($C$5,美西直送系列!$A:$DT,_xlfn.XLOOKUP($B8,定位!A:A,定位!V:V),FALSE),"-") -> - | F8: =IFERROR(VLOOKUP($C$5,美西直送系列!$A:$DT,_xlfn.XLOOKUP($B8,定位!A:A,定位!W:W),FALSE),"-") -> - | G8: =IF(LEFT($C$5,3)<>"WM-","FBA卡派包税:【10-49KG:+1元/KG】","沃尔玛卡派包税: 【21-49KG:+2元/KG】； 【50-99KG:+1元/KG】；") -> FBA卡派包税:【10-49KG:+1元/KG】 | I8: 陆运 | J8: 英国快铁25日达-卡派 | K8: {=IF(AND(AND(OR($K$5="LBA4",$K$5="BHX4",$K$5="BHX8"),$M$5<>"12-99KG"),AND(OR($K$5="LBA4",$K$5="BHX4",$K$5="BHX8"),$M$5<>"15CBM+")),INDEX(#REF!,MATCH("*"&$L$5&"*",#REF!,0)),"-")} -> - | L8: {=IF(AND(AND(OR($K$5="LBA4",$K$5="BHX4",$K$5="BHX8"),$M$5<>"12-99KG"),AND(OR($K$5="LBA4",$K$5="BHX4",$K$5="BHX8"),$M$5<>"15CBM+")),INDEX(#REF!,MATCH("*"&$L$5&"*",#REF!,0)),"-")} -> - | M8: {=IF(AND(AND(OR($K$5="LBA4",$K$5="BHX4",$K$5="BHX8"),$M$5<>"12-99KG"),AND(OR($K$5="LBA4",$K$5="BHX4",$K$5="BHX8"),$M$5<>"15CBM+")),INDEX(#REF!,MATCH("*"&$L$5&"*",#REF!,0)),"-")} -> - | N8: {=IF(AND(AND(OR($K$5="LBA4",$K$5="BHX4",$K$5="BHX8"),$M$5<>"12-99KG"),AND(OR($K$5="LBA4",$K$5="BHX4",$K$5="BHX8"),$M$5<>"15CBM+")),INDEX(#REF!,MATCH("*"&$L$5&"*",#REF!,0)),"-")} -> - | O8: =IF(OR(AND($M$5="12KG+",$N$8="-"),AND($M$5="71KG+",$N$8="-")),"100KG+起收",IF($M$5="15CBM+","KG价","")) | Q8: 直航 | R8: 加拿大加东直航30日达-卡派 | S8: {=IFERROR(VLOOKUP($S$5,#REF!,INDEX(定位!$A:$W,MATCH($R8,定位!$A:$A,0),MATCH("*"&$T$5&"*"&"-BS",定位!$1:$1,0)),FALSE),"-")} -> - | T8: {=IFERROR(VLOOKUP($S$5,#REF!,INDEX(定位!$A:$W,MATCH($R8,定位!$A:$A,0),MATCH("*"&$T$5&"*"&"-NBS",定位!$1:$1,0)),FALSE),"-")} -> - | U8: =IFERROR(VLOOKUP($C$5,#REF!,_xlfn.XLOOKUP($R8,定位!A:A,定位!V:V),FALSE),"-") -> - | V8: =IFERROR(VLOOKUP($C$5,#REF!,_xlfn.XLOOKUP($R8,定位!A:A,定位!W:W),FALSE),"-") -> - | W8: 包税21-49KG:+1.5元/KG；50-99KG:+1元/KG | AC8: 杭州仓 | AD8: 青岛/郑州/绍兴/苏州/杭州仓/连云港/温州/台州/南京/合肥
A9: 直送专线 | B9: 洛杉矶OA26日达直送 | C9: {=IFERROR(VLOOKUP($C$5,美西直送系列!$A:$DT,INDEX(定位!$A:$W,MATCH($B9,定位!$A:$A,0),MATCH("*"&$D$5&"*"&"-BS",定位!$1:$1,0)),FALSE),"-")} -> - | D9: {=IFERROR(VLOOKUP($C$5,美西直送系列!$A:$DT,INDEX(定位!$A:$W,MATCH($B9,定位!$A:$A,0),MATCH("*"&$D$5&"*"&"-NBS",定位!$1:$1,0)),FALSE),"-")} -> - | E9: =IFERROR(VLOOKUP($C$5,美西直送系列!$A:$DT,_xlfn.XLOOKUP($B9,定位!A:A,定位!V:V),FALSE),"-") -> - | F9: =IFERROR(VLOOKUP($C$5,美西直送系列!$A:$DT,_xlfn.XLOOKUP(B9,定位!A:A,定位!W:W),FALSE),"-") -> - | G9: =IF(LEFT($C$5,3)<>"WM-","FBA卡派包税:【10-49KG:+1元/KG】","沃尔玛卡派包税: 【21-49KG:+2元/KG】； 【50-99KG:+1元/KG】；") -> FBA卡派包税:【10-49KG:+1元/KG】 | I9: 陆运 | J9: 英国快铁25日达-DPD派 | K9: {=IF(AND($M$5<>"15CBM+",$M$5<>"12-99KG"),INDEX(#REF!,MATCH("*"&$L$5&"*",#REF!,0)),"-")} -> #REF! | L9: {=IF(AND($M$5<>"15CBM+",$M$5<>"12-99KG"),INDEX(#REF!,MATCH("*"&$L$5&"*",#REF!,0)),"-")} -> #REF! | M9: {=IF(AND($M$5<>"15CBM+",$M$5<>"12-99KG"),INDEX(#REF!,MATCH("*"&$L$5&"*",#REF!,0)),"-")} -> #REF! | N9: {=IF(AND($M$5<>"15CBM+",$M$5<>"12-99KG"),INDEX(#REF!,MATCH("*"&$L$5&"*",#REF!,0)),"-")} -> #REF! | O9: =IF($M$5="100KG+","12-70KG:+2元/KG；"&CHAR(10)&"71-99KG:+1元/KG；",IF($M$5="15CBM+","KG价","")) | Q9: 直航 | R9: 加拿大加东直航30日达-UPS派 | S9: {=IFERROR(VLOOKUP($S$5,#REF!,INDEX(定位!$A:$W,MATCH($R9,定位!$A:$A,0),MATCH("*"&$T$5&"*"&"-BS",定位!$1:$1,0)),FALSE),"-")} -> - | T9: {=IFERROR(VLOOKUP($S$5,#REF!,INDEX(定位!$A:$W,MATCH($R9,定位!$A:$A,0),MATCH("*"&$T$5&"*"&"-NBS",定位!$1:$1,0)),FALSE),"-")} -> - | U9: =IFERROR(VLOOKUP($C$5,#REF!,_xlfn.XLOOKUP($R9,定位!A:A,定位!V:V),FALSE),"-") -> - | V9: =IFERROR(VLOOKUP($C$5,#REF!,_xlfn.XLOOKUP($R9,定位!A:A,定位!W:W),FALSE),"-") -> - | W9: 包税21-49KG:+1.5元/KG；50-99KG:+1元/KG | AC9: 连云港 | AD9: 青岛/郑州/绍兴/苏州/杭州仓/连云港/温州/台州/南京/合肥
A10: 直送专线 | B10: 奥克兰OA29日达直送 | C10: {=IFERROR(VLOOKUP($C$5,美西直送系列!$A:$DT,INDEX(定位!$A:$W,MATCH($B10,定位!$A:$A,0),MATCH("*"&$D$5&"*"&"-BS",定位!$1:$1,0)),FALSE),"-")} -> - | D10: {=IFERROR(VLOOKUP($C$5,美西直送系列!$A:$DT,INDEX(定位!$A:$W,MATCH($B10,定位!$A:$A,0),MATCH("*"&$D$5&"*"&"-NBS",定位!$1:$1,0)),FALSE),"-")} -> - | E10: =IFERROR(VLOOKUP($C$5,美西直送系列!$A:$DT,_xlfn.XLOOKUP($B10,定位!A:A,定位!V:V),FALSE),"-") -> - | F10: =IFERROR(VLOOKUP($C$5,美西直送系列!$A:$DT,_xlfn.XLOOKUP(B10,定位!A:A,定位!W:W),FALSE),"-") -> - | G10: =IF(LEFT($C$5,3)<>"WM-","FBA卡派包税:【10-49KG:+1元/KG】","沃尔玛卡派包税: 【21-49KG:+2元/KG】； 【50-99KG:+1元/KG】；") -> FBA卡派包税:【10-49KG:+1元/KG】 | I10: 陆运 | J10: 英国中英铁卡-卡派（暂停） | K10: {=IF(AND(AND(OR($K$5="LBA4",$K$5="BHX4",$K$5="BHX8"),$M$5<>"12-99KG"),AND(OR($K$5="LBA4",$K$5="BHX4",$K$5="BHX8"),$M$5<>"15CBM+")),INDEX(#REF!,MATCH("*"&$L$5&"*",#REF!,0)),"-")} -> - | L10: {=IF(AND(AND(OR($K$5="LBA4",$K$5="BHX4",$K$5="BHX8"),$M$5<>"12-99KG"),AND(OR($K$5="LBA4",$K$5="BHX4",$K$5="BHX8"),$M$5<>"15CBM+")),INDEX(#REF!,MATCH("*"&$L$5&"*",#REF!,0)),"-")} -> - | M10: {=IF(AND(AND(OR($K$5="LBA4",$K$5="BHX4",$K$5="BHX8"),$M$5<>"12-99KG"),AND(OR($K$5="LBA4",$K$5="BHX4",$K$5="BHX8"),$M$5<>"15CBM+")),INDEX(#REF!,MATCH("*"&$L$5&"*",#REF!,0)),"-")} -> - | N10: {=IF(AND(AND(OR($K$5="LBA4",$K$5="BHX4",$K$5="BHX8"),$M$5<>"12-99KG"),AND(OR($K$5="LBA4",$K$5="BHX4",$K$5="BHX8"),$M$5<>"15CBM+")),INDEX(#REF!,MATCH("*"&$L$5&"*",#REF!,0)),"-")} -> - | O10: =IF(OR(AND($M$5="12KG+",$N$8="-"),AND($M$5="71KG+",$N$8="-")),"100KG+起收",IF($M$5="15CBM+","KG价","")) | Q10: 直航 | R10: 加拿大加西直航30日达-卡派 | S10: {=IFERROR(VLOOKUP($S$5,#REF!,INDEX(定位!$A:$W,MATCH($R10,定位!$A:$A,0),MATCH("*"&$T$5&"*"&"-BS",定位!$1:$1,0)),FALSE),"-")} -> - | T10: {=IFERROR(VLOOKUP($S$5,#REF!,INDEX(定位!$A:$W,MATCH($R10,定位!$A:$A,0),MATCH("*"&$T$5&"*"&"-NBS",定位!$1:$1,0)),FALSE),"-")} -> - | U10: =IFERROR(VLOOKUP($C$5,#REF!,_xlfn.XLOOKUP($R10,定位!A:A,定位!V:V),FALSE),"-") -> - | V10: =IFERROR(VLOOKUP($C$5,#REF!,_xlfn.XLOOKUP($R10,定位!A:A,定位!W:W),FALSE),"-") -> - | W10: 包税21-49KG:+1.5元/KG；50-99KG:+1元/KG | AC10: 温州 | AD10: 青岛/郑州/绍兴/苏州/杭州仓/连云港/温州/台州/南京/合肥
A11: 直送专线 | B11: 奥克兰普船36日达直送 | C11: {=IFERROR(VLOOKUP($C$5,美西直送系列!$A:$DT,INDEX(定位!$A:$W,MATCH($B11,定位!$A:$A,0),MATCH("*"&$D$5&"*"&"-BS",定位!$1:$1,0)),FALSE),"-")} -> - | D11: {=IFERROR(VLOOKUP($C$5,美西直送系列!$A:$DT,INDEX(定位!$A:$W,MATCH($B11,定位!$A:$A,0),MATCH("*"&$D$5&"*"&"-NBS",定位!$1:$1,0)),FALSE),"-")} -> - | E11: =IFERROR(VLOOKUP($C$5,美西直送系列!$A:$DT,_xlfn.XLOOKUP($B11,定位!A:A,定位!V:V),FALSE),"-") -> - | F11: =IFERROR(VLOOKUP($C$5,美西直送系列!$A:$DT,_xlfn.XLOOKUP(B11,定位!A:A,定位!W:W),FALSE),"-") -> - | G11: =IF(LEFT($C$5,3)<>"WM-","FBA卡派包税:【10-49KG:+1元/KG】","沃尔玛卡派包税: 【21-49KG:+2元/KG】； 【50-99KG:+1元/KG】；") -> FBA卡派包税:【10-49KG:+1元/KG】 | I11: 陆运 | J11: 英国中英铁卡-DPD派（暂停） | K11: {=IF(AND($M$5<>"15CBM+",$M$5<>"12-99KG"),INDEX(#REF!,MATCH("*"&$L$5&"*",#REF!,0)),"-")} -> #REF! | L11: {=IF(AND($M$5<>"15CBM+",$M$5<>"12-99KG"),INDEX(#REF!,MATCH("*"&$L$5&"*",#REF!,0)),"-")} -> #REF! | M11: {=IF(AND($M$5<>"15CBM+",$M$5<>"12-99KG"),INDEX(#REF!,MATCH("*"&$L$5&"*",#REF!,0)),"-")} -> #REF! | N11: {=IF(AND($M$5<>"15CBM+",$M$5<>"12-99KG"),INDEX(#REF!,MATCH("*"&$L$5&"*",#REF!,0)),"-")} -> #REF! | O11: =IF($M$5="100KG+","12-70KG:+2元/KG；"&CHAR(10)&"71-99KG:+1元/KG；",IF($M$5="15CBM+","KG价","")) | Q11: 直航 | R11: 加拿大加西直航30日达-UPS派 | S11: {=IFERROR(VLOOKUP($S$5,#REF!,INDEX(定位!$A:$W,MATCH($R11,定位!$A:$A,0),MATCH("*"&$T$5&"*"&"-BS",定位!$1:$1,0)),FALSE),"-")} -> - | T11: {=IFERROR(VLOOKUP($S$5,#REF!,INDEX(定位!$A:$W,MATCH($R11,定位!$A:$A,0),MATCH("*"&$T$5&"*"&"-NBS",定位!$1:$1,0)),FALSE),"-")} -> - | U11: =IFERROR(VLOOKUP($C$5,#REF!,_xlfn.XLOOKUP($R11,定位!A:A,定位!V:V),FALSE),"-") -> - | V11: =IFERROR(VLOOKUP($C$5,#REF!,_xlfn.XLOOKUP($R11,定位!A:A,定位!W:W),FALSE),"-") -> - | W11: 包税21-49KG:+1.5元/KG；50-99KG:+1元/KG | AC11: 台州 | AD11: 青岛/郑州/绍兴/苏州/杭州仓/连云港/温州/台州/南京/合肥
A12: 直送专线 | B12: 纽约直航42日达直送特价 | C12: {=IFERROR(VLOOKUP($C$5&"-直送特价",美东直航系列!$A:$CT,INDEX(定位!$A:$W,MATCH($B12,定位!$A:$A,0),MATCH("*"&$D$5&"*"&"-BS",定位!$1:$1,0)),FALSE),"-")} -> - | D12: {=IFERROR(VLOOKUP($C$5&"-直送特价",美东直航系列!$A:$CT,INDEX(定位!$A:$W,MATCH($B12,定位!$A:$A,0),MATCH("*"&$D$5&"*"&"-NBS",定位!$1:$1,0)),FALSE),"-")} -> - | E12: =IFERROR(VLOOKUP($C$5&"-直送特价",美东直航系列!$A:$CT,_xlfn.XLOOKUP($B12,定位!A:A,定位!V:V),FALSE),"-") -> - | F12: =IFERROR(VLOOKUP($C$5&"-直送特价",美东直航系列!$A:$CT,_xlfn.XLOOKUP($B12,定位!A:A,定位!W:W),FALSE),"-") -> - | G12: =IF(LEFT($C$5,3)<>"WM-","FBA卡派包税:【10-49KG:+1元/KG】","沃尔玛卡派包税: 【21-49KG:+2元/KG】； 【50-99KG:+1元/KG】；") -> FBA卡派包税:【10-49KG:+1元/KG】 | I12: 陆运 | J12: 苏新号-中英卡航20日达-卡派 | K12: {=IF(AND(AND(OR($K$5="LBA4",$K$5="BHX4",$K$5="BHX8"),$M$5<>"12-99KG"),AND(OR($K$5="LBA4",$K$5="BHX4",$K$5="BHX8"),$M$5<>"15CBM+")),INDEX(#REF!,MATCH("*"&$L$5&"*",#REF!,0)),"-")} -> - | L12: {=IF(AND(AND(OR($K$5="LBA4",$K$5="BHX4",$K$5="BHX8"),$M$5<>"12-99KG"),AND(OR($K$5="LBA4",$K$5="BHX4",$K$5="BHX8"),$M$5<>"15CBM+")),INDEX(#REF!,MATCH("*"&$L$5&"*",#REF!,0)),"-")} -> - | M12: {=IF(AND(AND(OR($K$5="LBA4",$K$5="BHX4",$K$5="BHX8"),$M$5<>"12-99KG"),AND(OR($K$5="LBA4",$K$5="BHX4",$K$5="BHX8"),$M$5<>"15CBM+")),INDEX(#REF!,MATCH("*"&$L$5&"*",#REF!,0)),"-")} -> - | N12: {=IF(AND(AND(OR($K$5="LBA4",$K$5="BHX4",$K$5="BHX8"),$M$5<>"12-99KG"),AND(OR($K$5="LBA4",$K$5="BHX4",$K$5="BHX8"),$M$5<>"15CBM+")),INDEX(#REF!,MATCH("*"&$L$5&"*",#REF!,0)),"-")} -> - | O12: =IF(OR(AND($M$5="12KG+",$N$8="-"),AND($M$5="71KG+",$N$8="-")),"100KG+起收",IF($M$5="15CBM+","KG价","")) | Q12: 直航 | R12: 加拿大加东直航33日达-卡派 | S12: {=IFERROR(VLOOKUP($S$5,#REF!,INDEX(定位!$A:$W,MATCH($R12,定位!$A:$A,0),MATCH("*"&$T$5&"*"&"-BS",定位!$1:$1,0)),FALSE),"-")} -> - | T12: {=IFERROR(VLOOKUP($S$5,#REF!,INDEX(定位!$A:$W,MATCH($R12,定位!$A:$A,0),MATCH("*"&$T$5&"*"&"-NBS",定位!$1:$1,0)),FALSE),"-")} -> - | U12: =IFERROR(VLOOKUP($C$5,#REF!,_xlfn.XLOOKUP($R12,定位!A:A,定位!V:V),FALSE),"-") -> - | V12: =IFERROR(VLOOKUP($C$5,#REF!,_xlfn.XLOOKUP($R12,定位!A:A,定位!W:W),FALSE),"-") -> - | W12: 包税21-49KG:+1.5元/KG；50-99KG:+1元/KG | AC12: 广州 | AD12: 广州/深圳/东莞南城
A13: 直送专线 | B13: 纽约直航38日达直送特价 | C13: {=IFERROR(VLOOKUP($C$5&"-直送特价",美东直航系列!$A:$CT,INDEX(定位!$A:$W,MATCH($B13,定位!$A:$A,0),MATCH("*"&$D$5&"*"&"-BS",定位!$1:$1,0)),FALSE),"-")} -> - | D13: {=IFERROR(VLOOKUP($C$5&"-直送特价",美东直航系列!$A:$CT,INDEX(定位!$A:$W,MATCH($B13,定位!$A:$A,0),MATCH("*"&$D$5&"*"&"-NBS",定位!$1:$1,0)),FALSE),"-")} -> - | E13: =IFERROR(VLOOKUP($C$5&"-直送特价",美东直航系列!$A:$CT,_xlfn.XLOOKUP($B13,定位!A:A,定位!V:V),FALSE),"-") -> - | F13: =IFERROR(VLOOKUP($C$5&"-直送特价",美东直航系列!$A:$CT,_xlfn.XLOOKUP($B13,定位!A:A,定位!W:W),FALSE),"-") -> - | G13: =IF(LEFT($C$5,3)<>"WM-","FBA卡派包税:【10-49KG:+1元/KG】","沃尔玛卡派包税: 【21-49KG:+2元/KG】； 【50-99KG:+1元/KG】；") -> FBA卡派包税:【10-49KG:+1元/KG】 | I13: 陆运 | J13: 苏新号-中英卡航20日达-DPD派 | K13: {=IF(AND($M$5<>"15CBM+",$M$5<>"12-99KG"),INDEX(#REF!,MATCH("*"&$L$5&"*",#REF!,0)),"-")} -> #REF! | L13: {=IF(AND($M$5<>"15CBM+",$M$5<>"12-99KG"),INDEX(#REF!,MATCH("*"&$L$5&"*",#REF!,0)),"-")} -> #REF! | M13: {=IF(AND($M$5<>"15CBM+",$M$5<>"12-99KG"),INDEX(#REF!,MATCH("*"&$L$5&"*",#REF!,0)),"-")} -> #REF! | N13: {=IF(AND($M$5<>"15CBM+",$M$5<>"12-99KG"),INDEX(#REF!,MATCH("*"&$L$5&"*",#REF!,0)),"-")} -> #REF! | O13: =IF($M$5="100KG+","12-70KG:+2元/KG；"&CHAR(10)&"71-99KG:+1元/KG；",IF($M$5="15CBM+","KG价","")) | Q13: 直航 | R13: 加拿大加东直航33日达-UPS派 | S13: {=IFERROR(VLOOKUP($S$5,#REF!,INDEX(定位!$A:$W,MATCH($R13,定位!$A:$A,0),MATCH("*"&$T$5&"*"&"-BS",定位!$1:$1,0)),FALSE),"-")} -> - | T13: {=IFERROR(VLOOKUP($S$5,#REF!,INDEX(定位!$A:$W,MATCH($R13,定位!$A:$A,0),MATCH("*"&$T$5&"*"&"-NBS",定位!$1:$1,0)),FALSE),"-")} -> - | U13: =IFERROR(VLOOKUP($C$5,#REF!,_xlfn.XLOOKUP($R13,定位!A:A,定位!V:V),FALSE),"-") -> - | V13: =IFERROR(VLOOKUP($C$5,#REF!,_xlfn.XLOOKUP($R13,定位!A:A,定位!W:W),FALSE),"-") -> - | W13: 包税21-49KG:+1.5元/KG；50-99KG:+1元/KG | AC13: 深圳 | AD13: 广州/深圳/东莞南城
A14: 直送专线 | B14: 萨凡纳直航36日达直送 | C14: {=IFERROR(VLOOKUP($C$5&"-直送特价",美东南直航系列!$A:$CT,INDEX(定位!$A:$W,MATCH($B14,定位!$A:$A,0),MATCH("*"&$D$5&"*"&"-BS",定位!$1:$1,0)),FALSE),"-")} -> - | D14: {=IFERROR(VLOOKUP($C$5&"-直送特价",美东南直航系列!$A:$CT,INDEX(定位!$A:$W,MATCH($B14,定位!$A:$A,0),MATCH("*"&$D$5&"*"&"-NBS",定位!$1:$1,0)),FALSE),"-")} -> - | E14: =IFERROR(VLOOKUP($C$5&"-直送特价",美东南直航系列!$A:$CT,_xlfn.XLOOKUP($B14,定位!A:A,定位!V:V),FALSE),"-") -> - | F14: =IFERROR(VLOOKUP($C$5&"-直送特价",美东南直航系列!$A:$CT,_xlfn.XLOOKUP($B14,定位!A:A,定位!W:W),FALSE),"-") -> - | G14: =IF(LEFT($C$5,3)<>"WM-","FBA卡派包税:【10-49KG:+1元/KG】","沃尔玛卡派包税: 【21-49KG:+2元/KG】； 【50-99KG:+1元/KG】；") -> FBA卡派包税:【10-49KG:+1元/KG】 | I14: 陆运 | J14: 中英专车-卡派 | K14: - | L14: - | M14: - | N14: - | O14: =IF(OR(AND($M$5="12KG+",$N$8="-"),AND($M$5="71KG+",$N$8="-")),"100KG+起收",IF($M$5="15CBM+","KG价","")) | Q14: 直航 | R14: 加拿大加西直航33日达-卡派 | S14: {=IFERROR(VLOOKUP($S$5,#REF!,INDEX(定位!$A:$W,MATCH($R14,定位!$A:$A,0),MATCH("*"&$T$5&"*"&"-BS",定位!$1:$1,0)),FALSE),"-")} -> - | T14: {=IFERROR(VLOOKUP($S$5,#REF!,INDEX(定位!$A:$W,MATCH($R14,定位!$A:$A,0),MATCH("*"&$T$5&"*"&"-NBS",定位!$1:$1,0)),FALSE),"-")} -> - | U14: =IFERROR(VLOOKUP($C$5,#REF!,_xlfn.XLOOKUP($R14,定位!A:A,定位!V:V),FALSE),"-") -> - | V14: =IFERROR(VLOOKUP($C$5,#REF!,_xlfn.XLOOKUP($R14,定位!A:A,定位!W:W),FALSE),"-") -> - | W14: 包税21-49KG:+1.5元/KG；50-99KG:+1元/KG | AC14: 东莞南城 | AD14: 广州/深圳/东莞南城
A15: 直送专线 | B15: 萨凡纳直航48日达直送 | C15: {=IFERROR(VLOOKUP($C$5&"-直送特价",美东南直航系列!$A:$CT,INDEX(定位!$A:$W,MATCH($B15,定位!$A:$A,0),MATCH("*"&$D$5&"*"&"-BS",定位!$1:$1,0)),FALSE),"-")} -> - | D15: {=IFERROR(VLOOKUP($C$5&"-直送特价",美东南直航系列!$A:$CT,INDEX(定位!$A:$W,MATCH($B15,定位!$A:$A,0),MATCH("*"&$D$5&"*"&"-NBS",定位!$1:$1,0)),FALSE),"-")} -> - | E15: =IFERROR(VLOOKUP($C$5&"-直送特价",美东南直航系列!$A:$CT,_xlfn.XLOOKUP($B15,定位!A:A,定位!V:V),FALSE),"-") -> - | F15: =IFERROR(VLOOKUP($C$5&"-直送特价",美东南直航系列!$A:$CT,_xlfn.XLOOKUP($B15,定位!A:A,定位!W:W),FALSE),"-") -> - | G15: =IF(LEFT($C$5,3)<>"WM-","FBA卡派包税:【10-49KG:+1元/KG】","沃尔玛卡派包税: 【21-49KG:+2元/KG】； 【50-99KG:+1元/KG】；") -> FBA卡派包税:【10-49KG:+1元/KG】 | I15: 陆运 | J15: 中英专车-DPD派 | K15: - | L15: - | M15: - | N15: - | O15: =IF(M5="100KG+","12-70KG：+2元/KG；"&CHAR(10)&"71-99KG：+1元/KG；",IF(M5="15CBM+","KG价","")) | Q15: 直航 | R15: 加拿大加西直航33日达-UPS派 | S15: {=IFERROR(VLOOKUP($S$5,#REF!,INDEX(定位!$A:$W,MATCH($R15,定位!$A:$A,0),MATCH("*"&$T$5&"*"&"-BS",定位!$1:$1,0)),FALSE),"-")} -> - | T15: {=IFERROR(VLOOKUP($S$5,#REF!,INDEX(定位!$A:$W,MATCH($R15,定位!$A:$A,0),MATCH("*"&$T$5&"*"&"-NBS",定位!$1:$1,0)),FALSE),"-")} -> - | U15: =IFERROR(VLOOKUP($C$5,#REF!,_xlfn.XLOOKUP($R15,定位!A:A,定位!V:V),FALSE),"-") -> - | V15: =IFERROR(VLOOKUP($C$5,#REF!,_xlfn.XLOOKUP($R15,定位!A:A,定位!W:W),FALSE),"-") -> - | W15: 包税21-49KG:+1.5元/KG；50-99KG:+1元/KG | AC15: 中山 | AD15: 中山/汕头
A16: 直送专线 | B16: 休斯顿直航38日达直送特价 | C16: {=IFERROR(VLOOKUP($C$5&"-直送特价",'美中-休斯顿'!$A:$BT,INDEX(定位!$A:$W,MATCH($B16,定位!$A:$A,0),MATCH("*"&$D$5&"*"&"-BS",定位!$1:$1,0)),FALSE),"-")} -> - | D16: {=IFERROR(VLOOKUP($C$5&"-直送特价",'美中-休斯顿'!$A:$BT,INDEX(定位!$A:$W,MATCH($B16,定位!$A:$A,0),MATCH("*"&$D$5&"*"&"-NBS",定位!$1:$1,0)),FALSE),"-")} -> - | E16: =IFERROR(VLOOKUP($C$5&"-直送特价",'美中-休斯顿'!$A:$BT,_xlfn.XLOOKUP($B16,定位!A:A,定位!V:V),FALSE),"-") -> - | F16: =IFERROR(VLOOKUP($C$5&"-直送特价",'美中-休斯顿'!$A:$BT,_xlfn.XLOOKUP($B16,定位!A:A,定位!W:W),FALSE),"-") -> - | G16: =IF(LEFT($C$5,3)<>"WM-","FBA卡派包税:【10-49KG:+1元/KG】","沃尔玛卡派包税: 【21-49KG:+2元/KG】； 【50-99KG:+1元/KG】；") -> FBA卡派包税:【10-49KG:+1元/KG】 | I16: 陆运 | J16: 中英专车快卡-卡派 | K16: - | L16: - | M16: - | N16: - | O16: =IF(OR(AND($M$5="12KG+",$N$8="-"),AND($M$5="71KG+",$N$8="-")),"100KG+起收",IF($M$5="15CBM+","KG价","")) | Q16: 美转加 | R16: 美转加加东25日达-卡派（OA） | S16: {=IFERROR(VLOOKUP($S$5,#REF!,INDEX(定位!$A:$W,MATCH($R16,定位!$A:$A,0),MATCH("*"&$T$5&"*"&"-BS",定位!$1:$1,0)),FALSE),"-")} -> - | T16: {=IFERROR(VLOOKUP($S$5,#REF!,INDEX(定位!$A:$W,MATCH($R16,定位!$A:$A,0),MATCH("*"&$T$5&"*"&"-NBS",定位!$1:$1,0)),FALSE),"-")} -> - | U16: =IFERROR(VLOOKUP($C$5,#REF!,_xlfn.XLOOKUP($R16,定位!A:A,定位!V:V),FALSE),"-") -> - | V16: =IFERROR(VLOOKUP($C$5,#REF!,_xlfn.XLOOKUP($R16,定位!A:A,定位!W:W),FALSE),"-") -> - | W16: 包税21-49KG:+1.5元/KG；50-99KG:+1元/KG | AC16: 汕头 | AD16: 中山/汕头
A17: 直送专线 | B17: 芝加哥海铁28日达直送特价 | C17: {=IFERROR(VLOOKUP($C$5&"-直送特价",'美中-芝加哥'!$A:$CX,INDEX(定位!$A:$W,MATCH($B17,定位!$A:$A,0),MATCH("*"&$D$5&"*"&"-BS",定位!$1:$1,0)),FALSE),"-")} -> - | D17: {=IFERROR(VLOOKUP($C$5&"-直送特价",'美中-芝加哥'!$A:$CX,INDEX(定位!$A:$W,MATCH($B17,定位!$A:$A,0),MATCH("*"&$D$5&"*"&"-NBS",定位!$1:$1,0)),FALSE),"-")} -> - | E17: =IFERROR(VLOOKUP($C$5&"-直送特价",'美中-芝加哥'!$A:$CX,_xlfn.XLOOKUP($B17,定位!A:A,定位!V:V),FALSE),"-") -> - | F17: =IFERROR(VLOOKUP($C$5&"-直送特价",'美中-芝加哥'!$A:$CX,_xlfn.XLOOKUP($B17,定位!A:A,定位!W:W),FALSE),"-") -> - | G17: =IF(LEFT($C$5,3)<>"WM-","FBA卡派包税:【10-49KG:+1元/KG】","沃尔玛卡派包税: 【21-49KG:+2元/KG】； 【50-99KG:+1元/KG】；") -> FBA卡派包税:【10-49KG:+1元/KG】 | I17: 陆运 | J17: 中英专车快卡-DPD派 | K17: - | L17: - | M17: - | N17: - | O17: =IF(M5="100KG+","12-70KG：+2元/KG；"&CHAR(10)&"71-99KG：+1元/KG；",IF(M5="15CBM+","KG价","")) | Q17: 美转加 | R17: 美转加加东25日达-UPS派（OA） | S17: {=IFERROR(VLOOKUP($S$5,#REF!,INDEX(定位!$A:$W,MATCH($R17,定位!$A:$A,0),MATCH("*"&$T$5&"*"&"-BS",定位!$1:$1,0)),FALSE),"-")} -> - | T17: {=IFERROR(VLOOKUP($S$5,#REF!,INDEX(定位!$A:$W,MATCH($R17,定位!$A:$A,0),MATCH("*"&$T$5&"*"&"-NBS",定位!$1:$1,0)),FALSE),"-")} -> - | U17: =IFERROR(VLOOKUP($C$5,#REF!,_xlfn.XLOOKUP($R17,定位!A:A,定位!V:V),FALSE),"-") -> - | V17: =IFERROR(VLOOKUP($C$5,#REF!,_xlfn.XLOOKUP($R17,定位!A:A,定位!W:W),FALSE),"-") -> - | W17: 包税21-49KG:+1.5元/KG；50-99KG:+1元/KG | AC17: 厦门 | AD17: 厦门/泉州/福州
A18: 直送专线 | B18: 芝加哥海铁32日达直送特价 | C18: {=IFERROR(VLOOKUP($C$5&"-直送特价",'美中-芝加哥'!$A:$CX,INDEX(定位!$A:$W,MATCH($B18,定位!$A:$A,0),MATCH("*"&$D$5&"*"&"-BS",定位!$1:$1,0)),FALSE),"-")} -> - | D18: {=IFERROR(VLOOKUP($C$5&"-直送特价",'美中-芝加哥'!$A:$CX,INDEX(定位!$A:$W,MATCH($B18,定位!$A:$A,0),MATCH("*"&$D$5&"*"&"-NBS",定位!$1:$1,0)),FALSE),"-")} -> - | E18: =IFERROR(VLOOKUP($C$5&"-直送特价",'美中-芝加哥'!$A:$CX,_xlfn.XLOOKUP($B18,定位!A:A,定位!V:V),FALSE),"-") -> - | F18: =IFERROR(VLOOKUP($C$5&"-直送特价",'美中-芝加哥'!$A:$CX,_xlfn.XLOOKUP($B18,定位!A:A,定位!W:W),FALSE),"-") -> - | G18: =IF(LEFT($C$5,3)<>"WM-","FBA卡派包税:【10-49KG:+1元/KG】","沃尔玛卡派包税: 【21-49KG:+2元/KG】； 【50-99KG:+1元/KG】；") -> FBA卡派包税:【10-49KG:+1元/KG】 | I18: 海运 | J18: 英国海卡(特价）-KG价 | K18: =IFERROR(IF(M5<>"15CBM+",_xlfn.LET(_xlpm.X,#REF!,_xlpm.Y,2,IF(VLOOKUP(L5,AC:AD,2,0)="广州/深圳/东莞南城",VLOOKUP(K5,_xlpm.X,_xlpm.Y,0),IF(VLOOKUP(L5,AC:AD,2,0)="重庆",VLOOKUP(K5,_xlpm.X,_xlpm.Y+1,0),IF(VLOOKUP(L5,AC:AD,2,0)="中山/汕头",VLOOKUP(K5,_xlpm.X,_xlpm.Y+3,0),IF(VLOOKUP(L5,AC:AD,2,0)="厦门/泉州/福州",VLOOKUP(K5,_xlpm.X,_xlpm.Y+4,0),IF(VLOOKUP(L5,AC:AD,2,0)="义乌",VLOOKUP(K5,_xlpm.X,_xlpm.Y+5,0),IF(VLOOKUP(L5,AC:AD,2,0)="上海/宁波",VLOOKUP(K5,_xlpm.X,_xlpm.Y+6,0),IF(VLOOKUP(L5,AC:AD,2,0)="青岛/郑州/绍兴/苏州/杭州仓/连云港/温州/台州/南京/合肥",VLOOKUP(K5,_xlpm.X,_xlpm.Y+7,0),IF(VLOOKUP(L5,AC:AD,2,0)="武汉/长沙/成都",VLOOKUP(K5,_xlpm.X,_xlpm.Y+8,0),IF(VLOOKUP(L5,AC:AD,2,0)="天津/南昌/石家庄",VLOOKUP(K5,_xlpm.X,_xlpm.Y+8,0),IF(VLOOKUP(L5,AC:AD,2,0)="西安",VLOOKUP(K5,_xlpm.X,_xlpm.Y+2,0),IF(VLOOKUP(L5,AC:AD,2,0)="济南/潍坊",VLOOKUP(K5,_xlpm.X,_xlpm.Y+9,0),IF(VLOOKUP(L5,AC:AD,2,0)="沧州/保定",VLOOKUP(K5,_xlpm.X,_xlpm.Y+10,0)))))))))))))),"-"),"-") -> - | L18: =IFERROR(IF(M5<>"15CBM+",_xlfn.LET(_xlpm.X,#REF!,_xlpm.Y,14,IF(VLOOKUP(L5,AC:AD,2,0)="广州/深圳/东莞南城",VLOOKUP(K5,_xlpm.X,_xlpm.Y,0),IF(VLOOKUP(L5,AC:AD,2,0)="重庆",VLOOKUP(K5,_xlpm.X,_xlpm.Y+1,0),IF(VLOOKUP(L5,AC:AD,2,0)="中山/汕头",VLOOKUP(K5,_xlpm.X,_xlpm.Y+3,0),IF(VLOOKUP(L5,AC:AD,2,0)="厦门/泉州/福州",VLOOKUP(K5,_xlpm.X,_xlpm.Y+4,0),IF(VLOOKUP(L5,AC:AD,2,0)="义乌",VLOOKUP(K5,_xlpm.X,_xlpm.Y+5,0),IF(VLOOKUP(L5,AC:AD,2,0)="上海/宁波",VLOOKUP(K5,_xlpm.X,_xlpm.Y+6,0),IF(VLOOKUP(L5,AC:AD,2,0)="青岛/郑州/绍兴/苏州/杭州仓/连云港/温州/台州/南京/合肥",VLOOKUP(K5,_xlpm.X,_xlpm.Y+7,0),IF(VLOOKUP(L5,AC:AD,2,0)="武汉/长沙/成都",VLOOKUP(K5,_xlpm.X,_xlpm.Y+8,0),IF(VLOOKUP(L5,AC:AD,2,0)="天津/南昌/石家庄",VLOOKUP(K5,_xlpm.X,_xlpm.Y+8,0),IF(VLOOKUP(L5,AC:AD,2,0)="西安",VLOOKUP(K5,_xlpm.X,_xlpm.Y+2,0),IF(VLOOKUP(L5,AC:AD,2,0)="济南/潍坊",VLOOKUP(K5,_xlpm.X,_xlpm.Y+9,0),IF(VLOOKUP(L5,AC:AD,2,0)="沧州/保定",VLOOKUP(K5,_xlpm.X,_xlpm.Y+10,0)))))))))))))),"-"),"-") -> - | M18: =IFERROR(IF(M5<>"15CBM+",_xlfn.LET(_xlpm.X,#REF!,_xlpm.Y,26,IF(VLOOKUP(L5,AC:AD,2,0)="广州/深圳/东莞南城",VLOOKUP(K5,_xlpm.X,_xlpm.Y,0),IF(VLOOKUP(L5,AC:AD,2,0)="重庆",VLOOKUP(K5,_xlpm.X,_xlpm.Y,0),IF(VLOOKUP(L5,AC:AD,2,0)="中山/汕头",VLOOKUP(K5,_xlpm.X,_xlpm.Y,0),IF(VLOOKUP(L5,AC:AD,2,0)="厦门/泉州/福州",VLOOKUP(K5,_xlpm.X,_xlpm.Y,0),IF(VLOOKUP(L5,AC:AD,2,0)="义乌",VLOOKUP(K5,_xlpm.X,_xlpm.Y,0),IF(VLOOKUP(L5,AC:AD,2,0)="上海/宁波",VLOOKUP(K5,_xlpm.X,_xlpm.Y,0),IF(VLOOKUP(L5,AC:AD,2,0)="青岛/郑州/绍兴/苏州/杭州仓/连云港/温州/台州/南京/合肥",VLOOKUP(K5,_xlpm.X,_xlpm.Y,0),IF(VLOOKUP(L5,AC:AD,2,0)="武汉/长沙/成都",VLOOKUP(K5,_xlpm.X,_xlpm.Y,0),IF(VLOOKUP(L5,AC:AD,2,0)="天津/南昌/石家庄",VLOOKUP(K5,_xlpm.X,_xlpm.Y,0),IF(VLOOKUP(L5,AC:AD,2,0)="西安",VLOOKUP(K5,_xlpm.X,_xlpm.Y,0),IF(VLOOKUP(L5,AC:AD,2,0)="济南/潍坊",VLOOKUP(K5,_xlpm.X,_xlpm.Y,0),IF(VLOOKUP(L5,AC:AD,2,0)="沧州/保定",VLOOKUP(K5,_xlpm.X,_xlpm.Y,0)))))))))))))),"-"),"-") -> - | N18: =IFERROR(IF(M5<>"15CBM+",_xlfn.LET(_xlpm.X,#REF!,_xlpm.Y,27,IF(VLOOKUP(L5,AC:AD,2,0)="广州/深圳/东莞南城",VLOOKUP(K5,_xlpm.X,_xlpm.Y,0),IF(VLOOKUP(L5,AC:AD,2,0)="重庆",VLOOKUP(K5,_xlpm.X,_xlpm.Y,0),IF(VLOOKUP(L5,AC:AD,2,0)="中山/汕头",VLOOKUP(K5,_xlpm.X,_xlpm.Y,0),IF(VLOOKUP(L5,AC:AD,2,0)="厦门/泉州/福州",VLOOKUP(K5,_xlpm.X,_xlpm.Y,0),IF(VLOOKUP(L5,AC:AD,2,0)="义乌",VLOOKUP(K5,_xlpm.X,_xlpm.Y,0),IF(VLOOKUP(L5,AC:AD,2,0)="上海/宁波",VLOOKUP(K5,_xlpm.X,_xlpm.Y,0),IF(VLOOKUP(L5,AC:AD,2,0)="青岛/郑州/绍兴/苏州/杭州仓/连云港/温州/台州/南京/合肥",VLOOKUP(K5,_xlpm.X,_xlpm.Y,0),IF(VLOOKUP(L5,AC:AD,2,0)="武汉/长沙/成都",VLOOKUP(K5,_xlpm.X,_xlpm.Y,0),IF(VLOOKUP(L5,AC:AD,2,0)="天津/南昌/石家庄",VLOOKUP(K5,_xlpm.X,_xlpm.Y,0),IF(VLOOKUP(L5,AC:AD,2,0)="西安",VLOOKUP(K5,_xlpm.X,_xlpm.Y,0),IF(VLOOKUP(L5,AC:AD,2,0)="济南/潍坊",VLOOKUP(K5,_xlpm.X,_xlpm.Y,0),IF(VLOOKUP(L5,AC:AD,2,0)="沧州/保定",VLOOKUP(K5,_xlpm.X,_xlpm.Y,0)))))))))))))),"-"),"-") -> - | O18: =IF(M5="100KG+","12-70KG：+2元/KG；"&CHAR(10)&"71-99KG：+1元/KG；",IF(M5="15CBM+","KG价","")) | Q18: 美转加 | R18: 美转加加西25日达-卡派（OA） | S18: {=IFERROR(VLOOKUP($S$5,#REF!,INDEX(定位!$A:$W,MATCH($R18,定位!$A:$A,0),MATCH("*"&$T$5&"*"&"-BS",定位!$1:$1,0)),FALSE),"-")} -> - | T18: {=IFERROR(VLOOKUP($S$5,#REF!,INDEX(定位!$A:$W,MATCH($R18,定位!$A:$A,0),MATCH("*"&$T$5&"*"&"-NBS",定位!$1:$1,0)),FALSE),"-")} -> - | U18: =IFERROR(VLOOKUP($C$5,#REF!,_xlfn.XLOOKUP($R18,定位!A:A,定位!V:V),FALSE),"-") -> - | V18: =IFERROR(VLOOKUP($C$5,#REF!,_xlfn.XLOOKUP($R18,定位!A:A,定位!W:W),FALSE),"-") -> - | W18: 包税21-49KG:+1.5元/KG；50-99KG:+1元/KG | AC18: 泉州 | AD18: 厦门/泉州/福州
A19: 直送专线 | B19: 芝加哥海铁22日达直送特价 | C19: {=IFERROR(VLOOKUP($C$5&"-直送特价",'美中-芝加哥'!$A:$CX,INDEX(定位!$A:$W,MATCH($B19,定位!$A:$A,0),MATCH("*"&$D$5&"*"&"-BS",定位!$1:$1,0)),FALSE),"-")} -> - | D19: {=IFERROR(VLOOKUP($C$5&"-直送特价",'美中-芝加哥'!$A:$CX,INDEX(定位!$A:$W,MATCH($B19,定位!$A:$A,0),MATCH("*"&$D$5&"*"&"-NBS",定位!$1:$1,0)),FALSE),"-")} -> - | E19: =IFERROR(VLOOKUP($C$5&"-直送特价",'美中-芝加哥'!$A:$CX,_xlfn.XLOOKUP($B19,定位!A:A,定位!V:V),FALSE),"-") -> - | F19: =IFERROR(VLOOKUP($C$5&"-直送特价",'美中-芝加哥'!$A:$CX,_xlfn.XLOOKUP($B19,定位!A:A,定位!W:W),FALSE),"-") -> - | G19: =IF(LEFT($C$5,3)<>"WM-","FBA卡派包税:【10-49KG:+1元/KG】","沃尔玛卡派包税: 【21-49KG:+2元/KG】； 【50-99KG:+1元/KG】；") -> FBA卡派包税:【10-49KG:+1元/KG】 | I19: 海运 | J19: 英国海卡-CBM价 | K19: - | L19: =IFERROR(IF(M5="15CBM+",_xlfn.LET(_xlpm.X,#REF!,_xlpm.Y,28,IF(VLOOKUP(L5,AC:AD,2,0)="广州/深圳/东莞南城",VLOOKUP(K5,_xlpm.X,_xlpm.Y,0),IF(VLOOKUP(L5,AC:AD,2,0)="重庆",VLOOKUP(K5,_xlpm.X,_xlpm.Y+1,0),IF(VLOOKUP(L5,AC:AD,2,0)="中山/汕头",VLOOKUP(K5,_xlpm.X,_xlpm.Y+3,0),IF(VLOOKUP(L5,AC:AD,3,0)="厦门/泉州/福州",VLOOKUP(K5,_xlpm.X,_xlpm.Y+4,0),IF(VLOOKUP(L5,AC:AD,2,0)="义乌",VLOOKUP(K5,_xlpm.X,_xlpm.Y+5,0),IF(VLOOKUP(L5,AC:AD,2,0)="上海/宁波",VLOOKUP(K5,_xlpm.X,_xlpm.Y+6,0),IF(VLOOKUP(L5,AC:AD,2,0)="青岛/郑州/绍兴/苏州/杭州仓/连云港/温州/台州/南京/合肥",VLOOKUP(K5,_xlpm.X,_xlpm.Y+7,0),IF(VLOOKUP(L5,AC:AD,2,0)="武汉/长沙/成都",VLOOKUP(K5,_xlpm.X,_xlpm.Y+8,0),IF(VLOOKUP(L5,AC:AD,2,0)="天津/南昌/石家庄",VLOOKUP(K5,_xlpm.X,_xlpm.Y+8,0),IF(VLOOKUP(L5,AC:AD,2,0)="西安",VLOOKUP(K5,_xlpm.X,_xlpm.Y+2,0),IF(VLOOKUP(L5,AC:AD,2,0)="济南/潍坊",VLOOKUP(K5,_xlpm.X,_xlpm.Y+9,0),IF(VLOOKUP(L5,AC:AD,2,0)="沧州/保定",VLOOKUP(K5,_xlpm.X,_xlpm.Y+10,0)))))))))))))),"-"),"-") -> - | M19: =IFERROR(IF(M5="15CBM+",_xlfn.LET(_xlpm.X,#REF!,_xlpm.Y,40,IF(VLOOKUP(L5,AC:AD,2,0)="广州/深圳/东莞南城",VLOOKUP(K5,_xlpm.X,_xlpm.Y,0),IF(VLOOKUP(L5,AC:AD,2,0)="重庆",VLOOKUP(K5,_xlpm.X,_xlpm.Y,0),IF(VLOOKUP(L5,AC:AD,2,0)="中山/汕头",VLOOKUP(K5,_xlpm.X,_xlpm.Y,0),IF(VLOOKUP(L5,AC:AD,3,0)="厦门/泉州/福州",VLOOKUP(K5,_xlpm.X,_xlpm.Y,0),IF(VLOOKUP(L5,AC:AD,2,0)="义乌",VLOOKUP(K5,_xlpm.X,_xlpm.Y,0),IF(VLOOKUP(L5,AC:AD,2,0)="上海/宁波",VLOOKUP(K5,_xlpm.X,_xlpm.Y,0),IF(VLOOKUP(L5,AC:AD,2,0)="青岛/郑州/绍兴/苏州/杭州仓/连云港/温州/台州/南京/合肥",VLOOKUP(K5,_xlpm.X,_xlpm.Y,0),IF(VLOOKUP(L5,AC:AD,2,0)="武汉/长沙/成都",VLOOKUP(K5,_xlpm.X,_xlpm.Y,0),IF(VLOOKUP(L5,AC:AD,2,0)="天津/南昌/石家庄",VLOOKUP(K5,_xlpm.X,_xlpm.Y,0),IF(VLOOKUP(L5,AC:AD,2,0)="西安",VLOOKUP(K5,_xlpm.X,_xlpm.Y,0),IF(VLOOKUP(L5,AC:AD,2,0)="济南/潍坊",VLOOKUP(K5,_xlpm.X,_xlpm.Y,0),IF(VLOOKUP(L5,AC:AD,2,0)="沧州/保定",VLOOKUP(K5,_xlpm.X,_xlpm.Y,0)))))))))))))),"-"),"单询") -> - | N19: =IFERROR(IF(M5="15CBM+",_xlfn.LET(_xlpm.X,#REF!,_xlpm.Y,41,IF(VLOOKUP(L5,AC:AD,2,0)="广州/深圳/东莞南城",VLOOKUP(K5,_xlpm.X,_xlpm.Y,0),IF(VLOOKUP(L5,AC:AD,2,0)="重庆",VLOOKUP(K5,_xlpm.X,_xlpm.Y,0),IF(VLOOKUP(L5,AC:AD,2,0)="中山/汕头",VLOOKUP(K5,_xlpm.X,_xlpm.Y,0),IF(VLOOKUP(L5,AC:AD,3,0)="厦门/泉州/福州",VLOOKUP(K5,_xlpm.X,_xlpm.Y,0),IF(VLOOKUP(L5,AC:AD,2,0)="义乌",VLOOKUP(K5,_xlpm.X,_xlpm.Y,0),IF(VLOOKUP(L5,AC:AD,2,0)="上海/宁波",VLOOKUP(K5,_xlpm.X,_xlpm.Y,0),IF(VLOOKUP(L5,AC:AD,2,0)="青岛/郑州/绍兴/苏州/杭州仓/连云港/温州/台州/南京/合肥",VLOOKUP(K5,_xlpm.X,_xlpm.Y,0),IF(VLOOKUP(L5,AC:AD,2,0)="武汉/长沙/成都",VLOOKUP(K5,_xlpm.X,_xlpm.Y,0),IF(VLOOKUP(L5,AC:AD,2,0)="天津/南昌/石家庄",VLOOKUP(K5,_xlpm.X,_xlpm.Y,0),IF(VLOOKUP(L5,AC:AD,2,0)="西安",VLOOKUP(K5,_xlpm.X,_xlpm.Y,0),IF(VLOOKUP(L5,AC:AD,2,0)="济南/潍坊",VLOOKUP(K5,_xlpm.X,_xlpm.Y,0),IF(VLOOKUP(L5,AC:AD,2,0)="沧州/保定",VLOOKUP(K5,_xlpm.X,_xlpm.Y,0)))))))))))))),"-"),"单询") -> - | O19: =IF(N19="单询","单询",IF(AND(M5<>"15CBM+",N19="-"),"立方价","【1-4.9CBM：+60元/CBM】; "&CHAR(10)&"【5-9.9CBM：+40元/CBM】; "&CHAR(10)&"【10-14.9CBM：+20元/CBM】; ")) -> 立方价 | Q19: 美转加 | R19: 美转加加西25日达-UPS派（OA） | S19: {=IFERROR(VLOOKUP($S$5,#REF!,INDEX(定位!$A:$W,MATCH($R19,定位!$A:$A,0),MATCH("*"&$T$5&"*"&"-BS",定位!$1:$1,0)),FALSE),"-")} -> - | T19: {=IFERROR(VLOOKUP($S$5,#REF!,INDEX(定位!$A:$W,MATCH($R19,定位!$A:$A,0),MATCH("*"&$T$5&"*"&"-NBS",定位!$1:$1,0)),FALSE),"-")} -> - | U19: =IFERROR(VLOOKUP($C$5,#REF!,_xlfn.XLOOKUP($R19,定位!A:A,定位!V:V),FALSE),"-") -> - | V19: =IFERROR(VLOOKUP($C$5,#REF!,_xlfn.XLOOKUP($R19,定位!A:A,定位!W:W),FALSE),"-") -> - | W19: 包税21-49KG:+1.5元/KG；50-99KG:+1元/KG | AC19: 福州 | AD19: 厦门/泉州/福州
A20: 拆派 | B20: 美森极速12日达 | C20: {=IFERROR(VLOOKUP($C$5,'美西-美森(12-17)'!$A:$DF,INDEX(定位!$A:$W,MATCH($B20,定位!$A:$A,0),MATCH("*"&$D$5&"*"&"-BS",定位!$1:$1,0)),FALSE),"-")} -> - | D20: {=IFERROR(VLOOKUP($C$5,'美西-美森(12-17)'!$A:$DF,INDEX(定位!$A:$W,MATCH($B20,定位!$A:$A,0),MATCH("*"&$D$5&"*"&"-NBS",定位!$1:$1,0)),FALSE),"-")} -> - | E20: =IFERROR(VLOOKUP($C$5,'美西-美森(12-17)'!$A:$DF,_xlfn.XLOOKUP($B20,定位!A:A,定位!V:V),FALSE),"-") -> - | F20: =IFERROR(VLOOKUP($C$5,'美西-美森(12-17)'!$A:$DF,_xlfn.XLOOKUP($B20,定位!A:A,定位!W:W),FALSE),"-") -> - | G20: =IF(LEFT($C$5,3)<>"WM-","FBA卡派包税:【10-49KG:+1元/KG】","沃尔玛卡派包税: 【21-49KG:+2元/KG】； 【50-99KG:+1元/KG】；") -> FBA卡派包税:【10-49KG:+1元/KG】 | I20: 海运 | J20: 英国海派-DPD派 | K20: {=IF(M5<>"15CBM+",_xlfn.LET(_xlpm.X,#REF!,IFERROR(_xlfn._xlws.FILTER(_xlpm.X,(ISNUMBER(FIND(L5,#REF!,1)))),"-")),"-")} -> - | L20: {=IF(M5<>"15CBM+",_xlfn.LET(_xlpm.X,#REF!,IFERROR(_xlfn._xlws.FILTER(_xlpm.X,(ISNUMBER(FIND(L5,#REF!,1)))),"-")),"-")} -> - | M20: {=IF(M5<>"15CBM+",_xlfn.LET(_xlpm.X,#REF!,IFERROR(_xlfn._xlws.FILTER(_xlpm.X,(ISNUMBER(FIND(L5,#REF!,1)))),"-")),"-")} -> - | N20: {=IF(M5<>"15CBM+",_xlfn.LET(_xlpm.X,#REF!,IFERROR(_xlfn._xlws.FILTER(_xlpm.X,(ISNUMBER(FIND(L5,#REF!,1)))),"-")),"-")} -> - | O20: =IF(M5="15CBM+","KG价","") | Q20: 美转加 | R20: 美转加加东20日达-卡派（HD） | S20: {=IFERROR(VLOOKUP($S$5,#REF!,INDEX(定位!$A:$W,MATCH($R20,定位!$A:$A,0),MATCH("*"&$T$5&"*"&"-BS",定位!$1:$1,0)),FALSE),"-")} -> - | T20: {=IFERROR(VLOOKUP($S$5,#REF!,INDEX(定位!$A:$W,MATCH($R20,定位!$A:$A,0),MATCH("*"&$T$5&"*"&"-NBS",定位!$1:$1,0)),FALSE),"-")} -> - | U20: =IFERROR(VLOOKUP($C$5,#REF!,_xlfn.XLOOKUP($R20,定位!A:A,定位!V:V),FALSE),"-") -> - | V20: =IFERROR(VLOOKUP($C$5,#REF!,_xlfn.XLOOKUP($R20,定位!A:A,定位!W:W),FALSE),"-") -> - | W20: 包税21-49KG:+1.5元/KG；50-99KG:+1元/KG | AC20: 义乌 | AD20: 义乌
A21: 拆派 | B21: 洛杉矶CLX13日达 | C21: {=IFERROR(VLOOKUP($C$5,'美西-美森(12-17)'!$A:$DF,INDEX(定位!$A:$W,MATCH($B21,定位!$A:$A,0),MATCH("*"&$D$5&"*"&"-BS",定位!$1:$1,0)),FALSE),"-")} -> - | D21: {=IFERROR(VLOOKUP($C$5,'美西-美森(12-17)'!$A:$DF,INDEX(定位!$A:$W,MATCH($B21,定位!$A:$A,0),MATCH("*"&$D$5&"*"&"-NBS",定位!$1:$1,0)),FALSE),"-")} -> - | E21: =IFERROR(VLOOKUP($C$5,'美西-美森(12-17)'!$A:$DF,_xlfn.XLOOKUP($B21,定位!A:A,定位!V:V),FALSE),"-") -> - | F21: =IFERROR(VLOOKUP($C$5,'美西-美森(12-17)'!$A:$DF,_xlfn.XLOOKUP(B21,定位!A:A,定位!W:W),FALSE),"-") -> - | G21: =IF(LEFT($C$5,3)<>"WM-","FBA卡派包税:【10-49KG:+1元/KG】","沃尔玛卡派包税: 【21-49KG:+2元/KG】； 【50-99KG:+1元/KG】；") -> FBA卡派包税:【10-49KG:+1元/KG】 | I21: 海运 | J21: 英国海派AEU1-DPD派(暂停) | K21: {=IF(M5<>"15CBM+",_xlfn.LET(_xlpm.X,#REF!,IFERROR(_xlfn._xlws.FILTER(_xlpm.X,(ISNUMBER(FIND(L5,#REF!,1)))),"-")),"-")} -> - | L21: {=IF(M5<>"15CBM+",_xlfn.LET(_xlpm.X,#REF!,IFERROR(_xlfn._xlws.FILTER(_xlpm.X,(ISNUMBER(FIND(L5,#REF!,1)))),"-")),"-")} -> - | M21: {=IF(M5<>"15CBM+",_xlfn.LET(_xlpm.X,#REF!,IFERROR(_xlfn._xlws.FILTER(_xlpm.X,(ISNUMBER(FIND(L5,#REF!,1)))),"-")),"-")} -> - | N21: {=IF(M5<>"15CBM+",_xlfn.LET(_xlpm.X,#REF!,IFERROR(_xlfn._xlws.FILTER(_xlpm.X,(ISNUMBER(FIND(L5,#REF!,1)))),"-")),"-")} -> - | O21: =IF(M5="15CBM+","KG价","") | Q21: 美转加 | R21: 美转加加东20日达-UPS派（HD） | S21: {=IFERROR(VLOOKUP($S$5,#REF!,INDEX(定位!$A:$W,MATCH($R21,定位!$A:$A,0),MATCH("*"&$T$5&"*"&"-BS",定位!$1:$1,0)),FALSE),"-")} -> - | T21: {=IFERROR(VLOOKUP($S$5,#REF!,INDEX(定位!$A:$W,MATCH($R21,定位!$A:$A,0),MATCH("*"&$T$5&"*"&"-NBS",定位!$1:$1,0)),FALSE),"-")} -> - | U21: =IFERROR(VLOOKUP($C$5,#REF!,_xlfn.XLOOKUP($R21,定位!A:A,定位!V:V),FALSE),"-") -> - | V21: =IFERROR(VLOOKUP($C$5,#REF!,_xlfn.XLOOKUP($R21,定位!A:A,定位!W:W),FALSE),"-") -> - | W21: 包税21-49KG:+1.5元/KG；50-99KG:+1元/KG | AC21: 上海 | AD21: 上海/宁波
A22: 拆派 | B22: 洛杉矶MAX14日达 | C22: {=IFERROR(VLOOKUP($C$5,'美西-美森(12-17)'!$A:$DF,INDEX(定位!$A:$W,MATCH($B22,定位!$A:$A,0),MATCH("*"&$D$5&"*"&"-BS",定位!$1:$1,0)),FALSE),"-")} -> - | D22: {=IFERROR(VLOOKUP($C$5,'美西-美森(12-17)'!$A:$DF,INDEX(定位!$A:$W,MATCH($B22,定位!$A:$A,0),MATCH("*"&$D$5&"*"&"-NBS",定位!$1:$1,0)),FALSE),"-")} -> - | E22: =IFERROR(VLOOKUP($C$5,'美西-美森(12-17)'!$A:$DF,_xlfn.XLOOKUP($B22,定位!A:A,定位!V:V),FALSE),"-") -> - | F22: =IFERROR(VLOOKUP($C$5,'美西-美森(12-17)'!$A:$DF,_xlfn.XLOOKUP(B22,定位!A:A,定位!W:W),FALSE),"-") -> - | G22: =IF(LEFT($C$5,3)<>"WM-","FBA卡派包税:【10-49KG:+1元/KG】","沃尔玛卡派包税: 【21-49KG:+2元/KG】； 【50-99KG:+1元/KG】；") -> FBA卡派包税:【10-49KG:+1元/KG】 | I22: 海运 | J22: 英国海派限时达 | K22: {=IF(M5<>"15CBM+",_xlfn.LET(_xlpm.X,#REF!,IFERROR(_xlfn._xlws.FILTER(_xlpm.X,(ISNUMBER(FIND(L5,#REF!,1)))),"-")),"-")} -> - | L22: {=IF(M5<>"15CBM+",_xlfn.LET(_xlpm.X,#REF!,IFERROR(_xlfn._xlws.FILTER(_xlpm.X,(ISNUMBER(FIND(L5,#REF!,1)))),"-")),"-")} -> - | M22: {=IF(M5<>"15CBM+",_xlfn.LET(_xlpm.X,#REF!,IFERROR(_xlfn._xlws.FILTER(_xlpm.X,(ISNUMBER(FIND(L5,#REF!,1)))),"-")),"-")} -> - | N22: {=IF(M5<>"15CBM+",_xlfn.LET(_xlpm.X,#REF!,IFERROR(_xlfn._xlws.FILTER(_xlpm.X,(ISNUMBER(FIND(L5,#REF!,1)))),"-")),"-")} -> - | O22: =IF(M5="15CBM+","KG价","") | Q22: 美转加 | R22: 美转加加西20日达-卡派（HD） | S22: {=IFERROR(VLOOKUP($S$5,#REF!,INDEX(定位!$A:$W,MATCH($R22,定位!$A:$A,0),MATCH("*"&$T$5&"*"&"-BS",定位!$1:$1,0)),FALSE),"-")} -> - | T22: {=IFERROR(VLOOKUP($S$5,#REF!,INDEX(定位!$A:$W,MATCH($R22,定位!$A:$A,0),MATCH("*"&$T$5&"*"&"-NBS",定位!$1:$1,0)),FALSE),"-")} -> - | U22: =IFERROR(VLOOKUP($C$5,#REF!,_xlfn.XLOOKUP($R22,定位!A:A,定位!V:V),FALSE),"-") -> - | V22: =IFERROR(VLOOKUP($C$5,#REF!,_xlfn.XLOOKUP($R22,定位!A:A,定位!W:W),FALSE),"-") -> - | W22: 包税21-49KG:+1.5元/KG；50-99KG:+1元/KG | AC22: 宁波 | AD22: 上海/宁波
A23: 拆派 | B23: 洛杉矶EXX16日达 | C23: {=IFERROR(VLOOKUP($C$5,'美西-美森(12-17)'!$A:$DF,INDEX(定位!$A:$W,MATCH($B23,定位!$A:$A,0),MATCH("*"&$D$5&"*"&"-BS",定位!$1:$1,0)),FALSE),"-")} -> - | D23: {=IFERROR(VLOOKUP($C$5,'美西-美森(12-17)'!$A:$DF,INDEX(定位!$A:$W,MATCH($B23,定位!$A:$A,0),MATCH("*"&$D$5&"*"&"-NBS",定位!$1:$1,0)),FALSE),"-")} -> - | E23: =IFERROR(VLOOKUP($C$5,'美西-美森(12-17)'!$A:$DF,_xlfn.XLOOKUP($B23,定位!A:A,定位!V:V),FALSE),"-") -> - | F23: =IFERROR(VLOOKUP($C$5,'美西-美森(12-17)'!$A:$DF,_xlfn.XLOOKUP(B23,定位!A:A,定位!W:W),FALSE),"-") -> - | G23: =IF(LEFT($C$5,3)<>"WM-","FBA卡派包税:【10-49KG:+1元/KG】","沃尔玛卡派包税: 【21-49KG:+2元/KG】； 【50-99KG:+1元/KG】；") -> FBA卡派包税:【10-49KG:+1元/KG】 | Q23: 美转加 | R23: 美转加加西20日达-UPS派（HD） | S23: {=IFERROR(VLOOKUP($S$5,#REF!,INDEX(定位!$A:$W,MATCH($R23,定位!$A:$A,0),MATCH("*"&$T$5&"*"&"-BS",定位!$1:$1,0)),FALSE),"-")} -> - | T23: {=IFERROR(VLOOKUP($S$5,#REF!,INDEX(定位!$A:$W,MATCH($R23,定位!$A:$A,0),MATCH("*"&$T$5&"*"&"-NBS",定位!$1:$1,0)),FALSE),"-")} -> - | U23: =IFERROR(VLOOKUP($C$5,#REF!,_xlfn.XLOOKUP($R23,定位!A:A,定位!V:V),FALSE),"-") -> - | V23: =IFERROR(VLOOKUP($C$5,#REF!,_xlfn.XLOOKUP($R23,定位!A:A,定位!W:W),FALSE),"-") -> - | W23: 包税21-49KG:+1.5元/KG；50-99KG:+1元/KG | AC23: 武汉 | AD23: 武汉/长沙/成都
A24: 拆派 | B24: 洛杉矶17日达 | C24: {=IFERROR(VLOOKUP($C$5,'美西-美森(12-17)'!$A:$DF,INDEX(定位!$A:$W,MATCH($B24,定位!$A:$A,0),MATCH("*"&$D$5&"*"&"-BS",定位!$1:$1,0)),FALSE),"-")} -> - | D24: {=IFERROR(VLOOKUP($C$5,'美西-美森(12-17)'!$A:$DF,INDEX(定位!$A:$W,MATCH($B24,定位!$A:$A,0),MATCH("*"&$D$5&"*"&"-NBS",定位!$1:$1,0)),FALSE),"-")} -> - | E24: =IFERROR(VLOOKUP($C$5,'美西-美森(12-17)'!$A:$DF,_xlfn.XLOOKUP($B24,定位!A:A,定位!V:V),FALSE),"-") -> - | F24: =IFERROR(VLOOKUP($C$5,'美西-美森(12-17)'!$A:$DF,_xlfn.XLOOKUP(B24,定位!A:A,定位!W:W),FALSE),"-") -> - | G24: =IF(LEFT($C$5,3)<>"WM-","FBA卡派包税:【10-49KG:+1元/KG】","沃尔玛卡派包税: 【21-49KG:+2元/KG】； 【50-99KG:+1元/KG】；") -> FBA卡派包税:【10-49KG:+1元/KG】 | Q24: 美转加 | R24: 美转加加东19日达-卡派（EXX） | S24: {=IFERROR(VLOOKUP($S$5,#REF!,INDEX(定位!$A:$W,MATCH($R24,定位!$A:$A,0),MATCH("*"&$T$5&"*"&"-BS",定位!$1:$1,0)),FALSE),"-")} -> - | T24: {=IFERROR(VLOOKUP($S$5,#REF!,INDEX(定位!$A:$W,MATCH($R24,定位!$A:$A,0),MATCH("*"&$T$5&"*"&"-NBS",定位!$1:$1,0)),FALSE),"-")} -> - | U24: =IFERROR(VLOOKUP($C$5,#REF!,_xlfn.XLOOKUP($R24,定位!A:A,定位!V:V),FALSE),"-") -> - | V24: =IFERROR(VLOOKUP($C$5,#REF!,_xlfn.XLOOKUP($R24,定位!A:A,定位!W:W),FALSE),"-") -> - | W24: 包税21-49KG:+1.5元/KG；50-99KG:+1元/KG | AC24: 长沙 | AD24: 武汉/长沙/成都
A25: 拆派 | B25: 洛杉矶20日达 | C25: {=IFERROR(VLOOKUP($C$5,'美西-以星&普船(17-26)'!$A:$BP,INDEX(定位!$A:$W,MATCH($B25,定位!$A:$A,0),MATCH("*"&$D$5&"*"&"-BS",定位!$1:$1,0)),FALSE),"-")} -> - | D25: {=IFERROR(VLOOKUP($C$5,'美西-以星&普船(17-26)'!$A:$BP,INDEX(定位!$A:$W,MATCH($B25,定位!$A:$A,0),MATCH("*"&$D$5&"*"&"-NBS",定位!$1:$1,0)),FALSE),"-")} -> - | E25: =IFERROR(VLOOKUP($C$5,'美西-以星&普船(17-26)'!$A:$BP,_xlfn.XLOOKUP($B25,定位!A:A,定位!V:V),FALSE),"-") -> - | F25: =IFERROR(VLOOKUP($C$5,'美西-以星&普船(17-26)'!$A:$BP,_xlfn.XLOOKUP($B25,定位!A:A,定位!W:W),FALSE),"-") -> - | G25: =IF(LEFT($C$5,3)<>"WM-","FBA卡派包税:【10-49KG:+1元/KG】","沃尔玛卡派包税: 【21-49KG:+2元/KG】； 【50-99KG:+1元/KG】；") -> FBA卡派包税:【10-49KG:+1元/KG】 | Q25: 美转加 | R25: 美转加加东19日达-UPS派（EXX） | S25: {=IFERROR(VLOOKUP($S$5,#REF!,INDEX(定位!$A:$W,MATCH($R25,定位!$A:$A,0),MATCH("*"&$T$5&"*"&"-BS",定位!$1:$1,0)),FALSE),"-")} -> - | T25: {=IFERROR(VLOOKUP($S$5,#REF!,INDEX(定位!$A:$W,MATCH($R25,定位!$A:$A,0),MATCH("*"&$T$5&"*"&"-NBS",定位!$1:$1,0)),FALSE),"-")} -> - | U25: =IFERROR(VLOOKUP($C$5,#REF!,_xlfn.XLOOKUP($R25,定位!A:A,定位!V:V),FALSE),"-") -> - | V25: =IFERROR(VLOOKUP($C$5,#REF!,_xlfn.XLOOKUP($R25,定位!A:A,定位!W:W),FALSE),"-") -> - | W25: 包税21-49KG:+1.5元/KG；50-99KG:+1元/KG | AC25: 成都 | AD25: 武汉/长沙/成都
A26: 拆派 | B26: 洛杉矶22日达 | C26: {=IFERROR(VLOOKUP($C$5,'美西-以星&普船(17-26)'!$A:$BP,INDEX(定位!$A:$W,MATCH($B26,定位!$A:$A,0),MATCH("*"&$D$5&"*"&"-BS",定位!$1:$1,0)),FALSE),"-")} -> - | D26: {=IFERROR(VLOOKUP($C$5,'美西-以星&普船(17-26)'!$A:$BP,INDEX(定位!$A:$W,MATCH($B26,定位!$A:$A,0),MATCH("*"&$D$5&"*"&"-NBS",定位!$1:$1,0)),FALSE),"-")} -> - | E26: =IFERROR(VLOOKUP($C$5,'美西-以星&普船(17-26)'!$A:$BP,_xlfn.XLOOKUP($B26,定位!A:A,定位!V:V),FALSE),"-") -> - | F26: =IFERROR(VLOOKUP($C$5,'美西-以星&普船(17-26)'!$A:$BP,_xlfn.XLOOKUP(B26,定位!A:A,定位!W:W),FALSE),"-") -> - | G26: =IF(LEFT($C$5,3)<>"WM-","FBA卡派包税:【10-49KG:+1元/KG】","沃尔玛卡派包税: 【21-49KG:+2元/KG】； 【50-99KG:+1元/KG】；") -> FBA卡派包税:【10-49KG:+1元/KG】 | Q26: 美转加 | R26: 美转加加西19日达-卡派（EXX） | S26: {=IFERROR(VLOOKUP($S$5,#REF!,INDEX(定位!$A:$W,MATCH($R26,定位!$A:$A,0),MATCH("*"&$T$5&"*"&"-BS",定位!$1:$1,0)),FALSE),"-")} -> - | T26: {=IFERROR(VLOOKUP($S$5,#REF!,INDEX(定位!$A:$W,MATCH($R26,定位!$A:$A,0),MATCH("*"&$T$5&"*"&"-NBS",定位!$1:$1,0)),FALSE),"-")} -> - | U26: =IFERROR(VLOOKUP($C$5,#REF!,_xlfn.XLOOKUP($R26,定位!A:A,定位!V:V),FALSE),"-") -> - | V26: =IFERROR(VLOOKUP($C$5,#REF!,_xlfn.XLOOKUP($R26,定位!A:A,定位!W:W),FALSE),"-") -> - | W26: 包税21-49KG:+1.5元/KG；50-99KG:+1元/KG | AC26: 重庆 | AD26: 重庆
A27: 拆派 | B27: 洛杉矶26日达 | C27: {=IFERROR(VLOOKUP($C$5,'美西-以星&普船(17-26)'!$A:$BP,INDEX(定位!$A:$W,MATCH($B27,定位!$A:$A,0),MATCH("*"&$D$5&"*"&"-BS",定位!$1:$1,0)),FALSE),"-")} -> - | D27: {=IFERROR(VLOOKUP($C$5,'美西-以星&普船(17-26)'!$A:$BP,INDEX(定位!$A:$W,MATCH($B27,定位!$A:$A,0),MATCH("*"&$D$5&"*"&"-NBS",定位!$1:$1,0)),FALSE),"-")} -> - | E27: =IFERROR(VLOOKUP($C$5,'美西-以星&普船(17-26)'!$A:$BP,_xlfn.XLOOKUP($B27,定位!A:A,定位!V:V),FALSE),"-") -> - | F27: =IFERROR(VLOOKUP($C$5,'美西-以星&普船(17-26)'!$A:$BP,_xlfn.XLOOKUP(B27,定位!A:A,定位!W:W),FALSE),"-") -> - | G27: =IF(LEFT($C$5,3)<>"WM-","FBA卡派包税:【10-49KG:+1元/KG】","沃尔玛卡派包税: 【21-49KG:+2元/KG】； 【50-99KG:+1元/KG】；") -> FBA卡派包税:【10-49KG:+1元/KG】 | Q27: 美转加 | R27: 美转加加西19日达-UPS派（EXX） | S27: {=IFERROR(VLOOKUP($S$5,#REF!,INDEX(定位!$A:$W,MATCH($R27,定位!$A:$A,0),MATCH("*"&$T$5&"*"&"-BS",定位!$1:$1,0)),FALSE),"-")} -> - | T27: {=IFERROR(VLOOKUP($S$5,#REF!,INDEX(定位!$A:$W,MATCH($R27,定位!$A:$A,0),MATCH("*"&$T$5&"*"&"-NBS",定位!$1:$1,0)),FALSE),"-")} -> - | U27: =IFERROR(VLOOKUP($C$5,#REF!,_xlfn.XLOOKUP($R27,定位!A:A,定位!V:V),FALSE),"-") -> - | V27: =IFERROR(VLOOKUP($C$5,#REF!,_xlfn.XLOOKUP($R27,定位!A:A,定位!W:W),FALSE),"-") -> - | W27: 包税21-49KG:+1.5元/KG；50-99KG:+1元/KG | AC27: 天津 | AD27: 天津/南昌/石家庄
A28: 拆派 | B28: 奥克兰直航26日达 | C28: {=IFERROR(VLOOKUP($C$5,美西北!$A:$DP,INDEX(定位!$A:$W,MATCH($B28,定位!$A:$A,0),MATCH("*"&$D$5&"*"&"-BS",定位!$1:$1,0)),FALSE),"-")} -> - | D28: {=IFERROR(VLOOKUP($C$5,美西北!$A:$DP,INDEX(定位!$A:$W,MATCH($B28,定位!$A:$A,0),MATCH("*"&$D$5&"*"&"-NBS",定位!$1:$1,0)),FALSE),"-")} -> - | E28: =IFERROR(VLOOKUP($C$5,美西北!$A:$DP,_xlfn.XLOOKUP($B28,定位!A:A,定位!V:V),FALSE),"-") -> - | F28: =IFERROR(VLOOKUP($C$5,美西北!$A:$DP,_xlfn.XLOOKUP($B28,定位!A:A,定位!W:W),FALSE),"-") -> - | G28: =IF(LEFT($C$5,3)<>"WM-","FBA卡派包税:【10-49KG:+1元/KG】","沃尔玛卡派包税: 【21-49KG:+2元/KG】； 【50-99KG:+1元/KG】；") -> FBA卡派包税:【10-49KG:+1元/KG】 | Q28: 美转加 | R28: 美转加MAX加东17日达-卡派 | S28: {=IFERROR(VLOOKUP($S$5,#REF!,INDEX(定位!$A:$W,MATCH($R28,定位!$A:$A,0),MATCH("*"&$T$5&"*"&"-BS",定位!$1:$1,0)),FALSE),"-")} -> - | T28: {=IFERROR(VLOOKUP($S$5,#REF!,INDEX(定位!$A:$W,MATCH($R28,定位!$A:$A,0),MATCH("*"&$T$5&"*"&"-NBS",定位!$1:$1,0)),FALSE),"-")} -> - | U28: =IFERROR(VLOOKUP($C$5,#REF!,_xlfn.XLOOKUP($R28,定位!A:A,定位!V:V),FALSE),"-") -> - | V28: =IFERROR(VLOOKUP($C$5,#REF!,_xlfn.XLOOKUP($R28,定位!A:A,定位!W:W),FALSE),"-") -> - | W28: 包税21-49KG:+1.5元/KG；50-99KG:+1元/KG | AC28: 南昌 | AD28: 天津/南昌/石家庄
A29: 拆派 | B29: 奥克兰直航32日达 | C29: {=IFERROR(VLOOKUP($C$5,美西北!$A:$DP,INDEX(定位!$A:$W,MATCH($B29,定位!$A:$A,0),MATCH("*"&$D$5&"*"&"-BS",定位!$1:$1,0)),FALSE),"-")} -> - | D29: {=IFERROR(VLOOKUP($C$5,美西北!$A:$DP,INDEX(定位!$A:$W,MATCH($B29,定位!$A:$A,0),MATCH("*"&$D$5&"*"&"-NBS",定位!$1:$1,0)),FALSE),"-")} -> - | E29: =IFERROR(VLOOKUP($C$5,美西北!$A:$DP,_xlfn.XLOOKUP($B29,定位!A:A,定位!V:V),FALSE),"-") -> - | F29: =IFERROR(VLOOKUP($C$5,美西北!$A:$DP,_xlfn.XLOOKUP($B29,定位!A:A,定位!W:W),FALSE),"-") -> - | G29: =IF(LEFT($C$5,3)<>"WM-","FBA卡派包税:【10-49KG:+1元/KG】","沃尔玛卡派包税: 【21-49KG:+2元/KG】； 【50-99KG:+1元/KG】；") -> FBA卡派包税:【10-49KG:+1元/KG】 | Q29: 美转加 | R29: 美转加MAX加东17日达-UPS派 | S29: {=IFERROR(VLOOKUP($S$5,#REF!,INDEX(定位!$A:$W,MATCH($R29,定位!$A:$A,0),MATCH("*"&$T$5&"*"&"-BS",定位!$1:$1,0)),FALSE),"-")} -> - | T29: {=IFERROR(VLOOKUP($S$5,#REF!,INDEX(定位!$A:$W,MATCH($R29,定位!$A:$A,0),MATCH("*"&$T$5&"*"&"-NBS",定位!$1:$1,0)),FALSE),"-")} -> - | U29: =IFERROR(VLOOKUP($C$5,#REF!,_xlfn.XLOOKUP($R29,定位!A:A,定位!V:V),FALSE),"-") -> - | V29: =IFERROR(VLOOKUP($C$5,#REF!,_xlfn.XLOOKUP($R29,定位!A:A,定位!W:W),FALSE),"-") -> - | W29: 包税21-49KG:+1.5元/KG；50-99KG:+1元/KG | AC29: 石家庄 | AD29: 天津/南昌/石家庄
A30: 拆派 | B30: 西雅图直航29日达 | C30: {=IFERROR(VLOOKUP($C$5,美西北!$A:$DP,INDEX(定位!$A:$W,MATCH($B30,定位!$A:$A,0),MATCH("*"&$D$5&"*"&"-BS",定位!$1:$1,0)),FALSE),"-")} -> - | D30: {=IFERROR(VLOOKUP($C$5,美西北!$A:$DP,INDEX(定位!$A:$W,MATCH($B30,定位!$A:$A,0),MATCH("*"&$D$5&"*"&"-NBS",定位!$1:$1,0)),FALSE),"-")} -> - | E30: =IFERROR(VLOOKUP($C$5,美西北!$A:$DP,_xlfn.XLOOKUP($B30,定位!A:A,定位!V:V),FALSE),"-") -> - | F30: =IFERROR(VLOOKUP($C$5,美西北!$A:$DP,_xlfn.XLOOKUP(B30,定位!A:A,定位!W:W),FALSE),"-") -> - | G30: =IF(LEFT($C$5,3)<>"WM-","FBA卡派包税:【10-49KG:+1元/KG】","沃尔玛卡派包税: 【21-49KG:+2元/KG】； 【50-99KG:+1元/KG】；") -> FBA卡派包税:【10-49KG:+1元/KG】 | Q30: 美转加 | R30: 美转加MAX加西17日达-卡派 | S30: {=IFERROR(VLOOKUP($S$5,#REF!,INDEX(定位!$A:$W,MATCH($R30,定位!$A:$A,0),MATCH("*"&$T$5&"*"&"-BS",定位!$1:$1,0)),FALSE),"-")} -> - | T30: {=IFERROR(VLOOKUP($S$5,#REF!,INDEX(定位!$A:$W,MATCH($R30,定位!$A:$A,0),MATCH("*"&$T$5&"*"&"-NBS",定位!$1:$1,0)),FALSE),"-")} -> - | U30: =IFERROR(VLOOKUP($C$5,#REF!,_xlfn.XLOOKUP($R30,定位!A:A,定位!V:V),FALSE),"-") -> - | V30: =IFERROR(VLOOKUP($C$5,#REF!,_xlfn.XLOOKUP($R30,定位!A:A,定位!W:W),FALSE),"-") -> - | W30: 包税21-49KG:+1.5元/KG；50-99KG:+1元/KG | AC30: 沧州 | AD30: 沧州/保定
A31: 拆派 | B31: 纽约直航42日达 | C31: {=IFERROR(VLOOKUP($C$5,美东直航系列!$A:$CT,INDEX(定位!$A:$W,MATCH($B31,定位!$A:$A,0),MATCH("*"&$D$5&"*"&"-BS",定位!$1:$1,0)),FALSE),"-")} -> - | D31: {=IFERROR(VLOOKUP($C$5,美东直航系列!$A:$CT,INDEX(定位!$A:$W,MATCH($B31,定位!$A:$A,0),MATCH("*"&$D$5&"*"&"-NBS",定位!$1:$1,0)),FALSE),"-")} -> - | E31: =IFERROR(VLOOKUP($C$5,美东直航系列!$A:$CT,_xlfn.XLOOKUP($B31,定位!A:A,定位!V:V),FALSE),"-") -> - | F31: =IFERROR(VLOOKUP($C$5,美东直航系列!$A:$CT,_xlfn.XLOOKUP($B31,定位!A:A,定位!W:W),FALSE),"-") -> - | G31: =IF(LEFT($C$5,3)<>"WM-","FBA卡派包税:【10-49KG:+1元/KG】","沃尔玛卡派包税: 【21-49KG:+2元/KG】； 【50-99KG:+1元/KG】；") -> FBA卡派包税:【10-49KG:+1元/KG】 | Q31: 美转加 | R31: 美转加MAX加西17日达-UPS派 | S31: {=IFERROR(VLOOKUP($S$5,#REF!,INDEX(定位!$A:$W,MATCH($R31,定位!$A:$A,0),MATCH("*"&$T$5&"*"&"-BS",定位!$1:$1,0)),FALSE),"-")} -> - | T31: {=IFERROR(VLOOKUP($S$5,#REF!,INDEX(定位!$A:$W,MATCH($R31,定位!$A:$A,0),MATCH("*"&$T$5&"*"&"-NBS",定位!$1:$1,0)),FALSE),"-")} -> - | U31: =IFERROR(VLOOKUP($C$5,#REF!,_xlfn.XLOOKUP($R31,定位!A:A,定位!V:V),FALSE),"-") -> - | V31: =IFERROR(VLOOKUP($C$5,#REF!,_xlfn.XLOOKUP($R31,定位!A:A,定位!W:W),FALSE),"-") -> - | W31: 包税21-49KG:+1.5元/KG；50-99KG:+1元/KG | AC31: 保定 | AD31: 沧州/保定
A32: 拆派 | B32: 纽约直航38日达 | C32: {=IFERROR(VLOOKUP($C$5,美东直航系列!$A:$CT,INDEX(定位!$A:$W,MATCH($B32,定位!$A:$A,0),MATCH("*"&$D$5&"*"&"-BS",定位!$1:$1,0)),FALSE),"-")} -> - | D32: {=IFERROR(VLOOKUP($C$5,美东直航系列!$A:$CT,INDEX(定位!$A:$W,MATCH($B32,定位!$A:$A,0),MATCH("*"&$D$5&"*"&"-NBS",定位!$1:$1,0)),FALSE),"-")} -> - | E32: =IFERROR(VLOOKUP($C$5,美东直航系列!$A:$CT,_xlfn.XLOOKUP($B32,定位!A:A,定位!V:V),FALSE),"-") -> - | F32: =IFERROR(VLOOKUP($C$5,美东直航系列!$A:$CT,_xlfn.XLOOKUP(B32,定位!A:A,定位!W:W),FALSE),"-") -> - | G32: =IF(LEFT($C$5,3)<>"WM-","FBA卡派包税:【10-49KG:+1元/KG】","沃尔玛卡派包税: 【21-49KG:+2元/KG】； 【50-99KG:+1元/KG】；") -> FBA卡派包税:【10-49KG:+1元/KG】 | Q32: 美转加 | R32: 美转加CLX加东16日达-卡派 | S32: {=IFERROR(VLOOKUP($S$5,#REF!,INDEX(定位!$A:$W,MATCH($R32,定位!$A:$A,0),MATCH("*"&$T$5&"*"&"-BS",定位!$1:$1,0)),FALSE),"-")} -> - | T32: {=IFERROR(VLOOKUP($S$5,#REF!,INDEX(定位!$A:$W,MATCH($R32,定位!$A:$A,0),MATCH("*"&$T$5&"*"&"-NBS",定位!$1:$1,0)),FALSE),"-")} -> - | U32: =IFERROR(VLOOKUP($C$5,'[4]美转加-美森CLX系列'!$A:$BQ,_xlfn.XLOOKUP($R32,[4]定位!A:A,[4]定位!V:V),FALSE),"-") -> 20-24日 | V32: =IFERROR(VLOOKUP($C$5,'[4]美转加-美森CLX系列'!$A:$BQ,_xlfn.XLOOKUP($R32,[4]定位!A:A,[4]定位!W:W),FALSE),"-") -> 超26日 | W32: 快递派包税21-99KG:+1元/KG； | AC32: 潍坊 | AD32: 济南/潍坊
A33: 拆派 | B33: 纽约海铁24日达 | C33: {=IFERROR(VLOOKUP($C$5,'美东-海铁系列'!$A:$CX,INDEX(定位!$A:$W,MATCH($B33,定位!$A:$A,0),MATCH("*"&$D$5&"*"&"-BS",定位!$1:$1,0)),FALSE),"-")} -> - | D33: {=IFERROR(VLOOKUP($C$5,'美东-海铁系列'!$A:$CX,INDEX(定位!$A:$W,MATCH($B33,定位!$A:$A,0),MATCH("*"&$D$5&"*"&"-NBS",定位!$1:$1,0)),FALSE),"-")} -> - | E33: =IFERROR(VLOOKUP($C$5,'美东-海铁系列'!$A:$CX,_xlfn.XLOOKUP($B33,定位!A:A,定位!V:V),FALSE),"-") -> - | F33: =IFERROR(VLOOKUP($C$5,'美东-海铁系列'!$A:$CX,_xlfn.XLOOKUP($B33,定位!A:A,定位!W:W),FALSE),"-") -> - | G33: =IF(LEFT($C$5,3)<>"WM-","FBA卡派包税:【10-49KG:+1元/KG】","沃尔玛卡派包税: 【21-49KG:+2元/KG】； 【50-99KG:+1元/KG】；") -> FBA卡派包税:【10-49KG:+1元/KG】 | Q33: 美转加 | R33: 美转加CLX加东16日达-UPS派 | S33: {=IFERROR(VLOOKUP($S$5,#REF!,INDEX(定位!$A:$W,MATCH($R33,定位!$A:$A,0),MATCH("*"&$T$5&"*"&"-BS",定位!$1:$1,0)),FALSE),"-")} -> - | T33: {=IFERROR(VLOOKUP($S$5,#REF!,INDEX(定位!$A:$W,MATCH($R33,定位!$A:$A,0),MATCH("*"&$T$5&"*"&"-NBS",定位!$1:$1,0)),FALSE),"-")} -> - | U33: =IFERROR(VLOOKUP($C$5,'[4]美转加-美森CLX系列'!$A:$BQ,_xlfn.XLOOKUP($R33,[4]定位!A:A,[4]定位!V:V),FALSE),"-") -> 18-22日 | V33: =IFERROR(VLOOKUP($C$5,'[4]美转加-美森CLX系列'!$A:$BQ,_xlfn.XLOOKUP($R33,[4]定位!A:A,[4]定位!W:W),FALSE),"-") -> 超24日 | W33: 快递派包税21-99KG:+1元/KG； | AC33: 西安 | AD33: 西安
A34: 拆派 | B34: 纽约MAX海铁22日达 | C34: {=IFERROR(VLOOKUP($C$5,'美东-海铁系列'!$A:$CX,INDEX(定位!$A:$W,MATCH($B34,定位!$A:$A,0),MATCH("*"&$D$5&"*"&"-BS",定位!$1:$1,0)),FALSE),"-")} -> - | D34: {=IFERROR(VLOOKUP($C$5,'美东-海铁系列'!$A:$CX,INDEX(定位!$A:$W,MATCH($B34,定位!$A:$A,0),MATCH("*"&$D$5&"*"&"-NBS",定位!$1:$1,0)),FALSE),"-")} -> - | E34: =IFERROR(VLOOKUP($C$5,'美东-海铁系列'!$A:$CX,_xlfn.XLOOKUP($B34,定位!A:A,定位!V:V),FALSE),"-") -> - | F34: =IFERROR(VLOOKUP($C$5,'美东-海铁系列'!$A:$CX,_xlfn.XLOOKUP(B34,定位!A:A,定位!W:W),FALSE),"-") -> - | G34: =IF(LEFT($C$5,3)<>"WM-","FBA卡派包税:【10-49KG:+1元/KG】","沃尔玛卡派包税: 【21-49KG:+2元/KG】； 【50-99KG:+1元/KG】；") -> FBA卡派包税:【10-49KG:+1元/KG】 | Q34: 美转加 | R34: 美转加CLX加西16日达-卡派 | S34: {=IFERROR(VLOOKUP($S$5,#REF!,INDEX(定位!$A:$W,MATCH($R34,定位!$A:$A,0),MATCH("*"&$T$5&"*"&"-BS",定位!$1:$1,0)),FALSE),"-")} -> - | T34: {=IFERROR(VLOOKUP($S$5,#REF!,INDEX(定位!$A:$W,MATCH($R34,定位!$A:$A,0),MATCH("*"&$T$5&"*"&"-NBS",定位!$1:$1,0)),FALSE),"-")} -> - | U34: =IFERROR(VLOOKUP($C$5,'[4]美转加-美森CLX系列'!$A:$BQ,_xlfn.XLOOKUP($R34,[4]定位!A:A,[4]定位!V:V),FALSE),"-") -> - | V34: =IFERROR(VLOOKUP($C$5,'[4]美转加-美森CLX系列'!$A:$BQ,_xlfn.XLOOKUP($R34,[4]定位!A:A,[4]定位!W:W),FALSE),"-") -> - | W34: 快递派包税21-99KG:+1元/KG； | AC34: 济南 | AD34: 济南/潍坊
A35: 拆派 | B35: 纽约海铁30日达 | C35: {=IFERROR(VLOOKUP($C$5,'美东-海铁系列'!$A:$CX,INDEX(定位!$A:$W,MATCH($B35,定位!$A:$A,0),MATCH("*"&$D$5&"*"&"-BS",定位!$1:$1,0)),FALSE),"-")} -> - | D35: {=IFERROR(VLOOKUP($C$5,'美东-海铁系列'!$A:$CX,INDEX(定位!$A:$W,MATCH($B35,定位!$A:$A,0),MATCH("*"&$D$5&"*"&"-NBS",定位!$1:$1,0)),FALSE),"-")} -> - | E35: =IFERROR(VLOOKUP($C$5,'美东-海铁系列'!$A:$CX,_xlfn.XLOOKUP($B35,定位!A:A,定位!V:V),FALSE),"-") -> - | F35: =IFERROR(VLOOKUP($C$5,'美东-海铁系列'!$A:$CX,_xlfn.XLOOKUP(B35,定位!A:A,定位!W:W),FALSE),"-") -> - | G35: =IF(LEFT($C$5,3)<>"WM-","FBA卡派包税:【10-49KG:+1元/KG】","沃尔玛卡派包税: 【21-49KG:+2元/KG】； 【50-99KG:+1元/KG】；") -> FBA卡派包税:【10-49KG:+1元/KG】 | Q35: 美转加 | R35: 美转加CLX加西16日达-UPS派 | S35: {=IFERROR(VLOOKUP($S$5,#REF!,INDEX(定位!$A:$W,MATCH($R35,定位!$A:$A,0),MATCH("*"&$T$5&"*"&"-BS",定位!$1:$1,0)),FALSE),"-")} -> - | T35: {=IFERROR(VLOOKUP($S$5,#REF!,INDEX(定位!$A:$W,MATCH($R35,定位!$A:$A,0),MATCH("*"&$T$5&"*"&"-NBS",定位!$1:$1,0)),FALSE),"-")} -> - | U35: =IFERROR(VLOOKUP($C$5,'[4]美转加-美森CLX系列'!$A:$BQ,_xlfn.XLOOKUP($R35,[4]定位!A:A,[4]定位!V:V),FALSE),"-") -> - | V35: =IFERROR(VLOOKUP($C$5,'[4]美转加-美森CLX系列'!$A:$BQ,_xlfn.XLOOKUP($R35,[4]定位!A:A,[4]定位!W:W),FALSE),"-") -> - | W35: 快递派包税21-99KG:+1元/KG； | AC35: 南京 | AD35: 青岛/郑州/绍兴/苏州/杭州仓/连云港/温州/台州/南京/合肥
A36: 拆派 | B36: 萨凡纳直航36日达 | C36: {=IFERROR(VLOOKUP($C$5,美东南直航系列!$A:$CT,INDEX(定位!$A:$W,MATCH($B36,定位!$A:$A,0),MATCH("*"&$D$5&"*"&"-BS",定位!$1:$1,0)),FALSE),"-")} -> - | D36: {=IFERROR(VLOOKUP($C$5,美东南直航系列!$A:$CT,INDEX(定位!$A:$W,MATCH($B36,定位!$A:$A,0),MATCH("*"&$D$5&"*"&"-NBS",定位!$1:$1,0)),FALSE),"-")} -> - | E36: =IFERROR(VLOOKUP($C$5,美东南直航系列!$A:$CT,_xlfn.XLOOKUP($B36,定位!A:A,定位!V:V),FALSE),"-") -> - | F36: =IFERROR(VLOOKUP($C$5,美东南直航系列!$A:$CT,_xlfn.XLOOKUP($B36,定位!A:A,定位!W:W),FALSE),"-") -> - | G36: =IF(LEFT($C$5,3)<>"WM-","FBA卡派包税:【10-49KG:+1元/KG】","沃尔玛卡派包税: 【21-49KG:+2元/KG】； 【50-99KG:+1元/KG】；") -> FBA卡派包税:【10-49KG:+1元/KG】 | AC36: 合肥 | AD36: 青岛/郑州/绍兴/苏州/杭州仓/连云港/温州/台州/南京/合肥
A37: 拆派 | B37: 萨凡纳直航48日达 | C37: {=IFERROR(VLOOKUP($C$5,美东南直航系列!$A:$CT,INDEX(定位!$A:$W,MATCH($B37,定位!$A:$A,0),MATCH("*"&$D$5&"*"&"-BS",定位!$1:$1,0)),FALSE),"-")} -> - | D37: {=IFERROR(VLOOKUP($C$5,美东南直航系列!$A:$CT,INDEX(定位!$A:$W,MATCH($B37,定位!$A:$A,0),MATCH("*"&$D$5&"*"&"-NBS",定位!$1:$1,0)),FALSE),"-")} -> - | E37: =IFERROR(VLOOKUP($C$5,美东南直航系列!$A:$CT,_xlfn.XLOOKUP($B37,定位!A:A,定位!V:V),FALSE),"-") -> - | F37: =IFERROR(VLOOKUP($C$5,美东南直航系列!$A:$CT,_xlfn.XLOOKUP(B37,定位!A:A,定位!W:W),FALSE),"-") -> - | G37: =IF(LEFT($C$5,3)<>"WM-","FBA卡派包税:【10-49KG:+1元/KG】","沃尔玛卡派包税: 【21-49KG:+2元/KG】； 【50-99KG:+1元/KG】；") -> FBA卡派包税:【10-49KG:+1元/KG】
A38: 拆派 | B38: 萨凡纳海陆24日达 | C38: {=IFERROR(VLOOKUP($C$5,美东南海陆系列!$A:$CP,INDEX(定位!$A:$W,MATCH($B38,定位!$A:$A,0),MATCH("*"&$D$5&"*"&"-BS",定位!$1:$1,0)),FALSE),"-")} -> - | D38: {=IFERROR(VLOOKUP($C$5,美东南海陆系列!$A:$CP,INDEX(定位!$A:$W,MATCH($B38,定位!$A:$A,0),MATCH("*"&$D$5&"*"&"-NBS",定位!$1:$1,0)),FALSE),"-")} -> - | E38: =IFERROR(VLOOKUP($C$5,美东南海陆系列!$A:$CP,_xlfn.XLOOKUP($B38,定位!A:A,定位!V:V),FALSE),"-") -> - | F38: =IFERROR(VLOOKUP($C$5,美东南海陆系列!$A:$CP,_xlfn.XLOOKUP(B38,定位!A:A,定位!W:W),FALSE),"-") -> - | G38: =IF(LEFT($C$5,3)<>"WM-","FBA卡派包税:【10-49KG:+1元/KG】","沃尔玛卡派包税: 【21-49KG:+2元/KG】； 【50-99KG:+1元/KG】；") -> FBA卡派包税:【10-49KG:+1元/KG】
A39: 拆派 | B39: 休斯顿海铁23日达 | C39: {=IFERROR(VLOOKUP($C$5,'美中-休斯顿'!$A:$BT,INDEX(定位!$A:$W,MATCH($B39,定位!$A:$A,0),MATCH("*"&$D$5&"*"&"-BS",定位!$1:$1,0)),FALSE),"-")} -> - | D39: {=IFERROR(VLOOKUP($C$5,'美中-休斯顿'!$A:$BT,INDEX(定位!$A:$W,MATCH($B39,定位!$A:$A,0),MATCH("*"&$D$5&"*"&"-NBS",定位!$1:$1,0)),FALSE),"-")} -> - | E39: =IFERROR(VLOOKUP($C$5,'美中-休斯顿'!$A:$BT,_xlfn.XLOOKUP($B39,定位!A:A,定位!V:V),FALSE),"-") -> - | F39: =IFERROR(VLOOKUP($C$5,'美中-休斯顿'!$A:$BT,_xlfn.XLOOKUP($B39,定位!A:A,定位!W:W),FALSE),"-") -> - | G39: =IF(LEFT($C$5,3)<>"WM-","FBA卡派包税:【10-49KG:+1元/KG】","沃尔玛卡派包税: 【21-49KG:+2元/KG】； 【50-99KG:+1元/KG】；") -> FBA卡派包税:【10-49KG:+1元/KG】
A40: 拆派 | B40: 休斯顿直航38日达 | C40: {=IFERROR(VLOOKUP($C$5,'美中-休斯顿'!$A:$BT,INDEX(定位!$A:$W,MATCH($B40,定位!$A:$A,0),MATCH("*"&$D$5&"*"&"-BS",定位!$1:$1,0)),FALSE),"-")} -> - | D40: {=IFERROR(VLOOKUP($C$5,'美中-休斯顿'!$A:$BT,INDEX(定位!$A:$W,MATCH($B40,定位!$A:$A,0),MATCH("*"&$D$5&"*"&"-NBS",定位!$1:$1,0)),FALSE),"-")} -> - | E40: =IFERROR(VLOOKUP($C$5,'美中-休斯顿'!$A:$BT,_xlfn.XLOOKUP($B40,定位!A:A,定位!V:V),FALSE),"-") -> - | F40: =IFERROR(VLOOKUP($C$5,'美中-休斯顿'!$A:$BT,_xlfn.XLOOKUP($B40,定位!A:A,定位!W:W),FALSE),"-") -> - | G40: =IF(LEFT($C$5,3)<>"WM-","FBA卡派包税:【10-49KG:+1元/KG】","沃尔玛卡派包税: 【21-49KG:+2元/KG】； 【50-99KG:+1元/KG】；") -> FBA卡派包税:【10-49KG:+1元/KG】
A41: 拆派 | B41: 芝加哥海铁28日达 | C41: {=IFERROR(VLOOKUP($C$5,'美中-芝加哥'!$A:$CX,INDEX(定位!$A:$W,MATCH($B41,定位!$A:$A,0),MATCH("*"&$D$5&"*"&"-BS",定位!$1:$1,0)),FALSE),"-")} -> - | D41: {=IFERROR(VLOOKUP($C$5,'美中-芝加哥'!$A:$CX,INDEX(定位!$A:$W,MATCH($B41,定位!$A:$A,0),MATCH("*"&$D$5&"*"&"-NBS",定位!$1:$1,0)),FALSE),"-")} -> - | E41: =IFERROR(VLOOKUP($C$5,'美中-芝加哥'!$A:$CX,_xlfn.XLOOKUP($B41,定位!A:A,定位!V:V),FALSE),"-") -> - | F41: =IFERROR(VLOOKUP($C$5,'美中-芝加哥'!$A:$CX,_xlfn.XLOOKUP($B41,定位!A:A,定位!W:W),FALSE),"-") -> - | G41: =IF(LEFT($C$5,3)<>"WM-","FBA卡派包税:【10-49KG:+1元/KG】","沃尔玛卡派包税: 【21-49KG:+2元/KG】； 【50-99KG:+1元/KG】；") -> FBA卡派包税:【10-49KG:+1元/KG】
A42: 拆派 | B42: 芝加哥海铁32日达 | C42: {=IFERROR(VLOOKUP($C$5,'美中-芝加哥'!$A:$CX,INDEX(定位!$A:$W,MATCH($B42,定位!$A:$A,0),MATCH("*"&$D$5&"*"&"-BS",定位!$1:$1,0)),FALSE),"-")} -> - | D42: {=IFERROR(VLOOKUP($C$5,'美中-芝加哥'!$A:$CX,INDEX(定位!$A:$W,MATCH($B42,定位!$A:$A,0),MATCH("*"&$D$5&"*"&"-NBS",定位!$1:$1,0)),FALSE),"-")} -> - | E42: =IFERROR(VLOOKUP($C$5,'美中-芝加哥'!$A:$CX,_xlfn.XLOOKUP($B42,定位!A:A,定位!V:V),FALSE),"-") -> - | F42: =IFERROR(VLOOKUP($C$5,'美中-芝加哥'!$A:$CX,_xlfn.XLOOKUP($B42,定位!A:A,定位!W:W),FALSE),"-") -> - | G42: =IF(LEFT($C$5,3)<>"WM-","FBA卡派包税:【10-49KG:+1元/KG】","沃尔玛卡派包税: 【21-49KG:+2元/KG】； 【50-99KG:+1元/KG】；") -> FBA卡派包税:【10-49KG:+1元/KG】
A43: 拆派 | B43: 芝加哥海铁22日达 | C43: {=IFERROR(VLOOKUP($C$5,'美中-芝加哥'!$A:$CX,INDEX(定位!$A:$W,MATCH($B43,定位!$A:$A,0),MATCH("*"&$D$5&"*"&"-BS",定位!$1:$1,0)),FALSE),"-")} -> - | D43: {=IFERROR(VLOOKUP($C$5,'美中-芝加哥'!$A:$CX,INDEX(定位!$A:$W,MATCH($B43,定位!$A:$A,0),MATCH("*"&$D$5&"*"&"-NBS",定位!$1:$1,0)),FALSE),"-")} -> - | E43: =IFERROR(VLOOKUP($C$5,'美中-芝加哥'!$A:$CX,_xlfn.XLOOKUP($B43,定位!A:A,定位!V:V),FALSE),"-") -> - | F43: =IFERROR(VLOOKUP($C$5,'美中-芝加哥'!$A:$CX,_xlfn.XLOOKUP($B43,定位!A:A,定位!W:W),FALSE),"-") -> - | G43: =IF(LEFT($C$5,3)<>"WM-","FBA卡派包税:【10-49KG:+1元/KG】","沃尔玛卡派包税: 【21-49KG:+2元/KG】； 【50-99KG:+1元/KG】；") -> FBA卡派包税:【10-49KG:+1元/KG】

Sheet 定位
A1: 渠道 | B1: 华南-BS | C1: 重庆-BS | D1: 汕头-BS | E1: 厦门/泉州/福州-BS | F1: 华东-BS | G1: 青岛/郑州/温州/台州/连云港/南京/合肥-BS | H1: 天津/南昌/石家庄-BS | I1: 济南/潍坊-BS | J1: 西安/沧州/保定-BS | K1: 武汉/长沙/成都-BS | L1: 华南-NBS | M1: 重庆-NBS | N1: 汕头-NBS | O1: 厦门/泉州/福州-NBS | P1: 华东-NBS | Q1: 青岛/郑州/温州/台州/连云港/南京/合肥-NBS | R1: 天津/南昌/石家庄-NBS | S1: 济南/潍坊-NBS | T1: 西安/沧州/保定-NBS | U1: 武汉/长沙/成都-NBS | V1: 签收时效 开船后-入仓时效 | W1: 延时赔付 开船后-不入仓时效
A2: 洛杉矶普船28日达直送 | B2: 2 | C2: 3 | D2: 4 | E2: 5 | F2: 6 | G2: 7 | H2: 8 | I2: 9 | J2: 10 | K2: 11 | L2: 12 | M2: 13 | N2: 14 | O2: 15 | P2: 16 | Q2: 17 | R2: 18 | S2: 19 | T2: 20 | U2: 21 | V2: 22 | W2: 23
A3: 洛杉矶OA26日达直送 | B3: =B2+22 -> 24 | C3: =C2+22 -> 25 | D3: =D2+22 -> 26 | E3: =E2+22 -> 27 | F3: =F2+22 -> 28 | G3: =G2+22 -> 29 | H3: =H2+22 -> 30 | I3: =I2+22 -> 31 | ... W3: =W2+22 -> 45
A4: 奥克兰OA29日达直送 | B4: =B3+22 -> 46 | C4: =C3+22 -> 47 | D4: =D3+22 -> 48 | E4: =E3+22 -> 49 | F4: =F3+22 -> 50 | G4: =G3+22 -> 51 | H4: =H3+22 -> 52 | I4: =I3+22 -> 53 | ... W4: =W3+22 -> 67
A5: 奥克兰普船36日达直送 | B5: =B4+22 -> 68 | C5: =C4+22 -> 69 | D5: =D4+22 -> 70 | E5: =E4+22 -> 71 | F5: =F4+22 -> 72 | G5: =G4+22 -> 73 | H5: =H4+22 -> 74 | I5: =I4+22 -> 75 | ... W5: =W4+22 -> 89
A6: 纽约直航42日达直送特价 | B6: 2 | C6: 3 | D6: 4 | E6: 5 | F6: 6 | G6: 7 | H6: 8 | I6: 9 | J6: 10 | K6: 11 | L6: 12 | M6: 13 | N6: 14 | O6: 15 | P6: 16 | Q6: 17 | R6: 18 | S6: 19 | T6: 20 | U6: 21 | V6: 22 | W6: 23
A7: 纽约直航38日达直送特价 | B7: =B6+22 -> 24 | C7: =C6+22 -> 25 | D7: =D6+22 -> 26 | E7: =E6+22 -> 27 | F7: =F6+22 -> 28 | G7: =G6+22 -> 29 | H7: =H6+22 -> 30 | I7: =I6+22 -> 31 | ... W7: =W6+22 -> 45
A8: 萨凡纳直航36日达直送 | B8: 2 | C8: 3 | D8: 4 | E8: 5 | F8: 6 | G8: 7 | H8: 8 | I8: 9 | J8: 10 | K8: 11 | L8: 12 | M8: 13 | N8: 14 | O8: 15 | P8: 16 | Q8: 17 | R8: 18 | S8: 19 | T8: 20 | U8: 21 | V8: 22 | W8: 23
A9: 萨凡纳直航48日达直送 | B9: =B8+22 -> 24 | C9: =C8+22 -> 25 | D9: =D8+22 -> 26 | E9: =E8+22 -> 27 | F9: =F8+22 -> 28 | G9: =G8+22 -> 29 | H9: =H8+22 -> 30 | I9: =I8+22 -> 31 | ... W9: =W8+22 -> 45
A10: 休斯顿海铁23日达直送特价 | B10: =B11+22 -> 24 | C10: =C11+22 -> 25 | D10: =D11+22 -> 26 | E10: =E11+22 -> 27 | F10: =F11+22 -> 28 | G10: =G11+22 -> 29 | H10: =H11+22 -> 30 | I10: =I11+22 -> 31 | ... W10: =W11+22 -> 45
A11: 休斯顿直航38日达直送特价 | B11: 2 | C11: 3 | D11: 4 | E11: 5 | F11: 6 | G11: 7 | H11: 8 | I11: 9 | J11: 10 | K11: 11 | L11: 12 | M11: 13 | N11: 14 | O11: 15 | P11: 16 | Q11: 17 | R11: 18 | S11: 19 | T11: 20 | U11: 21 | V11: 22 | W11: 23
A12: 芝加哥海铁28日达直送特价 | B12: 2 | C12: 3 | D12: 4 | E12: 5 | F12: 6 | G12: 7 | H12: 8 | I12: 9 | J12: 10 | K12: 11 | L12: 12 | M12: 13 | N12: 14 | O12: 15 | P12: 16 | Q12: 17 | R12: 18 | S12: 19 | T12: 20 | U12: 21 | V12: 22 | W12: 23
A13: 芝加哥海铁32日达直送特价 | B13: =B12+22 -> 24 | C13: =C12+22 -> 25 | D13: =D12+22 -> 26 | E13: =E12+22 -> 27 | F13: =F12+22 -> 28 | G13: =G12+22 -> 29 | H13: =H12+22 -> 30 | I13: =I12+22 -> 31 | ... W13: =W12+22 -> 45
A14: 芝加哥海铁22日达直送特价 | B14: =B13+22 -> 46 | C14: =C13+22 -> 47 | D14: =D13+22 -> 48 | E14: =E13+22 -> 49 | F14: =F13+22 -> 50 | G14: =G13+22 -> 51 | H14: =H13+22 -> 52 | I14: =I13+22 -> 53 | ... W14: =W13+22 -> 67
A15: 美森极速12日达 | B15: 2 | C15: 3 | D15: 4 | E15: 5 | F15: 6 | G15: 7 | H15: 8 | I15: 9 | J15: 10 | K15: 11 | L15: 12 | M15: 13 | N15: 14 | O15: 15 | P15: 16 | Q15: 17 | R15: 18 | S15: 19 | T15: 20 | U15: 21 | V15: 22 | W15: 23
A16: 洛杉矶CLX13日达 | B16: =B15+22 -> 24 | C16: =C15+22 -> 25 | D16: =D15+22 -> 26 | E16: =E15+22 -> 27 | F16: =F15+22 -> 28 | G16: =G15+22 -> 29 | H16: =H15+22 -> 30 | I16: =I15+22 -> 31 | ... W16: =W15+22 -> 45
A17: 洛杉矶MAX14日达 | B17: =B16+22 -> 46 | C17: =C16+22 -> 47 | D17: =D16+22 -> 48 | E17: =E16+22 -> 49 | F17: =F16+22 -> 50 | G17: =G16+22 -> 51 | H17: =H16+22 -> 52 | I17: =I16+22 -> 53 | ... W17: =W16+22 -> 67
A18: 洛杉矶EXX16日达 | B18: =B17+22 -> 68 | C18: =C17+22 -> 69 | D18: =D17+22 -> 70 | E18: =E17+22 -> 71 | F18: =F17+22 -> 72 | G18: =G17+22 -> 73 | H18: =H17+22 -> 74 | I18: =I17+22 -> 75 | ... W18: =W17+22 -> 89
A19: 洛杉矶17日达 | B19: =B18+22 -> 90 | C19: =C18+22 -> 91 | D19: =D18+22 -> 92 | E19: =E18+22 -> 93 | F19: =F18+22 -> 94 | G19: =G18+22 -> 95 | H19: =H18+22 -> 96 | I19: =I18+22 -> 97 | ... W19: =W18+22 -> 111
A20: 洛杉矶20日达 | B20: 2 | C20: 3 | D20: 4 | E20: 5 | F20: 6 | G20: 7 | H20: 8 | I20: 9 | J20: 10 | K20: 11 | L20: 12 | M20: 13 | N20: 14 | O20: 15 | P20: 16 | Q20: 17 | R20: 18 | S20: 19 | T20: 20 | U20: 21 | V20: 22 | W20: 23
A21: 洛杉矶22日达 | B21: =B20+22 -> 24 | C21: =C20+22 -> 25 | D21: =D20+22 -> 26 | E21: =E20+22 -> 27 | F21: =F20+22 -> 28 | G21: =G20+22 -> 29 | H21: =H20+22 -> 30 | I21: =I20+22 -> 31 | ... W21: =W20+22 -> 45
A22: 洛杉矶26日达 | B22: =B21+22 -> 46 | C22: =C21+22 -> 47 | D22: =D21+22 -> 48 | E22: =E21+22 -> 49 | F22: =F21+22 -> 50 | G22: =G21+22 -> 51 | H22: =H21+22 -> 52 | I22: =I21+22 -> 53 | ... W22: =W21+22 -> 67
A23: 奥克兰直航26日达 | B23: 2 | C23: 3 | D23: 4 | E23: 5 | F23: 6 | G23: 7 | H23: 8 | I23: 9 | J23: 10 | K23: 11 | L23: 12 | M23: 13 | N23: 14 | O23: 15 | P23: 16 | Q23: 17 | R23: 18 | S23: 19 | T23: 20 | U23: 21 | V23: 22 | W23: 23
A24: 奥克兰直航32日达 | B24: =B23+22 -> 24 | C24: =C23+22 -> 25 | D24: =D23+22 -> 26 | E24: =E23+22 -> 27 | F24: =F23+22 -> 28 | G24: =G23+22 -> 29 | H24: =H23+22 -> 30 | I24: =I23+22 -> 31 | ... W24: =W23+22 -> 45
A25: 西雅图直航29日达 | B25: =B24+22 -> 46 | C25: =C24+22 -> 47 | D25: =D24+22 -> 48 | E25: =E24+22 -> 49 | F25: =F24+22 -> 50 | G25: =G24+22 -> 51 | H25: =H24+22 -> 52 | I25: =I24+22 -> 53 | ... W25: =W24+22 -> 67
A26: 纽约直航42日达 | B26: 2 | C26: 3 | D26: 4 | E26: 5 | F26: 6 | G26: 7 | H26: 8 | I26: 9 | J26: 10 | K26: 11 | L26: 12 | M26: 13 | N26: 14 | O26: 15 | P26: 16 | Q26: 17 | R26: 18 | S26: 19 | T26: 20 | U26: 21 | V26: 22 | W26: 23
A27: 纽约直航38日达 | B27: =B26+22 -> 24 | C27: =C26+22 -> 25 | D27: =D26+22 -> 26 | E27: =E26+22 -> 27 | F27: =F26+22 -> 28 | G27: =G26+22 -> 29 | H27: =H26+22 -> 30 | I27: =I26+22 -> 31 | ... W27: =W26+22 -> 45
A28: 纽约海铁24日达 | B28: 2 | C28: 3 | D28: 4 | E28: 5 | F28: 6 | G28: 7 | H28: 8 | I28: 9 | J28: 10 | K28: 11 | L28: 12 | M28: 13 | N28: 14 | O28: 15 | P28: 16 | Q28: 17 | R28: 18 | S28: 19 | T28: 20 | U28: 21 | V28: 22 | W28: 23
A29: 纽约MAX海铁22日达 | B29: =B28+22 -> 24 | C29: =C28+22 -> 25 | D29: =D28+22 -> 26 | E29: =E28+22 -> 27 | F29: =F28+22 -> 28 | G29: =G28+22 -> 29 | H29: =H28+22 -> 30 | I29: =I28+22 -> 31 | ... W29: =W28+22 -> 45
A30: 纽约海铁30日达 | B30: =B29+22 -> 46 | C30: =C29+22 -> 47 | D30: =D29+22 -> 48 | E30: =E29+22 -> 49 | F30: =F29+22 -> 50 | G30: =G29+22 -> 51 | H30: =H29+22 -> 52 | I30: =I29+22 -> 53 | ... W30: =W29+22 -> 67
A31: 萨凡纳直航36日达 | B31: 2 | C31: 3 | D31: 4 | E31: 5 | F31: 6 | G31: 7 | H31: 8 | I31: 9 | J31: 10 | K31: 11 | L31: 12 | M31: 13 | N31: 14 | O31: 15 | P31: 16 | Q31: 17 | R31: 18 | S31: 19 | T31: 20 | U31: 21 | V31: 22 | W31: 23
A32: 萨凡纳直航48日达 | B32: =B31+22 -> 24 | C32: =C31+22 -> 25 | D32: =D31+22 -> 26 | E32: =E31+22 -> 27 | F32: =F31+22 -> 28 | G32: =G31+22 -> 29 | H32: =H31+22 -> 30 | I32: =I31+22 -> 31 | ... W32: =W31+22 -> 45
A33: 萨凡纳海陆24日达 | B33: 2 | C33: 3 | D33: 4 | E33: 5 | F33: 6 | G33: 7 | H33: 8 | I33: 9 | J33: 10 | K33: 11 | L33: 12 | M33: 13 | N33: 14 | O33: 15 | P33: 16 | Q33: 17 | R33: 18 | S33: 19 | T33: 20 | U33: 21 | V33: 22 | W33: 23
A34: 休斯顿海铁23日达 | B34: =B35+22 -> 24 | C34: =C35+22 -> 25 | D34: =D35+22 -> 26 | E34: =E35+22 -> 27 | F34: =F35+22 -> 28 | G34: =G35+22 -> 29 | H34: =H35+22 -> 30 | I34: =I35+22 -> 31 | ... W34: =W35+22 -> 45
A35: 休斯顿直航38日达 | B35: 2 | C35: 3 | D35: 4 | E35: 5 | F35: 6 | G35: 7 | H35: 8 | I35: 9 | J35: 10 | K35: 11 | L35: 12 | M35: 13 | N35: 14 | O35: 15 | P35: 16 | Q35: 17 | R35: 18 | S35: 19 | T35: 20 | U35: 21 | V35: 22 | W35: 23
A36: 芝加哥海铁28日达 | B36: 2 | C36: 3 | D36: 4 | E36: 5 | F36: 6 | G36: 7 | H36: 8 | I36: 9 | J36: 10 | K36: 11 | L36: 12 | M36: 13 | N36: 14 | O36: 15 | P36: 16 | Q36: 17 | R36: 18 | S36: 19 | T36: 20 | U36: 21 | V36: 22 | W36: 23
A37: 芝加哥海铁32日达 | B37: =B36+22 -> 24 | C37: =C36+22 -> 25 | D37: =D36+22 -> 26 | E37: =E36+22 -> 27 | F37: =F36+22 -> 28 | G37: =G36+22 -> 29 | H37: =H36+22 -> 30 | I37: =I36+22 -> 31 | ... W37: =W36+22 -> 45
A38: 芝加哥海铁22日达 | B38: =B37+22 -> 46 | C38: =C37+22 -> 47 | D38: =D37+22 -> 48 | E38: =E37+22 -> 49 | F38: =F37+22 -> 50 | G38: =G37+22 -> 51 | H38: =H37+22 -> 52 | I38: =I37+22 -> 53 | ... W38: =W37+22 -> 67
A39: 加拿大加东直航30日达-卡派 | B39: 2 | C39: 3 | D39: 4 | E39: 5 | F39: 6 | G39: 7 | H39: 8 | I39: 9 | J39: 10 | K39: 11 | L39: 12 | M39: 13 | N39: 14 | O39: 15 | P39: 16 | Q39: 17 | R39: 18 | S39: 19 | T39: 20 | U39: 21 | V39: 22 | W39: 23
A40: 加拿大加东直航30日达-UPS派 | B40: =B39+22 -> 24 | C40: =C39+22 -> 25 | D40: =D39+22 -> 26 | E40: =E39+22 -> 27 | F40: =F39+22 -> 28 | G40: =G39+22 -> 29 | H40: =H39+22 -> 30 | I40: =I39+22 -> 31 | ... K40: =K39+22 -> 33 | V40: =K40+1 -> 34 | W40: =V40+1 -> 35
A41: 加拿大加西直航30日达-卡派 | B41: =W40+1 -> 36 | C41: =B41+1 -> 37 | D41: =C41+1 -> 38 | E41: =D41+1 -> 39 | F41: =E41+1 -> 40 | G41: =F41+1 -> 41 | H41: =G41+1 -> 42 | I41: =H41+1 -> 43 | J41: =I41+1 -> 44 | ... W41: =V41+1 -> 57
A42: 加拿大加西直航30日达-UPS派 | B42: =B41+22 -> 58 | C42: =C41+22 -> 59 | D42: =D41+22 -> 60 | E42: =E41+22 -> 61 | F42: =F41+22 -> 62 | G42: =G41+22 -> 63 | H42: =H41+22 -> 64 | I42: =I41+22 -> 65 | ... K42: =K41+22 -> 67 | V42: =K42+1 -> 68 | W42: =V42+1 -> 69
A43: 加拿大加东直航33日达-卡派 | B43: 2 | C43: 3 | D43: 4 | E43: 5 | F43: 6 | G43: 7 | H43: 8 | I43: 9 | J43: 10 | K43: 11 | L43: 12 | M43: 13 | N43: 14 | O43: 15 | P43: 16 | Q43: 17 | R43: 18 | S43: 19 | T43: 20 | U43: 21 | V43: 22 | W43: 23
A44: 加拿大加东直航33日达-UPS派 | B44: =B43+22 -> 24 | C44: =C43+22 -> 25 | D44: =D43+22 -> 26 | E44: =E43+22 -> 27 | F44: =F43+22 -> 28 | G44: =G43+22 -> 29 | H44: =H43+22 -> 30 | I44: =I43+22 -> 31 | ... K44: =K43+22 -> 33 | V44: =K44+1 -> 34 | W44: =V44+1 -> 35
A45: 加拿大加西直航33日达-卡派 | B45: =W44+1 -> 36 | C45: =B45+1 -> 37 | D45: =C45+1 -> 38 | E45: =D45+1 -> 39 | F45: =E45+1 -> 40 | G45: =F45+1 -> 41 | H45: =G45+1 -> 42 | I45: =H45+1 -> 43 | J45: =I45+1 -> 44 | ... W45: =V45+1 -> 57
A46: 加拿大加西直航33日达-UPS派 | B46: =B45+22 -> 58 | C46: =C45+22 -> 59 | D46: =D45+22 -> 60 | E46: =E45+22 -> 61 | F46: =F45+22 -> 62 | G46: =G45+22 -> 63 | H46: =H45+22 -> 64 | I46: =I45+22 -> 65 | ... K46: =K45+22 -> 67 | V46: =K46+1 -> 68 | W46: =V46+1 -> 69
A47: 美转加加东25日达-卡派（OA） | B47: 2 | C47: 3 | D47: 4 | E47: 5 | F47: 6 | G47: 7 | H47: 8 | I47: 9 | J47: 10 | K47: 11 | L47: 12 | M47: 13 | N47: 14 | O47: 15 | P47: 16 | Q47: 17 | R47: 18 | S47: 19 | T47: 20 | U47: 21 | V47: 22 | W47: 23
A48: 美转加加东25日达-UPS派（OA） | B48: =B47+22 -> 24 | C48: =C47+22 -> 25 | D48: =D47+22 -> 26 | E48: =E47+22 -> 27 | F48: =F47+22 -> 28 | G48: =G47+22 -> 29 | H48: =H47+22 -> 30 | I48: =I47+22 -> 31 | ... K48: =K47+22 -> 33 | V48: =K48+1 -> 34 | W48: =V48+1 -> 35
A49: 美转加加西25日达-卡派（OA） | B49: =W48+1 -> 36 | C49: =B49+1 -> 37 | D49: =C49+1 -> 38 | E49: =D49+1 -> 39 | F49: =E49+1 -> 40 | G49: =F49+1 -> 41 | H49: =G49+1 -> 42 | I49: =H49+1 -> 43 | J49: =I49+1 -> 44 | ... W49: =V49+1 -> 57
A50: 美转加加西25日达-UPS派（OA） | B50: =B49+22 -> 58 | C50: =C49+22 -> 59 | D50: =D49+22 -> 60 | E50: =E49+22 -> 61 | F50: =F49+22 -> 62 | G50: =G49+22 -> 63 | H50: =H49+22 -> 64 | I50: =I49+22 -> 65 | ... K50: =K49+22 -> 67 | V50: =K50+1 -> 68 | W50: =V50+1 -> 69
A51: 美转加加东20日达-卡派（HD） | B51: 2 | C51: 3 | D51: 4 | E51: 5 | F51: 6 | G51: 7 | H51: 8 | I51: 9 | J51: 10 | K51: 11 | L51: 12 | M51: 13 | N51: 14 | O51: 15 | P51: 16 | Q51: 17 | R51: 18 | S51: 19 | T51: 20 | U51: 21 | V51: 22 | W51: 23
A52: 美转加加东20日达-UPS派（HD） | B52: =B51+22 -> 24 | C52: =C51+22 -> 25 | D52: =D51+22 -> 26 | E52: =E51+22 -> 27 | F52: =F51+22 -> 28 | G52: =G51+22 -> 29 | H52: =H51+22 -> 30 | I52: =I51+22 -> 31 | ... K52: =K51+22 -> 33 | V52: =K52+1 -> 34 | W52: =V52+1 -> 35
A53: 美转加加西20日达-卡派（HD） | B53: =W52+1 -> 36 | C53: =B53+1 -> 37 | D53: =C53+1 -> 38 | E53: =D53+1 -> 39 | F53: =E53+1 -> 40 | G53: =F53+1 -> 41 | H53: =G53+1 -> 42 | I53: =H53+1 -> 43 | J53: =I53+1 -> 44 | ... W53: =V53+1 -> 57
A54: 美转加加西20日达-UPS派（HD） | B54: =B53+22 -> 58 | C54: =C53+22 -> 59 | D54: =D53+22 -> 60 | E54: =E53+22 -> 61 | F54: =F53+22 -> 62 | G54: =G53+22 -> 63 | H54: =H53+22 -> 64 | I54: =I53+22 -> 65 | ... K54: =K53+22 -> 67 | V54: =K54+1 -> 68 | W54: =V54+1 -> 69
A55: 美转加加东19日达-卡派（EXX） | B55: 2 | C55: 3 | D55: 4 | E55: 5 | F55: 6 | G55: 7 | H55: 8 | I55: 9 | J55: 10 | K55: 11 | L55: 12 | M55: 13 | N55: 14 | O55: 15 | P55: 16 | Q55: 17 | R55: 18 | S55: 19 | T55: 20 | U55: 21 | V55: 22 | W55: 23
A56: 美转加加东19日达-UPS派（EXX） | B56: =B55+22 -> 24 | C56: =C55+22 -> 25 | D56: =D55+22 -> 26 | E56: =E55+22 -> 27 | F56: =F55+22 -> 28 | G56: =G55+22 -> 29 | H56: =H55+22 -> 30 | I56: =I55+22 -> 31 | ... K56: =K55+22 -> 33 | V56: =K56+1 -> 34 | W56: =V56+1 -> 35
A57: 美转加加西19日达-卡派（EXX） | B57: =W56+1 -> 36 | C57: =B57+1 -> 37 | D57: =C57+1 -> 38 | E57: =D57+1 -> 39 | F57: =E57+1 -> 40 | G57: =F57+1 -> 41 | H57: =G57+1 -> 42 | I57: =H57+1 -> 43 | J57: =I57+1 -> 44 | ... W57: =V57+1 -> 57
A58: 美转加加西19日达-UPS派（EXX） | B58: =B57+22 -> 58 | C58: =C57+22 -> 59 | D58: =D57+22 -> 60 | E58: =E57+22 -> 61 | F58: =F57+22 -> 62 | G58: =G57+22 -> 63 | H58: =H57+22 -> 64 | I58: =I57+22 -> 65 | ... K58: =K57+22 -> 67 | V58: =K58+1 -> 68 | W58: =V58+1 -> 69
A59: 美转加MAX加东17日达-卡派 | B59: 2 | C59: 3 | D59: 4 | E59: 5 | F59: 6 | G59: 7 | H59: 8 | I59: 9 | J59: 10 | K59: 11 | L59: 12 | M59: 13 | N59: 14 | O59: 15 | P59: 16 | Q59: 17 | R59: 18 | S59: 19 | T59: 20 | U59: 21 | V59: 22 | W59: 23
A60: 美转加MAX加东17日达-UPS派 | B60: =B59+22 -> 24 | C60: =C59+22 -> 25 | D60: =D59+22 -> 26 | E60: =E59+22 -> 27 | F60: =F59+22 -> 28 | G60: =G59+22 -> 29 | H60: =H59+22 -> 30 | I60: =I59+22 -> 31 | ... K60: =K59+22 -> 33 | V60: =K60+1 -> 34 | W60: =V60+1 -> 35
A61: 美转加MAX加西17日达-卡派 | B61: =W60+1 -> 36 | C61: =B61+1 -> 37 | D61: =C61+1 -> 38 | E61: =D61+1 -> 39 | F61: =E61+1 -> 40 | G61: =F61+1 -> 41 | H61: =G61+1 -> 42 | I61: =H61+1 -> 43 | J61: =I61+1 -> 44 | ... W61: =V61+1 -> 57
A62: 美转加MAX加西17日达-UPS派 | B62: =B61+22 -> 58 | C62: =C61+22 -> 59 | D62: =D61+22 -> 60 | E62: =E61+22 -> 61 | F62: =F61+22 -> 62 | G62: =G61+22 -> 63 | H62: =H61+22 -> 64 | I62: =I61+22 -> 65 | ... K62: =K61+22 -> 67 | V62: =K62+1 -> 68 | W62: =V62+1 -> 69
A63: 美转加CLX加东16日达-卡派 | B63: 2 | C63: 3 | D63: 4 | E63: 5 | F63: 6 | G63: 7 | H63: 8 | I63: 9 | J63: 10 | K63: 11 | L63: 12 | M63: 13 | N63: 14 | O63: 15 | P63: 16 | Q63: 17 | R63: 18 | S63: 19 | T63: 20 | U63: 21 | V63: 22 | W63: 23
A64: 美转加CLX加东16日达-UPS派 | B64: =B63+22 -> 24 | C64: =C63+22 -> 25 | D64: =D63+22 -> 26 | E64: =E63+22 -> 27 | F64: =F63+22 -> 28 | G64: =G63+22 -> 29 | H64: =H63+22 -> 30 | I64: =I63+22 -> 31 | ... K64: =K63+22 -> 33 | V64: =K64+1 -> 34 | W64: =V64+1 -> 35
A65: 美转加CLX加西16日达-卡派 | B65: =W64+1 -> 36 | C65: =B65+1 -> 37 | D65: =C65+1 -> 38 | E65: =D65+1 -> 39 | F65: =E65+1 -> 40 | G65: =F65+1 -> 41 | H65: =G65+1 -> 42 | I65: =H65+1 -> 43 | J65: =I65+1 -> 44 | ... W65: =V65+1 -> 57
A66: 美转加CLX加西16日达-UPS派 | B66: =B65+22 -> 58 | C66: =C65+22 -> 59 | D66: =D65+22 -> 60 | E66: =E65+22 -> 61 | F66: =F65+22 -> 62 | G66: =G65+22 -> 63 | H66: =H65+22 -> 64 | I66: =I65+22 -> 65 | ... K66: =K65+22 -> 67 | V66: =K66+1 -> 68 | W66: =V66+1 -> 69

Sheet 偏远邮编库
A1: 快递类型 | B1: 邮编 | C1: 地址类型 | E1: 快递类型 | F1: 邮编 | G1: 地址类型 | I1: 快递类型 | J1: 邮编（From） | K1: 邮编（To） | L1: 地址类型
A2: UPS | B2: 1002 | C2: 偏远 | E2: FEDEX | F2: 1002 | G2: 偏远 | I2: UPS | J2: A0A0A0 | K2: A0K1M0 | L2: 偏远
A3: UPS | B3: 1380 | C3: 偏远 | E3: FEDEX | F3: 1007 | G3: 偏远 | I3: UPS | J3: A0K1N0 | K3: A0K1N0 | L3: 偏远
A4: UPS | B4: 1741 | C4: 偏远 | E4: FEDEX | F4: 1010 | G4: 偏远 | I4: UPS | J4: A0K1P0 | K4: A0K1S0 | L4: 偏远
A5: UPS | B5: 2114 | C5: 偏远 | E5: FEDEX | F5: 1029 | G5: 偏远 | I5: UPS | J5: A0K1T0 | K5: A0K1V0 | L5: 偏远
A6: UPS | B6: 2662 | C6: 偏远 | E6: FEDEX | F6: 1032 | G6: 偏远 | I6: UPS | J6: A0K1W0 | K6: A0K2N0 | L6: 偏远
A7: UPS | B7: 3033 | C7: 偏远 | E7: FEDEX | F7: 1033 | G7: 偏远 | I7: UPS | J7: A0K2P0 | K7: A0K2P0 | L7: 偏远
A8: UPS | B8: 3469 | C8: 偏远 | E8: FEDEX | F8: 1036 | G8: 偏远 | I8: UPS | J8: A0K2V0 | K8: A0K3H0 | L8: 偏远
A9: UPS | B9: 3907 | C9: 偏远 | E9: FEDEX | F9: 1038 | G9: 偏远 | I9: UPS | J9: A0K3K0 | K9: A0K3L0 | L9: 偏远
A10: UPS | B10: 4270 | C10: 偏远 | E10: FEDEX | F10: 1039 | G10: 偏远 | I10: UPS | J10: A0K3M0 | K10: A0K3N0 | L10: 偏远
A11: UPS | B11: 4690 | C11: 偏远 | E11: FEDEX | F11: 1056 | G11: 偏远 | I11: UPS | J11: A0K3P0 | K11: A0K3P0 | L11: 偏远
A12: UPS | B12: 5158 | C12: 偏远 | E12: FEDEX | F12: 1057 | G12: 偏远 | I12: UPS | J12: A0K3R0 | K12: A0K3X0 | L12: 偏远
A13: UPS | B13: 5740 | C13: 偏远 | E13: FEDEX | F13: 1069 | G13: 偏远 | I13: UPS | J13: A0K3Y0 | K13: A0K3Y0 | L13: 偏远
... A2115: UPS | B2115: 24083 | C2115: 偏远 | E2115: FEDEX | F2115: 20676 | G2115: 偏远 | I2115: UPS | J2115: Y1A0A1 | K2115: Y1A9Z0 | L2115: 偏远
A2116: UPS | B2116: 24441 | C2116: 偏远 | E2116: FEDEX | F2116: 20677 | G2116: 偏远
A2117: UPS | B2117: 18070 | C2117: 偏远 | E2117: FEDEX | F2117: 20678 | G2117: 偏远
A2118: UPS | B2118: 18337 | C2118: 偏远 | E2118: FEDEX | F2118: 20684 | G2118: 偏远
A2119: UPS | B2119: 18654 | C2119: 偏远 | E2119: FEDEX | F2119: 20688 | G2119: 偏远
A2120: UPS | B2120: 19362 | C2120: 偏远 | E2120: FEDEX | F2120: 20689 | G2120: 偏远
A2121: UPS | B2121: 19640 | C2121: 偏远 | E2121: FEDEX | F2121: 20690 | G2121: 偏远
A2122: UPS | B2122: 20138 | C2122: 偏远 | E2122: FEDEX | F2122: 20693 | G2122: 偏远
A2123: UPS | B2123: 20660 | C2123: 偏远 | E2123: FEDEX | F2123: 20695 | G2123: 偏远
A2124: UPS | B2124: 21028 | C2124: 偏远 | E2124: FEDEX | F2124: 20711 | G2124: 偏远
A2125: UPS | B2125: 21620 | C2125: 偏远 | E2125: FEDEX | F2125: 20732 | G2125: 偏远
A2126: UPS | B2126: 21773 | C2126: 偏远 | E2126: FEDEX | F2126: 20733 | G2126: 偏远
A2127: UPS | B2127: 22451 | C2127: 偏远 | E2127: FEDEX | F2127: 20736 | G2127: 偏远
... A22912: UPS | B22912: 36016 | C22912: 无服务 | E22912: FEDEX | F22912: 41257 | G22912: 无服务
A22913: UPS | B22913: Effective June 1, 2025 | C22913: 无服务 | E22913: FEDEX | F22913: 41317 | G22913: 无服务
A22914: UPS | B22914: Remote US 48 ZIP Codes | C22914: 无服务 | E22914: FEDEX | F22914: 41339 | G22914: 无服务
A22915: UPS | B22915: 36017 | C22915: 无服务 | E22915: FEDEX | F22915: 41348 | G22915: 无服务
A22916: UPS | B22916: 36556 | C22916: 无服务 | E22916: FEDEX | F22916: 41351 | G22916: 无服务
A22917: UPS | B22917: 37301 | C22917: 无服务 | E22917: FEDEX | F22917: 41352 | G22917: 无服务
A22918: UPS | B22918: 38477 | C22918: 无服务 | E22918: FEDEX | F22918: 41385 | G22918: 无服务
A22919: UPS | B22919: 39045 | C22919: 无服务 | E22919: FEDEX | F22919: 41425 | G22919: 无服务
A22920: UPS | B22920: 39740 | C22920: 无服务 | E22920: FEDEX | F22920: 41464 | G22920: 无服务
A22921: UPS | B22921: 40858 | C22921: 无服务 | E22921: FEDEX | F22921: 41472 | G22921: 无服务
A22922: UPS | B22922: 41714 | C22922: 无服务 | E22922: FEDEX | F22922: 41534 | G22922: 无服务
A22923: UPS | B22923: 43156 | C22923: 无服务 | E22923: FEDEX | F22923: 41632 | G22923: 无服务
A22924: UPS | B22924: 47946 | C22924: 无服务 | E22924: FEDEX | F22924: 41712 | G22924: 无服务
A22925: UPS | B22925: 50275 | C22925: 无服务 | E22925: FEDEX | F22925: 41713 | G22925: 无服务
A22926: UPS | B22926: 54517 | C22926: 无服务 | E22926: FEDEX | F22926: 41714 | G22926: 无服务
... A23529: UPS | B23529: 57639 | C23529: 无服务 | E23529: FEDEX | F23529: 59339 | G23529: 无服务
A23530: UPS | B23530: Effective June 1, 2025 | C23530: 无服务 | E23530: FEDEX | F23530: 59341 | G23530: 无服务
A23531: UPS | B23531: Remote US 48 ZIP Codes | C23531: 无服务 | E23531: FEDEX | F23531: 59343 | G23531: 无服务
A23532: UPS | B23532: 57641 | C23532: 无服务 | E23532: FEDEX | F23532: 59344 | G23532: 无服务
A23533: UPS | B23533: 57792 | C23533: 无服务 | E23533: FEDEX | F23533: 59345 | G23533: 无服务
A23534: UPS | B23534: 58386 | C23534: 无服务 | E23534: FEDEX | F23534: 59347 | G23534: 无服务
A23535: UPS | B23535: 58535 | C23535: 无服务 | E23535: FEDEX | F23535: 59349 | G23535: 无服务
A23536: UPS | B23536: 58771 | C23536: 无服务 | E23536: FEDEX | F23536: 59351 | G23536: 无服务
A23537: UPS | B23537: 59050 | C23537: 无服务 | E23537: FEDEX | F23537: 59353 | G23537: 无服务
A23538: UPS | B23538: 59247 | C23538: 无服务 | E23538: FEDEX | F23538: 59354 | G23538: 无服务
A23539: UPS | B23539: 59416 | C23539: 无服务 | E23539: FEDEX | F23539: 59410 | G23539: 无服务
A23540: UPS | B23540: 59538 | C23540: 无服务 | E23540: FEDEX | F23540: 59411 | G23540: 无服务
A23541: UPS | B23541: 59859 | C23541: 无服务 | E23541: FEDEX | F23541: 59416 | G23541: 无服务
A23542: UPS | B23542: 62898 | C23542: 无服务 | E23542: FEDEX | F23542: 59418 | G23542: 无服务
A23543: UPS | B23543: 63784 | C23543: 无服务 | E23543: FEDEX | F23543: 59419 | G23543: 无服务
... A24146: UPS | B24146: 67109 | C24146: 无服务 | E24146: FEDEX | F24146: 72328 | G24146: 无服务
A24147: UPS | B24147: Effective June 1, 2025 | C24147: 无服务 | E24147: FEDEX | F24147: 72367 | G24147: 无服务
A24148: UPS | B24148: Remote US 48 ZIP Codes | C24148: 无服务 | E24148: FEDEX | F24148: 72368 | G24148: 无服务
A24149: UPS | B24149: 67122 | C24149: 无服务 | E24149: FEDEX | F24149: 72379 | G24149: 无服务
A24150: UPS | B24150: 67736 | C24150: 无服务 | E24150: FEDEX | F24150: 72394 | G24150: 无服务
A24151: UPS | B24151: 68753 | C24151: 无服务 | E24151: FEDEX | F24151: 72410 | G24151: 无服务
A24152: UPS | B24152: 69046 | C24152: 无服务 | E24152: FEDEX | F24152: 72421 | G24152: 无服务
A24153: UPS | B24153: 69345 | C24153: 无服务 | E24153: FEDEX | F24153: 72424 | G24153: 无服务
A24154: UPS | B24154: 71326 | C24154: 无服务 | E24154: FEDEX | F24154: 72425 | G24154: 无服务
A24155: UPS | B24155: 71935 | C24155: 无服务 | E24155: FEDEX | F24155: 72428 | G24155: 无服务
A24156: UPS | B24156: 72459 | C24156: 无服务 | E24156: FEDEX | F24156: 72459 | G24156: 无服务
A24157: UPS | B24157: 72686 | C24157: 无服务 | E24157: FEDEX | F24157: 72465 | G24157: 无服务
A24158: UPS | B24158: 73544 | C24158: 无服务 | E24158: FEDEX | F24158: 72466 | G24158: 无服务
A24159: UPS | B24159: 74029 | C24159: 无服务 | E24159: FEDEX | F24159: 72482 | G24159: 无服务
A24160: UPS | B24160: 74735 | C24160: 无服务 | E24160: FEDEX | F24160: 72512 | G24160: 无服务
... A24763: UPS | B24763: 76885 | C24763: 无服务 | E24763: FEDEX | F24763: 82210 | G24763: 无服务
A24764: UPS | B24764: Effective June 1, 2025 | C24764: 无服务 | E24764: FEDEX | F24764: 82213 | G24764: 无服务
A24765: UPS | B24765: Remote US 48 ZIP Codes | C24765: 无服务 | E24765: FEDEX | F24765: 82217 | G24765: 无服务
A24766: UPS | B24766: 76887 | C24766: 无服务 | E24766: FEDEX | F24766: 82218 | G24766: 无服务
A24767: UPS | B24767: 78019 | C24767: 无服务 | E24767: FEDEX | F24767: 82219 | G24767: 无服务
A24768: UPS | B24768: 78932 | C24768: 无服务 | E24768: FEDEX | F24768: 82222 | G24768: 无服务
A24769: UPS | B24769: 79330 | C24769: 无服务 | E24769: FEDEX | F24769: 82223 | G24769: 无服务
A24770: UPS | B24770: 80447 | C24770: 无服务 | E24770: FEDEX | F24770: 82224 | G24770: 无服务
A24771: UPS | B24771: 80834 | C24771: 无服务 | E24771: FEDEX | F24771: 82229 | G24771: 无服务
A24772: UPS | B24772: 81220 | C24772: 无服务 | E24772: FEDEX | F24772: 82243 | G24772: 无服务
A24773: UPS | B24773: 82229 | C24773: 无服务 | E24773: FEDEX | F24773: 82244 | G24773: 无服务
A24774: UPS | B24774: 82936 | C24774: 无服务 | E24774: FEDEX | F24774: 82310 | G24774: 无服务
A24775: UPS | B24775: 83525 | C24775: 无服务 | E24775: FEDEX | F24775: 82322 | G24775: 无服务
A24776: UPS | B24776: 84313 | C24776: 无服务 | E24776: FEDEX | F24776: 82329 | G24776: 无服务
A24777: UPS | B24777: 85354 | C24777: 无服务 | E24777: FEDEX | F24777: 82334 | G24777: 无服务
... A25380: UPS | B25380: 88034 | C25380: 无服务 | E25380: FEDEX | F25380: 96132 | G25380: 无服务
A25381: UPS | B25381: Effective June 1, 2025 | C25381: 无服务 | E25381: FEDEX | F25381: 96136 | G25381: 无服务
A25382: UPS | B25382: Remote US 48 ZIP Codes | C25382: 无服务 | E25382: FEDEX | F25382: 96142 | G25382: 无服务
A25383: UPS | B25383: 88038 | C25383: 无服务 | E25383: FEDEX | F25383: 97001 | G25383: 无服务
A25384: UPS | B25384: 88418 | C25384: 无服务 | E25384: FEDEX | F25384: 97021 | G25384: 无服务
A25385: UPS | B25385: 89438 | C25385: 无服务 | E25385: FEDEX | F25385: 97028 | G25385: 无服务
A25386: UPS | B25386: 93252 | C25386: 无服务 | E25386: FEDEX | F25386: 97029 | G25386: 无服务
A25387: UPS | B25387: 93930 | C25387: 无服务 | E25387: FEDEX | F25387: 97033 | G25387: 无服务
A25388: UPS | B25388: 95466 | C25388: 无服务 | E25388: FEDEX | F25388: 97040 | G25388: 无服务
A25389: UPS | B25389: 96017 | C25389: 无服务 | E25389: FEDEX | F25389: 97063 | G25389: 无服务
A25390: UPS | B25390: 97028 | C25390: 无服务 | E25390: FEDEX | F25390: 97118 | G25390: 无服务
A25391: UPS | B25391: 97634 | C25391: 无服务 | E25391: FEDEX | F25391: 97125 | G25391: 无服务
A25392: UPS | B25392: 97910 | C25392: 无服务 | E25392: FEDEX | F25392: 97143 | G25392: 无服务
A25393: UPS | B25393: 98817 | C25393: 无服务 | E25393: FEDEX | F25393: 97324 | G25393: 无服务
...

Sheet 出运计划-海运
B2: 出运计划（海运）-WEEK 26
B3: Shipping Schedule
A5: 线路 | B5: 渠道名称 | C5: 起运港 | D5: 预配船公司 | E5: 船名航次 | F5: 装柜地点 | G5: 目的港 | H5: 码头 | I5: 预计 开船 | J5: 预计到港 | K5: 船期 | L5: 本周截单时间&截补料时间（截止拣货时间） | AB5: 备注
L6: 华南 | S6: 华中 | T6: 华东 | AA6: 转货时间需预留40个小时
L7: 塘厦 | M7: 东莞南城 | N7: 福永/惠州 | O7: 广州 | P7: 中山 | Q7: 汕头 | R7: 厦门/泉州/福州 | S7: 武汉/长沙 | T7: 义乌 | U7: 上海 | V7: 宁波 | W7: 青岛 | X7: 郑州/苏州/杭州/绍兴/温州/台州/南昌 | Y7: 成都/重庆 | Z7: 南京/合肥 | AA7: 天津/石家庄/连云港/西安/沧州/保定/济南/潍坊仓
A8: 英国 | B8: 英国海派限时达 （AEU1线） | C8: 盐田 | D8: COSCO/EMC | E8: XIN LIAN YUN GANG 009W | F8: 东莞/广州 | G8: 费利克斯托 | H8: LANDGUARD | I8: 46200 | J8: 46236 | K8: =J8-I8 -> 36 | L8: 周五 18:00 | M8: 周五 12:00 | N8: 周五 15:00 | O8: 周五 12:00 | P8: 周五 12:00 | Q8: 周四 12:00 | R8: 周二 18:00 | S8: 周三18:00 | T8: - | V8: - | W8: 周二 18:00 | X8: 周二 18:00 | Y8: 周三18:00
C9: 盐田 | D9: COSCO/EMC AEU1空班替换AEU7 | E9: COSCO SHIPPING ANDES 048W(AEU7) | F9: 东莞/广州 | G9: 费利克斯托 | H9: LANDGUARD | I9: 46201 | J9: 46234 | K9: =J9-I9 -> 33 | L9: 周五 18:00 | M9: 周五 12:00 | N9: 周五 15:00 | O9: 周五 12:00 | P9: 周五 12:00 | Q9: 周四 12:00 | R9: 周二 18:00 | S9: 周三18:00 | T9: - | V9: - | W9: 周二 18:00 | X9: 周二 18:00 | Y9: 周三18:00
C10: 盐田 | D10: COSCO/EMC | E10: OOCL ZEEBRUGGE 010W | F10: 东莞/广州 | G10: 费利克斯托 | H10: LANDGUARD | I10: 46208 | J10: 46243 | K10: =J10-I10 -> 35 | L10: 下周五 18:00 | M10: 下周五 12:00 | N10: 下周五 15:00 | O10: 下周五 12:00 | P10: 下周五 12:00 | Q10: 下周四 12:00 | R10: 下周二 18:00 | S10: 下周三18:00 | T10: - | V10: - | W10: 下周二 18:00 | X10: 下周二 18:00 | Y10: 下周三18:00
B11: 英国海派&卡派 AEU1线 | C11: 盐田 | D11: COSCO/EMC | E11: XIN LIAN YUN GANG 009W | F11: 东莞/广州 | G11: 费利克斯托 | H11: LANDGUARD | I11: 46200 | J11: 46236 | K11: =J11-I11 -> 36 | L11: 周四 18:00 | M11: 周四 12:00 | N11: 周四 15:00 | O11: 周四 12:00 | P11: 周四 12:00 | Q11: 周三 12:00 | R11: 周一 18:00 | S11: 周二 18:00 | T11: - | V11: - | W11: 周一 18:00 | X11: 周一 18:00 | Y11: 周二 18:00
C12: 盐田 | D12: COSCO/EMC AEU1空班替换AEU7 | E12: COSCO SHIPPING ANDES 048W(AEU7) | F12: 东莞/广州 | G12: 费利克斯托 | H12: LANDGUARD | I12: 46201 | J12: 46234 | K12: =J12-I12 -> 33 | L12: 周四 18:00 | M12: 周四 12:00 | N12: 周四 15:00 | O12: 周四 12:00 | P12: 周四 12:00 | Q12: 周三 12:00 | R12: 周一 18:00 | S12: 周二 18:00 | T12: - | V12: - | W12: 周一 18:00 | X12: 周一 18:00 | Y12: 周二 18:00
C13: 盐田 | D13: COSCO/EMC | E13: OOCL ZEEBRUGGE 010W | F13: 东莞/广州 | G13: 费利克斯托 | H13: LANDGUARD | I13: 46208 | J13: 46243 | K13: =J13-I13 -> 35 | L13: 下周四 18:00 | M13: 下周四 12:00 | N13: 下周四 15:00 | O13: 下周四 12:00 | P13: 下周四 12:00 | Q13: 下周三 12:00 | R13: 下周一 18:00 | S13: 下周二 18:00 | T13: - | V13: - | W13: 下周一 18:00 | X13: 下周一 18:00 | Y13: 下周二 18:00
C14: 宁波 | D14: COSCO/EMC | E14: OOCL ZEEBRUGGE 010W(AEU1) | F14: 义乌 | G14: 费利克斯托 | H14: LANDGUARD | I14: 46204 | J14: 46243 | K14: =J14-I14 -> 39 | L14: - | M14: - | N14: - | O14: - | P14: - | R14: - | S14: - | T14: 周五 18:00 | V14: 周四 18:00 | W14: - | X14: - | Y14: -
C15: 宁波 | D15: COSCO/EMC | E15: OOCL WISDOM 001W | F15: 义乌 | G15: 费利克斯托 | H15: LANDGUARD | I15: 46211 | J15: 46250 | K15: =J15-I15 -> 39 | L15: - | M15: - | N15: - | O15: - | P15: - | R15: - | S15: - | T15: 下周五 18:00 | V15: 下周四 18:00 | W15: - | X15: - | Y15: -
C16: 厦门 | D16: COSCO/EMC | E16: OOCL ZEEBRUGGE 010W | F16: 厦门 | G16: 费利克斯托 | H16: LANDGUARD | I16: 46206 | J16: 46243 | K16: =J16-I16 -> 37 | L16: - | M16: - | N16: - | O16: - | P16: - | Q16: - | R16: 周二18：00 | S16: - | T16: - | V16: - | W16: - | X16: - | Y16: -
C17: 厦门 | D17: COSCO/EMC | E17: OOCL WISDOM 001W | F17: 厦门 | G17: 费利克斯托 | H17: LANDGUARD | I17: 46214 | J17: 46250 | K17: =J17-I17 -> 36 | L17: - | M17: - | N17: - | O17: - | P17: - | Q17: - | R17: 下周二18：00 | S17: - | T17: - | V17: - | W17: - | X17: - | Y17: -
A18: 美转加 | B18: 美转加25日达 | C18: 盐田 | D18: COSCO | E18: OOCL VIOLET 010E | F18: 东莞/广州 | G18: 长滩 | H18: LBCT | I18: 46205 | J18: 46220 | K18: =J18-I18 -> 15 | L18: 周六 | M18: 周六 | N18: 周六 | O18: 周六 | P18: 周六 | Q18: 周五 | R18: 周五 | S18: 周四 | T18: - | V18: - | W18: - | X18: - | Y18: 周四 | Z18: -
C19: 宁波 | D19: COSCO | E19: COSCO Taicang 110E | F19: 东莞/义乌 | G19: 长滩 | H19: PCT | I19: 46205 | J19: 46219 | K19: =J19-I19 -> 14 | L19: - | M19: - | N19: - | O19: - | P19: - | Q19: - | S19: - | T19: 周五 | U19: 周五 | V19: 周四 | W19: 周四 | X19: 周三 | Y19: - | Z19: 周三 | AA19: 周三 18:00
B20: 美转加CLX16日达 | C20: 上海 | D20: MATSON | E20: LURLINE 101E | F20: 东莞/义乌 | G20: 长滩 | H20: MATSON | I20: 46204 | J20: 46215 | K20: =J20-I20 -> 11 | L20: 周六 | M20: 周六 | N20: 周六 | O20: 周六 | P20: 周六 | Q20: 周五 | R20: 周六 | S20: 周四 | T20: 下周一 18:00 | U20: 周六 | V20: 周六 | W20: 周六 | X20: 周五 | Y20: 周四 | Z20: 周五 | AA20: 周四 18:00
B21: 美转加MAX17日达 | C21: 上海 | D21: MATSON | E21: MATSON MAUI 038E | F21: 东莞/义乌 | G21: 长滩 | H21: SSA | I21: 46205 | J21: 46216 | K21: =J21-I21 -> 11 | L21: 周六 | M21: 周六 | N21: 周六 | O21: 周六 | P21: 周六 | Q21: 周五 | R21: 周六 | S21: 周五 | T21: 下周一 | U21: 周六 | V21: 周六 | W21: 周六 | X21: 周五 | Y21: 周五 | Z21: 周五 | AA21: 周五 18:00
B22: 美转加19日达 | C22: 宁波 | D22: EXX | E22: CMA CGM NEW JERSEY 0GVN0E1MA | F22: 东莞/义乌 | G22: 洛杉矶 | H22: FENIX | I22: 46204 | J22: 46216 | K22: =J22-I22 -> 12 | L22: 周六 | M22: 周六 | N22: 周六 | O22: 周六 | P22: 周六 | Q22: 周五 | R22: 周六 | S22: 周五 | T22: 下周一 | U22: 下周一 | V22: 下周一 | W22: 周六 | X22: 周五 | Y22: 周五 | Z22: 周五 | AA22: 周四 18:00
B23: 美转加19日达 | C23: 上海 | D23: EXX | E23: CMA CGM NEW JERSEY 0GVN0E1MA | F23: 东莞/义乌 | G23: 洛杉矶 | H23: FENIX | I23: 46205 | J23: 46216 | K23: =J23-I23 -> 11 | L23: 周六 | M23: 周六 | N23: 周六 | O23: 周六 | P23: 周六 | Q23: 周五 | R23: 周六 | S23: 周五 | T23: 下周一 | U23: 下周一 | V23: 下周一 | W23: 周六 | X23: 周五 | Y23: 周五 | Z23: 周五 | AA23: 周四 18:00
B24: 美转加20日达-卡派（HD/以星） | C24: 南沙 | D24: 合德 | E24: ADAMASTOS 2610E | F24: 东莞/广州 | G24: 洛杉矶 | H24: WBCT | I24: 46204 | J24: 46218 | K24: =J24-I24 -> 14 | L24: 周六 | M24: 周六 | N24: 周六 | O24: 周六 | P24: 周六 | Q24: 周五 | R24: - | S24: 周四 | T24: - | V24: - | W24: - | X24: - | Y24: 周四 | Z24: -
C25: 盐田 | D25: ZIM | E25: NESTOS 17E | F25: 东莞/广州 | G25: 洛杉矶 | H25: ITS | I25: 46204 | J25: 46217 | K25: =J25-I25 -> 13 | L25: 周六 | M25: 周六 | N25: 周六 | O25: 周六 | P25: 周六 | Q25: 周五 | R25: - | S25: 周四 | T25: - | V25: - | W25: - | X25: - | Y25: 周四 | Z25: -
C26: 上海 | D26: HEDE | E26: POSEN 2606E | F26: 义乌 | G26: 洛杉矶 | H26: WBCT | I26: 46205 | J26: 46218 | K26: =J26-I26 -> 13 | L26: - | M26: - | N26: - | O26: - | P26: - | Q26: - | R26: 周五 | S26: - | T26: 周六 | U26: 周六 | V26: 周六 | W26: 周五 | X26: 周五 | Y26: - | Z26: 周五 | AA26: 周四 18:00
C27: 宁波 | D27: ZIM | E27: PELICAN I 14E | F27: 义乌 | G27: 洛杉矶 | H27: TRAPAC | I27: 46205 | J27: 46218 | K27: =J27-I27 -> 13 | L27: - | M27: - | N27: - | O27: - | P27: - | Q27: - | R27: 周五 | S27: - | T27: 周六 | U27: 周六 | V27: 周六 | W27: 周五 | X27: 周五 | Y27: - | Z27: 周五 | AA27: 周四 18:00
B28: 加拿大加东直航30日达 （当周所有船期统配） | C28: 盐田 | D28: EMC | E28: OOCL NEW YORK 120E | F28: 东莞/广州 | G28: 温哥华转火车到多伦多 | H28: - | I28: 46206 | J28: 46223 | K28: =J28-I28 -> 17 | L28: 周六 | M28: 周六 | N28: 周六 | O28: 周六 | P28: 周六 | Q28: 周五 | R28: 周五 | S28: 周四 | T28: - | V28: - | W28: - | Y28: 周四 | Z28: - | AB28: 以当周船期表为准
C29: 宁波 | D29: COSCO | E29: XIN DAN DONG 562N | F29: 义乌 | G29: 温哥华转火车到多伦多 | H29: - | I29: 46201 | J29: 46218 | K29: =J29-I29 -> 17 | L29: - | M29: - | N29: - | O29: - | P29: - | Q29: - | R29: - | S29: - | T29: 周三 | U29: 周二 | V29: 周二 | W29: 周一 | X29: 周一 | Y29: - | Z29: 周一
C30: 宁波 | D30: COSCO | E30: COSCO JEDDAH 096N | F30: 义乌 | G30: 温哥华转火车到多伦多 | H30: - | I30: 46209 | J30: 46225 | K30: =J30-I30 -> 16 | L30: - | M30: - | N30: - | O30: - | P30: - | Q30: - | R30: - | S30: - | T30: 下周三 | U30: 下周二 | V30: 下周二 | W30: 下周一 | X30: 下周一 | Y30: - | Z30: 下周一
B31: 加拿大加东直航33日达 （当周所有船期统配） | C31: 盐田 | D31: SML | E31: SM QINGDAO 2605E | F31: 东莞/广州 | G31: 温哥华转火车到多伦多 | H31: - | I31: 46203 | J31: 46222 | K31: =J31-I31 -> 19 | L31: 周四 | M31: 周四 | N31: 周四 | O31: 周四 | P31: 周四 | Q31: 周三 | R31: 周三 | S31: 周二 | T31: - | V31: - | W31: - | X31: - | Y31: 周二 | Z31: -
B32: 加拿大加东直航33日达 | C32: 盐田 | D32: SML | E32: SM PORTLAND 2605E | F32: 东莞/广州 | G32: 温哥华转火车到多伦多 | H32: - | I32: 46210 | J32: 46229 | K32: =J32-I32 -> 19 | L32: 下周四 | M32: 下周四 | N32: 下周四 | O32: 下周四 | P32: 下周四 | Q32: 下周三 | R32: 下周三 | S32: 下周二 | T32: - | V32: - | W32: - | X32: - | Y32: 下周二 | Z32: -
C33: 宁波 | D33: SML | E33: SM QINGDAO 2605E | F33: 义乌 | G33: 温哥华转火车到多伦多 | H33: - | I33: 46206 | J33: 46222 | K33: =J33-I33 -> 16 | L33: - | M33: - | N33: - | O33: - | P33: - | Q33: - | R33: - | S33: - | T33: 周六 | U33: 周五 | V33: 周五 | W33: 周四 | X33: 周四 | Y33: - | Z33: 周四 | AA33: 周四 18:00
B34: 加拿大加西直航30日达 （当周所有船期统配） | C34: 盐田 | D34: EMC | E34: OOCL NEW YORK 120E | F34: 东莞/广州 | G34: 温哥华转火车到卡尔加里 | H34: - | I34: 46206 | J34: 46223 | K34: =J34-I34 -> 17 | L34: 周六 | M34: 周六 | N34: 周六 | O34: 周六 | P34: 周六 | Q34: 周五 | R34: 周五 | S34: 周四 | T34: - | V34: - | W34: - | Y34: 周四 | Z34: -
C35: 宁波 | D35: COSCO | E35: XIN DAN DONG 562N | F35: 义乌 | G35: 温哥华转火车到卡尔加里 | H35: - | I35: 46201 | J35: 46218 | K35: =J35-I35 -> 17 | L35: - | M35: - | N35: - | O35: - | P35: - | Q35: - | R35: - | S35: - | T35: 周三 | U35: 周二 | V35: 周二 | W35: 周一 | X35: 周一 | Y35: - | Z35: 周一 | AA35: 周一 18:00
C36: 宁波 | D36: COSCO | E36: COSCO JEDDAH 096N | F36: 义乌 | G36: 温哥华转火车到卡尔加里 | H36: - | I36: 46209 | J36: 46225 | K36: =J36-I36 -> 16 | L36: - | M36: - | N36: - | O36: - | P36: - | Q36: - | R36: - | S36: - | T36: 下周三 | U36: 下周二 | V36: 下周二 | W36: 下周一 | X36: 下周一 | Y36: - | Z36: 下周一 | AA36: 下周一 18:00
B37: 加拿大加西直航33日达 （当周所有船期统配） | C37: 盐田 | D37: SML | E37: SM QINGDAO 2605E | F37: 东莞/广州 | G37: 温哥华转火车到卡尔加里 | H37: - | I37: 46203 | J37: 46222 | K37: =J37-I37 -> 19 | L37: 周四 | M37: 周四 | N37: 周四 | O37: 周四 | P37: 周四 | Q37: 周三 | R37: 周三 | S37: 周二 | T37: - | V37: - | W37: - | X37: - | Y37: 周二 | Z37: -
B38: 加拿大加西直航33日达 | C38: 盐田 | D38: SML | E38: SM PORTLAND 2605E | F38: 东莞/广州 | G38: 温哥华转火车到卡尔加里 | H38: - | I38: 46210 | J38: 46229 | K38: =J38-I38 -> 19 | L38: 下周四 | M38: 下周四 | N38: 下周四 | O38: 下周四 | P38: 下周四 | Q38: 下周三 | R38: 下周三 | S38: 下周二 | T38: - | V38: - | W38: - | X38: - | Y38: 下周二 | Z38: -
C39: 宁波 | D39: SML | E39: SM QINGDAO 2605E | F39: 义乌 | G39: 温哥华转火车到卡尔加里 | H39: - | I39: 46206 | J39: 46222 | K39: =J39-I39 -> 16 | L39: - | M39: - | N39: - | O39: - | P39: - | Q39: - | R39: - | S39: - | T39: 周六 | U39: 周五 | V39: 周五 | W39: 周四 | X39: 周四 | Y39: - | Z39: 周四 | AA39: 周四 18:00
A40: 美国 | B40: 美森极速12日达 洛杉矶CLX13日达 特快线小包-美森正班 | C40: 宁波 | D40: MATSON | E40: LURLINE 101E | F40: 东莞/义乌 | G40: 长滩 | H40: MATSON | I40: 46202 | J40: 46215 | K40: =J40-I40 -> 13 | L40: 周六 | M40: 周六 | N40: 周六 | O40: 周六 | P40: 周六 | Q40: 周五 | R40: 周六 | S40: 周四 | T40: 下周一 18:00 | U40: 下周一 12:00 | V40: 下周一 12:00 | W40: 周六 | X40: 周五 | Y40: 周四 | Z40: 周五 | AA40: 周五 18:00
B41: 美转加17日达 | C41: 上海 | D41: MATSON | E41: LURLINE 101E | F41: 东莞/义乌 | G41: 长滩 | H41: MATSON | I41: 46204 | J41: 46215 | K41: =J41-I41 -> 11 | AA41: 周五 18:00
B42: 洛杉矶MAX14日达 | C42: 宁波 | D42: MATSON | E42: MATSON MAUI 038E | F42: 东莞/义乌 | G42: 长滩 | H42: SSA | I42: 46203 | J42: 46216 | K42: =J42-I42 -> 13 | L42: 周六 | M42: 周六 | N42: 周六 | O42: 周六 | P42: 周六 | Q42: 周六 | R42: 周六 | S42: 周五 | T42: 下周一 | U42: 下周一 18:00 | V42: 下周一 | W42: 周六 | X42: 周五 | Y42: 周五 | Z42: 周五 | AA42: 周五 18:00
C43: 上海 | D43: MATSON | E43: MATSON MAUI 038E | F43: 东莞/义乌 | G43: 长滩 | H43: SSA | I43: 46205 | J43: 46216 | K43: =J43-I43 -> 11 | L43: 周六 | M43: 周六 | N43: 周六 | O43: 周六 | P43: 周六 | Q43: 周六 | R43: 周六 | S43: 周五 | T43: 下周一 | U43: 下周一 18:00 | V43: 下周一 | W43: 周六 | X43: 周五 | Y43: 周五 | Z43: 周五 | AA43: 周五 18:00
B44: 洛杉矶EXX16日达-卡派 | C44: 宁波 | D44: EXX | E44: CMA CGM NEW JERSEY 0GVN0E1MA | F44: 东莞/义乌 | G44: 洛杉矶 | H44: FENIX | I44: 46204 | J44: 46216 | K44: =J44-I44 -> 12 | L44: 周六 | M44: 周六 | N44: 周六 | O44: 周六 | P44: 周六 | Q44: 周六 | R44: 周六 | S44: 周五 | T44: 下周一 | U44: 下周一 18:00 | V44: 下周一 | W44: 周六 | X44: 周六 | Y44: 周五 | Z44: 周五 | AA44: 周五 18:00
C45: 上海 | D45: EXX | E45: CMA CGM NEW JERSEY 0GVN0E1MA | F45: 东莞/义乌 | G45: 洛杉矶 | H45: FENIX | I45: 46205 | J45: 46216 | K45: =J45-I45 -> 11 | L45: 周六 | M45: 周六 | N45: 周六 | O45: 周六 | P45: 周六 | Q45: 周六 | R45: 周六 | S45: 周五 | T45: 下周一 | U45: 下周一 18:00 | V45: 下周一 | W45: 周六 | X45: 周六 | Y45: 周五 | Z45: 周五 | AA45: 周五 18:00
B46: 洛杉矶17日达 普快线小包 | C46: 南沙 | D46: 合德 | E46: ADAMASTOS 2610E | F46: 东莞/广州 | G46: 洛杉矶 | H46: WBCT | I46: 46204 | J46: 46218 | K46: =J46-I46 -> 14 | L46: 周六 | M46: 周六 | N46: 周六 | O46: 周六 | P46: 周六 | Q46: 周五 | R46: - | S46: 周四 | T46: - | V46: - | W46: - | X46: - | Y46: 周四 | Z46: -
C47: 盐田 | D47: ZIM | E47: NESTOS 17E | F47: 东莞/广州 | G47: 洛杉矶 | H47: ITS | I47: 46204 | J47: 46217 | K47: =J47-I47 -> 13 | L47: 周六 | M47: 周六 | N47: 周六 | O47: 周六 | P47: 周六 | Q47: 周五 | R47: - | S47: 周四 | T47: - | V47: - | W47: - | X47: - | Y47: 周四 | Z47: -
C48: 上海 | D48: HEDE | E48: POSEN 2606E | F48: 义乌 | G48: 洛杉矶 | H48: WBCT | I48: 46205 | J48: 46218 | K48: =J48-I48 -> 13 | R48: 周六 | T48: 下周一 18:00 | U48: 下周一 12:00 | V48: 下周一 12:00 | W48: 周六 | X48: 周五 | Z48: 周五 | AA48: 周四 18:00
C49: 宁波 | D49: ZIM | E49: PELICAN I 14E | F49: 义乌 | G49: 洛杉矶 | H49: TRAPAC | I49: 46205 | J49: 46218 | K49: =J49-I49 -> 13 | L49: - | M49: - | N49: - | O49: - | P49: - | Q49: - | R49: 周六 | S49: - | T49: 周六 | U49: 周六 | V49: 周六 | W49: 周四 | X49: 周五 | Y49: - | Z49: 周四 | AA49: 周四 18:00
B50: 洛杉矶20日达 | C50: 南沙 | D50: 合德 | E50: ADAMASTOS 2610E | F50: 东莞/广州 | G50: 洛杉矶 | H50: WBCT | I50: 46204 | J50: 46218 | K50: =J50-I50 -> 14 | L50: 周六 | M50: 周六 | N50: 周六 | O50: 周六 | P50: 周六 | Q50: 周五 | R50: - | S50: 周四 | T50: - | V50: - | W50: - | X50: - | Y50: 周四 | Z50: -
C51: 盐田 | D51: ZIM | E51: NESTOS 17E | F51: 东莞/广州 | G51: 洛杉矶 | H51: ITS | I51: 46204 | J51: 46217 | K51: =J51-I51 -> 13 | L51: 周六 | M51: 周六 | N51: 周六 | O51: 周六 | P51: 周六 | Q51: 周五 | R51: - | S51: 周四 | T51: - | V51: - | W51: - | X51: - | Y51: 周四 | Z51: -
C52: 宁波 | D52: ZIM | E52: PELICAN I 14E | F52: 义乌 | G52: 洛杉矶 | H52: TRAPAC | I52: 46205 | J52: 46218 | K52: =J52-I52 -> 13 | L52: - | M52: - | N52: - | O52: - | P52: - | Q52: - | R52: 周六 | S52: - | T52: 周六 | U52: 周六 | V52: 周六 | W52: 周四 | X52: 周五 | Y52: - | Z52: 周四 | AA52: 周四 18:00
C53: 上海 | D53: HEDE | E53: POSEN 2606E | F53: 义乌 | G53: 洛杉矶 | H53: WBCT | I53: 46205 | J53: 46218 | K53: =J53-I53 -> 13 | L53: - | M53: - | N53: - | O53: - | P53: - | Q53: - | R53: 周六 | S53: - | T53: 下周一 18:00 | U53: 下周一 12:00 | V53: 下周一 12:00 | W53: 周六 | X53: 周五 | Y53: - | Z53: 周五 | AA53: 周四 18:00
B54: 洛杉矶22日达 洛杉矶OA26日达直送 标准线小包-OA联盟 （当周所有船期统配） | C54: 盐田 | D54: EMC | E54: EVER MATCH 1460-005E | F54: 东莞/广州 | G54: 洛杉矶 | H54: LBCT | I54: 46202 | J54: 46217 | K54: =J54-I54 -> 15 | L54: 周四 | M54: 周四 | N54: 周四 | O54: 周四 | P54: 周四 | R54: - | S54: 周二 | T54: - | V54: - | W54: - | X54: - | Y54: 周二 | Z54: -
C55: 盐田 | D55: COSCO | E55: XIN DA YANG ZHOU 108E | F55: 东莞/广州 | G55: 长滩 | H55: LBCT | I55: 46203 | J55: 46217 | K55: =J55-I55 -> 14 | L55: 周四 | M55: 周四 | N55: 周四 | O55: 周四 | P55: 周四 | R55: - | S55: 周二 | T55: - | V55: - | W55: - | X55: - | Y55: 周二 | Z55: -
C56: 盐田 | D56: COSCO | E56: OOCL VIOLET 010E | F56: 东莞/广州 | G56: 长滩 | H56: LBCT | I56: 46205 | J56: 46220 | K56: =J56-I56 -> 15 | L56: 周六 | M56: 周六 | N56: 周六 | O56: 周六 | P56: 周六 | S56: 周四 | T56: - | V56: - | W56: - | X56: - | Y56: 周四 | Z56: -
C57: 宁波 | D57: COSCO | E57: COSCO Taicang 110E | F57: 东莞/义乌 | G57: 长滩 | H57: PCT | I57: 46205 | J57: 46219 | K57: =J57-I57 -> 14 | L57: - | M57: - | N57: - | O57: - | P57: - | Q57: - | S57: - | T57: 周六 | U57: 周六 | V57: 周六 | W57: 周四 | X57: 周五 | Y57: - | Z57: 周四 | AA57: 周四 18:00
C58: 上海 | D58: COSCO | E58: CSCL AUTUMN 073E(CEN) | F58: 东莞/义乌 | G58: 长滩 | H58: PCT | I58: 46207 | J58: 46220 | K58: =J58-I58 -> 13 | L58: - | M58: - | N58: - | O58: - | P58: - | Q58: - | S58: - | T58: 周六 | U58: 周六 | V58: 周六 | W58: 周四 | X58: 周五 | Y58: - | Z58: 周四 | AA58: 周四 18:00
C59: 厦门 | D59: MSC | E59: MSC ARCHIMIDIS VIII GQ626N | F59: 厦门 | G59: 长滩 | H59: TTI | I59: 46204 | J59: 46218 | K59: =J59-I59 -> 14 | Q59: 周三 | R59: 周三
C60: 厦门 | D60: MSC | E60: MSC DYMPHNA VI GQ627N | F60: 厦门 | G60: 长滩 | H60: TTI | I60: 46210 | J60: 46224 | K60: =J60-I60 -> 14 | Q60: 下周三 | R60: 下周三
C61: 青岛 | D61: COSCO | E61: CSCL AUTUMN 073E(CEN) | F61: 青岛 | G61: 长滩 | H61: PCT | I61: 46202 | J61: 46218 | K61: =J61-I61 -> 16 | L61: - | M61: - | N61: - | O61: - | P61: - | Q61: - | R61: - | S61: - | T61: - | V61: - | W61: 周三 | X61: 周三 | Y61: - | Z61: 周三
C62: 青岛 | D62: COSCO | E62: CSCL BOHAI SEA 077E(CEN) | F62: 青岛 | G62: 长滩 | H62: PCT | I62: 46209 | J62: 46225 | K62: =J62-I62 -> 16 | L62: - | M62: - | N62: - | O62: - | P62: - | Q62: - | R62: - | S62: - | T62: - | V62: - | W62: 下周三 | X62: 下周三 | Y62: - | Z62: 下周三
B63: 奥克兰OA29日达直送 奥克兰直航26日达 | C63: 盐田 | D63: EMC | E63: EVER MATCH 1460-005E | F63: 东莞/广州 | G63: 奥克兰 | H63: EVERGREEN | I63: 46202 | J63: 46223 | K63: =J63-I63 -> 21 | L63: 周四 | M63: 周四 | N63: 周四 | O63: 周四 | P63: 周四 | Q63: 周三 | R63: - | S63: 周二 | T63: - | V63: - | W63: - | X63: - | Y63: 周一 | Z63: -
C64: 盐田 | D64: EMC | E64: EVER MEMO 1461-012E | F64: 东莞/广州 | G64: 奥克兰 | H64: EVERGREEN | I64: 46209 | J64: 46230 | K64: =J64-I64 -> 21 | L64: 下周四 | M64: 下周四 | N64: 下周四 | O64: 下周四 | P64: 下周四 | Q64: 下周三 | R64: - | S64: 下周二 | T64: - | V64: - | W64: - | X64: - | Y64: 下周一 | Z64: -
C65: 宁波 | D65: EMC | E65: EVER LINKING 1227-070E | F65: 义乌 | G65: 奥克兰 | H65: TRAPAC | I65: 46204 | J65: 46227 | K65: =J65-I65 -> 23 | L65: - | M65: - | N65: - | O65: - | P65: - | Q65: - | R65: 周三 | S65: - | T65: 周四 | U65: 周三 | V65: 周三 | W65: 周二 | X65: 周二 | Y65: - | Z65: 周二 | AA65: 周二 18:00
C66: 宁波 | D66: EMC | E66: EVER LIVELY 1228-078E | F66: 义乌 | G66: 奥克兰 | H66: TRAPAC | I66: 46212 | J66: 46234 | K66: =J66-I66 -> 22 | L66: - | M66: - | N66: - | O66: - | P66: - | Q66: - | R66: 下周三 | S66: - | T66: 下周四 | U66: 下周三 | V66: 下周三 | W66: 下周二 | X66: 下周二 | Y66: - | Z66: 下周二 | AA66: 下周二 18:00
B67: 奥克兰直航32日达 奥克兰普船36日达直送 | C67: 盐田 | D67: HMM | E67: YM WIDTH 040E（MP2) | F67: 东莞/广州 | G67: 奥克兰 | H67: TRAPAC | I67: 46207 | J67: 46233 | K67: =J67-I67 -> 26 | L67: 周六 | M67: 周六 | N67: 周六 | O67: 周六 | P67: 周六 | Q67: 周五 | R67: - | S67: 周四 | T67: - | V67: - | W67: - | X67: - | Y67: 周四 | Z67: -
C68: 宁波 | D68: HMM | E68: HMM NURI 020E(PS6) | F68: 义乌 | G68: 奥克兰 | H68: OICT | I68: 46208 | J68: 46237 | K68: =J68-I68 -> 29 | L68: - | M68: - | N68: - | O68: - | P68: - | Q68: - | R68: 周五 | S68: - | T68: 周六 | U68: 周五 | V68: 周五 | W68: 周四 | X68: 周四 | Y68: - | Z68: 周四 | AA68: 周四 18:00
B69: 西雅图直航29日达 PSC2直送促销价 | C69: 盐田 | D69: EMC | E69: EVER SIGMA 0482-142E | F69: 东莞/广州 | G69: 塔科马 | H69: PIERCE | I69: 46206 | J69: 46224 | K69: =J69-I69 -> 18 | L69: 周六 | M69: 周六 | N69: 周六 | O69: 周六 | P69: 周六 | Q69: 周五 | R69: 周五 | S69: 周四 | T69: - | V69: - | W69: - | X69: - | Y69: 周四 | Z69: -
C70: 宁波 | D70: COSCO | E70: EVER SUMMIT 0481-131E | F70: 义乌 | G70: 塔科马 | H70: PIERCE | I70: 46204 | J70: 46218 | K70: =J70-I70 -> 14 | L70: - | M70: - | N70: - | O70: - | P70: - | Q70: - | R70: - | S70: - | T70: 周六 | U70: 周五 | V70: 周五 | W70: 周四 | X70: 周四 | Y70: - | Z70: 周四 | AA70: 周四 18:00
B71: 洛杉矶26日达 洛杉矶普船28日达直送 (PSC2船期请参考西雅图渠道) （当周所有船期统配) | C71: 蛇口 | D71: WHL | E71: 空班 | F71: 东莞/广州 | G71: 洛杉矶 | H71: WBCT | I71: 空班 | J71: 空班 | K71: 空班 | L71: - | M71: - | N71: - | O71: - | P71: - | Q71: - | R71: - | S71: - | T71: - | V71: - | W71: - | X71: - | Y71: - | Z71: -
C72: 盐田 | D72: YML | E72: YM WIDTH 040E（MP2) | F72: 东莞/广州 | G72: 长滩 | H72: PSA | I72: 46207 | J72: 46225 | K72: =J72-I72 -> 18 | L72: 周六 | M72: 周六 | N72: 周六 | O72: 周六 | P72: 周六 | Q72: - | R72: - | S72: 周四 | T72: - | V72: - | W72: - | X72: - | Y72: 周四 | Z72: -
C73: 盐田 | D73: MSC | E73: MSC DARLENE FV625N | F73: 东莞/广州 | G73: 洛杉矶 | H73: LBCT | I73: 46208 | J73: 46223 | K73: =J73-I73 -> 15 | L73: 周六 | M73: 周六 | N73: 周六 | O73: 周六 | P73: 周六 | Q73: - | R73: - | S73: 周四 | T73: - | V73: - | W73: - | X73: - | Y73: 周四 | Z73: -
C74: 宁波 | D74: MSC | E74: MSC MILAN GO626N | F74: 义乌 | G74: 长滩 | H74: APM | I74: 46207 | J74: 46225 | K74: =J74-I74 -> 18 | L74: - | M74: - | N74: - | O74: - | P74: - | Q74: - | R74: - | S74: - | T74: 周六 | U74: 周五 | V74: 周五 | W74: 周四 | X74: 周四 | Y74: - | Z74: 周四 | AA74: 周四 18:00
C75: 宁波 | D75: HMM | E75: HMM NURI 020E(PS6) | F75: 义乌 | G75: 洛杉矶 | H75: APM | I75: 46208 | J75: 46229 | K75: =J75-I75 -> 21 | L75: - | M75: - | N75: - | O75: - | P75: - | Q75: - | R75: - | S75: - | T75: 周六 | U75: 周五 | V75: 周五 | W75: 周四 | X75: 周四 | Y75: - | Z75: 周四 | AA75: 周四 18:00
C76: 宁波 | D76: HMM | E76: WAN HAI 513 E109(PS8) | F76: 义乌 | G76: 洛杉矶 | H76: APM | I76: 46208 | J76: 46222 | K76: =J76-I76 -> 14 | L76: - | M76: - | N76: - | O76: - | P76: - | Q76: - | R76: - | S76: - | T76: 周六 | U76: 周五 | V76: 周五 | W76: 周四 | X76: 周四 | Y76: - | Z76: 周四 | AA76: 周四 18:00
C77: 厦门 | D77: WHL | E77: 空班 | F77: 厦门 | G77: 洛杉矶 | H77: YUSEN | I77: 空班 | J77: 空班 | K77: 空班 | L77: - | M77: - | N77: - | O77: - | P77: - | Q77: - | R77: - | S77: - | T77: - | V77: - | W77: - | X77: - | Y77: - | Z77: -
C78: 厦门 | D78: MSC | E78: MSC DYMPHNA VI GQ627N | F78: 厦门 | G78: 长滩 | H78: TTI | I78: 46210 | J78: 46224 | K78: =J78-I78 -> 14 | Q78: 下周三 | R78: 下周三
C79: 青岛 | D79: SML | E79: 空班 | F79: 青岛 | G79: 长滩 | H79: SSA | I79: 空班 | J79: 空班 | K79: 空班 | L79: - | M79: - | N79: - | O79: - | P79: - | Q79: - | R79: - | S79: - | T79: - | V79: - | W79: - | X79: - | Y79: - | Z79: - | AA79: -
C80: 青岛 | D80: SML | E80: SM BUSAN 2604E | F80: 青岛 | G80: 长滩 | H80: SSA | I80: 46208 | J80: 46225 | K80: =J80-I80 -> 17 | L80: - | M80: - | N80: - | O80: - | P80: - | Q80: - | R80: - | S80: - | T80: - | V80: - | W80: 周三 | X80: 周三 | Y80: - | Z80: 周三 | AA80: -
B81: 纽约直航38日达 | C81: 盐田 | D81: COSCO | E81: OOCL MAGNOLIA 005E(AWE4) | F81: 东莞/广州 | G81: 纽约 | H81: MAHER | I81: 46201 | J81: 46231 | K81: =J81-I81 -> 30 | L81: 周三 | M81: 周三 | N81: 周三 | O81: 周三 | P81: 周三 | Q81: - | R81: - | S81: 周一 | T81: - | V81: - | W81: - | X81: - | Y81: 周一 | Z81: -
C82: 盐田 | D82: COSCO | E82: OOCL KAPOK 004E(AWE4) | F82: 东莞/广州 | G82: 纽约 | H82: MAHER | I82: 46208 | J82: 46238 | K82: =J82-I82 -> 30 | L82: 下周三 | M82: 下周三 | N82: 下周三 | O82: 下周三 | P82: 下周三 | Q82: - | R82: - | S82: 下周一 | T82: - | V82: - | W82: - | X82: - | Y82: 下周一 | Z82: -
C83: 上海 | D83: COSCO | E83: OOCL MAGNOLIA 005E(AWE4) | F83: 义乌 | G83: 纽约 | H83: MAHER | I83: 46206 | J83: 46231 | K83: =J83-I83 -> 25 | L83: - | M83: - | N83: - | O83: - | P83: - | Q83: - | R83: - | S83: - | T83: 周六 | U83: 周五 | V83: 周五 | W83: 周四 | X83: 周四 | Y83: - | Z83: 周四 | AA83: 周四 18:00
C84: 上海 | D84: COSCO | E84: COSCO SHIPPING LOTUS 033E(AWE2) | F84: 义乌 | G84: 纽约 | H84: MAHER | I84: 46205 | J84: 46233 | K84: =J84-I84 -> 28 | L84: - | M84: - | N84: - | O84: - | P84: - | Q84: - | R84: - | S84: - | T84: 周六 | U84: 周五 | V84: 周五 | W84: 周四 | X84: 周四 | Y84: - | Z84: 周四 | AA84: 周四 18:00
C85: 厦门 | D85: COSCO | E85: OOCL MAGNOLIA 005E(AWE4) | F85: 厦门 | G85: 纽约 | H85: MAHER | I85: 46203 | J85: 46231 | K85: =J85-I85 -> 28 | L85: - | M85: - | N85: - | O85: - | P85: - | Q85: 周四 | R85: 周四 | S85: - | T85: - | V85: - | W85: - | X85: - | Y85: - | Z85: -
C86: 厦门 | D86: COSCO | E86: OOCL KAPOK 004E(AWE4) | F86: 厦门 | G86: 纽约 | H86: MAHER | I86: 46210 | J86: 46238 | K86: =J86-I86 -> 28 | L86: - | M86: - | N86: - | O86: - | P86: - | Q86: 下周四 | R86: 下周四 | S86: - | T86: - | V86: - | W86: - | X86: - | Y86: - | Z86: -
C87: 青岛 | D87: COSCO | E87: OOCL Korea 058E | F87: 青岛 | G87: 纽约 | H87: MAHER | I87: 46208 | J87: 46240 | K87: =J87-I87 -> 32 | L87: - | M87: - | N87: - | O87: - | P87: - | Q87: - | R87: - | S87: - | T87: - | V87: - | W87: 周六 | X87: 周六 | Y87: - | Z87: 周六
B88: 纽约直航42日达 | C88: 蛇口 | D88: WHL | E88: WAN HAI A13 E010 | F88: 东莞/广州 | G88: 纽约 | H88: APM | I88: 46206 | J88: 46246 | K88: =J88-I88 -> 40 | L88: 周六 | M88: 周六 | N88: 周六 | O88: 周六 | P88: 周六 | Q88: 周四 | R88: 周四 | S88: 周四 | T88: - | V88: - | W88: - | X88: - | Y88: 周四 | Z88: -
C89: 盐田 | D89: ZIM | E89: ZIM MOUNT FUJI 11E(ZXB) | F89: 东莞/广州 | G89: 纽约 | H89: MAHER | I89: 46206 | J89: 46241 | K89: =J89-I89 -> 35 | L89: 周六 | M89: 周六 | N89: 周六 | O89: 周六 | P89: 周六 | Q89: 周四 | R89: 周四 | S89: 周四 | T89: - | V89: - | W89: - | X89: - | Y89: 周四 | Z89: -
C90: 宁波 | D90: ZIM | E90: MSC MUMBAI VIII GE627E | F90: 义乌 | G90: 纽约 | H90: NEWARK | I90: 46206 | J90: 46237 | K90: =J90-I90 -> 31 | L90: - | M90: - | N90: - | O90: - | P90: - | Q90: - | R90: - | S90: - | T90: 周六 | U90: 周五 | V90: 周五 | W90: 周四 | X90: 周四 | Y90: - | Z90: 周四 | AA90: 周四 18:00
B91: 纽约海铁24日达 （当周所有船期统配) | C91: 盐田 | D91: ZIM | E91: NESTOS 17E | F91: 东莞/广州 | G91: 洛杉矶转纽约 | H91: - | I91: 46204 | J91: 46217 | K91: =J91-I91 -> 13 | L91: 周六 | M91: 周六 | N91: 周六 | O91: 周六 | P91: 周六 | Q91: 周五 | R91: - | S91: 周四 | T91: - | V91: - | W91: - | X91: - | Y91: 周四 | Z91: -
C92: 宁波 | D92: EXX-闪电达 | E92: CMA CGM NEW JERSEY 0GVN0E1MA | F92: 东莞/义乌 | G92: 洛杉矶转纽约 | H92: - | I92: 46204 | J92: 46216 | K92: =J92-I92 -> 12 | L92: - | M92: - | N92: - | O92: - | P92: - | Q92: - | R92: 周六 | S92: - | T92: 下周一 | U92: 周六 | V92: 周六 | W92: 周五 | X92: 周五 | Y92: - | Z92: 周五 | AA92: 周五 18:00
C93: 上海 | D93: EXX-闪电达 | E93: CMA CGM NEW JERSEY 0GVN0E1MA | F93: 东莞/义乌 | G93: 洛杉矶转纽约 | H93: - | I93: 46205 | J93: 46216 | K93: =J93-I93 -> 11 | L93: - | M93: - | N93: - | O93: - | P93: - | Q93: - | R93: 周六 | S93: - | T93: 下周一 | U93: 周六 | V93: 周六 | W93: 周五 | X93: 周五 | Y93: - | Z93: 周五 | AA93: 周五 18:00
C94: 宁波 | D94: ZIM | E94: PELICAN I 14E | F94: 义乌 | G94: 洛杉矶转纽约 | H94: - | I94: 46205 | J94: 46218 | K94: =J94-I94 -> 13 | L94: - | M94: - | N94: - | O94: - | P94: - | Q94: - | R94: 周六 | S94: - | T94: 下周一 | U94: 周六 | V94: 周六 | W94: 周五 | X94: 周五 | Y94: - | Z94: 周五 | AA94: 周五 18:00
B95: 纽约MAX海铁22日达 | C95: 宁波 | D95: MATSON | E95: MATSON MAUI 038E | F95: 东莞/义乌 | G95: 长滩转纽约 | H95: - | I95: 46203 | J95: 46216 | K95: =J95-I95 -> 13 | L95: 周六 | M95: 周六 | N95: 周六 | O95: 周六 | P95: 周六 | Q95: 周六 | R95: 周六 | S95: 周五 | T95: 下周一 | U95: 周六 | V95: 周六 | W95: 周六 | X95: 周五 | Y95: 周五 | Z95: 周五 | AA95: 周五 18:00
C96: 上海 | D96: MATSON | E96: MATSON MAUI 038E | F96: 东莞/义乌 | G96: 长滩转纽约 | H96: - | I96: 46205 | J96: 46216 | K96: =J96-I96 -> 11 | L96: 周六 | M96: 周六 | N96: 周六 | O96: 周六 | P96: 周六 | Q96: 周六 | R96: 周六 | S96: 周五 | T96: 下周一 | U96: 周六 | V96: 周六 | W96: 周六 | X96: 周五 | Y96: 周五 | Z96: 周五 | AA96: 周五 18:00
B97: 纽约海铁30日达 | C97: 盐田 | D97: COSCO/OOCL- 美速达/东方快航 | E97: OOCL VIOLET 010E | F97: 东莞/广州 | G97: 长滩转纽约 | H97: - | I97: 46205 | J97: 46220 | K97: =J97-I97 -> 15 | L97: 周六 | M97: 周六 | N97: 周六 | O97: 周六 | P97: 周六 | Q97: 周五 | R97: 周五 | S97: 周四 | T97: 周五 | U97: 周五 | V97: 周四 | W97: 周三 | X97: 周三 | Y97: 周四 | Z97: 周三
C98: 宁波 | D98: COSCO/OOCL- 美速达/东方快航 | E98: COSCO Taicang 110E | F98: 东莞/义乌 | G98: 长滩转纽约 | H98: - | I98: 46205 | J98: 46219 | K98: =J98-I98 -> 14 | L98: - | M98: - | N98: - | O98: - | P98: - | Q98: - | R98: 周五 | S98: - | T98: 周五 | U98: 周五 | V98: 周四 | W98: 周三 | X98: 周三 | Y98: - | Z98: 周三 | AA98: 周三 18:00
B99: 芝加哥海铁22日达 | C99: 盐田 | D99: ZIM | E99: NESTOS 17E | F99: 东莞/广州 | G99: 洛杉矶转芝加哥 | H99: - | I99: 46204 | J99: 46217 | K99: =J99-I99 -> 13 | L99: 周六 | M99: 周六 | N99: 周六 | O99: 周六 | P99: 周六 | Q99: 周五 | R99: - | S99: 周三 | T99: - | V99: - | W99: - | X99: - | Y99: 周三 | Z99: -
C100: 宁波 | D100: ZIM | E100: PELICAN I 14E | F100: 义乌 | G100: 洛杉矶转芝加哥 | H100: - | I100: 46205 | J100: 46218 | K100: =J100-I100 -> 13 | L100: - | M100: - | N100: - | O100: - | P100: - | Q100: - | R100: 周五 | S100: - | T100: 周五 | U100: 周五 | V100: 周四 | W100: 周三 | X100: 周四 | Y100: - | Z100: 周三 | AA100: 周三 18:00
B101: 芝加哥海铁24日达-TK专属 | C101: 盐田 | D101: ZIM | E101: NESTOS 17E | F101: 东莞/广州 | G101: 洛杉矶转芝加哥 | H101: - | I101: 46204 | J101: 46217 | K101: =J101-I101 -> 13 | L101: 周六 | M101: 周六 | N101: 周六 | O101: 周六 | P101: 周六 | Q101: 周五 | R101: - | S101: 周三 | T101: - | V101: - | W101: - | X101: - | Y101: 周三 | Z101: -
C102: 宁波 | D102: ZIM | E102: PELICAN I 14E | F102: 义乌 | G102: 洛杉矶转芝加哥 | H102: - | I102: 46205 | J102: 46218 | K102: =J102-I102 -> 13 | L102: - | M102: - | N102: - | O102: - | P102: - | Q102: - | R102: 周五 | S102: - | T102: 周五 | U102: 周五 | V102: 周四 | W102: 周三 | X102: 周四 | Y102: - | Z102: 周三 | AA102: 周三 18:00
...

Sheet 出运计划 -陆运
B2: 出运计划（陆运）-WEEK 26
B3: Shipping Schedule
A5: 国家 | B5: 渠道名称 | C5: 发运地 | D5: 最新时效参考 | E5: 出仓日期 | F5: 预计发运时间 | G5: 预计抵达时间 | H5: 塘厦 | I5: 福永 | J5: 广州/中山/东莞南城 | K5: 惠州 | L5: 汕头 | M5: 厦门/泉州/福州/义乌 | N5: 上海/宁波 | O5: 武汉/长沙 | P5: 成都/重庆 | Q5: 青岛/郑州 | R5: 杭州/台州/苏州/绍兴/温州/南昌/南京/合肥 | S5: 天津/石家庄仓/济南/潍坊/保定/沧州/西安/连云港 | T5: 备注
A6: 英国 | B6: 英国卡航 | C6: 深圳 | D6: 18-25天 | E6: 46197 | F6: =E6+1 -> 46198 | G6: =F6+20 -> 46218 | H6: 周三 18:00 | I6: 周三 15:00 | J6: 周三 12:00 | K6: 周二18:00 | L6: 周二12:00 | M6: 周一 18:00 | N6: 周一 18:00 | O6: 周一 18:00 | P6: - | Q6: - | R6: - | S6: - | T6: 预计运行时间，以实际发运时间为准
E7: 46200 | F7: =E7+1 -> 46201 | G7: =F7+20 -> 46221 | H7: 周六 18:00 | I7: 周六 15:00 | J7: 周六 12:00 | K7: 周五18:00 | L7: 周五12:00 | M7: 周四 18:00 | N7: 周四 18:00 | O7: 周三 18:00 | P7: 周三 18:00 | Q7: 周二 18:00 | R7: 周二 18:00 | S7: 周一18:00
E8: 46204 | F8: =E8+1 -> 46205 | G8: =F8+20 -> 46225 | H8: 下周三 18:00 | I8: 下周三 15:00 | J8: 下周三 12:00 | K8: 下周二18:00 | L8: 下周二12:00 | M8: 下周一 18:00 | N8: 下周一 18:00 | O8: 下周一 18:00 | P8: 周六 18:00 | Q8: 周六 18:00 | R8: 周六 18:00 | S8: 周五18:00
B9: 英国快铁 | C9: 西安/重庆 | D9: 20-25天 | E9: 46197 | F9: =E9+5 -> 46202 | G9: =F9+23 -> 46225 | H9: 周三 18:00 | I9: 周三 15:00 | J9: 周三 12:00 | K9: 周二18:00 | L9: 周二12:00 | M9: 周一 18:00 | N9: 周一 18:00 | O9: 周一 18:00 | P9: - | Q9: - | R9: - | S9: -
E10: 46200 | F10: =E10+6 -> 46206 | G10: =F10+23 -> 46229 | H10: 周六 18:00 | I10: 周六 15:00 | J10: 周六 12:00 | K10: 周五18:00 | L10: 周五12:00 | M10: 周四 18:00 | N10: 周四 18:00 | O10: 周三 18:00 | P10: 周三 18:00 | Q10: 周二 18:00 | R10: 周二 18:00 | S10: 周一18:00
E11: 46205 | F11: =E11+6 -> 46211 | G11: =F11+23 -> 46234 | H11: 下周四 18:00 | I11: 下周四 15:00 | J11: 下周四 12:00 | K11: 下周三18:00 | L11: 下周三12:00 | M11: 下周二 18:00 | N11: 下周二 18:00 | O11: 下周二 18:00 | P11: 周一 18:00 | Q11: 周六 18:00 | R11: 下周六 18:00 | S11: 周六18:00
A13: 线路 | B13: 渠道名称 | C13: 发运地 | D13: 最新时效参考 | E13: 出仓日期 | F13: 预计发运时间 | G13: 预计抵达时间 | H13: 塘厦 | I13: 福永 | J13: 广州/中山/东莞南城 | K13: 汕头 | L13: 厦门/泉州/福州 | M13: 武汉/长沙/青岛 | N13: 上海/义乌/宁波 | O13: 备注
A14: 越南陆运 | B14: 越南陆运正报不包税 | C14: 广/深 | D14: 3-5个自然日 | E14: 46197 | F14: =E14+1 -> 46198 | G14: =F14+5 -> 46203 | H14: 周三 18：00 | I14: 周三 15：00 | J14: 周三 12：00 | K14: 周二 18：00 | L14: 周一 18：00 | M14: - | N14: 周一 18：00 | O14: 1.北越转南越时效会延误2天左右 2.预计发运时间，以实际发运时间为准
E15: 46200 | F15: =E15+1 -> 46201 | G15: =F15+5 -> 46206 | H15: 周六 18：00 | I15: 周六 15：00 | J15: 周五 16：00 | K15: 周四 18：00 | L15: 周三 18：00 | M15: - | N15: 周三 18：00
B16: 越南陆运双清包税 | D16: 北部：3-5自然日 南部：8-10自然日 | E16: 46197 | F16: =E16+1 -> 46198 | G16: =F16+5 -> 46203 | H16: 周三 18：00 | I16: 周三 15：00 | J16: 周三 12：00 | K16: 周二 18：00 | L16: 周一 18：00 | M16: - | N16: 周一 18：00
E17: 46200 | F17: =E17+1 -> 46201 | G17: =F17+5 -> 46206 | H17: 周六 18：00 | I17: 周六 15：00 | J17: 周五 16：00 | K17: 周四 18：00 | L17: 周三 18：00 | M17: - | N17: 周三 18：00
B18: 越南陆运双清不包税 | D18: 北部：3-5自然日 南部：8-10自然日 | E18: 46197 | F18: =E18+1 -> 46198 | G18: =F18+5 -> 46203 | H18: 周三 18：00 | I18: 周三 15：00 | J18: 周三 12：00 | K18: 周二 18：00 | L18: 周一 18：00 | M18: - | N18: 周一 18：00
E19: 46200 | F19: =E19+1 -> 46201 | G19: =F19+5 -> 46206 | H19: 周六 18：00 | I19: 周六 15：00 | J19: 周五 16：00 | K19: 周四 18：00 | L19: 周三 18：00 | M19: - | N19: 周三 18：00
A21: 线路 | B21: 渠道名称 | C21: 起运港 | D21: 预配船公司 | E21: 装柜地点 | F21: 目的港 | G21: 预计 开船 | H21: 本周截单时间（截止越南当地拣货时间）
H22: 越南（北越） | I22: 越南（南越） | J22: 备注
H23: 海防仓 | I23: 胡志明仓
A24: 越美 | B24: 越美普船专线 | C24: 胡志明 | D24: 统配 | E24: 胡志明 | F24: 洛杉矶 | G24: 周三 | I24: 周二 | J24: 预计发运时间，以实际发运时间为准
C25: 海防 | E25: 海防 | F25: 洛杉矶 | G25: 周六 | H25: 周一

Sheet FBA预计送达周
B1: FBA预计送达周
A4: 美西
A5: 渠道 | B5: 美森极速12日达-卡派（CLX） | C5: 美森正班13日达-卡派（CLX） | D5: 美森正班14日达-卡派（MAX） | E5: 洛杉矶16日达-卡派(EXX/MAX) | F5: 洛杉矶17日达-卡派 | G5: 洛杉矶20日达-卡派（保舱保柜） | H5: 洛杉矶22日达-卡派（OA） | I5: 洛杉矶26日达-卡派 （开船可能有1-7天延时）
A6: 仓库地址 | B6: 预计送达周 | C6: 预计送达周 | D6: 预计送达周 | E6: 预计送达周 | F6: 预计送达周 | G6: 预计送达周 | H6: 预计送达周 | I6: 预计送达周
A7: ONT8 | B7: 7月26日~8月1日 | C7: 7月26日~8月1日 | D7: 7月26日~8月1日 | E7: 8月2日~8月8日 | F7: 8月2日~8月8日 | G7: 8月2日~8月8日 | H7: 8月9日~8月15日 | I7: 8月16日~8月22日
A8: LGB8 | B8: 7月26日~8月1日 | C8: 7月26日~8月1日 | D8: 7月26日~8月1日 | E8: 8月2日~8月8日 | F8: 8月2日~8月8日 | G8: 8月2日~8月8日 | H8: 8月9日~8月15日 | I8: 8月16日~8月22日
A9: LAX9 | B9: 7月26日~8月1日 | C9: 7月26日~8月1日 | D9: 7月26日~8月1日 | E9: 8月2日~8月8日 | F9: 8月2日~8月8日 | G9: 8月2日~8月8日 | H9: 8月9日~8月15日 | I9: 8月16日~8月22日
A10: SBD1 | B10: 7月26日~8月1日 | C10: 7月26日~8月1日 | D10: 7月26日~8月1日 | E10: 8月2日~8月8日 | F10: 8月2日~8月8日 | G10: 8月2日~8月8日 | H10: 8月9日~8月15日 | I10: 8月16日~8月22日
A11: IUTI | B11: 7月26日~8月1日 | C11: 7月26日~8月1日 | D11: 7月26日~8月1日 | E11: 8月2日~8月8日 | F11: 8月9日~8月15日 | G11: 8月9日~8月15日 | H11: 8月9日~8月15日 | I11: 8月23日~8月29日
A12: IUSW | B12: 7月26日~8月1日 | C12: 7月26日~8月1日 | D12: 7月26日~8月1日 | E12: 8月2日~8月8日 | F12: 8月9日~8月15日 | G12: 8月9日~8月15日 | H12: 8月9日~8月15日 | I12: 8月16日~8月22日
A13: SNA4 | B13: 7月26日~8月1日 | C13: 7月26日~8月1日 | D13: 7月26日~8月1日 | E13: 8月2日~8月8日 | F13: 8月2日~8月8日 | G13: 8月2日~8月8日 | H13: 8月9日~8月15日 | I13: 8月16日~8月22日
A14: SBD2 | B14: 7月26日~8月1日 | C14: 7月26日~8月1日 | D14: 7月26日~8月1日 | E14: 8月2日~8月8日 | F14: 8月9日~8月15日 | G14: 8月9日~8月15日 | H14: 8月9日~8月15日 | I14: 8月23日~8月29日
A15: LGB4 | B15: 7月26日~8月1日 | C15: 7月26日~8月1日 | D15: 7月26日~8月1日 | E15: 8月2日~8月8日 | F15: 8月2日~8月8日 | G15: 8月2日~8月8日 | H15: 8月9日~8月15日 | I15: 8月16日~8月22日
A16: LGB6 | B16: 7月26日~8月1日 | C16: 7月26日~8月1日 | D16: 7月26日~8月1日 | E16: 8月2日~8月8日 | F16: 8月2日~8月8日 | G16: 8月2日~8月8日 | H16: 8月9日~8月15日 | I16: 8月16日~8月22日
... A134: WM-IND2 | B134: - | C134: - | D134: - | E134: - | F134: - | G134: - | H134: - | I134: -
A136: 美西直送系列 | G136: 美西北
A137: 渠道 | B137: 洛杉矶普船28日达直送-卡派 | C137: 洛杉矶OA26日达直送-卡派 | D137: 奥克兰OA29日达直送-卡派 | E137: 奥克兰普船36日达直送-卡派 | G137: 渠道 | H137: 奥克兰直航26日达-卡派 | I137: 西雅图直航29日达-卡派 | J137: 奥克兰直航32日-卡派
A138: 仓库地址 | B138: 预计送达周 | C138: 预计送达周 | D138: 预计送达周 | E138: 预计送达周 | G138: 仓库地址 | H138: 预计送达周 | I138: 预计送达周 | J138: 预计送达周
A139: ONT8 | B139: 8月16日~8月22日 | C139: 8月9日~8月15日 | D139: 8月16日~8月22日 | E139: 8月23日~8月29日 | G139: SMF3 | H139: 8月16日~8月22日 | I139: 8月30日~9月5日 | J139: 8月23日~8月29日
A140: LGB8 | B140: 8月16日~8月22日 | C140: 8月9日~8月15日 | D140: 8月16日~8月22日 | E140: 8月23日~8月29日 | G140: SCK1 | H140: 8月9日~8月15日 | I140: 8月23日~8月29日 | J140: 8月16日~8月22日
A141: LAX9 | B141: 8月16日~8月22日 | C141: 8月9日~8月15日 | D141: 8月16日~8月22日 | E141: 8月23日~8月29日 | G141: SCK3 | H141: 8月16日~8月22日 | I141: 8月30日~9月5日 | J141: 8月23日~8月29日
A142: SBD1 | B142: 8月16日~8月22日 | C142: 8月9日~8月15日 | D142: 8月16日~8月22日 | E142: 8月23日~8月29日 | G142: SCK4 | H142: 8月16日~8月22日 | I142: 8月30日~9月5日 | J142: 8月23日~8月29日
A143: POC1 | B143: 8月16日~8月22日 | C143: 8月9日~8月15日 | D143: 8月16日~8月22日 | E143: 8月23日~8月29日 | G143: QXY5 | H143: 8月23日~8月29日 | I143: 9月6日~9月12日 | J143: 8月30日~9月5日
A144: POC2 | B144: 8月23日~8月29日 | C144: 8月9日~8月15日 | D144: 8月16日~8月22日 | E144: 8月23日~8月29日 | G144: OAK3 | H144: 8月16日~8月22日 | I144: 8月30日~9月5日 | J144: 8月23日~8月29日
A145: POC3 | B145: 8月23日~8月29日 | C145: 8月9日~8月15日 | D145: 8月16日~8月22日 | E145: 8月23日~8月29日 | G145: SJC7 | H145: 8月16日~8月22日 | I145: 8月30日~9月5日 | J145: 8月23日~8月29日
A146: IUSP | B146: 8月23日~8月29日 | C146: 8月9日~8月15日 | D146: 8月16日~8月22日 | E146: 8月23日~8月29日 | G146: SCK8 | H146: 8月16日~8月22日 | I146: 8月30日~9月5日 | J146: 8月23日~8月29日
A147: IUSQ | B147: 8月23日~8月29日 | C147: 8月16日~8月22日 | D147: 8月16日~8月22日 | E147: 8月23日~8月29日 | G147: TCY1 | H147: 8月16日~8月22日 | I147: 8月30日~9月5日 | J147: 8月23日~8月29日
A148: WM-LAX1 | B148: - | C148: - | D148: - | E148: - | G148: TCY2 | H148: 8月16日~8月22日 | I148: 8月30日~9月5日 | J148: 8月23日~8月29日
... A163: GEU5 | B163: 8月23日~8月29日 | C163: 8月16日~8月22日 | D163: 8月23日~8月29日 | E163: 8月30日~9月5日 | G163: PSC2 | H163: 8月16日~8月22日 | I163: 8月30日~9月5日 | J163: 8月23日~8月29日
A164: QXY8 | B164: 8月23日~8月29日 | C164: 8月9日~8月15日 | D164: 8月16日~8月22日 | E164: 8月23日~8月29日
A165: PSC2 | B165: 8月23日~8月29日 | C165: 8月9日~8月15日 | D165: 8月16日~8月22日 | E165: 8月23日~8月29日
A166: HLI2 | B166: 8月23日~8月29日 | C166: 8月9日~8月15日 | D166: 8月16日~8月22日 | E166: 8月23日~8月29日
A167: MCC1 | B167: 9月13日~9月19日 | C167: 8月30日~9月5日 | D167: 9月6日~9月12日 | E167: 9月13日~9月19日
A168: SMF7 | B168: 8月16日~8月22日 | C168: 8月9日~8月15日 | D168: 8月16日~8月22日 | E168: 8月23日~8月29日
A169: MCE1 | B169: 8月16日~8月22日 | C169: 8月9日~8月15日 | D169: 8月16日~8月22日 | E169: 8月23日~8月29日
A170: OAK3 | B170: 8月23日~8月29日 | C170: 8月9日~8月15日 | D170: 8月16日~8月22日 | E170: 8月23日~8月29日
A171: SMF3 | B171: 8月23日~8月29日 | C171: 8月9日~8月15日 | D171: 8月16日~8月22日 | E171: 8月23日~8月29日
A172: SCK4 | B172: 8月16日~8月22日 | C172: 8月9日~8月15日 | D172: 8月16日~8月22日 | E172: 8月23日~8月29日
A173: SCK8 | B173: 8月16日~8月22日 | C173: 8月9日~8月15日 | D173: 8月16日~8月22日 | E173: 8月23日~8月29日
A174: TCY1 | B174: 8月23日~8月29日 | C174: 8月9日~8月15日 | D174: 8月16日~8月22日 | E174: 8月23日~8月29日
A175: TCY2 | B175: 8月23日~8月29日 | C175: 8月9日~8月15日 | D175: 8月16日~8月22日 | E175: 8月23日~8月29日
A177: 美东直航系列 | E177: 美东-海铁系列
A178: 渠道 | B178: 纽约直航42日达-卡派 | C178: 纽约直航38日达-卡派 | F178: 纽约海铁24日达-卡派 | G178: 纽约MAX海铁22日达-卡派 | H178: 纽约海铁30日达-卡派
A179: 仓库地址 | B179: 预计送达周 | C179: 预计送达周 | E179: 仓库地址 | F179: 预计送达周 | G179: 预计送达周 | H179: 预计送达周
A180: ABE8-直送特价 | B180: 9月13日~9月19日 | C180: 8月23日~8月29日 | E180: ABE3 | F180: 8月9日~8月15日 | G180: 8月2日~8月8日 | H180: 8月23日~8月29日
A181: TEB9-直送特价 | B181: 9月13日~9月19日 | C181: 8月23日~8月29日 | E181: ABE4 | F181: 8月9日~8月15日 | G181: 8月2日~8月8日 | H181: 8月23日~8月29日
A182: TEB6-直送特价 | B182: 9月13日~9月19日 | C182: 8月23日~8月29日 | E182: ABE8 | F182: 8月9日~8月15日 | G182: 8月2日~8月8日 | H182: 8月23日~8月29日
A183: ACY2-直送特价 | B183: 9月13日~9月19日 | C183: 8月23日~8月29日 | E183: TEB3 | F183: 8月9日~8月15日 | G183: 8月2日~8月8日 | H183: 8月23日~8月29日
A184: ABE4-直送特价 | B184: 9月13日~9月19日 | C184: 8月23日~8月29日 | E184: TEB4 | F184: 8月9日~8月15日 | G184: 8月2日~8月8日 | H184: 8月23日~8月29日
A185: SWF2-直送特价 | B185: 9月13日~9月19日 | C185: 8月23日~8月29日 | E185: TEB6 | F185: 8月9日~8月15日 | G185: 8月2日~8月8日 | H185: 8月23日~8月29日
A186: TEB3-直送特价 | B186: 9月13日~9月19日 | C186: 8月23日~8月29日 | E186: TEB9 | F186: 8月9日~8月15日 | G186: 8月2日~8月8日 | H186: 8月23日~8月29日
A187: AVP1-直送特价 | B187: 9月13日~9月19日 | C187: 8月23日~8月29日 | E187: TTN2 | F187: 8月16日~8月22日 | G187: 8月9日~8月15日 | H187: 8月30日~9月5日
A188: RMN3-直送特价 | B188: 9月13日~9月19日 | C188: 8月23日~8月29日 | E188: ACY2 | F188: 8月9日~8月15日 | G188: 8月2日~8月8日 | H188: 8月23日~8月29日
A189: XLX1-直送特价 | B189: 9月13日~9月19日 | C189: 8月23日~8月29日 | E189: XEW5 | F189: 8月9日~8月15日 | G189: 8月2日~8月8日 | H189: 8月23日~8月29日
A190: ABE3 | B190: 9月13日~9月19日 | C190: 8月23日~8月29日 | E190: HIA1 | F190: 8月16日~8月22日 | G190: 8月9日~8月15日 | H190: 8月30日~9月5日
... A255: IND5 | B255: 9月13日~9月19日 | C255: 8月30日~9月5日 | E255: IUSL | F255: 8月9日~8月15日 | G255: 8月2日~8月8日 | H255: 8月23日~8月29日
A256: IND9 | B256: 9月13日~9月19日 | C256: 8月30日~9月5日
A257: MDW2 | B257: 9月13日~9月19日 | C257: 8月30日~9月5日
A258: MDW6 | B258: 9月13日~9月19日 | C258: 8月23日~8月29日
A259: MDW9 | B259: 9月13日~9月19日 | C259: 8月23日~8月29日
A260: ORD2 | B260: 9月13日~9月19日 | C260: 8月30日~9月5日
A261: IGQ2 | B261: 9月13日~9月19日 | C261: 8月30日~9月5日
A262: FWA4 | B262: 9月13日~9月19日 | C262: 8月30日~9月5日
A263: JVL1 | B263: 9月13日~9月19日 | C263: 8月30日~9月5日
A264: RFD2 | B264: 9月13日~9月19日 | C264: 8月23日~8月29日
A265: IUSL | B265: 9月13日~9月19日 | C265: 8月30日~9月5日
A267: 美中-芝加哥 | F267: 美东南直航系列 | K267: 美中-休斯顿
A268: 渠道 | B268: 芝加哥海铁28日达-卡派 | C268: 芝加哥海铁32日达-卡派 | D268: 芝加哥海铁22日达-卡派 | F268: 渠道 | G268: 萨凡纳直航36日达-卡派 | H268: 萨凡纳直航48日达-卡派 | I268: 萨凡纳海陆24日达-卡派 | K268: 渠道 | L268: 休斯顿直航38日达-卡派
A269: 仓库地址 | B269: 预计送达周 | C269: 预计送达周 | D269: 预计送达周 | F269: 仓库地址 | G269: 预计送达周 | H269: 预计送达周 | I269: 预计送达周 | K269: 仓库地址 | L269: 预计送达周
A270: MDW2-直送特价 | B270: 8月23日~8月29日 | C270: 8月30日~9月5日 | D270: 8月20日~8月26日 | F270: IUSR-直送特价 | G270: 9月6日~9月12日 | H270: 9月13日~9月19日 | I270: - | K270: HOU8 | L270: 8月30日~9月5日
A271: RFD2-直送特价 | B271: 8月23日~8月29日 | C271: 8月30日~9月5日 | D271: 8月20日~8月26日 | F271: CLT2-直送特价 | G271: 9月6日~9月12日 | H271: 9月13日~9月19日 | I271: - | K271: HOU7 | L271: 8月30日~9月5日
A272: ORD2-直送特价 | B272: 8月23日~8月29日 | C272: 8月30日~9月5日 | D272: 8月20日~8月26日 | F272: SAV3 | G272: 9月6日~9月12日 | H272: 9月20日~9月26日 | I272: 8月23日~8月29日 | K272: HOU3 | L272: 8月30日~9月5日
A273: IND9-直送特价 | B273: 8月23日~8月29日 | C273: 8月30日~9月5日 | D273: 8月20日~8月26日 | F273: JAX3 | G273: 9月6日~9月12日 | H273: 9月20日~9月26日 | I273: 8月23日~8月29日 | K273: HOU2 | L273: 8月30日~9月5日
A274: FWA4-直送特价 | B274: 8月23日~8月29日 | C274: 8月30日~9月5日 | D274: 8月20日~8月26日 | F274: XLX6 | G274: 9月6日~9月12日 | H274: 9月20日~9月26日 | I274: 8月23日~8月29日 | K274: HOU1 | L274: 8月30日~9月5日
A275: MDW2 | B275: 8月30日~9月5日 | C275: 9月6日~9月12日 | D275: 8月27日~9月2日 | F275: GSO1 | G275: 9月13日~9月19日 | H275: 9月27日~10月3日 | I275: 8月30日~9月5日 | K275: IAH3 | L275: 8月30日~9月5日
A276: ORD2 | B276: 8月30日~9月5日 | C276: 9月6日~9月12日 | D276: 8月27日~9月2日 | F276: IUSR | G276: 9月6日~9月12日 | H276: 9月20日~9月26日 | I276: 8月23日~8月29日 | K276: FTW9 | L276: 9月6日~9月12日
A277: IGQ2 | B277: 8月30日~9月5日 | C277: 9月6日~9月12日 | D277: 8月27日~9月2日 | F277: MGE3 | G277: 9月13日~9月19日 | H277: 9月27日~10月3日 | I277: 8月30日~9月5日 | K277: FTW1 | L277: 9月6日~9月12日
A278: MDW6 | B278: 8月23日~8月29日 | C278: 8月30日~9月5日 | D278: 8月20日~8月26日 | F278: RYY2 | G278: 9月6日~9月12日 | H278: 9月20日~9月26日 | I278: 8月23日~8月29日 | K278: FTW5 | L278: 8月30日~9月5日
A279: MDW8 | B279: 8月23日~8月29日 | C279: 8月30日~9月5日 | D279: 8月20日~8月26日 | F279: CLT2 | G279: 9月13日~9月19日 | H279: 9月20日~9月26日 | I279: 8月30日~9月5日 | K279: FTW3 | L279: 9月6日~9月12日
... A297: WM-IND2N | B297: - | C297: - | D297: - | F297: WM-MCO1 | G297: - | H297: - | I297: - | K297: WM-DFW5s | L297: -
A298: WM-IND2T | B298: - | C298: - | D298: - | K298: WM-DFW6S | L298: -
A299: CMH7 | B299: 8月30日~9月5日 | C299: 9月6日~9月12日 | D299: 8月27日~9月2日
A300: DET1 | B300: 8月30日~9月5日 | C300: 9月6日~9月12日 | D300: 8月27日~9月2日
A301: DET2 | B301: 8月30日~9月5日 | C301: 9月6日~9月12日 | D301: 8月27日~9月2日
A302: CMH2 | B302: 8月30日~9月5日 | C302: 9月6日~9月12日 | D302: 8月27日~9月2日
A303: CMH3 | B303: 8月30日~9月5日 | C303: 9月6日~9月12日 | D303: 8月27日~9月2日
A304: LAN2 | B304: 8月30日~9月5日 | C304: 9月6日~9月12日 | D304: 8月27日~9月2日
A305: FOE1 | B305: 8月30日~9月5日 | C305: 9月6日~9月12日 | D305: 8月27日~9月2日
A306: MKC4 | B306: 9月6日~9月12日 | C306: 9月13日~9月19日 | D306: 9月3日~9月9日
A307: MCI3 | B307: 8月30日~9月5日 | C307: 9月6日~9月12日 | D307: 8月27日~9月2日
A308: STL3 | B308: 8月30日~9月5日 | C308: 9月6日~9月12日 | D308: 8月27日~9月2日
A309: MEM1 | B309: 8月30日~9月5日 | C309: 9月6日~9月12日 | D309: 8月27日~9月2日
A310: MEM6 | B310: 8月30日~9月5日 | C310: 9月6日~9月12日 | D310: 8月27日~9月2日
... A326: STL8 | B326: 8月30日~9月5日 | C326: 9月6日~9月12日 | D326: 8月27日~9月2日

Sheet 发货须知-美国&英国
A1: 美 国 发 货 须 知 | C1: 英 国 发 货 须 知
A2: 产品说明 | C2: 产品说明
A3: 1、 计费重：计费重量取货物的体积重量和实际重量中数值较大的一方。体积重量计算方式为：长CMX宽CMX高CM/6000=体积重（KG） 2、此渠道可以接带弱磁、带马达、带电机产品 3、为了便于清关，请在每件货外箱上贴上“made in china"的字样，亚马逊仓外箱要贴两张入仓条码，不要贴在封箱口，因为我司需查货； 4、汇率请查阅我司财务部发放的通知； 5、此以上渠道只提供美国本土服务，不提供附属岛屿等偏远地区服务，不接受PO BOX等邮箱地址；偏远地区邮编如下：006-009 PUERTO RICO AND VIRGIN LSLANDS 波多黎各、维尔京群岛，966-969 HAWAIIAND GUAM 夏威夷、关岛,995-999 ALASKA 阿拉斯加等； 6、此渠道需及时支付货款，否则货物到当地清关后不予派送服务； 7、此渠道拒收仿牌、违禁品货物液体、粉末、食品、药品、易燃易爆、古董、货币、气体等易燃易爆产等国家禁止出口及航空公司禁运物品 8、以上时效参考不含海关查验、航线变更导致延误到站、疫情，以及港口工人罢工和节假日等影响； 9、走玩具要求如下：1.安全证书，CPSC等；2.tracking label：追溯标签，追溯标签就是一个可以追溯到发件人或者生产工厂的标签。 10、我司会抽查货物实际装箱情况，但不确保100%的查货率，如因产品、包装等货物本身问题导致的扣货及其他损失，须由发货方承担相关责任，我司保留追诉的权利；此渠道拒收仿牌、违禁品货物，如查到将会没收货物且通知相关执法部门并处罚金60000RMB/票起。 11、美国港口“CHI/HOU/OAK/Seattle/NY/Tacoma”清关查验预计1~3个月左右 | C3: 1、我司采用单票清关，单独出海关退税文件（税金单）； 2、需做关税预付（自主税号：申报价值的30%，PVA：总申报的12%），税单下来多退少补！如果遇见海关查验扣货所产生的海关仓租全部由客户自行承担； 3、汇率请查阅我司财务部发放的通知；VAT增值税：（货值+运费+关税）*20% ；DUTY关税：货值的5%-10%左右； 4、需及时支付货款，否则货物到当地清关后不予派送服务； 5、拒收仿牌、违禁品货物液体、粉末、食品、药品、易燃易爆、古董、货币、指甲油，气体等易燃易爆产等国家禁止出口及航司，船司禁运物品； 6、发亚马逊货物，可做自税递延（PVA），提供清关所需递延资料审核通过即可； 7、时效参考不含海关查验、航线变更导致延误到站、疫情，以及港口工人罢工和节假日等影响； 8、产品请一定如实申报，包括品牌、型号等，我司会抽查货物实际装箱情况，但不确保100%的查货率，如因产品、包装等货物本身问题导致的扣货及其他损失，须由发货方承担相关责任，我司保留追诉的权利；此渠道拒收仿牌、违禁品货物，如查到将会没收货物且通知相关执法部门并处罚金60000RMB/票起。
A11: 货物尺寸 | C11: 产品附加费（英国全渠道）
A12: 1、快递派送标准尺寸：最长边不超过120CM，第二边长不超过76CM，围长不超过266CM。围长计算方法：长+[2 x(宽+高）] 。 2、快递派送单件重量不超过22.6KG；单箱计费重为最低12KG，不足12KG按照12KG计费。 3、快递派私人地址：商业地址+1元/KG，住宅私人地址+25元/件，偏远+30元/件，超偏远+40元/件。 超长收费标准：266CM＜围长≤ 315CM，此尺寸范围的超长费140元/件；围长超315CM单询； 超重收费标准：22.6KG＜实际重量＜ 68KG，此范围的超重费+140元/件； 快递派无服务的尺寸范围如下： a)实重>68KG b)最长边>274CM d)最长边+围长>419CM 关于异形费的产生与补收： 异形费产生的原因：货物外箱包装有“黄胶带、编织袋、气泡袋、缠膜、扎带、木箱、金属箱、蛇皮袋、防撞角、等非瓦楞纸箱包装；桶状、条状、拼箱、等不规则形状。外箱缠绕过多透明胶带，也有概率在国外被识别成缠膜或者吸塑包装。尾端快递派送途中因挤压导致箱体变形，畸形等，也会有概率被判定成异形件。最终判定标准与结果以快递官方为准。 补收政策：相关异形费用，我司会根据快递服务商的账单进行实报实销。 4、卡派打板标准：按照1.8CBM/板，不足的按照实际方数计算，卡板尺寸40*48*72inch，单板不超过1000bl；超尺寸/超重请单询,如收货方无卸货能力也需单询，单票计费重量不低于10KG。 亚马逊卡派最长边130CM-180CM ，包税+0.8元/KG，不包税+140元/CBM; 亚马逊卡派最长边180CM-220CM ，包税+1.7元/KG，不包税+280元/CBM;以上超长附加费只适用于非海陆渠道（海陆渠道超180CM单询） 注意事项:超2.2米单询;最长边不超1.2m，第二边长超过1米不需要加收;最长边超过1.2米，第二边长超过1米附加费单询； 5、快递派单箱收费重未达到12KG，按照12KG计费；单票收费重不足12KG，按照12KG计费。 6、直送渠道：货型要求，单件实重不超22.3KG，次长边不超63cm，最长边不超91cm，但如因此尺寸拒收，产生的额外改拆，打托，派送等费用按照RMB0.4/KG，80/CBM收取。 7、美国空运渠道快递派送标准及收费要求，请按照美国空运渠道注意事项。 8、美国海运渠道如需指定快递或快递专用地址 ，超长超重超围长超偏远等按打单实际费用收取。 | C12: 1、单票品名超5个加收15元/个； 2、私人地址：+1元/KG（非亚马逊地址）； 3、偏远地址：+480元/件（需要提供具体地址单询）； 4、超尺寸：+300元/件（需要提供具体尺寸单询）；非兼容包裹费用70元/件（DPD异形包裹，详细请咨询我司客服）。 5、产品包税附加费，请参考“英国专线附加费清单 ”； 6、敏感产品： 灯类、玩具类，化妆品类，气球等确认是否购买"天图保险 "（按货值买保险）或者 "单价+1元/KG"投保（如遇到清关查验，无法清关的情况，我司会按照40元/KG赔偿）；如客户不愿投保，遇查验，无法提供认证或质量不过关等情况，我司不承担任何责任与赔偿，请知悉！！！ 7、单票如果小于2箱会加收快递提取服务费RMB50/件，单票低消2箱。 8、若需要拦截改派操作，拦截费用：1-99箱，150英镑/票；100-199箱，200英镑/票，200箱+，请单询（不含换标和派送等费用），如有其它特殊操作请单询。
C16: 英国空运
C17: 1、带磁产品： A、英国空运普货：带磁产品收取+1元/KG，低消200元/品名（普货五日提免收低消），若报关件带磁，收取480元/品名磁鉴定费用。（只收弱磁，不收强磁）； B、带电渠道：可接带磁产品； C、MGH渠道：可接带磁产品； 2、带马达、电机等产品： A、英国空运普货：马达、电机、少量干燥剂等产品收取480元/品名； B、带电渠道：可接马达、电机产品； C、MGH渠道：可接带马达、电机产品； 3、敏感类产品： A、英国空运普货：带电，带液体，带粉末颗粒仓库查出罚款5000元/票起，机场查验代收安检罚金5000元/票起；少量配件带酒精棉收取+1元/KG；低消200元/票，报关件收取480元/票； B、带电渠道：可接带电产品，不接液体粉末 C、MGH渠道：可接液体、粉末、颗粒产品等，产品请提前单询 4、超轻费：单箱平均重量未达到12KG请参照超轻费表； 5、木制品附加费：+1元/KG； （空运渠道木制品：报关件需客户自行提供商检单；托管报关：商检费或处理费按实报实销收取） 6、DPD派送：尺寸不超100CM*70CM*60CM；单箱实重不超过30KG！；单票最低收费重不低于12KG； 7、可接报关件：¥350/票，续页费:¥50/页(6项/页)；贸易国：中国香港/香港较敏感，建议在发货前提供报关资料审核；
A20: 产品附加费
A21: 1、可接报关件+200/票，续页费：¥50／页，要报关行提供9710/9810订单编号，¥30/个收取，1039报关件，组货费250/票（部分地区因报关系统问题，可能会有部分页面有留白，默认按超出页面为准）
A22: 2、单票品名超5个加收15元/个。
A23: 3、空运渠道：普货渠道可以接带弱磁、带马达、带电机等产品附加费分别为+1元/kg，低消200元/品名，若报关件带磁/带马达/电机，收取480元/品名。普货渠道不接带电/液体/粉末产品。带电渠道可以接带磁、带马达、带电机产品，带内置电产品等（注：纯电不接）。酒精棉 +1/KG，低消200元/票；带磁、马达、电机产品。（请在来货前确认货物是否带电、带弱磁、带马达、带电机等，如有请在运单下单系统进行标注，如未申报，被机场查出，补报以及罚款等一切费用实报实销）
A24: 4、A.托管报关，木制品达到800KG~1000kG及以上，发货前务必单询。 木制品非报关件（国内）-包税：+0.5元/KG---不包税:+89元/CBM； 最高按￥800元/票标准收取； B.手册报关如不能提供核注清单，另外+150/票 （空运渠道木制品：报关件/托管报关，商检费或处理费按实报实销收取）
A25: 5、服装类/鞋子类、纯纺织品（纺织成分含80%及以上）+1元/KG
A26: 6、箱包类/行李箱/收纳箱/包包+1元/KG
A27: 7、健身器材类+1元/KG | C27: 英国海运
A28: 8、自行车类&自行车配件+1元/KG | C28: 1、木制品附加费：+350元/票； （海运木制品：报关件需客户自行提供商检单；托管报关：木制品达到800KG~1000kG及以上，发货前务必单询。） 2、报关件：¥200/票，续页费：¥50/页；贸易国：中国香港/香港较敏感，建议在发货前提供报关资料审核；要报关行提供9710/9810订单编号，¥30/个收取，1039报关件，组货费250/票（部分地区因报关系统问题，可能会有部分页面有留白，默认按超出页面为准）；手册报关不能提供核注清单，另外+150/票。 3、DPD派送：尺寸不超100CM*70CM*60CM；单箱实重不超过30KG； 4、低消：单票最低收费重不低于12KG；单箱计费重不足12KG，按照12KG计费； 5、卡派限制：①亚马逊地址：最长边＜120CM，长+2*(宽+高)＜300CM，超出请单询，实重＞28KG，请单询，单票收费体积最低1CBM起收，不足1CBM照1CBM计费；②非亚马逊地址：尺寸不超120CM*100CM*150CM，单票收费体积最低1.5CBM起收，不足1.5CBM照1.5CBM计费。 卡派续收费重不足0.1CBM，按照0.1CBM计算；
A29: 9、高货值+2元/KG
A30: 10.材质为纯钢铁铝/铜制品+1.5元/KG，（详情见后页海关编码）
A31: 11.金属类按照实际材质如实申报，否则按照钢铁铝铜处理，加收相应附加费
A32: 12.注意：高货值与其它附加费叠加收取
A33: 拒收产品
A34: 1：FDA产品：与皮肤接触类产品例如简易的美容仪、脸部按摩仪、牙刷头、电动牙刷、眼镜等需FDA认证产品。
A35: 2：侵权产品：动漫或政治人物外观侵权、蓝牙标及包装有蓝牙字样及标识产品，三叉戟数据线，CE,HDMI,FCC,LACEY ACT DOT标识。
A36: 3：违禁品：护照身份证私人物品，打火机(包括USB打火机),手机，电子烟，安全锤，纯电池，折叠刀（按动式），蝴蝶刀，危险品，液体，木箱/铁箱等包装难以打开检查的货物，不规则货物，非纸箱货物等。
A37: 4：反倾销类产品：折叠礼品盒，铁钳合金，邹纹纸，天然猪鬃油漆刷及刷头，重煅造手工具，带横线的纸，刹车转子，无可锻性铸铁管件，镁金属，铁制建筑铸件，纯镁，圆锥滚子轴承及部件，硅金属，草坪和花园铁制栅栏支架 | C37: 英国中英快卡/铁卡
A38: ，彩色电视机，氯代异氰，碳钢焊接接口，落地式金属台面烫衣板及部件，石油蜡烛，钢筋，铸造焦碳，原聚酯棉印花布，螺旋形弹簧锁垫圈，定尺碳钢板，颗粒状纯镁，热轧碳钢板，棕刚玉，曲别针，搪瓷厨具， 硅锰合金，"可锻性玛钢管件"，咔唑紫颜料，圆形焊接碳钢管件，新充气工程机械轮胎，低克重热敏纸，未加工橡胶磁，小直径石墨电极，圆形焊接奥氏体不锈高压套管，汽车大灯及汽车设备部件，贱金属及其制品(铁、钢、铜、镍、铝、铅、锌、锡、钨), 化学产品，木制卧室家具，复合木地板，非晶硅织物，晶体硅光伏电池，机械电气设备及部件，纸及纸制品，纺织制品-聚酯人造纤维，编织电热毯，预制食品与饮料，复合编织袋，聚乙烯手提袋，矿石及矿物燃料，家用电器，自行车，车船运输设备及部件， 建材与玻璃制品、轮胎、手推车，电动滑板车，独轮车（平衡车）、钢钉，铅笔，折叠型金属桌等。 | C38: 1、木制品附加费：+1元/KG，报关件需客户自行提供商检单； 2、产品必须如实申报，包括品牌，型号等，如因瞒报，漏报等而产生的后果，由客户自行承担； 3、超轻费：单箱平均重量未达到12KG请参照超轻费表； 4、DPD派送：尺寸不超100CM*70CM*60CM；单箱实重不超过30KG！； 5、低消：单票最低收费重不低于12KG； 6、卡派派送：尺寸不超150CM*120CM*100CM；亚马逊单票收费重最低100KG起收，不足100KG照100KG计； 7、英国铁卡可接报关件：¥350/票，续页费:¥50/页(6项/页)；贸易国：中国香港/香港较敏感，建议在发货前提供报关资料审核， 9710/9810订单编号，¥30/个收取。 8、英国卡航可接报关件：¥300/票，续页费:¥50/页(6项/页)；贸易国：中国香港/香港较敏感，建议在发货前提供报关资料审核， 9710/9810订单编号，¥30/个收取。
A39: 5：拒收：仿牌，冒牌，侵权、移动电源、纯电、液体、粉末、化工品、易燃易爆、点火器、军事产品、电动滑板车、食品，药品、需提供出口报关商检类产品、动植物及制品等及其他违禁品； 如检查有冲货行为，我司将没收货物，并处以1000元的罚金，情节严重者移交相关执法部门处理。
A40: 6：若有其它未提及且敏感的产品，请单询！ | E40: 英国超轻费附加费表（DPD）
A41: 备注 | C41: 备注 | E41: 国家 | F41: 5KG-6.5KG | H41: 7KG-9.5KG | J41: 10KG-12KG | L41: 12.5KG-15KG
A42: 1、如亚马逊或者海外仓仓库因包装问题产生拒收等原因，我司不承担任何责任，我司不再对包装做任何审核.发往亚马逊货物请自行贴好入仓FBA标签贴纸，每件外箱包装上须粘贴2个以上合格的FBA标签贴纸并用透明胶布覆盖(必须达到条码字体清晰、防潮湿耐磨损)，如因FBA标签不能被识别导致无法派送入亚玛逊仓库所带来的后果将由发件人自行承担！ 2、租用货拉拉或外地客户通过物流发货到我司, 须按我司流程提前向我司客服提交<货拉拉交货清单>, 样本请联系我司客服, 货拉拉司机到仓后须填写<货拉拉交货清单> 3、我司无法保证逐一审核所有货物发票、箱单、外箱包装等，若申报的产品品名，数量与实际不符或货物包装所产生的任何问题和费用，由发件方承担，我司不承担任何责任； 关于（含税线路）查验费用说明： 1.海关例行抽查且最终未产生任何问题（包含未产生通关费）且正常放行所产生的操作费，如调柜、掏箱、场地使用等费用。海关本身不收取查验费，但查验过程中使用码头资源和人工会产生费用，由物流方/约定方承担。 2.因客户提供的产品信息、单证（如品名、数量、价值、许可证等）有问题导致查验、扣货、罚款等一切后果及相关费用，由客户方承担。 3.申报货值不符合海关要求（如低于销售链接价值的30%或CIF贸易条款标准）时，海关要求补缴的税款及相关费用，由客户方承担。 | C42: 1、如亚马逊或者海外仓仓库因包装问题产生拒收等原因，我司不承担任何责任，我司不再对包装做任何审核.发往亚马逊货物请自行贴好入仓FBA标签贴纸，每件外箱包装上须粘贴2个以上合格的FBA标签贴纸并用透明胶布覆盖(必须达到条码字体清晰、防潮湿耐磨损)，如因FBA标签不能被识别导致无法派送入亚玛逊仓库所带来的后果将由发件人自行承担！ 2、租用货拉拉或外地客户通过物流发货到我司, 须按我司流程提前向我司客服提交<货拉拉交货清单>, 样本请联系我司客服, 货拉拉司机到仓后须填写<货拉拉交货清单> 3、我司无法保证逐一审核所有货物发票、箱单、外箱包装等，若申报的产品品名，数量与实际不符或货物包装所产生的任何问题和费用，由发件方承担，我司不承担任何责任； 关于（含税线路）查验费用说明： 1.海关例行抽查且最终未产生任何问题（包含未产生通关费）且正常放行所产生的操作费，如调柜、掏箱、场地使用等费用。海关本身不收取查验费，但查验过程中使用码头资源和人工会产生费用，由物流方/约定方承担。 2.因客户提供的产品信息、单证（如品名、数量、价值、许可证等）有问题导致查验、扣货、罚款等一切后果及相关费用，由客户方承担。 3.申报货值不符合海关要求（如低于销售链接价值的30%或CIF贸易条款标准）时，海关要求补缴的税款及相关费用，由客户方承担。 | E42: 英国 | F42: 4.5/KG | H42: 2/KG | J42: 1/KG | L42: 免
E43: 单票平均重量不足12KG附加费表 不足0.5KG按照0.5KG进制且不足1KG按照1KG进制
A45: 注意事项 | C45: 注意事项
A46: 1、此渠道申报的中英文品名以及产品数量，务必以实际为准，如出现瞒报、冲货等现象，经仓库/海关查验所产生的罚金以及额外费用，均有贵司自行承担。品名，数量，材质，品牌等不对应，当前渠道可走货物，罚款1000元 【FBA如查出实际货物与申报不符：罚款5000元，私人地址如查出实际货物与申报不符：罚款60000元】 2、如因客户产品自身问题：产品不具备CE认证，没有贴CE标签或者产品配件不符合欧盟国家的要求等原因导致海关扣关。我司会负责协助清关处理，但不承担责任 3、产品没有如实申报、侵犯知识产权或者欧盟禁止进口导致海关扣关。 4、当地海关认定货物是品牌货物，或者如CE、蓝牙、HDMI、FDA、FCC、Lacey Act、DOT（不限于以上列举）等等认证的问题，或者货物属于当地反倾销货物或不符合当地进口要求的货物，发件人应于发货前提供相应授权书或认证报告，如未提供导致货物扣关甚至退运而产生的，所有责任和相关费用将由发件人承担。 5、此渠道交货后，需更改派送地址、须在我司出仓前提出申请，出仓后只能尝试性扣货并且会产生额外的费用。 6、美国海运带电产品（非危险品，不超功率产品-单电池不超20WH，电池组不超100WH）默认客户资料齐全，包括但不限于海关、船司等方面进行查验，我司会配合并要求发货方提供MSDS（产品、型号、颜色等），UN38.3（电池），运输鉴定报告（产品、型号、颜色等）等文件，如无法提供，所有风险，责任及费用将全额向发货方收取；（美森正班渠道报关件拒收）。 7、由于客户自行向快递官方发起开查，我司打单账号可能会被官方警告，所以快递派开查索赔只能由我司发起，开查索赔只有一个通道，不允许客户私自发起开查索赔。一旦发生客户私自开查的情况，我司将不再提供售后服务且不承担相关赔偿。请知悉。 8、由于我司每个渠道收尾货会存在全口岸调货或者渠道升舱的情况，故客户一旦送货，就视同默认我司有自主配货和调货权。 | C46: 1、此渠道申报的中英文品名以及产品数量，务必以实际为准，如出现瞒报、冲货等现象，经仓库/海关查验所产生的罚金以及额外费用，均有贵司自行承担。【罚金RMB5000/品名以上】 品名，数量，材质，品牌等不对应，当前渠道可走货物，罚款1000元 【FBA如查出实际货物与申报不符：罚款5000元，私人地址如查出实际货物与申报不符：罚款60000元】 2、如因客户产品自身问题：产品不具备CE认证，没有贴CE标签或者产品配件不符合欧盟国家的要求等原因导致海关扣关。我司会负责协助清关处理，但不承担责任； 3、产品没有如实申报、侵犯知识产权或者欧盟禁止进口导致海关扣关； 4、当地海关认定货物是品牌货物，或者如CE、蓝牙、HDMI、FDA、FCC、Lacey Act、DOT（不限于以上列举）等等认证的问题，或者货物属于当地反倾销货物或不符合当地进口要求的货物，发件人应于发货前提供相应授权书或认证报告，如未提供导致货物扣关甚至退运而产生的，所有责任和相关费用将由发件人承担； 5、此渠道交货后，需更改派送地址、须在我司出仓前提出申请，出仓后只能尝试性扣货并且会产生额外的费用。 6、尾端交仓后若收件方私自联系承运商修改地址，会产生改单等费用（产生费用以我司报出价格收取），同时会造成货物延误，甚至出现丢件或退回等情况，此类问题需客户自行承担费用及风险。如需要拦截货物，请联系我司操作处理。
A51: 赔偿说明 | C51: 赔偿说明
A52: 1、 未上网提取（即货未交快递前）丢件、损害等，赔付标准如下： 1）按货值赔偿，货值以委托人采购成本价为准。 2）整箱丢失无法证明该箱重量，产品数量和品名，按单箱平均采购价值计算，采购价值参考1688平台同类产品价格。 3）非整箱丢失，货物外包装完好的，托运人自行承担损失。 4）本条赔付最高赔付标准不超过40元/kg，加退运费。 2、已上网提取（即货已交快递后）丢件、损害等，责任归实际承运人本地快递。己上网提取丢件，按照尾程快递官方赔偿准则进行赔付，最高不超过100USD/票。 因收件人地址关门/地址不明确/搬家等快递上门派送时无法获得正确派送地址，而导致退件或继而产生丢件的，此种情况产生的责任和损失，由托运人自己承担。 3、索赔程序：同批次货物派送后，请客户在签收后7-10个工作日内查询FBA后台是否上架，如递送后45个自然日内提供货物未上架，请提供后台截图至我司客服，开启索赔程序(需带有电脑屏幕右下角当下真实时间)；如递送后超过20工作日未开启索赔程序的，不予受理。 4、扣关赔偿：如因发件人低申报、品名申报不符、产品涉及反倾销、认证、侵权等不符合当地法规的，由此产生的责任和损失，由发件人承担，我司保留追究法律责任的权利且不予任何赔偿。 5、卡派服务，签收后超过60个自然日，由于FBA货件编码失效，导致ISA失效，故无法受理提供ISA和赔付，递送后需在180内提出受理申请，逾期超过180天的诉求不予受理。 6、①在UPS/FedEx完成交仓后，若发生漏扫描现象，暂不提供延时赔付服务。 ②若需申请UPS/FedEx调查，必须在货物提取后的75天内提出申请。若超过75天提出调查申请，我司将协助客户向UPS/FedEx发起调查。调查及赔偿结果将依据UPS/FedEx官方的规定执行。 ③对于UPS交仓后，若官网显示货物未提取/未派送，客户应在打单后的90天内提交调查申请。调查及赔偿结果将依据UPS/FedEx官方的规定执行。 ④延时赔付请于快递提取/卡车交付后60天内提交索赔函，超时不予以赔偿；延时赔付金额最高至运费抵完。 | C52: 1、未上网提取（即货未交DPD或其他国外本地快递前）丢件、损害等，赔付标准如下： 1）按货值赔偿，货值以委托人采购成本价为准。 2）整箱丢失无法证明该箱重量，产品数量和品名，按单箱平均采购价值计算，采购价值参考1688平台同类产品价格。 3）非整箱丢失，货物外包装完好的，托运人自行承担损失。 4）本条赔付最高赔付标准不超过40元/kg，加退运费。 2、已上网提取（即货已交快递后）丢件、损害等，责任归实际承运人本地快递。已上网提取丢件，按申报价值赔偿最高不超过100USD/票。 因收件人地址关门/地址不明确/搬家等快递上门派送时无法获得正确派送地址，而导致退件或继而产生丢件的，此种情况产生的责任和损失，由托运人自己承担。 3、索赔程序： 1）同航班/提单/车次提取后未签收或未提取的，请于60天内，提供对应的亚马逊未上架截图/私人地址未收到货物证明，开启索赔程序(需带有电脑屏幕右下角当下真实时间)；①开查超45个工作日客户仍未上架，可发起索赔；索赔在30天内有效。②赔偿函需在确认当日，30天内签回，逾期未签回将不予赔付。③开查在同批次货物提取后60天内有效，如超60天未发起开查，我司会配合开查，但不给予赔偿； 2）延时赔付请于快递提取/卡车交付后60天内提交索赔函，超时不予以赔偿；赔偿函需在30天内签回，逾期未签回将不予赔付；延时赔付金额最高至运费抵完。 在快递完成交仓后，若发生漏扫描现象，暂不提供延时赔付服务。 4、扣关：如因发件人低申报、品名申报不符、产品涉及反倾销、认证、侵权等不符合当地法规的，由此产生的责任和损失，由发件人承担，我司保留追究法律责任的权利且不予任何赔偿。建议您单价+1元/KG，购买天图保险。如遇到有清关查验，无法清关的情况，我司会按照40元/KG赔偿（不退运费），请知悉！
A57: 7、 A.送错仓，赔付1元/KG+亚马逊平台瑕疵费； B.送仓时若未按我司仓库要求进行排队卸货，送货司机自行卸货，从而导致的货损，货丢等情况，不在我司赔付范围内； C.客户下单拣货货后如需更改收货地址，第1次免费，2次及以上100元/次； D.仓库拍摄增值服务，收费如下： 1.拍摄照片：第1-5张，10元/张；第6-7张，50元/张，超过以上张数不接受服务； 2.拍摄视频：100元/次； | C57: 温馨提示
C58: 1）交货时请备注好清楚的交货代码渠道,若备注不清晰,我司一律以该服务商最贵的渠道结算； 2）交货时请将清单、面单、发票等检查清楚，是否互相统一，若出现其中二者不符，我司不予收货操作； 3）此线路需现结支付货款，申报的产品品名，种类，数量与实际不符、侵权、货物本身问题所产生的任何问题，我司不承担任何责任； 4）对于需要合并报关的货物，请在送达仓库之前完成下单并同一车同一时间入仓且需在系统备注以及向我司服务团队提供合并报关的相关数据，以防止报关件被分散装柜，造成物流风险; 5）单独询价货物，请在入仓前进行询价，并在核对确认价格后再进行入仓，以免造成货物错装等问题。
A59: 关于不包税渠道，注意事项： | C59: 关于查验
A60: 1）下单时需要提供产品的销售链接；无销售链接的情况，会根据亚马逊美国站同款/类似款式的产品，采用平均售价方式，核定销售单价； 2）根据申报总额预收关税，计算公式如下：预收关税=（申报总额*税率）+（申报总额*港建费0.125%）+（申报总额*商品处理费0.3464%）； 3）不包税渠道：不含关税的税费，查验及查验而产生的查验费，仓租，柜租，托架等相关费用实报实销；查验及查验相关费用统一按65CBM摊分；查验而产生的相关费用，请在出具账单2天内完成支付，逾期导致扣货等相关费用，客户自行承担。 4）如送货前未及时与我司确认申报单价，申报海关编码，申报产品等信息，默认按我司建议的申报单价及海关编码申报；冲货类产品走我司不包税渠道，需客户自行提供进口商，安排清关。 | C60: 1）海关查验，会产生查验费，以及仓租等杂费： 查验费：75GBP/票。 仓储费：前两天免仓租（含进仓当天），从第三天起算：A、50件以下--1镑/箱/天；B、 50件以上（含50件）--10镑/方/天
C62: 弃货
C63: 1）海关查验时长产生的额外费用大于货值，建议弃货处理，具体额外费用，实报实销。
C64: 关于产生费用收取标准：
C65: 涉及国内外查验所产生的异常费用(如罚款等)通常并非一次性生成，而是分多次陆续产生，为进一步规范国内外查验环节中因客户货物问题所产生费用的收取流程，相关操作要求明确如下: 一、费用预收机制 如遇国内查验，统一预收费用 人民币1万元 如遇国外查验，统一预收费用 人民币2万元 二、账单结算与逾期处理 相关罚款账单将采取现结方式; 如客户逾期未付，系统将执行锁单操作，并通知海外仓对相应货物进行扣货处理。 三、最终结算 所有实际费用结清后，公司将根据实际发生金额进行“多退少补"。
A66: 温馨提示
A67: 1） 交货时请备注好清楚的交货代码渠道,若备注不清晰,我司一律以该服务商最贵的渠道结算 2） 交货时请将清单、面单、发票等检查清楚，是否互相统一，若出现其中二者不符，我司不予收货操作！ 3）此渠道需现结支付货款，申报的产品品名，种类，数量与实际不符、侵权、货物本身问题所产生的任何问题，我司不承担任何责任； 4）对于需要合并报关的货物，请在送达仓库之前完成下单并同一车同一时间入仓且需在系统备注以及向我司服务团队提供合并报关的相关数据，以防止报关件被分散装柜，造成物流风险; 5）为保障仓库快进快出装柜，发货前请确认货物渠道是否准确，凡在周五、周六送仓的货物，一旦入仓，将不再接受任何渠道更改的请求;如有拦截要求，可能无法拦截成功，请及时与服务团队联系； 6）单独询价货物，请在入仓前进行询价，并在核对确认价格后再进行入仓，以免造成货物错装等问题。
A70: 弃货 | C70: 贵司一旦交货，我司则视已阅读并默认以上所有内容!
A71: 1)海关查验时长产生的额外费用大于货值，建议弃货处理，具体额外费用，实报实销。
A72: 关于产生费用收取标准：
A73: 涉及国内外查验所产生的异常费用(如罚款等)通常并非一次性生成，而是分多次陆续产生，为进一步规范国内外查验环节中因客户货物问题所产生费用的收取流程，相关操作要求明确如下: 一、费用预收机制 如遇国内查验，统一预收费用 人民币1万元 如遇国外查验，统一预收费用 人民币2万元 二、账单结算与逾期处理 相关罚款账单将采取现结方式; 如客户逾期未付，系统将执行锁单操作，并通知海外仓对相应货物进行扣货处理。 三、最终结算 所有实际费用结清后，公司将根据实际发生金额进行“多退少补"。 从拣货时间2026/3/31 14：00开始，此报价表包含如遇美国海关5H查验，相关仓租、柜租、查验费、退运指定启运港的来回运费全包;不包含贴标换标费、暂存仓租费，不含改派送地址的派送费(实际派送地址-原先派送地址，差价多退少补)，不含弃货，无时效赔偿，首次运费需正常支付，发货默认此条款； 国内查验宝：包税+0.1元/KG，不包税+18元/CBM（含货物申报和实际申报一致时所遇查验，不含冲货、申报不符合、瞒报等不符合正常报关流程等情况）
A79: 贵司一旦交货，我司则视已阅读并默认以上所有内容!

Sheet 英国价格查询表
A1: 天图通逊供应链有限公司 立志打造一家具有社会价值的百年跨境物流企业 | R1: 其它 | S1: 12-99KG | T1: 深圳 | U1: 华南
R2: {=_xlfn.UNIQUE(INDIRECT("'英国海运-卡派(23-40) '!A7:A"&COUNTA(#REF!)))} -> #REF! | S2: 100KG+ | T2: 广州 | U2: 华南
A3: 价格快速查询栏 | S3: 300KG+ | T3: 中山 | U3: 华南
A4: 备注： “美国”渠道不在本快速查找范围，请查询报价表内页详情。 | C4: 目的仓 | D4: 国内仓 | E4: 公斤段 | F4: 时间 | S4: 15CBM+ | T4: 泉州 | U4: 厦门/泉州
C5: BHX4 | D5: 厦门 | E5: 15CBM+ | F5: =TODAY() -> 46202 | T5: 厦门 | U5: 厦门/泉州
T6: 义乌 | U6: 华东
A7: 运输方式 | B7: 渠道类型 | C7: 包税 | D7: 不包税 | E7: 签收时效 | F7: 延时赔付 | G7: 备注 | T7: 上海 | U7: 华东
A8: 空运 | B8: 英国（普货）-五日提（分泡50%） | C8: {=_xlfn.LET(_xlpm.X,#REF!,IFERROR(IF(D5="深圳",_xlfn._xlws.FILTER(_xlpm.X,(#REF!=E5)*(ISNUMBER(FIND(D5,#REF!,1)))),IF(D5="广州",_xlfn._xlws.FILTER(_xlpm.X,(#REF!=E5)*(ISNUMBER(FIND(D5,#REF!,1)))),IF(D5="中山",_xlfn._xlws.FILTER(_xlpm.X,(#REF!=E5)*(ISNUMBER(FIND(D5,#REF!,1)))),IF(D5="泉州",_xlfn._xlws.FILTER(_xlpm.X,(#REF!=E5)*(ISNUMBER(FIND(D5,#REF!,1)))),IF(D5="厦门",_xlfn._xlws.FILTER(_xlpm.X,(#REF!=E5)*(ISNUMBER(FIND(D5,#REF!,1)))),IF(D5="义乌",_xlfn._xlws.FILTER(_xlpm.X,(#REF!=E5)*(ISNUMBER(FIND(D5,#REF!,1)))),IF(D5="上海",_xlfn._xlws.FILTER(_xlpm.X,(#REF!=E5)*(ISNUMBER(FIND(D5,#REF!,1))))))))))),"-"))} -> - | D8: {=_xlfn.LET(_xlpm.X,#REF!,IFERROR(IF(D5="深圳",_xlfn._xlws.FILTER(_xlpm.X,(#REF!=E5)*(ISNUMBER(FIND(D5,#REF!,1)))),IF(D5="广州",_xlfn._xlws.FILTER(_xlpm.X,(#REF!=E5)*(ISNUMBER(FIND(D5,#REF!,1)))),IF(D5="中山",_xlfn._xlws.FILTER(_xlpm.X,(#REF!=E5)*(ISNUMBER(FIND(D5,#REF!,1)))),IF(D5="泉州",_xlfn._xlws.FILTER(_xlpm.X,(#REF!=E5)*(ISNUMBER(FIND(D5,#REF!,1)))),IF(D5="厦门",_xlfn._xlws.FILTER(_xlpm.X,(#REF!=E5)*(ISNUMBER(FIND(D5,#REF!,1)))),IF(D5="义乌",_xlfn._xlws.FILTER(_xlpm.X,(#REF!=E5)*(ISNUMBER(FIND(D5,#REF!,1)))),IF(D5="上海",_xlfn._xlws.FILTER(_xlpm.X,(#REF!=E5)*(ISNUMBER(FIND(D5,#REF!,1))))))))))),"-"))} -> - | E8: {=_xlfn.LET(_xlpm.X,#REF!,IFERROR(IF(D5="深圳",_xlfn._xlws.FILTER(_xlpm.X,(#REF!=E5)*(ISNUMBER(FIND(D5,#REF!,1)))),IF(D5="广州",_xlfn._xlws.FILTER(_xlpm.X,(#REF!=E5)*(ISNUMBER(FIND(D5,#REF!,1)))),IF(D5="中山",_xlfn._xlws.FILTER(_xlpm.X,(#REF!=E5)*(ISNUMBER(FIND(D5,#REF!,1)))),IF(D5="泉州",_xlfn._xlws.FILTER(_xlpm.X,(#REF!=E5)*(ISNUMBER(FIND(D5,#REF!,1)))),IF(D5="厦门",_xlfn._xlws.FILTER(_xlpm.X,(#REF!=E5)*(ISNUMBER(FIND(D5,#REF!,1)))),IF(D5="义乌",_xlfn._xlws.FILTER(_xlpm.X,(#REF!=E5)*(ISNUMBER(FIND(D5,#REF!,1)))),IF(D5="上海",_xlfn._xlws.FILTER(_xlpm.X,(#REF!=E5)*(ISNUMBER(FIND(D5,#REF!,1))))))))))),"-"))} -> - | F8: {=_xlfn.LET(_xlpm.X,#REF!,IFERROR(IF(D5="深圳",_xlfn._xlws.FILTER(_xlpm.X,(#REF!=E5)*(ISNUMBER(FIND(D5,#REF!,1)))),IF(D5="广州",_xlfn._xlws.FILTER(_xlpm.X,(#REF!=E5)*(ISNUMBER(FIND(D5,#REF!,1)))),IF(D5="中山",_xlfn._xlws.FILTER(_xlpm.X,(#REF!=E5)*(ISNUMBER(FIND(D5,#REF!,1)))),IF(D5="泉州",_xlfn._xlws.FILTER(_xlpm.X,(#REF!=E5)*(ISNUMBER(FIND(D5,#REF!,1)))),IF(D5="厦门",_xlfn._xlws.FILTER(_xlpm.X,(#REF!=E5)*(ISNUMBER(FIND(D5,#REF!,1)))),IF(D5="义乌",_xlfn._xlws.FILTER(_xlpm.X,(#REF!=E5)*(ISNUMBER(FIND(D5,#REF!,1)))),IF(D5="上海",_xlfn._xlws.FILTER(_xlpm.X,(#REF!=E5)*(ISNUMBER(FIND(D5,#REF!,1))))))))))),"-"))} -> - | G8: =IF(E5="15CBM+","KG价","") -> KG价 | H8: =MATCH("*"&D5&"*",#REF!,0) -> #REF!
B9: 英国（普货）-十日提（分泡50%） | C9: {=_xlfn.LET(_xlpm.X,#REF!,IFERROR(IF(D5="深圳",_xlfn._xlws.FILTER(_xlpm.X,(#REF!=E5)*(ISNUMBER(FIND(D5,#REF!,1)))),IF(D5="广州",_xlfn._xlws.FILTER(_xlpm.X,(#REF!=E5)*(ISNUMBER(FIND(D5,#REF!,1)))),IF(D5="中山",_xlfn._xlws.FILTER(_xlpm.X,(#REF!=E5)*(ISNUMBER(FIND(D5,#REF!,1)))),IF(D5="泉州",_xlfn._xlws.FILTER(_xlpm.X,(#REF!=E5)*(ISNUMBER(FIND(D5,#REF!,1)))),IF(D5="厦门",_xlfn._xlws.FILTER(_xlpm.X,(#REF!=E5)*(ISNUMBER(FIND(D5,#REF!,1)))),IF(D5="义乌",_xlfn._xlws.FILTER(_xlpm.X,(#REF!=E5)*(ISNUMBER(FIND(D5,#REF!,1)))),IF(D5="上海",_xlfn._xlws.FILTER(_xlpm.X,(#REF!=E5)*(ISNUMBER(FIND(D5,#REF!,1))))))))))),"-"))} -> - | D9: {=_xlfn.LET(_xlpm.X,#REF!,IFERROR(IF(D5="深圳",_xlfn._xlws.FILTER(_xlpm.X,(#REF!=E5)*(ISNUMBER(FIND(D5,#REF!,1)))),IF(D5="广州",_xlfn._xlws.FILTER(_xlpm.X,(#REF!=E5)*(ISNUMBER(FIND(D5,#REF!,1)))),IF(D5="中山",_xlfn._xlws.FILTER(_xlpm.X,(#REF!=E5)*(ISNUMBER(FIND(D5,#REF!,1)))),IF(D5="泉州",_xlfn._xlws.FILTER(_xlpm.X,(#REF!=E5)*(ISNUMBER(FIND(D5,#REF!,1)))),IF(D5="厦门",_xlfn._xlws.FILTER(_xlpm.X,(#REF!=E5)*(ISNUMBER(FIND(D5,#REF!,1)))),IF(D5="义乌",_xlfn._xlws.FILTER(_xlpm.X,(#REF!=E5)*(ISNUMBER(FIND(D5,#REF!,1)))),IF(D5="上海",_xlfn._xlws.FILTER(_xlpm.X,(#REF!=E5)*(ISNUMBER(FIND(D5,#REF!,1))))))))))),"-"))} -> - | E9: {=_xlfn.LET(_xlpm.X,#REF!,IFERROR(IF(D5="深圳",_xlfn._xlws.FILTER(_xlpm.X,(#REF!=E5)*(ISNUMBER(FIND(D5,#REF!,1)))),IF(D5="广州",_xlfn._xlws.FILTER(_xlpm.X,(#REF!=E5)*(ISNUMBER(FIND(D5,#REF!,1)))),IF(D5="中山",_xlfn._xlws.FILTER(_xlpm.X,(#REF!=E5)*(ISNUMBER(FIND(D5,#REF!,1)))),IF(D5="泉州",_xlfn._xlws.FILTER(_xlpm.X,(#REF!=E5)*(ISNUMBER(FIND(D5,#REF!,1)))),IF(D5="厦门",_xlfn._xlws.FILTER(_xlpm.X,(#REF!=E5)*(ISNUMBER(FIND(D5,#REF!,1)))),IF(D5="义乌",_xlfn._xlws.FILTER(_xlpm.X,(#REF!=E5)*(ISNUMBER(FIND(D5,#REF!,1)))),IF(D5="上海",_xlfn._xlws.FILTER(_xlpm.X,(#REF!=E5)*(ISNUMBER(FIND(D5,#REF!,1))))))))))),"-"))} -> - | F9: {=_xlfn.LET(_xlpm.X,#REF!,IFERROR(IF(D5="深圳",_xlfn._xlws.FILTER(_xlpm.X,(#REF!=E5)*(ISNUMBER(FIND(D5,#REF!,1)))),IF(D5="广州",_xlfn._xlws.FILTER(_xlpm.X,(#REF!=E5)*(ISNUMBER(FIND(D5,#REF!,1)))),IF(D5="中山",_xlfn._xlws.FILTER(_xlpm.X,(#REF!=E5)*(ISNUMBER(FIND(D5,#REF!,1)))),IF(D5="泉州",_xlfn._xlws.FILTER(_xlpm.X,(#REF!=E5)*(ISNUMBER(FIND(D5,#REF!,1)))),IF(D5="厦门",_xlfn._xlws.FILTER(_xlpm.X,(#REF!=E5)*(ISNUMBER(FIND(D5,#REF!,1)))),IF(D5="义乌",_xlfn._xlws.FILTER(_xlpm.X,(#REF!=E5)*(ISNUMBER(FIND(D5,#REF!,1)))),IF(D5="上海",_xlfn._xlws.FILTER(_xlpm.X,(#REF!=E5)*(ISNUMBER(FIND(D5,#REF!,1))))))))))),"-"))} -> - | G9: =IF(E5="15CBM+","KG价","") -> KG价
B10: 英国（带电）-十日提（分泡50%） | C10: {=_xlfn.LET(_xlpm.X,#REF!,IFERROR(IF(D5="深圳",_xlfn._xlws.FILTER(_xlpm.X,(#REF!=E5)*(ISNUMBER(FIND(D5,#REF!,1)))),IF(D5="广州",_xlfn._xlws.FILTER(_xlpm.X,(#REF!=E5)*(ISNUMBER(FIND(D5,#REF!,1)))),IF(D5="中山",_xlfn._xlws.FILTER(_xlpm.X,(#REF!=E5)*(ISNUMBER(FIND(D5,#REF!,1)))),IF(D5="泉州",_xlfn._xlws.FILTER(_xlpm.X,(#REF!=E5)*(ISNUMBER(FIND(D5,#REF!,1)))),IF(D5="厦门",_xlfn._xlws.FILTER(_xlpm.X,(#REF!=E5)*(ISNUMBER(FIND(D5,#REF!,1)))),IF(D5="义乌",_xlfn._xlws.FILTER(_xlpm.X,(#REF!=E5)*(ISNUMBER(FIND(D5,#REF!,1)))),IF(D5="上海",_xlfn._xlws.FILTER(_xlpm.X,(#REF!=E5)*(ISNUMBER(FIND(D5,#REF!,1))))))))))),"-"))} -> - | D10: {=_xlfn.LET(_xlpm.X,#REF!,IFERROR(IF(D5="深圳",_xlfn._xlws.FILTER(_xlpm.X,(#REF!=E5)*(ISNUMBER(FIND(D5,#REF!,1)))),IF(D5="广州",_xlfn._xlws.FILTER(_xlpm.X,(#REF!=E5)*(ISNUMBER(FIND(D5,#REF!,1)))),IF(D5="中山",_xlfn._xlws.FILTER(_xlpm.X,(#REF!=E5)*(ISNUMBER(FIND(D5,#REF!,1)))),IF(D5="泉州",_xlfn._xlws.FILTER(_xlpm.X,(#REF!=E5)*(ISNUMBER(FIND(D5,#REF!,1)))),IF(D5="厦门",_xlfn._xlws.FILTER(_xlpm.X,(#REF!=E5)*(ISNUMBER(FIND(D5,#REF!,1)))),IF(D5="义乌",_xlfn._xlws.FILTER(_xlpm.X,(#REF!=E5)*(ISNUMBER(FIND(D5,#REF!,1)))),IF(D5="上海",_xlfn._xlws.FILTER(_xlpm.X,(#REF!=E5)*(ISNUMBER(FIND(D5,#REF!,1))))))))))),"-"))} -> - | E10: {=_xlfn.LET(_xlpm.X,#REF!,IFERROR(IF(D5="深圳",_xlfn._xlws.FILTER(_xlpm.X,(#REF!=E5)*(ISNUMBER(FIND(D5,#REF!,1)))),IF(D5="广州",_xlfn._xlws.FILTER(_xlpm.X,(#REF!=E5)*(ISNUMBER(FIND(D5,#REF!,1)))),IF(D5="中山",_xlfn._xlws.FILTER(_xlpm.X,(#REF!=E5)*(ISNUMBER(FIND(D5,#REF!,1)))),IF(D5="泉州",_xlfn._xlws.FILTER(_xlpm.X,(#REF!=E5)*(ISNUMBER(FIND(D5,#REF!,1)))),IF(D5="厦门",_xlfn._xlws.FILTER(_xlpm.X,(#REF!=E5)*(ISNUMBER(FIND(D5,#REF!,1)))),IF(D5="义乌",_xlfn._xlws.FILTER(_xlpm.X,(#REF!=E5)*(ISNUMBER(FIND(D5,#REF!,1)))),IF(D5="上海",_xlfn._xlws.FILTER(_xlpm.X,(#REF!=E5)*(ISNUMBER(FIND(D5,#REF!,1))))))))))),"-"))} -> - | F10: {=_xlfn.LET(_xlpm.X,#REF!,IFERROR(IF(D5="深圳",_xlfn._xlws.FILTER(_xlpm.X,(#REF!=E5)*(ISNUMBER(FIND(D5,#REF!,1)))),IF(D5="广州",_xlfn._xlws.FILTER(_xlpm.X,(#REF!=E5)*(ISNUMBER(FIND(D5,#REF!,1)))),IF(D5="中山",_xlfn._xlws.FILTER(_xlpm.X,(#REF!=E5)*(ISNUMBER(FIND(D5,#REF!,1)))),IF(D5="泉州",_xlfn._xlws.FILTER(_xlpm.X,(#REF!=E5)*(ISNUMBER(FIND(D5,#REF!,1)))),IF(D5="厦门",_xlfn._xlws.FILTER(_xlpm.X,(#REF!=E5)*(ISNUMBER(FIND(D5,#REF!,1)))),IF(D5="义乌",_xlfn._xlws.FILTER(_xlpm.X,(#REF!=E5)*(ISNUMBER(FIND(D5,#REF!,1)))),IF(D5="上海",_xlfn._xlws.FILTER(_xlpm.X,(#REF!=E5)*(ISNUMBER(FIND(D5,#REF!,1))))))))))),"-"))} -> - | G10: =IF(E5="15CBM+","KG价","") -> KG价
B11: 英国韩国飞-MGH（分泡50%） | C11: {=_xlfn.LET(_xlpm.X,#REF!,IFERROR(IF(D5="深圳",_xlfn._xlws.FILTER(_xlpm.X,(#REF!=E5)*(ISNUMBER(FIND(D5,#REF!,1)))),IF(D5="广州",_xlfn._xlws.FILTER(_xlpm.X,(#REF!=E5)*(ISNUMBER(FIND(D5,#REF!,1)))),IF(D5="中山",_xlfn._xlws.FILTER(_xlpm.X,(#REF!=E5)*(ISNUMBER(FIND(D5,#REF!,1)))),IF(D5="泉州",_xlfn._xlws.FILTER(_xlpm.X,(#REF!=E5)*(ISNUMBER(FIND(D5,#REF!,1)))),IF(D5="厦门",_xlfn._xlws.FILTER(_xlpm.X,(#REF!=E5)*(ISNUMBER(FIND(D5,#REF!,1)))),IF(D5="义乌",_xlfn._xlws.FILTER(_xlpm.X,(#REF!=E5)*(ISNUMBER(FIND(D5,#REF!,1)))),IF(D5="上海",_xlfn._xlws.FILTER(_xlpm.X,(#REF!=E5)*(ISNUMBER(FIND(D5,#REF!,1))))))))))),"-"))} -> - | D11: {=_xlfn.LET(_xlpm.X,#REF!,IFERROR(IF(D5="深圳",_xlfn._xlws.FILTER(_xlpm.X,(#REF!=E5)*(ISNUMBER(FIND(D5,#REF!,1)))),IF(D5="广州",_xlfn._xlws.FILTER(_xlpm.X,(#REF!=E5)*(ISNUMBER(FIND(D5,#REF!,1)))),IF(D5="中山",_xlfn._xlws.FILTER(_xlpm.X,(#REF!=E5)*(ISNUMBER(FIND(D5,#REF!,1)))),IF(D5="泉州",_xlfn._xlws.FILTER(_xlpm.X,(#REF!=E5)*(ISNUMBER(FIND(D5,#REF!,1)))),IF(D5="厦门",_xlfn._xlws.FILTER(_xlpm.X,(#REF!=E5)*(ISNUMBER(FIND(D5,#REF!,1)))),IF(D5="义乌",_xlfn._xlws.FILTER(_xlpm.X,(#REF!=E5)*(ISNUMBER(FIND(D5,#REF!,1)))),IF(D5="上海",_xlfn._xlws.FILTER(_xlpm.X,(#REF!=E5)*(ISNUMBER(FIND(D5,#REF!,1))))))))))),"-"))} -> - | E11: {=_xlfn.LET(_xlpm.X,#REF!,IFERROR(IF(D5="深圳",_xlfn._xlws.FILTER(_xlpm.X,(#REF!=E5)*(ISNUMBER(FIND(D5,#REF!,1)))),IF(D5="广州",_xlfn._xlws.FILTER(_xlpm.X,(#REF!=E5)*(ISNUMBER(FIND(D5,#REF!,1)))),IF(D5="中山",_xlfn._xlws.FILTER(_xlpm.X,(#REF!=E5)*(ISNUMBER(FIND(D5,#REF!,1)))),IF(D5="泉州",_xlfn._xlws.FILTER(_xlpm.X,(#REF!=E5)*(ISNUMBER(FIND(D5,#REF!,1)))),IF(D5="厦门",_xlfn._xlws.FILTER(_xlpm.X,(#REF!=E5)*(ISNUMBER(FIND(D5,#REF!,1)))),IF(D5="义乌",_xlfn._xlws.FILTER(_xlpm.X,(#REF!=E5)*(ISNUMBER(FIND(D5,#REF!,1)))),IF(D5="上海",_xlfn._xlws.FILTER(_xlpm.X,(#REF!=E5)*(ISNUMBER(FIND(D5,#REF!,1))))))))))),"-"))} -> - | F11: {=_xlfn.LET(_xlpm.X,#REF!,IFERROR(IF(D5="深圳",_xlfn._xlws.FILTER(_xlpm.X,(#REF!=E5)*(ISNUMBER(FIND(D5,#REF!,1)))),IF(D5="广州",_xlfn._xlws.FILTER(_xlpm.X,(#REF!=E5)*(ISNUMBER(FIND(D5,#REF!,1)))),IF(D5="中山",_xlfn._xlws.FILTER(_xlpm.X,(#REF!=E5)*(ISNUMBER(FIND(D5,#REF!,1)))),IF(D5="泉州",_xlfn._xlws.FILTER(_xlpm.X,(#REF!=E5)*(ISNUMBER(FIND(D5,#REF!,1)))),IF(D5="厦门",_xlfn._xlws.FILTER(_xlpm.X,(#REF!=E5)*(ISNUMBER(FIND(D5,#REF!,1)))),IF(D5="义乌",_xlfn._xlws.FILTER(_xlpm.X,(#REF!=E5)*(ISNUMBER(FIND(D5,#REF!,1)))),IF(D5="上海",_xlfn._xlws.FILTER(_xlpm.X,(#REF!=E5)*(ISNUMBER(FIND(D5,#REF!,1))))))))))),"-"))} -> - | G11: =IF(E5="15CBM+","KG价","") -> KG价
B12: 英国（普货）-促销价（分泡50%） | C12: {=_xlfn.LET(_xlpm.X,#REF!,IFERROR(IF(D5="深圳",_xlfn._xlws.FILTER(_xlpm.X,(#REF!=E5)*(ISNUMBER(FIND(D5,#REF!,1)))),IF(D5="广州",_xlfn._xlws.FILTER(_xlpm.X,(#REF!=E5)*(ISNUMBER(FIND(D5,#REF!,1)))),IF(D5="中山",_xlfn._xlws.FILTER(_xlpm.X,(#REF!=E5)*(ISNUMBER(FIND(D5,#REF!,1)))),IF(D5="泉州",_xlfn._xlws.FILTER(_xlpm.X,(#REF!=E5)*(ISNUMBER(FIND(D5,#REF!,1)))),IF(D5="厦门",_xlfn._xlws.FILTER(_xlpm.X,(#REF!=E5)*(ISNUMBER(FIND(D5,#REF!,1)))),IF(D5="义乌",_xlfn._xlws.FILTER(_xlpm.X,(#REF!=E5)*(ISNUMBER(FIND(D5,#REF!,1)))),IF(D5="上海",_xlfn._xlws.FILTER(_xlpm.X,(#REF!=E5)*(ISNUMBER(FIND(D5,#REF!,1))))))))))),"-"))} -> - | D12: {=_xlfn.LET(_xlpm.X,#REF!,IFERROR(IF(D5="深圳",_xlfn._xlws.FILTER(_xlpm.X,(#REF!=E5)*(ISNUMBER(FIND(D5,#REF!,1)))),IF(D5="广州",_xlfn._xlws.FILTER(_xlpm.X,(#REF!=E5)*(ISNUMBER(FIND(D5,#REF!,1)))),IF(D5="中山",_xlfn._xlws.FILTER(_xlpm.X,(#REF!=E5)*(ISNUMBER(FIND(D5,#REF!,1)))),IF(D5="泉州",_xlfn._xlws.FILTER(_xlpm.X,(#REF!=E5)*(ISNUMBER(FIND(D5,#REF!,1)))),IF(D5="厦门",_xlfn._xlws.FILTER(_xlpm.X,(#REF!=E5)*(ISNUMBER(FIND(D5,#REF!,1)))),IF(D5="义乌",_xlfn._xlws.FILTER(_xlpm.X,(#REF!=E5)*(ISNUMBER(FIND(D5,#REF!,1)))),IF(D5="上海",_xlfn._xlws.FILTER(_xlpm.X,(#REF!=E5)*(ISNUMBER(FIND(D5,#REF!,1))))))))))),"-"))} -> - | E12: {=_xlfn.LET(_xlpm.X,#REF!,IFERROR(IF(D5="深圳",_xlfn._xlws.FILTER(_xlpm.X,(#REF!=E5)*(ISNUMBER(FIND(D5,#REF!,1)))),IF(D5="广州",_xlfn._xlws.FILTER(_xlpm.X,(#REF!=E5)*(ISNUMBER(FIND(D5,#REF!,1)))),IF(D5="中山",_xlfn._xlws.FILTER(_xlpm.X,(#REF!=E5)*(ISNUMBER(FIND(D5,#REF!,1)))),IF(D5="泉州",_xlfn._xlws.FILTER(_xlpm.X,(#REF!=E5)*(ISNUMBER(FIND(D5,#REF!,1)))),IF(D5="厦门",_xlfn._xlws.FILTER(_xlpm.X,(#REF!=E5)*(ISNUMBER(FIND(D5,#REF!,1)))),IF(D5="义乌",_xlfn._xlws.FILTER(_xlpm.X,(#REF!=E5)*(ISNUMBER(FIND(D5,#REF!,1)))),IF(D5="上海",_xlfn._xlws.FILTER(_xlpm.X,(#REF!=E5)*(ISNUMBER(FIND(D5,#REF!,1))))))))))),"-"))} -> - | F12: {=_xlfn.LET(_xlpm.X,#REF!,IFERROR(IF(D5="深圳",_xlfn._xlws.FILTER(_xlpm.X,(#REF!=E5)*(ISNUMBER(FIND(D5,#REF!,1)))),IF(D5="广州",_xlfn._xlws.FILTER(_xlpm.X,(#REF!=E5)*(ISNUMBER(FIND(D5,#REF!,1)))),IF(D5="中山",_xlfn._xlws.FILTER(_xlpm.X,(#REF!=E5)*(ISNUMBER(FIND(D5,#REF!,1)))),IF(D5="泉州",_xlfn._xlws.FILTER(_xlpm.X,(#REF!=E5)*(ISNUMBER(FIND(D5,#REF!,1)))),IF(D5="厦门",_xlfn._xlws.FILTER(_xlpm.X,(#REF!=E5)*(ISNUMBER(FIND(D5,#REF!,1)))),IF(D5="义乌",_xlfn._xlws.FILTER(_xlpm.X,(#REF!=E5)*(ISNUMBER(FIND(D5,#REF!,1)))),IF(D5="上海",_xlfn._xlws.FILTER(_xlpm.X,(#REF!=E5)*(ISNUMBER(FIND(D5,#REF!,1))))))))))),"-"))} -> - | G12: =IF(E5="15CBM+","KG价","") -> KG价
A13: 陆运 | B13: 英国快铁25日达-卡派 | C13: {=IF(AND(AND(OR(C5="LBA4",C5="BHX4"),E5<>"12-99KG"),AND(OR(C5="LBA4",C5="BHX4"),E5<>"15CBM+")),INDEX(#REF!,MATCH("*"&D5&"*",#REF!,0)),"-")} -> - | D13: {=IF(AND(AND(OR(C5="LBA4",C5="BHX4"),E5<>"12-99KG"),AND(OR(C5="LBA4",C5="BHX4"),E5<>"15CBM+")),INDEX(#REF!,MATCH("*"&D5&"*",#REF!,0)),"-")} -> - | E13: {=IF(AND(AND(OR(C5="LBA4",C5="BHX4"),E5<>"12-99KG"),AND(OR(C5="LBA4",C5="BHX4"),E5<>"15CBM+")),INDEX(#REF!,MATCH("*"&D5&"*",#REF!,0)),"-")} -> - | F13: {=IF(AND(AND(OR(C5="LBA4",C5="BHX4"),E5<>"12-99KG"),AND(OR(C5="LBA4",C5="BHX4"),E5<>"15CBM+")),INDEX(#REF!,MATCH("*"&D5&"*",#REF!,0)),"-")} -> - | G13: =IF(AND(E5="12-99KG",F13="-"),"100KG+起收",IF(E5="15CBM+","KG价","")) -> KG价
B14: 英国快铁25日达-DPD派 | C14: {=IF(E5<>"15CBM+",INDEX(#REF!,MATCH("*"&D5&"*",#REF!,0)),"-")} -> - | D14: {=IF(E5<>"15CBM+",INDEX(#REF!,MATCH("*"&D5&"*",#REF!,0)),"-")} -> - | E14: {=IF(E5<>"15CBM+",INDEX(#REF!,MATCH("*"&D5&"*",#REF!,0)),"-")} -> - | F14: {=IF(E5<>"15CBM+",INDEX(#REF!,MATCH("*"&D5&"*",#REF!,0)),"-")} -> - | G14: =IF(E5="12-99KG","12-70KG：+2元/KG"&CHAR(10)&"71-99KG：+1元/KG",IF(E5="15CBM+","KG价","")) -> KG价
B15: 英国中英铁卡-卡派 | C15: {=IF(AND(AND(OR(C5="LBA4",C5="BHX4"),E5<>"12-99KG"),AND(OR(C5="LBA4",C5="BHX4"),E5<>"15CBM+")),INDEX(#REF!,MATCH("*"&D5&"*",#REF!,0)),"-")} -> - | D15: {=IF(AND(AND(OR(C5="LBA4",C5="BHX4"),E5<>"12-99KG"),AND(OR(C5="LBA4",C5="BHX4"),E5<>"15CBM+")),INDEX(#REF!,MATCH("*"&D5&"*",#REF!,0)),"-")} -> - | E15: {=IF(AND(AND(OR(C5="LBA4",C5="BHX4"),E5<>"12-99KG"),AND(OR(C5="LBA4",C5="BHX4"),E5<>"15CBM+")),INDEX(#REF!,MATCH("*"&D5&"*",#REF!,0)),"-")} -> - | F15: {=IF(AND(AND(OR(C5="LBA4",C5="BHX4"),E5<>"12-99KG"),AND(OR(C5="LBA4",C5="BHX4"),E5<>"15CBM+")),INDEX(#REF!,MATCH("*"&D5&"*",#REF!,0)),"-")} -> - | G15: =IF(AND(E5="12-99KG",F15="-"),"100KG+起收",IF(E5="15CBM+","KG价","")) -> KG价
B16: 英国中英铁卡-DPD派 | C16: {=IF(E5<>"15CBM+",INDEX(#REF!,MATCH("*"&D5&"*",#REF!,0)),"-")} -> - | D16: {=IF(E5<>"15CBM+",INDEX(#REF!,MATCH("*"&D5&"*",#REF!,0)),"-")} -> - | E16: {=IF(E5<>"15CBM+",INDEX(#REF!,MATCH("*"&D5&"*",#REF!,0)),"-")} -> - | F16: {=IF(E5<>"15CBM+",INDEX(#REF!,MATCH("*"&D5&"*",#REF!,0)),"-")} -> - | G16: =IF(E5="12-99KG","12-70KG：+2元/KG"&CHAR(10)&"71-99KG：+1元/KG",IF(E5="15CBM+","KG价","")) -> KG价
A17: 海运 | B17: 英国海卡(特价）-KG价 | C17: =IFERROR(IF(E5<>"15CBM+",_xlfn.LET(_xlpm.X,#REF!,_xlpm.Y,2,IF(D5="深圳",VLOOKUP(C5,_xlpm.X,_xlpm.Y,0),IF(D5="广州",VLOOKUP(C5,_xlpm.X,_xlpm.Y+1,0),IF(D5="中山",VLOOKUP(C5,_xlpm.X,_xlpm.Y+1,0),IF(D5="泉州",VLOOKUP(C5,_xlpm.X,_xlpm.Y+2,0),IF(D5="厦门",VLOOKUP(C5,_xlpm.X,_xlpm.Y+2,0),IF(D5="义乌",VLOOKUP(C5,_xlpm.X,_xlpm.Y+3,0),IF(D5="上海",VLOOKUP(C5,_xlpm.X,_xlpm.Y+4,0))))))))),"-"),"-") -> - | D17: =IFERROR(IF(E5<>"15CBM+",_xlfn.LET(_xlpm.X,#REF!,_xlpm.Y,7,IF(D5="深圳",VLOOKUP(C5,_xlpm.X,_xlpm.Y,0),IF(D5="广州",VLOOKUP(C5,_xlpm.X,_xlpm.Y+1,0),IF(D5="中山",VLOOKUP(C5,_xlpm.X,_xlpm.Y+1,0),IF(D5="泉州",VLOOKUP(C5,_xlpm.X,_xlpm.Y+2,0),IF(D5="厦门",VLOOKUP(C5,_xlpm.X,_xlpm.Y+2,0),IF(D5="义乌",VLOOKUP(C5,_xlpm.X,_xlpm.Y+3,0),IF(D5="上海",VLOOKUP(C5,_xlpm.X,_xlpm.Y+4,0))))))))),"-"),"-") -> - | E17: =IFERROR(IF(E5<>"15CBM+",_xlfn.LET(_xlpm.X,#REF!,_xlpm.Y,12,IF(D5="深圳",VLOOKUP(C5,_xlpm.X,_xlpm.Y,0),IF(D5="广州",VLOOKUP(C5,_xlpm.X,_xlpm.Y,0),IF(D5="中山",VLOOKUP(C5,_xlpm.X,_xlpm.Y,0),IF(D5="泉州",VLOOKUP(C5,_xlpm.X,_xlpm.Y,0),IF(D5="厦门",VLOOKUP(C5,_xlpm.X,_xlpm.Y,0),IF(D5="义乌",VLOOKUP(C5,_xlpm.X,_xlpm.Y,0),IF(D5="上海",VLOOKUP(C5,_xlpm.X,_xlpm.Y,0))))))))),"-"),"-") -> - | F17: =IFERROR(IF(E5<>"15CBM+",_xlfn.LET(_xlpm.X,#REF!,_xlpm.Y,13,IF(D5="深圳",VLOOKUP(C5,_xlpm.X,_xlpm.Y,0),IF(D5="广州",VLOOKUP(C5,_xlpm.X,_xlpm.Y,0),IF(D5="中山",VLOOKUP(C5,_xlpm.X,_xlpm.Y,0),IF(D5="泉州",VLOOKUP(C5,_xlpm.X,_xlpm.Y,0),IF(D5="厦门",VLOOKUP(C5,_xlpm.X,_xlpm.Y,0),IF(D5="义乌",VLOOKUP(C5,_xlpm.X,_xlpm.Y,0),IF(D5="上海",VLOOKUP(C5,_xlpm.X,_xlpm.Y,0))))))))),"-"),"-") -> - | G17: =IF(E5="12-99KG","12-70KG：+2元/KG"&CHAR(10)&"71-99KG：+1元/KG",IF(E5="15CBM+","KG价","")) -> KG价
B18: 英国海卡-CBM价 | C18: - | D18: =IF(E5="15CBM+",_xlfn.LET(_xlpm.X,#REF!,_xlpm.Y,14,IF(D5="深圳",VLOOKUP(C5,_xlpm.X,_xlpm.Y,0),IF(D5="广州",VLOOKUP(C5,_xlpm.X,_xlpm.Y+1,0),IF(D5="中山",VLOOKUP(C5,_xlpm.X,_xlpm.Y+1,0),IF(D5="泉州",VLOOKUP(C5,_xlpm.X,_xlpm.Y+2,0),IF(D5="厦门",VLOOKUP(C5,_xlpm.X,_xlpm.Y+2,0),IF(D5="义乌",VLOOKUP(C5,_xlpm.X,_xlpm.Y+3,0),IF(D5="上海",VLOOKUP(C5,_xlpm.X,_xlpm.Y+4,0))))))))),"-") -> #REF! | E18: =IF(E5="15CBM+",_xlfn.LET(_xlpm.X,#REF!,_xlpm.Y,19,IF(D5="深圳",VLOOKUP(C5,_xlpm.X,_xlpm.Y,0),IF(D5="广州",VLOOKUP(C5,_xlpm.X,_xlpm.Y,0),IF(D5="中山",VLOOKUP(C5,_xlpm.X,_xlpm.Y,0),IF(D5="泉州",VLOOKUP(C5,_xlpm.X,_xlpm.Y,0),IF(D5="厦门",VLOOKUP(C5,_xlpm.X,_xlpm.Y,0),IF(D5="义乌",VLOOKUP(C5,_xlpm.X,_xlpm.Y,0),IF(D5="上海",VLOOKUP(C5,_xlpm.X,_xlpm.Y,0))))))))),"-") -> #REF! | F18: =IF(E5="15CBM+",_xlfn.LET(_xlpm.X,#REF!,_xlpm.Y,20,IF(D5="深圳",VLOOKUP(C5,_xlpm.X,_xlpm.Y,0),IF(D5="广州",VLOOKUP(C5,_xlpm.X,_xlpm.Y,0),IF(D5="中山",VLOOKUP(C5,_xlpm.X,_xlpm.Y,0),IF(D5="泉州",VLOOKUP(C5,_xlpm.X,_xlpm.Y,0),IF(D5="厦门",VLOOKUP(C5,_xlpm.X,_xlpm.Y,0),IF(D5="义乌",VLOOKUP(C5,_xlpm.X,_xlpm.Y,0),IF(D5="上海",VLOOKUP(C5,_xlpm.X,_xlpm.Y,0))))))))),"-") -> #REF! | G18: =IF(AND(E5<>"15CBM+",F18="-"),"立方价","1-4.9CBM：+60元/CBM"&CHAR(10)&"5-9.9CBM：+40元/CBM"&CHAR(10)&"10-14.9CBM：+20元/CBM") -> #REF!
B19: 英国海派-DPD派 | C19: {=IF(E5<>"15CBM+",_xlfn.LET(_xlpm.X,#REF!,IFERROR(IF(D5="深圳",_xlfn._xlws.FILTER(_xlpm.X,(ISNUMBER(FIND(D5,#REF!,1)))),IF(D5="广州",_xlfn._xlws.FILTER(_xlpm.X,(ISNUMBER(FIND(D5,#REF!,1)))),IF(D5="中山",_xlfn._xlws.FILTER(_xlpm.X,(ISNUMBER(FIND(D5,#REF!,1)))),IF(D5="泉州",_xlfn._xlws.FILTER(_xlpm.X,(ISNUMBER(FIND(D5,#REF!,1)))),IF(D5="厦门",_xlfn._xlws.FILTER(_xlpm.X,(ISNUMBER(FIND(D5,#REF!,1)))),IF(D5="义乌",_xlfn._xlws.FILTER(_xlpm.X,(ISNUMBER(FIND(D5,#REF!,1)))),IF(D5="上海",_xlfn._xlws.FILTER(_xlpm.X,(ISNUMBER(FIND(D5,#REF!,1))))))))))),"-")),"-")} -> - | D19: {=IF(E5<>"15CBM+",_xlfn.LET(_xlpm.X,#REF!,IFERROR(IF(D5="深圳",_xlfn._xlws.FILTER(_xlpm.X,(ISNUMBER(FIND(D5,#REF!,1)))),IF(D5="广州",_xlfn._xlws.FILTER(_xlpm.X,(ISNUMBER(FIND(D5,#REF!,1)))),IF(D5="中山",_xlfn._xlws.FILTER(_xlpm.X,(ISNUMBER(FIND(D5,#REF!,1)))),IF(D5="泉州",_xlfn._xlws.FILTER(_xlpm.X,(ISNUMBER(FIND(D5,#REF!,1)))),IF(D5="厦门",_xlfn._xlws.FILTER(_xlpm.X,(ISNUMBER(FIND(D5,#REF!,1)))),IF(D5="义乌",_xlfn._xlws.FILTER(_xlpm.X,(ISNUMBER(FIND(D5,#REF!,1)))),IF(D5="上海",_xlfn._xlws.FILTER(_xlpm.X,(ISNUMBER(FIND(D5,#REF!,1))))))))))),"-")),"-")} -> - | E19: {=IF(E5<>"15CBM+",_xlfn.LET(_xlpm.X,#REF!,IFERROR(IF(D5="深圳",_xlfn._xlws.FILTER(_xlpm.X,(ISNUMBER(FIND(D5,#REF!,1)))),IF(D5="广州",_xlfn._xlws.FILTER(_xlpm.X,(ISNUMBER(FIND(D5,#REF!,1)))),IF(D5="中山",_xlfn._xlws.FILTER(_xlpm.X,(ISNUMBER(FIND(D5,#REF!,1)))),IF(D5="泉州",_xlfn._xlws.FILTER(_xlpm.X,(ISNUMBER(FIND(D5,#REF!,1)))),IF(D5="厦门",_xlfn._xlws.FILTER(_xlpm.X,(ISNUMBER(FIND(D5,#REF!,1)))),IF(D5="义乌",_xlfn._xlws.FILTER(_xlpm.X,(ISNUMBER(FIND(D5,#REF!,1)))),IF(D5="上海",_xlfn._xlws.FILTER(_xlpm.X,(ISNUMBER(FIND(D5,#REF!,1))))))))))),"-")),"-")} -> - | F19: {=IF(E5<>"15CBM+",_xlfn.LET(_xlpm.X,#REF!,IFERROR(IF(D5="深圳",_xlfn._xlws.FILTER(_xlpm.X,(ISNUMBER(FIND(D5,#REF!,1)))),IF(D5="广州",_xlfn._xlws.FILTER(_xlpm.X,(ISNUMBER(FIND(D5,#REF!,1)))),IF(D5="中山",_xlfn._xlws.FILTER(_xlpm.X,(ISNUMBER(FIND(D5,#REF!,1)))),IF(D5="泉州",_xlfn._xlws.FILTER(_xlpm.X,(ISNUMBER(FIND(D5,#REF!,1)))),IF(D5="厦门",_xlfn._xlws.FILTER(_xlpm.X,(ISNUMBER(FIND(D5,#REF!,1)))),IF(D5="义乌",_xlfn._xlws.FILTER(_xlpm.X,(ISNUMBER(FIND(D5,#REF!,1)))),IF(D5="上海",_xlfn._xlws.FILTER(_xlpm.X,(ISNUMBER(FIND(D5,#REF!,1))))))))))),"-")),"-")} -> - | G19: =IF(E5="15CBM+","KG价","") -> KG价
B20: 英国海派AEU1-DPD派 | C20: {=IF(E5<>"15CBM+",_xlfn.LET(_xlpm.X,#REF!,IFERROR(IF(D5="深圳",_xlfn._xlws.FILTER(_xlpm.X,(ISNUMBER(FIND(D5,#REF!,1)))),IF(D5="广州",_xlfn._xlws.FILTER(_xlpm.X,(ISNUMBER(FIND(D5,#REF!,1)))),IF(D5="中山",_xlfn._xlws.FILTER(_xlpm.X,(ISNUMBER(FIND(D5,#REF!,1)))),IF(D5="泉州",_xlfn._xlws.FILTER(_xlpm.X,(ISNUMBER(FIND(D5,#REF!,1)))),IF(D5="厦门",_xlfn._xlws.FILTER(_xlpm.X,(ISNUMBER(FIND(D5,#REF!,1)))),IF(D5="义乌",_xlfn._xlws.FILTER(_xlpm.X,(ISNUMBER(FIND(D5,#REF!,1)))),IF(D5="上海",_xlfn._xlws.FILTER(_xlpm.X,(ISNUMBER(FIND(D5,#REF!,1))))))))))),"-")),"-")} -> - | D20: {=IF(E5<>"15CBM+",_xlfn.LET(_xlpm.X,#REF!,IFERROR(IF(D5="深圳",_xlfn._xlws.FILTER(_xlpm.X,(ISNUMBER(FIND(D5,#REF!,1)))),IF(D5="广州",_xlfn._xlws.FILTER(_xlpm.X,(ISNUMBER(FIND(D5,#REF!,1)))),IF(D5="中山",_xlfn._xlws.FILTER(_xlpm.X,(ISNUMBER(FIND(D5,#REF!,1)))),IF(D5="泉州",_xlfn._xlws.FILTER(_xlpm.X,(ISNUMBER(FIND(D5,#REF!,1)))),IF(D5="厦门",_xlfn._xlws.FILTER(_xlpm.X,(ISNUMBER(FIND(D5,#REF!,1)))),IF(D5="义乌",_xlfn._xlws.FILTER(_xlpm.X,(ISNUMBER(FIND(D5,#REF!,1)))),IF(D5="上海",_xlfn._xlws.FILTER(_xlpm.X,(ISNUMBER(FIND(D5,#REF!,1))))))))))),"-")),"-")} -> - | E20: {=IF(E5<>"15CBM+",_xlfn.LET(_xlpm.X,#REF!,IFERROR(IF(D5="深圳",_xlfn._xlws.FILTER(_xlpm.X,(ISNUMBER(FIND(D5,#REF!,1)))),IF(D5="广州",_xlfn._xlws.FILTER(_xlpm.X,(ISNUMBER(FIND(D5,#REF!,1)))),IF(D5="中山",_xlfn._xlws.FILTER(_xlpm.X,(ISNUMBER(FIND(D5,#REF!,1)))),IF(D5="泉州",_xlfn._xlws.FILTER(_xlpm.X,(ISNUMBER(FIND(D5,#REF!,1)))),IF(D5="厦门",_xlfn._xlws.FILTER(_xlpm.X,(ISNUMBER(FIND(D5,#REF!,1)))),IF(D5="义乌",_xlfn._xlws.FILTER(_xlpm.X,(ISNUMBER(FIND(D5,#REF!,1)))),IF(D5="上海",_xlfn._xlws.FILTER(_xlpm.X,(ISNUMBER(FIND(D5,#REF!,1))))))))))),"-")),"-")} -> - | F20: {=IF(E5<>"15CBM+",_xlfn.LET(_xlpm.X,#REF!,IFERROR(IF(D5="深圳",_xlfn._xlws.FILTER(_xlpm.X,(ISNUMBER(FIND(D5,#REF!,1)))),IF(D5="广州",_xlfn._xlws.FILTER(_xlpm.X,(ISNUMBER(FIND(D5,#REF!,1)))),IF(D5="中山",_xlfn._xlws.FILTER(_xlpm.X,(ISNUMBER(FIND(D5,#REF!,1)))),IF(D5="泉州",_xlfn._xlws.FILTER(_xlpm.X,(ISNUMBER(FIND(D5,#REF!,1)))),IF(D5="厦门",_xlfn._xlws.FILTER(_xlpm.X,(ISNUMBER(FIND(D5,#REF!,1)))),IF(D5="义乌",_xlfn._xlws.FILTER(_xlpm.X,(ISNUMBER(FIND(D5,#REF!,1)))),IF(D5="上海",_xlfn._xlws.FILTER(_xlpm.X,(ISNUMBER(FIND(D5,#REF!,1))))))))))),"-")),"-")} -> - | G20: =IF(E5="15CBM+","KG价","") -> KG价
B21: 英国海派限时达 | C21: {=IF(E5<>"15CBM+",_xlfn.LET(_xlpm.X,#REF!,IFERROR(IF(D5="深圳",_xlfn._xlws.FILTER(_xlpm.X,(ISNUMBER(FIND(D5,#REF!,1)))),IF(D5="广州",_xlfn._xlws.FILTER(_xlpm.X,(ISNUMBER(FIND(D5,#REF!,1)))),IF(D5="中山",_xlfn._xlws.FILTER(_xlpm.X,(ISNUMBER(FIND(D5,#REF!,1)))),IF(D5="泉州",_xlfn._xlws.FILTER(_xlpm.X,(ISNUMBER(FIND(D5,#REF!,1)))),IF(D5="厦门",_xlfn._xlws.FILTER(_xlpm.X,(ISNUMBER(FIND(D5,#REF!,1)))),IF(D5="义乌",_xlfn._xlws.FILTER(_xlpm.X,(ISNUMBER(FIND(D5,#REF!,1)))),IF(D5="上海",_xlfn._xlws.FILTER(_xlpm.X,(ISNUMBER(FIND(D5,#REF!,1))))))))))),"-")),"-")} -> - | D21: {=IF(E5<>"15CBM+",_xlfn.LET(_xlpm.X,#REF!,IFERROR(IF(D5="深圳",_xlfn._xlws.FILTER(_xlpm.X,(ISNUMBER(FIND(D5,#REF!,1)))),IF(D5="广州",_xlfn._xlws.FILTER(_xlpm.X,(ISNUMBER(FIND(D5,#REF!,1)))),IF(D5="中山",_xlfn._xlws.FILTER(_xlpm.X,(ISNUMBER(FIND(D5,#REF!,1)))),IF(D5="泉州",_xlfn._xlws.FILTER(_xlpm.X,(ISNUMBER(FIND(D5,#REF!,1)))),IF(D5="厦门",_xlfn._xlws.FILTER(_xlpm.X,(ISNUMBER(FIND(D5,#REF!,1)))),IF(D5="义乌",_xlfn._xlws.FILTER(_xlpm.X,(ISNUMBER(FIND(D5,#REF!,1)))),IF(D5="上海",_xlfn._xlws.FILTER(_xlpm.X,(ISNUMBER(FIND(D5,#REF!,1))))))))))),"-")),"-")} -> - | E21: {=IF(E5<>"15CBM+",_xlfn.LET(_xlpm.X,#REF!,IFERROR(IF(D5="深圳",_xlfn._xlws.FILTER(_xlpm.X,(ISNUMBER(FIND(D5,#REF!,1)))),IF(D5="广州",_xlfn._xlws.FILTER(_xlpm.X,(ISNUMBER(FIND(D5,#REF!,1)))),IF(D5="中山",_xlfn._xlws.FILTER(_xlpm.X,(ISNUMBER(FIND(D5,#REF!,1)))),IF(D5="泉州",_xlfn._xlws.FILTER(_xlpm.X,(ISNUMBER(FIND(D5,#REF!,1)))),IF(D5="厦门",_xlfn._xlws.FILTER(_xlpm.X,(ISNUMBER(FIND(D5,#REF!,1)))),IF(D5="义乌",_xlfn._xlws.FILTER(_xlpm.X,(ISNUMBER(FIND(D5,#REF!,1)))),IF(D5="上海",_xlfn._xlws.FILTER(_xlpm.X,(ISNUMBER(FIND(D5,#REF!,1))))))))))),"-")),"-")} -> - | F21: {=IF(E5<>"15CBM+",_xlfn.LET(_xlpm.X,#REF!,IFERROR(IF(D5="深圳",_xlfn._xlws.FILTER(_xlpm.X,(ISNUMBER(FIND(D5,#REF!,1)))),IF(D5="广州",_xlfn._xlws.FILTER(_xlpm.X,(ISNUMBER(FIND(D5,#REF!,1)))),IF(D5="中山",_xlfn._xlws.FILTER(_xlpm.X,(ISNUMBER(FIND(D5,#REF!,1)))),IF(D5="泉州",_xlfn._xlws.FILTER(_xlpm.X,(ISNUMBER(FIND(D5,#REF!,1)))),IF(D5="厦门",_xlfn._xlws.FILTER(_xlpm.X,(ISNUMBER(FIND(D5,#REF!,1)))),IF(D5="义乌",_xlfn._xlws.FILTER(_xlpm.X,(ISNUMBER(FIND(D5,#REF!,1)))),IF(D5="上海",_xlfn._xlws.FILTER(_xlpm.X,(ISNUMBER(FIND(D5,#REF!,1))))))))))),"-")),"-")} -> - | G21: =IF(E5="15CBM+","KG价","") -> KG价

Sheet 美国海运查询表 (2)
A1: 天图通逊供应链有限公司 立志打造一家具有社会价值的百年跨境物流企业 | M1: {=_xlfn.LET(_xlpm.X,IFERROR(_wpsfn.REGEXP(_xlfn._xlws.FILTER(_xlfn.VSTACK(_xlfn.UNIQUE(INDIRECT("美西直送系列!A7:A"&COUNTA(美西直送系列!A:A)+6-1)),_xlfn.UNIQUE(INDIRECT("'美西-美森(12-17)'!A7:A"&COUNTA('美西-美森(12-17)'!A7:A125)+6-1)),_xlfn.UNIQUE(INDIRECT("'美西-以星&普船(17-26)'!A7:A"&COUNTA('美西-以星&普船(17-26)'!A:A)+6-1)),_xlfn.UNIQUE(INDIRECT("美西北!A7:A"&COUNTA(美西北!A:A)+6-1)),_xlfn.UNIQUE(INDIRECT("美东!A7:A"&COUNTA('美东-海铁系列'!#REF!)+6-1)),_xlfn.UNIQUE(INDIRECT("美东南!A7:A"&COUNTA(美东南直航系列!A:A)+6-1)),_xlfn.UNIQUE(INDIRECT("美中!A7:A"&COUNTA(#REF!)+6-1))),IF(ISNUMBER(FIND("-直送特价",_xlfn.VSTACK(_xlfn.UNIQUE(INDIRECT("美西直送系列!A7:A"&COUNTA(美西直送系列!A:A)+6-1)),_xlfn.UNIQUE(INDIRECT("'美西-美森(12-17)'!A7:A"&COUNTA('美西-美森(12-17)'!A7:A125)+6-1)),_xlfn.UNIQUE(INDIRECT("'美西-以星&普船(17-26)'!A7:A"&COUNTA('美西-以星&普船(17-26)'!A:A)+6-1)),_xlfn.UNIQUE(INDIRECT("美西北!A7:A"&COUNTA(美西北!A:A)+6-1)),_xlfn.UNIQUE(INDIRECT("美东!A7:A"&COUNTA('美东-海铁系列'!#REF!)+6-1)),_xlfn.UNIQUE(INDIRECT("美东南!A7:A"&COUNTA(美东南直航系列!A:A)+6-1)),_xlfn.UNIQUE(INDIRECT("美中!A7:A"&COUNTA(#REF!)+6-1))),1))=FALSE,TRUE,FALSE)),"[^一-龟]+"),""),_xlfn._xlws.FILTER(_xlpm.X,(_xlpm.X<>"0")*(_xlpm.X<>"")*(_xlpm.X<>CHAR(10)&"(")*(_xlpm.X<>CHAR(10))))} -> #VALUE! | N1: {=_xlfn.UNIQUE(INDIRECT("'英国海运-卡派(23-40) '!A7:A"&COUNTA(#REF!)))} -> #REF! | O1: 12-99KG | P1: 美国 | Q1: 类型 | R1: 英国 | S1: 类型 | T1: 深圳
O2: 100KG+ | P2: 直送促销价 | Q2: 直送 | R2: 英国（普货）-五日提（分泡50%） | S2: 空运 | T2: 广州
A3: 价格快速查询栏 | O3: 300KG+ | P3: 直送快速达 | Q3: 直送 | R3: 英国（普货）-十日提（分泡50%） | S3: 空运 | T3: 中山
A4: 备注： “英国”&“快递派”&“空运”渠道不在本快速查找范围，请查询报价表内页详情。 | C4: 国家 | D4: 国内仓 | E4: 目的仓 | F4: 公斤段 | G4: 时间 | O4: 15CBM+ | P4: OAK直送促销价 | Q4: 直送 | R4: 英国（带电）-十日提（分泡50%） | S4: 空运 | T4: 泉州
C5: 英国 | D5: 广州 | E5: LAX9 | F5: 12-99KG | G5: =TODAY() -> 46202 | O5: 不适用 | P5: 纽约普船直送特价 | Q5: 直送 | R5: 英国韩国飞-MGH（分泡50%） | S5: 空运 | T5: 厦门
P6: 芝加哥普船直送特价 | Q6: 直送 | R6: 英国（普货）-促销价（分泡50%） | S6: 空运 | T6: 义乌
A7: 运输类型 | B7: 渠道类型 | C7: 包税 | D7: 不包税 | E7: 签收时效 （开船后） | F7: 延时赔付 （开船后） | G7: 备注 | P7: 美森极速12日达 | Q7: 拆派 | R7: 英国快铁25日达-卡派 | S7: 陆运 | T7: 上海
A8: =IFERROR(IFERROR(VLOOKUP(B8,P:Q,2,0),VLOOKUP(B8,R:S,2,0)),"") -> 空运 | B8: {=_xlfn._xlws.FILTER(INDIRECT(C5),INDIRECT(C5)<>"")} -> 英国（普货）-五日提（分泡50%） | P8: 美森正班13日达 | Q8: 拆派 | R8: 英国快铁25日达-DPD派 | S8: 陆运
A9: =IFERROR(IFERROR(VLOOKUP(B9,P:Q,2,0),VLOOKUP(B9,R:S,2,0)),"") -> 空运 | B9: 英国（普货）-十日提（分泡50%） | P9: 美森15日达 | Q9: 拆派 | R9: 英国中英铁卡-卡派 | S9: 陆运
A10: =IFERROR(IFERROR(VLOOKUP(B10,P:Q,2,0),VLOOKUP(B10,R:S,2,0)),"") -> 空运 | B10: 英国（带电）-十日提（分泡50%） | P10: 美森统配17日达 | Q10: 拆派 | R10: 英国中英铁卡-DPD派 | S10: 陆运
A11: =IFERROR(IFERROR(VLOOKUP(B11,P:Q,2,0),VLOOKUP(B11,R:S,2,0)),"") -> 空运 | B11: 英国韩国飞-MGH（分泡50%） | P11: OA/以星17日达 | Q11: 拆派 | R11: 英国海卡(特价）-KG价 | S11: 海运
A12: =IFERROR(IFERROR(VLOOKUP(B12,P:Q,2,0),VLOOKUP(B12,R:S,2,0)),"") -> 空运 | B12: 英国（普货）-促销价（分泡50%） | P12: 以星/合德20日达 | Q12: 拆派 | R12: 英国海卡-CBM价 | S12: 海运
A13: =IFERROR(IFERROR(VLOOKUP(B13,P:Q,2,0),VLOOKUP(B13,R:S,2,0)),"") -> 陆运 | B13: 英国快铁25日达-卡派 | P13: 盐田23日达 | Q13: 拆派 | R13: 英国海派-DPD派 | S13: 海运
A14: =IFERROR(IFERROR(VLOOKUP(B14,P:Q,2,0),VLOOKUP(B14,R:S,2,0)),"") -> 陆运 | B14: 英国快铁25日达-DPD派 | P14: 盐田26日达 | Q14: 拆派 | R14: 英国海派AEU1-DPD派 | S14: 海运
A15: =IFERROR(IFERROR(VLOOKUP(B15,P:Q,2,0),VLOOKUP(B15,R:S,2,0)),"") -> 陆运 | B15: 英国中英铁卡-卡派 | P15: OAK专线 | Q15: 拆派 | R15: 英国海派限时达 | S15: 海运
A16: =IFERROR(IFERROR(VLOOKUP(B16,P:Q,2,0),VLOOKUP(B16,R:S,2,0)),"") -> 陆运 | B16: 英国中英铁卡-DPD派 | P16: 西雅图专线 | Q16: 拆派
A17: =IFERROR(IFERROR(VLOOKUP(B17,P:Q,2,0),VLOOKUP(B17,R:S,2,0)),"") -> 海运 | B17: 英国海卡(特价）-KG价 | P17: 纽约普船专线 | Q17: 拆派
A18: =IFERROR(IFERROR(VLOOKUP(B18,P:Q,2,0),VLOOKUP(B18,R:S,2,0)),"") -> 海运 | B18: 英国海卡-CBM价 | P18: 纽约美森快线 | Q18: 拆派
A19: =IFERROR(IFERROR(VLOOKUP(B19,P:Q,2,0),VLOOKUP(B19,R:S,2,0)),"") -> 海运 | B19: 英国海派-DPD派 | P19: 纽约海陆快线 | Q19: 拆派
A20: =IFERROR(IFERROR(VLOOKUP(B20,P:Q,2,0),VLOOKUP(B20,R:S,2,0)),"") -> 海运 | B20: 英国海派AEU1-DPD派 | P20: 纽约海陆以星快线 | Q20: 拆派
A21: =IFERROR(IFERROR(VLOOKUP(B21,P:Q,2,0),VLOOKUP(B21,R:S,2,0)),"") -> 海运 | B21: 英国海派限时达 | P21: 萨凡纳OA专线 | Q21: 拆派
A22: =IFERROR(IFERROR(VLOOKUP(B22,P:Q,2,0),VLOOKUP(B22,R:S,2,0)),"") | P22: 萨凡纳HMM专线 | Q22: 拆派
A23: =IFERROR(IFERROR(VLOOKUP(B23,P:Q,2,0),VLOOKUP(B23,R:S,2,0)),"") | P23: 休斯顿普船专线 | Q23: 拆派
A24: =IFERROR(IFERROR(VLOOKUP(B24,P:Q,2,0),VLOOKUP(B24,R:S,2,0)),"") | P24: 芝加哥普船专线 | Q24: 拆派
A25: =IFERROR(IFERROR(VLOOKUP(B25,P:Q,2,0),VLOOKUP(B25,R:S,2,0)),"") | P25: 芝加哥海陆以星快线 | Q25: 拆派
A26: =IFERROR(IFERROR(VLOOKUP(B26,P:Q,2,0),VLOOKUP(B26,R:S,2,0)),"")
A27: =IFERROR(IFERROR(VLOOKUP(B27,P:Q,2,0),VLOOKUP(B27,R:S,2,0)),"")
A28: =IFERROR(IFERROR(VLOOKUP(B28,P:Q,2,0),VLOOKUP(B28,R:S,2,0)),"")
A29: =IFERROR(IFERROR(VLOOKUP(B29,P:Q,2,0),VLOOKUP(B29,R:S,2,0)),"")
A30: =IFERROR(IFERROR(VLOOKUP(B30,P:Q,2,0),VLOOKUP(B30,R:S,2,0)),"")
A31: =IFERROR(IFERROR(VLOOKUP(B31,P:Q,2,0),VLOOKUP(B31,R:S,2,0)),"")
N35: 其它

Sheet 英国中英专车(20-25)
F1: 英国陆运系列
F2: UK Groud Transportation Routes
A4: 英国陆运 | C4: 中英专车-卡派（暂停） （100KG+起收） | G4: 中英专车-DPD派（暂停） | K4: 中英专车快卡-卡派（暂停） （100KG+起收） | O4: 中英专车快卡-DPD派（暂停）
C5: BHX4 LBA4 BHX8 包税 | D5: BHX4 LBA4 BHX8 不包税 | E5: 签收时效 （发班列后） | F5: 延时赔付 （发班列后） | G5: 包税 | H5: 不包税 | I5: 签收时效 （发班列后） | J5: 延时赔付 （发班列后） | K5: BHX4 LBA4 BHX8 包税 | L5: BHX4 LBA4 BHX8 不包税 | M5: 签收时效 （发班列后） | N5: 延时赔付 （发班列后） | O5: 包税 | P5: 不包税 | Q5: 签收时效 （发班列后） | R5: 延时赔付 （发班列后）
A6: 深圳/广州/中山/汕头/东莞南城 （华南） | B6: 100KG+ | C6: - | D6: - | E6: 25-28日 | F6: - | G6: - | H6: - | I6: 25-28日 | J6: - | K6: - | L6: - | M6: 18-25日 | N6: - | O6: - | P6: - | Q6: 18-25日 | R6: 超27日
A7: 厦门/泉州/福州 | B7: 100KG+ | C7: - | D7: - | E7: 25-28日 | F7: - | G7: - | H7: - | I7: 25-28日 | J7: - | K7: - | L7: - | M7: 18-25日 | N7: - | O7: - | P7: - | Q7: 18-25日 | R7: 超27日
A8: 华东 （上海/义乌/宁波） | B8: 100KG+ | C8: - | D8: - | E8: 25-28日 | F8: - | G8: - | H8: - | I8: 25-28日 | J8: - | K8: - | L8: - | M8: 18-25日 | N8: - | O8: - | P8: - | Q8: 18-25日 | R8: 超27日
A9: 青岛 | B9: 100KG+ | C9: - | D9: - | E9: 25-28日 | F9: - | G9: - | H9: - | I9: 25-28日 | J9: - | K9: - | L9: - | M9: 18-25日 | N9: - | O9: - | P9: - | Q9: 18-25日 | R9: 超27日
A10: 武汉/长沙 | B10: 100KG+ | C10: - | D10: - | E10: 25-28日 | F10: - | G10: - | H10: - | I10: 25-28日 | J10: - | K10: - | L10: - | M10: 18-25日 | N10: - | O10: - | P10: - | Q10: 18-25日 | R10: 超27日
A11: 赔偿标准 | C11: 【中英专车快卡-DPD派】：超时效赔付0.25元/kg/工作日，最高赔付6个工作日
A12: 线路图 | C12: 【中英专车】：深圳装车→阿拉山口→哈萨克斯坦→俄罗斯→白俄罗斯→拉脱维亚T1→波兰→天图英国监管仓（伦敦） 【中英专车快卡】：深圳装车→阿拉山口→哈萨克斯坦→俄罗斯→白俄罗斯→拉脱维亚T1→波兰→天图英国监管仓（伦敦）
A13: 注意事项 | C13: 货型比例超过1:210，可申请单价减0.2元/KG; 货型比例超过1:250，可申请单价减0.5元/KG; 货型比例超过1:300，可申请单价减0.8元/KG; 货型比例超过1:330，可申请单价减1元/KG; 货型比例超过1:500，可申请单价减1.5元/KG;
C14: 1.自用VAT清关费:200元/票； 控税：客户自VAT走包税，清关费正常收取，100kg以下收300元/票操作费；
C15: 2.特别提醒：以上时效参考不含海关查验、班列延误、换轨延误，政府政策，疫情，罢工，节假日等影响；
C16: 3.货物计费标准，操作要求、赔偿条款，注意事项，拦截改派操作请参考左上侧链接“英国发货须知”；
C17: 4.产品包税附加费，可参考右侧链接“附加费清单 ”；
C18: 5.英国快铁25日达，报关件报关费350元/票，且报关件不收带电产品，请知悉；

Sheet 美国快递
K1: 美国海运-快递系列
K2: Western United States
A4: 邮编 UPS/联邦混打 12-44KG+3/KG； 45-99KG+1.5元/KG | B4: 美森极速12日达-快递派（CLX） | N4: 洛杉矶CLX13日达-快递派（CLX） 此渠道为上海港开船时效，若因市场变化，调整为宁波港开船，时效赔付需顺延两个自然日 | Z4: 洛杉矶MAX14日达-快递派（MAX） | AL4: 洛杉矶EXX16日达-快递派(EXX) | AX4: 洛杉矶17日达-快递派（ZIM/HD) 华南/华东：指定ZIM：包税+0.1元/KG，不包税+18元/CBM | BK4: 注意事项
B5: 包税-100kg+ | L5: 提取时效 开船后 | M5: 延时赔付 开船后 | N5: 包税-100kg+ | X5: 提取时效 开船后 | Y5: 延时赔付 开船后 | Z5: 包税-100kg+ | AJ5: 提取时效 开船后 | AK5: 延时赔付 开船后 | AL5: 包税-100kg+ | AV5: 提取时效 开船后 | AW5: 延时赔付 开船后 | AX5: 包税-100kg+ | BH5: 提取时效 开船后 | BI5: 延时赔付 开船后 | BK5: 货型比例超过1:200，可申请单价减0.2元/KG;（美森/EXX/合德带托/以星带托头程的渠道减0.5元/KG） 货型比例超过1:250，可申请单价减0.5元/KG;（美森/EXX/合德带托/以星带托头程的渠道减0.7元/KG） 货型比例超过1:300，可申请单价减1元/KG; 货型比例超过1:400，可申请单价减1.5元/KG; 货型比例超过1:500，可申请单价减2元/KG; 货型比例超过1:600，可申请单价减2.3元/KG;（美森/EXX/合德带托/以星带托头程的渠道减2.5元/KG） 货型比例超过1:700，可申请单价减2.5元/KG;（美森/EXX/合德带托/以星带托头程的渠道减2.7元/KG）
B6: 华南 | C6: 重庆 | D6: 汕头 | E6: 厦门/泉州/福州 | F6: 华东 | G6: 青岛/郑州/温州/台州/连云港/南京/合肥 | H6: 天津/南昌/石家庄 | I6: 济南/潍坊 | J6: 西安/沧州/保定 | K6: 武汉/长沙/成都 | N6: 华南 | O6: 重庆 | P6: 汕头 | Q6: 厦门/泉州/福州 | R6: 华东 | S6: 青岛/郑州/温州/台州/连云港/南京/合肥 | T6: 天津/南昌/石家庄 | U6: 济南/潍坊 | V6: 西安/沧州/保定 | W6: 武汉/长沙/成都 | Z6: 华南 | AA6: 重庆 | AB6: 汕头 | AC6: 厦门/泉州/福州 | AD6: 华东 | AE6: 青岛/郑州/温州/台州/连云港/南京/合肥 | AF6: 天津/南昌/石家庄 | AG6: 济南/潍坊 | AH6: 西安/沧州/保定 | AI6: 武汉/长沙/成都 | AL6: 华南 | AM6: 重庆 | AN6: 汕头 | AO6: 厦门/泉州/福州 | AP6: 华东 | AQ6: 青岛/郑州/温州/台州/连云港/南京/合肥 | AR6: 天津/南昌/石家庄 | AS6: 济南/潍坊 | AT6: 西安/沧州/保定 | AU6: 武汉/长沙/成都 | AX6: 华南 | AY6: 重庆 | AZ6: 汕头 | BA6: 厦门/泉州/福州 | BB6: 华东 | BC6: 青岛/郑州/温州/台州/连云港/南京/合肥 | BD6: 天津/南昌/石家庄 | BE6: 济南/潍坊 | BF6: 西安/沧州/保定 | BG6: 武汉/长沙/成都
A7: 美国西岸 (邮编8.9开头) | B7: 18.5 | C7: 19.3 | D7: 18.7 | E7: 17.9 | F7: 17.5 | G7: 17.8 | H7: 18.1 | I7: 18 | J7: 18.3 | K7: 18.1 | L7: 11-12日 | M7: 超13日 | N7: 15.4 | O7: 16.2 | P7: 15.6 | Q7: 14.5 | R7: 14.1 | S7: 14.4 | T7: 14.7 | U7: 14.6 | V7: 14.9 | W7: 14.7 | X7: 12-14日 | Y7: 超14日 | Z7: 13.8 | AA7: 14.6 | AB7: 14 | AC7: 13.7 | AD7: 13.3 | AE7: 13.6 | AF7: 13.9 | AG7: 13.8 | AH7: 14.1 | AI7: 14.4 | AJ7: 13-15日 | AK7: 超15日 | AL7: 12 | AM7: 12.8 | AN7: 12.2 | AO7: 11.8 | AP7: 11.4 | AQ7: 11.7 | AR7: 12 | AS7: 11.9 | AT7: 12.2 | AU7: 12 | AV7: 14-16日 | AW7: 超17日 | AX7: 10.8 | AY7: 11.6 | AZ7: 11.2 | BA7: 11.1 | BB7: 10.7 | BC7: 11 | BD7: 11.3 | BE7: 11.2 | BF7: 11.5 | BG7: 11.4 | BH7: 15-17日 | BI7: 超18日
A8: 美国西岸北 （邮编97.98.99开头） | B8: 19 | C8: 19.8 | D8: 19.2 | E8: 18.4 | F8: 18 | G8: 18.3 | H8: 18.6 | I8: 18.5 | J8: 18.8 | K8: 18.6 | L8: 11-12日 | M8: 超13日 | N8: 15.9 | O8: 16.7 | P8: 16.1 | Q8: 15 | R8: 14.6 | S8: 14.9 | T8: 15.2 | U8: 15.1 | V8: 15.4 | W8: 15.2 | X8: 12-14日 | Y8: 超14日 | Z8: 14.3 | AA8: 15.1 | AB8: 14.5 | AC8: 14.2 | AD8: 13.8 | AE8: 14.1 | AF8: 14.4 | AG8: 14.3 | AH8: 14.6 | AI8: 14.9 | AJ8: 13-15日 | AK8: 超15日 | AL8: 12.5 | AM8: 13.3 | AN8: 12.7 | AO8: 12.3 | AP8: 11.9 | AQ8: 12.2 | AR8: 12.5 | AS8: 12.4 | AT8: 12.7 | AU8: 12.5 | AV8: 14-16日 | AW8: 超17日 | AX8: 11.3 | AY8: 12.1 | AZ8: 11.7 | BA8: 11.6 | BB8: 11.2 | BC8: 11.5 | BD8: 11.8 | BE8: 11.7 | BF8: 12 | BG8: 11.9 | BH8: 15-17日 | BI8: 超18日
A9: 美国中部 (邮编4.5.6.7开头) | B9: 21 | C9: 21.8 | D9: 21.2 | E9: 20.4 | F9: 20 | G9: 20.3 | H9: 20.6 | I9: 20.5 | J9: 20.8 | K9: 20.6 | L9: 11-12日 | M9: 超13日 | N9: 17.4 | O9: 18.2 | P9: 17.6 | Q9: 16.5 | R9: 16.1 | S9: 16.4 | T9: 16.7 | U9: 16.6 | V9: 16.9 | W9: 16.7 | X9: 12-14日 | Y9: 超14日 | Z9: 16.3 | AA9: 17.1 | AB9: 16.5 | AC9: 16.2 | AD9: 15.8 | AE9: 16.1 | AF9: 16.4 | AG9: 16.3 | AH9: 16.6 | AI9: 16.9 | AJ9: 13-15日 | AK9: 超15日 | AL9: 14 | AM9: 14.8 | AN9: 14.2 | AO9: 13.8 | AP9: 13.4 | AQ9: 13.7 | AR9: 14 | AS9: 13.9 | AT9: 14.2 | AU9: 14 | AV9: 14-16日 | AW9: 超17日 | AX9: 12.8 | AY9: 13.6 | AZ9: 13.2 | BA9: 13.1 | BB9: 12.7 | BC9: 13 | BD9: 13.3 | BE9: 13.2 | BF9: 13.5 | BG9: 13.4 | BH9: 15-17日 | BI9: 超18日 | BK9: 1.承诺时效和承诺赔付不包括以下情况 ①美国/加拿大节假日等不可抗力：码头工人罢工、码头拥堵、天气原因、平台爆仓（及平台爆仓导致的海外仓爆仓）、平台删约、推约、拒收、不放约、疫情、快递漏扫描等； ②集装箱被进到封闭区/集装箱无法预约提柜/码头设备故障、延误时间需去除后再计算赔付时效； ③国内外海关查验，从系统通知查验到查验放行这段时间需去除后再计算赔付时效（含海关其他部门FDA/EPA/USDA/DOT/CPSC等HOLD货时间去除）从LFD可提柜多次发生预约推迟，预约困难，无理由拒收这期间需去除后再计算赔付时效；
A10: 美国东岸 (邮编0.1.2.3开头) | B10: 21.7 | C10: 22.5 | D10: 21.9 | E10: 21.1 | F10: 20.7 | G10: 21 | H10: 21.3 | I10: 21.2 | J10: 21.5 | K10: 21.3 | L10: 11-12日 | M10: 超13日 | N10: 18.4 | O10: 19.2 | P10: 18.6 | Q10: 17.5 | R10: 17.1 | S10: 17.4 | T10: 17.7 | U10: 17.6 | V10: 17.9 | W10: 17.7 | X10: 12-14日 | Y10: 超14日 | Z10: 17 | AA10: 17.8 | AB10: 17.2 | AC10: 16.9 | AD10: 16.5 | AE10: 16.8 | AF10: 17.1 | AG10: 17 | AH10: 17.3 | AI10: 17.6 | AJ10: 13-15日 | AK10: 超15日 | AL10: 15 | AM10: 15.8 | AN10: 15.2 | AO10: 14.8 | AP10: 14.4 | AQ10: 14.7 | AR10: 15 | AS10: 14.9 | AT10: 15.2 | AU10: 15 | AV10: 14-16日 | AW10: 超17日 | AX10: 13.8 | AY10: 14.6 | AZ10: 14.2 | BA10: 14.1 | BB10: 13.7 | BC10: 14 | BD10: 14.3 | BE10: 14.2 | BF10: 14.5 | BG10: 14.4 | BH10: 15-17日 | BI10: 超18日
A11: 赔偿标准 | B11: 快递服务建议：美中(邮编4.5.6开头)选择芝加哥-快递派服务；美东(邮编0.1.2.3开头)选择纽约-快递派服务； 【美森极速12日达-快递派】：赔偿标准：超时效赔2.5元/kg/工作日（5元/KG封顶）；查验一周后，按2.5元/KG赔付。 【美森正班13日达-快递派】&【洛杉矶17日达-快递派】&【洛杉矶16日达-快递派】：超时效赔0.5元/kg/工作日（直至运费抵完为止）；美森正班13日达查验一周后，按1元/KG赔付。
BK12: 2.以船公司官网为准： 美西： 正班不超11天船期（含11天），超过赔付顺延； 加班不超12天船期（含12天），超过赔付顺延。 EXX以船公司官网为准：不超12天船期（含12天），超过赔付顺延； 普船统配船公司官网为准：不超18天船期（含18天），超过赔付顺延; 以星不超14天船期（含14天），超过赔付顺延； EMC定提不超14天船期（含14天），超过赔付顺延； 普船不超16天船期（含16天），超过赔付顺延; 美东\美东南\美中： 普船统配船公司官网为准：不超30-33天船期（含33天），超过赔付顺延。 以星不超14天船期（含14天），超过赔付顺延；加班不超12天船期（含12天），超过赔付顺延； 普船-配载火车：5-7天（含7天），超过赔付顺延； 以星-配载火车：3-5天（含5天），超过赔付顺延； 美森-配载火车：2-4天（含4天），超过赔付顺延；
A13: 邮编 UPS/联邦混打 12-44KG+3/KG； 45-99KG+1.5元/KG | B13: 洛杉矶20日达-快递派（保舱保柜） （ZIM不带托架/ 合德普提/COSCO 美速达/东方快航 统配 ） 华南/华东：指定ZIM：包税+0.1元/KG，不包税+18元/CBM | N13: 洛杉矶22日达-快递派（OA） 指定保舱快提服务：包税+0.3元/KG，不包税+53元/CBM | Z13: 洛杉矶26日达-快递派 （开船可能有1-7天延时） （MSC/HMM/ONE/合德/海领（义乌）/TSL统配/HPL/CUL/KMCT等所有普船统配）
B14: 包税-100kg+ | L14: 提取时效 开船后 | M14: 延时赔付 开船后 | N14: 包税-100kg+ | X14: 提取时效 开船后 | Y14: 延时赔付 开船后 | Z14: 包税-100kg+ | AJ14: 提取时效 开船后 | AK14: 延时赔付 开船后
B15: 华南 | C15: 重庆 | D15: 汕头 | E15: 厦门/泉州/福州 | F15: 华东 | G15: 青岛/郑州/温州/台州/连云港/南京/合肥 | H15: 天津/南昌/石家庄 | I15: 济南/潍坊 | J15: 西安/沧州/保定 | K15: 武汉/长沙/成都 | N15: 华南 | O15: 重庆 | P15: 汕头 | Q15: 厦门/泉州/福州 | R15: 华东 | S15: 青岛/郑州/温州/台州/连云港/南京/合肥 | T15: 天津/南昌/石家庄 | U15: 济南/潍坊 | V15: 西安/沧州/保定 | W15: 武汉/长沙/成都 | Z15: 华南 | AA15: 重庆 | AB15: 汕头 | AC15: 厦门/泉州/福州 | AD15: 华东 | AE15: 青岛/郑州/温州/台州/连云港/南京/合肥 | AF15: 天津/南昌/石家庄 | AG15: 济南/潍坊 | AH15: 西安/沧州/保定 | AI15: 武汉/长沙/成都
A16: 美国西岸 (邮编8.9开头) | B16: 10.2 | C16: 11 | D16: 10.4 | E16: 10.8 | F16: 10.4 | G16: 10.7 | H16: 11 | I16: 10.9 | J16: 11.2 | K16: 10.8 | L16: 18-20日 | M16: 超21日 | N16: 10.1 | O16: 10.9 | P16: 10.3 | Q16: 10.1 | R16: 10.5 | S16: 10.3 | T16: 11.1 | U16: 11 | V16: 11.3 | W16: 10.7 | X16: 19-23日 | Y16: 超24日 | Z16: 9.8 | AA16: 10.6 | AB16: 10 | AC16: 9.9 | AD16: 10.1 | AE16: 10 | AF16: 10.7 | AG16: 10.6 | AH16: 10.9 | AI16: 10.4 | AJ16: 29-31日 | AK16: -
A17: 美国西岸北 （邮编97.98.99开头） | B17: 10.7 | C17: 11.5 | D17: 10.9 | E17: 11.3 | F17: 10.9 | G17: 11.2 | H17: 11.5 | I17: 11.4 | J17: 11.7 | K17: 11.3 | L17: 18-20日 | M17: 超21日 | N17: 10.6 | O17: 11.4 | P17: 10.8 | Q17: 10.6 | R17: 11 | S17: 10.8 | T17: 11.6 | U17: 11.5 | V17: 11.8 | W17: 11.2 | X17: 19-23日 | Y17: 超24日 | Z17: 10.3 | AA17: 11.1 | AB17: 10.5 | AC17: 10.4 | AD17: 10.6 | AE17: 10.5 | AF17: 11.2 | AG17: 11.1 | AH17: 11.4 | AI17: 10.9 | AJ17: 29-31日 | AK17: -
A18: 美国中部 (邮编4.5.6.7开头) | B18: 12.7 | C18: 13.5 | D18: 12.9 | E18: 13.3 | F18: 12.9 | G18: 13.2 | H18: 13.5 | I18: 13.4 | J18: 13.7 | K18: 13.3 | L18: 18-20日 | M18: 超21日 | N18: 12.6 | O18: 13.4 | P18: 12.8 | Q18: 12.6 | R18: 13 | S18: 12.8 | T18: 13.6 | U18: 13.5 | V18: 13.8 | W18: 13.2 | X18: 19-23日 | Y18: 超24日 | Z18: 12.3 | AA18: 13.1 | AB18: 12.5 | AC18: 12.4 | AD18: 12.6 | AE18: 12.5 | AF18: 13.2 | AG18: 13.1 | AH18: 13.4 | AI18: 12.9 | AJ18: 29-31日 | AK18: -
A19: 美国东岸 (邮编0.1.2.3开头) | B19: 13.4 | C19: 14.2 | D19: 13.6 | E19: 14 | F19: 13.6 | G19: 13.9 | H19: 14.2 | I19: 14.1 | J19: 14.4 | K19: 14 | L19: 18-20日 | M19: 超21日 | N19: 13.3 | O19: 14.1 | P19: 13.5 | Q19: 13.3 | R19: 13.7 | S19: 13.5 | T19: 14.3 | U19: 14.2 | V19: 14.5 | W19: 13.9 | X19: 19-23日 | Y19: 超24日 | Z19: 13 | AA19: 13.8 | AB19: 13.2 | AC19: 13.1 | AD19: 13.3 | AE19: 13.2 | AF19: 13.9 | AG19: 13.8 | AH19: 14.1 | AI19: 13.6 | AJ19: 29-31日 | AK19: - | BK19: 3.若需拦截改派/操作，拦截费用：900元/票（不含换标和派送等费用），如有其它特殊操作请单询。
A20: 赔偿标准 | B20: 快递服务建议：美中(邮编4.5.6开头)选择芝加哥-快递派服务；美东(邮编0.1.2.3开头)选择纽约-快递派服务； 超时效赔0.5元/kg/工作日（直至运费抵完为止）； | BK20: 4.如若遭遇国外部分仓库删约、推约或预约时间过晚等情况，为了保证货物能尽快交仓，我司可能会采用快递的方式进行递送。
BK21: 5.报关件：同渠道快递派和卡派相互不可合并报关。
A22: 邮编 UPS/联邦混打 12-44KG+3/KG； 45-99KG+1.5元/KG | B22: 纽约海铁24日达-快递派 （华南：ZIM带托-火车线 华东：ZIM带托/EXX-闪电达-火车线） | N22: 纽约MAX海铁22日达-快递派 (MAX-火车线) | Z22: 纽约海铁30日达-快递派 （OA-火车线）
B23: 包税-100kg+ | L23: 提取时效 开船后 | M23: 延时赔付 开船后 | N23: 包税-100kg+ | X23: 提取时效 开船后 | Y23: 延时赔付 开船后 | Z23: 包税-100kg+ | AJ23: 提取时效 开船后 | AK23: 延时赔付 开船后
B24: 华南 | C24: 重庆 | D24: 汕头 | E24: 厦门/泉州/福州 | F24: 华东 | G24: 青岛/郑州/温州/台州/连云港/南京/合肥 | H24: 天津/南昌/石家庄 | I24: 济南/潍坊 | J24: 西安/沧州/保定 | K24: 武汉/长沙/成都 | N24: 华南 | O24: 重庆 | P24: 汕头 | Q24: 厦门/泉州/福州 | R24: 华东 | S24: 青岛/郑州/温州/台州/连云港/南京/合肥 | T24: 天津/南昌/石家庄 | U24: 济南/潍坊 | V24: 西安/沧州/保定 | W24: 武汉/长沙/成都 | Z24: 华南 | AA24: 重庆 | AB24: 汕头 | AC24: 厦门/泉州/福州 | AD24: 华东 | AE24: 青岛/郑州/温州/台州/连云港/南京/合肥 | AF24: 天津/南昌/石家庄 | AG24: 济南/潍坊 | AH24: 西安/沧州/保定 | AI24: 武汉/长沙/成都
A25: 美国东岸 (邮编0.1.2开头) | B25: 15 | C25: 15.8 | D25: 15.2 | E25: 15.2 | F25: 14.8 | G25: 15.1 | H25: 15.4 | I25: 15.3 | J25: 15.6 | K25: 15.6 | L25: 23-30日 | M25: 超31日 | N25: 17.9 | O25: 18.7 | P25: 17.5 | Q25: 17.1 | R25: 16.7 | S25: 17 | T25: 17.3 | U25: 17.2 | V25: 17.5 | W25: 17.9 | X25: 21-28日 | Y25: 超29日 | Z25: 14.2 | AA25: 15 | AB25: 14.4 | AC25: 14.5 | AD25: 14.6 | AE25: 14.9 | AF25: 15.2 | AG25: 15.1 | AH25: 15.4 | AI25: 14.8 | AJ25: 31-38日 | AK25: 超40日
A26: 美国中部 (邮编3.4开头) | B26: 17.5 | C26: 18.3 | D26: 17.7 | E26: 17.7 | F26: 17.3 | G26: 17.6 | H26: 17.9 | I26: 17.8 | J26: 18.1 | K26: 18.1 | L26: 23-30日 | M26: 超31日 | N26: 20.4 | O26: 21.2 | P26: 20 | Q26: 19.6 | R26: 19.2 | S26: 19.5 | T26: 19.8 | U26: 19.7 | V26: 20 | W26: 20.4 | X26: 21-28日 | Y26: 超29日 | Z26: 16.7 | AA26: 17.5 | AB26: 16.9 | AC26: 17 | AD26: 17.1 | AE26: 17.4 | AF26: 17.7 | AG26: 17.6 | AH26: 17.9 | AI26: 17.3 | AJ26: 31-38日 | AK26: 超40日
A27: 美国中北岸 (邮编5.6开头) | B27: 18.3 | C27: 19.1 | D27: 18.5 | E27: 18.5 | F27: 18.1 | G27: 18.4 | H27: 18.7 | I27: 18.6 | J27: 18.9 | K27: 18.9 | L27: 23-30日 | M27: 超31日 | N27: 21.2 | O27: 22 | P27: 20.8 | Q27: 20.4 | R27: 20 | S27: 20.3 | T27: 20.6 | U27: 20.5 | V27: 20.8 | W27: 21.2 | X27: 21-28日 | Y27: 超29日 | Z27: 17.5 | AA27: 18.3 | AB27: 17.7 | AC27: 17.8 | AD27: 17.9 | AE27: 18.2 | AF27: 18.5 | AG27: 18.4 | AH27: 18.7 | AI27: 18.1 | AJ27: 31-38日 | AK27: 超40日
A28: 赔偿标准 | B28: 超时效快递派包税赔0.5元/kg/工作日（直至运费抵完为止）
A30: 邮编 UPS/联邦混打 12-44KG+3/KG； 45-99KG+1.5元/KG | B30: 纽约直航42日达-快递派 （MSC/ZIM/WHL） | N30: 纽约直航38日达-快递派 （OA,直航）
B31: 包税-100kg+ | L31: 提取时效 开船后 | M31: 延时赔付 开船后 | N31: 包税-100kg+ | X31: 提取时效 开船后 | Y31: 延时赔付 开船后
B32: 华南 | C32: 重庆 | D32: 汕头 | E32: 厦门/泉州/福州 | F32: 华东 | G32: 青岛/郑州/温州/台州/连云港/南京/合肥 | H32: 天津/南昌/石家庄 | I32: 济南/潍坊 | J32: 西安/沧州/保定 | K32: 武汉/长沙/成都 | N32: 华南 | O32: 重庆 | P32: 汕头 | Q32: 厦门/泉州/福州 | R32: 华东 | S32: 青岛/郑州/温州/台州/连云港/南京/合肥 | T32: 天津/南昌/石家庄 | U32: 济南/潍坊 | V32: 西安/沧州/保定 | W32: 武汉/长沙/成都
A33: 美国东岸 (邮编0.1.2开头) | B33: 12 | C33: 12.8 | D33: 12.2 | E33: 12.3 | F33: 12.3 | G33: 12.6 | H33: 12.9 | I33: 12.8 | J33: 13.1 | K33: 12.6 | L33: 45-52日 | M33: - | N33: 12.1 | O33: 12.9 | P33: 12.4 | Q33: 12.3 | R33: 12.4 | S33: 12.2 | T33: 13 | U33: 12.9 | V33: 13.2 | W33: 12.7 | X33: 40-47日 | Y33: -
A34: 美国中部 (邮编3.4开头) | B34: 14.5 | C34: 15.3 | D34: 14.7 | E34: 14.8 | F34: 14.8 | G34: 15.1 | H34: 15.4 | I34: 15.3 | J34: 15.6 | K34: 15.1 | L34: 45-52日 | M34: - | N34: 14.6 | O34: 15.4 | P34: 14.9 | Q34: 14.8 | R34: 14.9 | S34: 14.7 | T34: 15.5 | U34: 15.4 | V34: 15.7 | W34: 15.2 | X34: 40-47日 | Y34: -
A35: 美国中北岸 (邮编5.6开头) | B35: 15.3 | C35: 16.1 | D35: 15.5 | E35: 15.6 | F35: 15.6 | G35: 15.9 | H35: 16.2 | I35: 16.1 | J35: 16.4 | K35: 15.9 | L35: 45-52日 | M35: - | N35: 15.4 | O35: 16.2 | P35: 15.7 | Q35: 15.6 | R35: 15.7 | S35: 15.5 | T35: 16.3 | U35: 16.2 | V35: 16.5 | W35: 16 | X35: 40-47日 | Y35: -
A36: 赔偿标准 | B36: 超时效快递派包税赔0.5元/kg/工作日（直至运费抵完为止）
A38: 邮编 UPS/联邦混打 12-44KG+3/KG； 45-99KG+1.5元/KG | B38: 萨凡纳直航36日达-快递派 （OA直航） | N38: 萨凡纳直航48日达-快递派 （MSC/HMM/ZIM直航） | Z38: 萨凡纳海陆24日达-快递派
B39: 包税-100kg+ | L39: 提取时效 开船后 | M39: 延时赔付 开船后 | N39: 包税-100kg+ | X39: 提取时效 开船后 | Y39: 延时赔付 开船后 | Z39: 包税-100kg+ | AJ39: 签收时效 开船后-入仓时效 | AK39: 延时赔付 开船后-不入仓时效
B40: 华南 | C40: 重庆 | D40: 汕头 | E40: 厦门/泉州/福州 | F40: 华东 | G40: 青岛/郑州/温州/台州/连云港/南京/合肥 | H40: 天津/南昌/石家庄 | I40: 济南/潍坊 | J40: 西安/沧州/保定 | K40: 武汉/长沙/成都 | N40: 华南 | O40: 重庆 | P40: 汕头 | Q40: 厦门/泉州/福州 | R40: 华东 | S40: 青岛/郑州/温州/台州/连云港/南京/合肥 | T40: 天津/南昌/石家庄 | U40: 济南/潍坊 | V40: 西安/沧州/保定 | W40: 武汉/长沙/成都 | Z40: 华南 | AA40: 重庆 | AB40: 汕头 | AC40: 厦门/泉州/福州 | AD40: 华东 | AE40: 青岛/郑州/温州/台州/连云港/南京/合肥 | AF40: 天津/南昌/石家庄 | AG40: 济南/潍坊 | AH40: 西安/沧州/保定 | AI40: 武汉/长沙/成都
A41: 美国东岸 (邮编0.1.2开头) | B41: 12.2 | C41: 13 | D41: 12.5 | E41: 12.4 | F41: 13.3 | G41: 11.9 | H41: 13.9 | I41: 13.8 | J41: 14.1 | K41: 12.8 | L41: 40-47日 | M41: - | N41: 12 | O41: 12.8 | P41: 12.2 | Q41: 12.4 | R41: 12.4 | S41: 12.7 | T41: 13 | U41: 12.9 | V41: 13.2 | W41: 12.6 | X41: 55-62日 | Y41: - | Z41: 16.9 | AA41: 17.7 | AB41: 17.1 | AC41: 17.2 | AD41: 17.1 | AE41: 17.4 | AF41: 17.7 | AG41: 17.6 | AH41: 17.9 | AI41: 17.5 | AJ41: 29-33日 | AK41: 超34日
A42: 美国中部 (邮编3.4开头) | B42: 14.7 | C42: 15.5 | D42: 15 | E42: 14.9 | F42: 17.3 | G42: 12.9 | H42: 17.9 | I42: 17.8 | J42: 18.1 | K42: 15.3 | L42: 40-47日 | M42: - | N42: 14.5 | O42: 15.3 | P42: 14.7 | Q42: 14.9 | R42: 14.9 | S42: 15.2 | T42: 15.5 | U42: 15.4 | V42: 15.7 | W42: 15.1 | X42: 55-62日 | Y42: - | Z42: 19.4 | AA42: 20.2 | AB42: 19.6 | AC42: 19.7 | AD42: 19.6 | AE42: 19.9 | AF42: 20.2 | AG42: 20.1 | AH42: 20.4 | AI42: 20 | AJ42: 29-33日 | AK42: 超34日
A43: 美国中北岸 (邮编5.6开头) | B43: 15.5 | C43: 16.3 | D43: 15.8 | E43: 15.7 | F43: 18.4 | G43: 13.4 | H43: 19 | I43: 18.9 | J43: 19.2 | K43: 16.1 | L43: 40-47日 | M43: - | N43: 15.3 | O43: 16.1 | P43: 15.5 | Q43: 15.7 | R43: 15.7 | S43: 16 | T43: 16.3 | U43: 16.2 | V43: 16.5 | W43: 15.9 | X43: 55-62日 | Y43: - | Z43: 20.2 | AA43: 21 | AB43: 20.4 | AC43: 20.5 | AD43: 20.4 | AE43: 20.7 | AF43: 21 | AG43: 20.9 | AH43: 21.2 | AI43: 20.8 | AJ43: 29-33日 | AK43: 超34日
A44: 赔偿标准 | B44: -
A46: 邮编 UPS/联邦混打 12-44KG+3/KG； 45-99KG+1.5元/KG | B46: 休斯顿直航38日达-快递派 （ZIM,OA,MSC统配） | N46: 休斯顿海铁23日达-快递派 （EXX-闪电达）
B47: 包税-100kg+ | L47: 提取时效 开船后 | M47: 延时赔付 开船后 | N47: 包税-100kg+ | X47: 提取时效 开船后 | Y47: 延时赔付 开船后
B48: 华南 | C48: 重庆 | D48: 汕头 | E48: 厦门/泉州/福州 | F48: 华东 | G48: 青岛/郑州/温州/台州/连云港/南京/合肥 | H48: 天津/南昌/石家庄 | I48: 济南/潍坊 | J48: 西安/沧州/保定 | K48: 武汉/长沙/成都 | N48: 华南 | O48: 重庆 | P48: 汕头 | Q48: 厦门/泉州/福州 | R48: 华东 | S48: 青岛/郑州/温州/台州/连云港/南京/合肥 | T48: 天津/南昌/石家庄 | U48: 济南/潍坊 | V48: 西安/沧州/保定 | W48: 武汉/长沙/成都
A49: 美国中部 (邮编4.5.6.7开头) | B49: 10.9 | C49: 11.7 | D49: 11.1 | E49: 11.2 | F49: 11.1 | G49: 11.4 | H49: 11.7 | I49: 11.6 | J49: 11.9 | K49: 11.5 | L49: 34-39日 | M49: - | N49: 11.9 | O49: 12.7 | P49: 11.8 | Q49: 11.9 | R49: 11.8 | S49: 12.1 | T49: 12.4 | U49: 12.3 | V49: 12.6 | W49: 12.2 | X49: 25-30日 | Y49: -
A50: 美国东部 (邮编0.1.2.3开头) | B50: 13.4 | C50: 14.2 | D50: 13.6 | E50: 13.7 | F50: 13.6 | G50: 13.9 | H50: 14.2 | I50: 14.1 | J50: 14.4 | K50: 14 | L50: 34-39日 | M50: - | N50: 14.4 | O50: 15.2 | P50: 14.3 | Q50: 14.4 | R50: 14.3 | S50: 14.6 | T50: 14.9 | U50: 14.8 | V50: 15.1 | W50: 14.7 | X50: 25-30日 | Y50: -
A51: - | B51: - | C51: - | D51: - | E51: - | F51: - | G51: - | H51: - | I51: - | J51: - | K51: - | L51: - | M51: - | N51: - | O51: - | P51: - | Q51: - | R51: - | S51: - | T51: - | U51: - | V51: - | W51: - | X51: - | Y51: -
A52: 赔偿标准 | B52: -
A54: 邮编 UPS/联邦混打 12-44KG+3/KG； 45-99KG+1.5元/KG | B54: 芝加哥海铁28日达-快递派（OA） (华南-OA.ZIM统配 华东-OA.EXX统配) | N54: 芝加哥海铁32日达-快递派 (华南-WHL/MSK统配 华东-MSK) | Z54: 芝加哥海铁22日达-快递派 (以星带托架）
B55: 包税-100kg+ | L55: 提取时效 开船后 | M55: 延时赔付 开船后 | N55: 包税-100kg+ | X55: 提取时效 开船后 | Y55: 延时赔付 开船后 | Z55: 包税-100kg+ | AJ55: 签收时效 开船后-入仓时效 | AK55: 延时赔付 开船后-不入仓时效
B56: 华南 | C56: 重庆 | D56: 汕头 | E56: 厦门/泉州/福州 | F56: 华东 | G56: 青岛/郑州/温州/台州/连云港/南京/合肥 | H56: 天津/南昌/石家庄 | I56: 济南/潍坊 | J56: 西安/沧州/保定 | K56: 武汉/长沙/成都 | N56: 华南 | O56: 重庆 | P56: 汕头 | Q56: 厦门/泉州/福州 | R56: 华东 | S56: 青岛/郑州/温州/台州/连云港/南京/合肥 | T56: 天津/南昌/石家庄 | U56: 济南/潍坊 | V56: 西安/沧州/保定 | W56: 武汉/长沙/成都 | Z56: 华南 | AA56: 重庆 | AB56: 汕头 | AC56: 厦门/泉州/福州 | AD56: 华东 | AE56: 青岛/郑州/温州/台州/连云港/南京/合肥 | AF56: 天津/南昌/石家庄 | AG56: 济南/潍坊 | AH56: 西安/沧州/保定 | AI56: 武汉/长沙/成都
A57: 美国中部 (邮编4.5.6开头) | B57: 11.2 | C57: 12 | D57: 11.4 | E57: 11.8 | F57: 11.4 | G57: 11.7 | H57: 12 | I57: 11.9 | J57: 12.2 | K57: 11.8 | L57: 29-36日 | M57: - | N57: 10.7 | O57: 11.5 | P57: 10.9 | Q57: 11 | R57: 11.1 | S57: 11.4 | T57: 11.7 | U57: 11.6 | V57: 11.9 | W57: 11.3 | X57: 36-43日 | Y57: - | Z57: 13.9 | AA57: 14.7 | AB57: 14.1 | AC57: 14.4 | AD57: 14 | AE57: 14.3 | AF57: 14.6 | AG57: 14.5 | AH57: 14.8 | AI57: 14.5 | AJ57: 24-28日 | AK57: 超29日
A58: 美国东岸 (邮编0.1.2开头) | B58: 13.7 | C58: 14.5 | D58: 13.9 | E58: 14.3 | F58: 13.9 | G58: 14.2 | H58: 14.5 | I58: 14.4 | J58: 14.7 | K58: 14.3 | L58: 29-36日 | M58: - | N58: 13.2 | O58: 14 | P58: 13.4 | Q58: 13.5 | R58: 13.6 | S58: 13.9 | T58: 14.2 | U58: 14.1 | V58: 14.4 | W58: 13.8 | X58: 36-43日 | Y58: - | Z58: 16.4 | AA58: 17.2 | AB58: 16.6 | AC58: 16.9 | AD58: 16.5 | AE58: 16.8 | AF58: 17.1 | AG58: 17 | AH58: 17.3 | AI58: 17 | AJ58: 24-28日 | AK58: 超29日
A59: 美国东南岸 (邮编3开头) | B59: 13.7 | C59: 14.5 | D59: 13.9 | E59: 14.3 | F59: 13.9 | G59: 14.2 | H59: 14.5 | I59: 14.4 | J59: 14.7 | K59: 14.3 | L59: 29-36日 | M59: - | N59: 13.2 | O59: 14 | P59: 13.4 | Q59: 13.5 | R59: 13.6 | S59: 13.9 | T59: 14.2 | U59: 14.1 | V59: 14.4 | W59: 13.8 | X59: 36-43日 | Y59: - | Z59: 16.4 | AA59: 17.2 | AB59: 16.6 | AC59: 16.9 | AD59: 16.5 | AE59: 16.8 | AF59: 17.1 | AG59: 17 | AH59: 17.3 | AI59: 17 | AJ59: 24-28日 | AK59: 超29日
A60: 赔偿标准 | B60: -

Sheet 美西直送系列
F1: 整柜直送系列
F2: Direct container sevice
A4: 仓库代码 | B4: 洛杉矶普船28日达直送-卡派（ 开船可能有1-7天延时） （MSC/HMM/ONE/合德/海领（义乌）/TSL统配/HPL/CUL/KMCT等所有普船统配） | X4: 洛杉矶OA26日达直送-卡派 | AT4: 奥克兰OA29日达直送-卡派 （ 开船可能有1-5天延时）（华南/华东：OA） | BP4: 奥克兰普船36日达直送-卡派 （ 开船可能有1-5天延时）（普船统配）
B5: 包税-50kg+ | L5: 不包税-0.5CBM+ | V5: 签收时效 开船后-入仓时效 | W5: 延时赔付 开船后-不入仓时效 | X5: 包税-50kg+ | AH5: 不包税-0.5CBM+ | AR5: 签收时效 开船后-入仓时效 | AS5: 延时赔付 开船后-不入仓时效 | AT5: 包税-50kg+ | BD5: 不包税-0.5CBM+ | BN5: 签收时效 开船后-入仓时效 | BO5: 延时赔付 开船后-不入仓时效 | BP5: 包税-50kg+ | BZ5: 不包税-0.5CBM+ | CJ5: 签收时效 开船后-入仓时效 | CK5: 延时赔付 开船后-不入仓时效
B6: 华南 | C6: 重庆 | D6: 汕头 | E6: 厦门/泉州/福州 | F6: 华东 | G6: 青岛/郑州/温州/台州/连云港/南京/合肥 | H6: 天津/南昌/石家庄 | I6: 济南/潍坊 | J6: 西安/沧州/保定 | K6: 武汉/长沙/成都 | L6: 华南 | M6: 重庆 | N6: 汕头 | O6: 厦门/泉州/福州 | P6: 华东 | Q6: 青岛/郑州/温州/台州/连云港/南京/合肥 | R6: 天津/南昌/石家庄 | S6: 济南/潍坊 | T6: 西安/沧州/保定 | U6: 武汉/长沙/成都 | X6: 华南 | Y6: 重庆 | Z6: 汕头 | AA6: 厦门/泉州/福州 | AB6: 华东 | AC6: 青岛/郑州/温州/台州/连云港/南京/合肥 | AD6: 天津/南昌/石家庄 | AE6: 济南/潍坊 | AF6: 西安/沧州/保定 | AG6: 武汉/长沙/成都 | AH6: 华南 | AI6: 重庆 | AJ6: 汕头 | AK6: 厦门/泉州/福州 | AL6: 华东 | AM6: 青岛/郑州/温州/台州/连云港/南京/合肥 | AN6: 天津/南昌/石家庄 | AO6: 济南/潍坊 | AP6: 西安/沧州/保定 | AQ6: 武汉/长沙/成都 | AT6: 华南 | AU6: 重庆 | AV6: 汕头 | AW6: 厦门/泉州/福州 | AX6: 华东 | AY6: 青岛/郑州/温州/台州/连云港/南京/合肥 | AZ6: 天津/南昌/石家庄 | BA6: 济南/潍坊 | BB6: 西安/沧州/保定 | BC6: 武汉/长沙/成都 | BD6: 华南 | BE6: 重庆 | BF6: 汕头 | BG6: 厦门/泉州/福州 | BH6: 华东 | BI6: 青岛/郑州/温州/台州/连云港/南京/合肥 | BJ6: 天津/南昌/石家庄 | BK6: 济南/潍坊 | BL6: 西安/沧州/保定 | BM6: 武汉/长沙/成都 | BP6: 华南 | BQ6: 重庆 | BR6: 汕头 | BS6: 厦门/泉州/福州 | BT6: 华东 | BU6: 青岛/郑州/温州/台州/连云港/南京/合肥 | BV6: 天津/南昌/石家庄 | BW6: 济南/潍坊 | BX6: 西安/沧州/保定 | BY6: 武汉/长沙/成都 | BZ6: 华南 | CA6: 重庆 | CB6: 汕头 | CC6: 厦门/泉州/福州 | CD6: 华东 | CE6: 青岛/郑州/温州/台州/连云港/南京/合肥 | CF6: 天津/南昌/石家庄 | CG6: 济南/潍坊 | CH6: 西安/沧州/保定 | CI6: 武汉/长沙/成都
A7: ONT8 | B7: 5.4 | C7: 6.2 | D7: 6 | E7: 5.6 | F7: 5.8 | G7: 5.6 | H7: 6.4 | I7: 6.3 | J7: 6.6 | K7: 6 | L7: 825 | M7: 967 | N7: 923 | O7: 927 | P7: 844 | Q7: 875 | R7: 950 | S7: 933 | T7: 986 | U7: 931 | V7: 27-33天 | W7: - | X7: 5.7 | Y7: 6.5 | Z7: 5.9 | AA7: 5.6 | AB7: 5.8 | AC7: 6 | AD7: 6.4 | AE7: 6.3 | AF7: 6.6 | AG7: 6.3 | AH7: 875 | AI7: 1017 | AJ7: 910 | AK7: 927 | AL7: 891 | AM7: 931 | AN7: 997 | AO7: 980 | AP7: 1033 | AQ7: 981 | AR7: 25-31天 | AS7: - | AT7: - | AU7: - | AV7: - | AW7: - | AX7: - | AY7: - | AZ7: - | BA7: - | BB7: - | BC7: - | BD7: - | BE7: - | BF7: - | BG7: - | BH7: - | BI7: - | BJ7: - | BK7: - | BL7: - | BM7: - | BN7: - | BO7: - | BP7: - | BQ7: - | BR7: - | BS7: - | BT7: - | BU7: - | BV7: - | BW7: - | BX7: - | BY7: - | BZ7: - | CA7: - | CB7: - | CC7: - | CD7: - | CE7: - | CF7: - | CG7: - | CH7: - | CI7: - | CJ7: - | CK7: -
A8: LGB8 | B8: 5.4 | C8: 6.2 | D8: 6 | E8: 5.6 | F8: 5.8 | G8: 5.6 | H8: 6.4 | I8: 6.3 | J8: 6.6 | K8: 6 | L8: 825 | M8: 967 | N8: 923 | O8: 927 | P8: 844 | Q8: 875 | R8: 950 | S8: 933 | T8: 986 | U8: 931 | V8: 27-33天 | W8: - | X8: 5.7 | Y8: 6.5 | Z8: 5.9 | AA8: 5.6 | AB8: 5.8 | AC8: 6 | AD8: 6.4 | AE8: 6.3 | AF8: 6.6 | AG8: 6.3 | AH8: 875 | AI8: 1017 | AJ8: 910 | AK8: 927 | AL8: 891 | AM8: 931 | AN8: 997 | AO8: 980 | AP8: 1033 | AQ8: 981 | AR8: 25-31天 | AS8: - | AT8: - | AU8: - | AV8: - | AW8: - | AX8: - | AY8: - | AZ8: - | BA8: - | BB8: - | BC8: - | BD8: - | BE8: - | BF8: - | BG8: - | BH8: - | BI8: - | BJ8: - | BK8: - | BL8: - | BM8: - | BN8: - | BO8: - | BP8: - | BQ8: - | BR8: - | BS8: - | BT8: - | BU8: - | BV8: - | BW8: - | BX8: - | BY8: - | BZ8: - | CA8: - | CB8: - | CC8: - | CD8: - | CE8: - | CF8: - | CG8: - | CH8: - | CI8: - | CJ8: - | CK8: -
A9: LAX9 | B9: 5.4 | C9: 6.2 | D9: 6 | E9: 5.6 | F9: 5.8 | G9: 5.6 | H9: 6.4 | I9: 6.3 | J9: 6.6 | K9: 6 | L9: 825 | M9: 967 | N9: 923 | O9: 927 | P9: 844 | Q9: 875 | R9: 950 | S9: 933 | T9: 986 | U9: 931 | V9: 24-29天 | W9: - | X9: 5.7 | Y9: 6.5 | Z9: 5.9 | AA9: 5.6 | AB9: 5.8 | AC9: 6 | AD9: 6.4 | AE9: 6.3 | AF9: 6.6 | AG9: 6.3 | AH9: 875 | AI9: 1017 | AJ9: 910 | AK9: 927 | AL9: 891 | AM9: 931 | AN9: 997 | AO9: 980 | AP9: 1033 | AQ9: 981 | AR9: 22-27天 | AS9: - | AT9: - | AU9: - | AV9: - | AW9: - | AX9: - | AY9: - | AZ9: - | BA9: - | BB9: - | BC9: - | BD9: - | BE9: - | BF9: - | BG9: - | BH9: - | BI9: - | BJ9: - | BK9: - | BL9: - | BM9: - | BN9: - | BO9: - | BP9: - | BQ9: - | BR9: - | BS9: - | BT9: - | BU9: - | BV9: - | BW9: - | BX9: - | BY9: - | BZ9: - | CA9: - | CB9: - | CC9: - | CD9: - | CE9: - | CF9: - | CG9: - | CH9: - | CI9: - | CJ9: - | CK9: -
A10: SBD1 | B10: 5.4 | C10: 6.2 | D10: 6 | E10: 5.6 | F10: 5.8 | G10: 5.6 | H10: 6.4 | I10: 6.3 | J10: 6.6 | K10: 6 | L10: 825 | M10: 967 | N10: 923 | O10: 927 | P10: 844 | Q10: 875 | R10: 950 | S10: 933 | T10: 986 | U10: 931 | V10: 24-29天 | W10: - | X10: 5.7 | Y10: 6.5 | Z10: 5.9 | AA10: 5.6 | AB10: 5.8 | AC10: 6 | AD10: 6.4 | AE10: 6.3 | AF10: 6.6 | AG10: 6.3 | AH10: 875 | AI10: 1017 | AJ10: 910 | AK10: 927 | AL10: 891 | AM10: 931 | AN10: 997 | AO10: 980 | AP10: 1033 | AQ10: 981 | AR10: 22-27天 | AS10: - | AT10: - | AU10: - | AV10: - | AW10: - | AX10: - | AY10: - | AZ10: - | BA10: - | BB10: - | BC10: - | BD10: - | BE10: - | BF10: - | BG10: - | BH10: - | BI10: - | BJ10: - | BK10: - | BL10: - | BM10: - | BN10: - | BO10: - | BP10: - | BQ10: - | BR10: - | BS10: - | BT10: - | BU10: - | BV10: - | BW10: - | BX10: - | BY10: - | BZ10: - | CA10: - | CB10: - | CC10: - | CD10: - | CE10: - | CF10: - | CG10: - | CH10: - | CI10: - | CJ10: - | CK10: -
A11: POC1 | B11: 5.5 | C11: 6.3 | D11: 6.1 | E11: 5.6 | F11: 5.8 | G11: 5.7 | H11: 6.4 | I11: 6.3 | J11: 6.6 | K11: 6.1 | L11: 853 | M11: 995 | N11: 933 | O11: 937 | P11: 853 | Q11: 884 | R11: 959 | S11: 942 | T11: 995 | U11: 959 | V11: 24-29天 | W11: - | X11: 5.7 | Y11: 6.5 | Z11: 5.9 | AA11: 5.6 | AB11: 5.8 | AC11: 6 | AD11: 6.4 | AE11: 6.3 | AF11: 6.6 | AG11: 6.3 | AH11: 885 | AI11: 1027 | AJ11: 920 | AK11: 937 | AL11: 901 | AM11: 941 | AN11: 1007 | AO11: 990 | AP11: 1043 | AQ11: 991 | AR11: 22-27天 | AS11: - | AT11: - | AU11: - | AV11: - | AW11: - | AX11: - | AY11: - | AZ11: - | BA11: - | BB11: - | BC11: - | BD11: - | BE11: - | BF11: - | BG11: - | BH11: - | BI11: - | BJ11: - | BK11: - | BL11: - | BM11: - | BN11: - | BO11: - | BP11: - | BQ11: - | BR11: - | BS11: - | BT11: - | BU11: - | BV11: - | BW11: - | BX11: - | BY11: - | BZ11: - | CA11: - | CB11: - | CC11: - | CD11: - | CE11: - | CF11: - | CG11: - | CH11: - | CI11: - | CJ11: - | CK11: -
A12: POC2 | B12: 5.5 | C12: 6.3 | D12: 6.1 | E12: 5.6 | F12: 5.8 | G12: 5.7 | H12: 6.4 | I12: 6.3 | J12: 6.6 | K12: 6.1 | L12: 853 | M12: 995 | N12: 933 | O12: 937 | P12: 853 | Q12: 884 | R12: 959 | S12: 942 | T12: 995 | U12: 959 | V12: 24-29天 | W12: - | X12: 5.7 | Y12: 6.5 | Z12: 5.9 | AA12: 5.6 | AB12: 5.8 | AC12: 6 | AD12: 6.4 | AE12: 6.3 | AF12: 6.6 | AG12: 6.3 | AH12: 885 | AI12: 1027 | AJ12: 920 | AK12: 937 | AL12: 901 | AM12: 941 | AN12: 1007 | AO12: 990 | AP12: 1043 | AQ12: 991 | AR12: 22-27天 | AS12: - | AT12: - | AU12: - | AV12: - | AW12: - | AX12: - | AY12: - | AZ12: - | BA12: - | BB12: - | BC12: - | BD12: - | BE12: - | BF12: - | BG12: - | BH12: - | BI12: - | BJ12: - | BK12: - | BL12: - | BM12: - | BN12: - | BO12: - | BP12: - | BQ12: - | BR12: - | BS12: - | BT12: - | BU12: - | BV12: - | BW12: - | BX12: - | BY12: - | BZ12: - | CA12: - | CB12: - | CC12: - | CD12: - | CE12: - | CF12: - | CG12: - | CH12: - | CI12: - | CJ12: - | CK12: -
A13: POC3 | B13: 5.5 | C13: 6.3 | D13: 6.1 | E13: 5.6 | F13: 5.8 | G13: 5.7 | H13: 6.4 | I13: 6.3 | J13: 6.6 | K13: 6.1 | L13: 853 | M13: 995 | N13: 933 | O13: 937 | P13: 853 | Q13: 884 | R13: 959 | S13: 942 | T13: 995 | U13: 959 | V13: 24-29天 | W13: - | X13: 5.7 | Y13: 6.5 | Z13: 5.9 | AA13: 5.6 | AB13: 5.8 | AC13: 6 | AD13: 6.4 | AE13: 6.3 | AF13: 6.6 | AG13: 6.3 | AH13: 885 | AI13: 1027 | AJ13: 920 | AK13: 937 | AL13: 901 | AM13: 941 | AN13: 1007 | AO13: 990 | AP13: 1043 | AQ13: 991 | AR13: 22-27天 | AS13: - | AT13: - | AU13: - | AV13: - | AW13: - | AX13: - | AY13: - | AZ13: - | BA13: - | BB13: - | BC13: - | BD13: - | BE13: - | BF13: - | BG13: - | BH13: - | BI13: - | BJ13: - | BK13: - | BL13: - | BM13: - | BN13: - | BO13: - | BP13: - | BQ13: - | BR13: - | BS13: - | BT13: - | BU13: - | BV13: - | BW13: - | BX13: - | BY13: - | BZ13: - | CA13: - | CB13: - | CC13: - | CD13: - | CE13: - | CF13: - | CG13: - | CH13: - | CI13: - | CJ13: - | CK13: -
A14: IUSP | B14: 5.6 | C14: 6.4 | D14: 6.1 | E14: 5.7 | F14: 5.9 | G14: 5.8 | H14: 6.5 | I14: 6.4 | J14: 6.7 | K14: 6.2 | L14: 867 | M14: 1009 | N14: 948 | O14: 952 | P14: 866 | Q14: 899 | R14: 972 | S14: 955 | T14: 1008 | U14: 973 | V14: 24-29天 | W14: - | X14: 5.9 | Y14: 6.7 | Z14: 6.1 | AA14: 5.7 | AB14: 6 | AC14: 6.1 | AD14: 6.6 | AE14: 6.5 | AF14: 6.8 | AG14: 6.5 | AH14: 917 | AI14: 1059 | AJ14: 952 | AK14: 952 | AL14: 933 | AM14: 955 | AN14: 1039 | AO14: 1022 | AP14: 1075 | AQ14: 1023 | AR14: 22-27天 | AS14: - | AT14: - | AU14: - | AV14: - | AW14: - | AX14: - | AY14: - | AZ14: - | BA14: - | BB14: - | BC14: - | BD14: - | BE14: - | BF14: - | BG14: - | BH14: - | BI14: - | BJ14: - | BK14: - | BL14: - | BM14: - | BN14: - | BO14: - | BP14: - | BQ14: - | BR14: - | BS14: - | BT14: - | BU14: - | BV14: - | BW14: - | BX14: - | BY14: - | BZ14: - | CA14: - | CB14: - | CC14: - | CD14: - | CE14: - | CF14: - | CG14: - | CH14: - | CI14: - | CJ14: - | CK14: -
A15: IUSJ | B15: 5.6 | C15: 6.4 | D15: 6.1 | E15: 5.7 | F15: 5.9 | G15: 5.8 | H15: 6.5 | I15: 6.4 | J15: 6.7 | K15: 6.2 | L15: 867 | M15: 1009 | N15: 948 | O15: 952 | P15: 866 | Q15: 899 | R15: 972 | S15: 955 | T15: 1008 | U15: 973 | V15: 24-29天 | W15: - | X15: 5.9 | Y15: 6.7 | Z15: 6.1 | AA15: 5.7 | AB15: 6 | AC15: 6.1 | AD15: 6.6 | AE15: 6.5 | AF15: 6.8 | AG15: 6.5 | AH15: 917 | AI15: 1059 | AJ15: 952 | AK15: 952 | AL15: 933 | AM15: 955 | AN15: 1039 | AO15: 1022 | AP15: 1075 | AQ15: 1023 | AR15: 22-27天 | AS15: - | AT15: - | AU15: - | AV15: - | AW15: - | AX15: - | AY15: - | AZ15: - | BA15: - | BB15: - | BC15: - | BD15: - | BE15: - | BF15: - | BG15: - | BH15: - | BI15: - | BJ15: - | BK15: - | BL15: - | BM15: - | BN15: - | BO15: - | BP15: - | BQ15: - | BR15: - | BS15: - | BT15: - | BU15: - | BV15: - | BW15: - | BX15: - | BY15: - | BZ15: - | CA15: - | CB15: - | CC15: - | CD15: - | CE15: - | CF15: - | CG15: - | CH15: - | CI15: - | CJ15: - | CK15: -
A16: IUSQ | B16: 5.6 | C16: 6.4 | D16: 6.1 | E16: 5.7 | F16: 5.9 | G16: 5.8 | H16: 6.5 | I16: 6.4 | J16: 6.7 | K16: 6.2 | L16: 867 | M16: 1009 | N16: 948 | O16: 952 | P16: 866 | Q16: 899 | R16: 972 | S16: 955 | T16: 1008 | U16: 973 | V16: 24-29天 | W16: - | X16: 5.9 | Y16: 6.7 | Z16: 6.1 | AA16: 5.7 | AB16: 6 | AC16: 6.1 | AD16: 6.6 | AE16: 6.5 | AF16: 6.8 | AG16: 6.5 | AH16: 917 | AI16: 1059 | AJ16: 952 | AK16: 952 | AL16: 933 | AM16: 955 | AN16: 1039 | AO16: 1022 | AP16: 1075 | AQ16: 1023 | AR16: 22-27天 | AS16: - | AT16: - | AU16: - | AV16: - | AW16: - | AX16: - | AY16: - | AZ16: - | BA16: - | BB16: - | BC16: - | BD16: - | BE16: - | BF16: - | BG16: - | BH16: - | BI16: - | BJ16: - | BK16: - | BL16: - | BM16: - | BN16: - | BO16: - | BP16: - | BQ16: - | BR16: - | BS16: - | BT16: - | BU16: - | BV16: - | BW16: - | BX16: - | BY16: - | BZ16: - | CA16: - | CB16: - | CC16: - | CD16: - | CE16: - | CF16: - | CG16: - | CH16: - | CI16: - | CJ16: - | CK16: -
A17: WM-LAX1 | B17: 5.6 | C17: 6.4 | D17: 6.1 | E17: 5.6 | F17: 5.9 | G17: 5.7 | H17: 6.5 | I17: 6.4 | J17: 6.7 | K17: 6.2 | L17: 871 | M17: 1013 | N17: 933 | O17: 937 | P17: 870 | Q17: 884 | R17: 976 | S17: 959 | T17: 1012 | U17: 977 | V17: 24-29天 | W17: - | X17: 5.8 | Y17: 6.6 | Z17: 6 | AA17: 5.6 | AB17: 5.9 | AC17: 6 | AD17: 6.5 | AE17: 6.4 | AF17: 6.7 | AG17: 6.4 | AH17: 903 | AI17: 1045 | AJ17: 938 | AK17: 937 | AL17: 919 | AM17: 941 | AN17: 1025 | AO17: 1008 | AP17: 1061 | AQ17: 1009 | AR17: 22-27天 | AS17: - | AT17: - | AU17: - | AV17: - | AW17: - | AX17: - | AY17: - | AZ17: - | BA17: - | BB17: - | BC17: - | BD17: - | BE17: - | BF17: - | BG17: - | BH17: - | BI17: - | BJ17: - | BK17: - | BL17: - | BM17: - | BN17: - | BO17: - | BP17: - | BQ17: - | BR17: - | BS17: - | BT17: - | BU17: - | BV17: - | BW17: - | BX17: - | BY17: - | BZ17: - | CA17: - | CB17: - | CC17: - | CD17: - | CE17: - | CF17: - | CG17: - | CH17: - | CI17: - | CJ17: - | CK17: -
A18: WM-LAX2 | B18: 5.6 | C18: 6.4 | D18: 6.1 | E18: 5.6 | F18: 5.9 | G18: 5.7 | H18: 6.5 | I18: 6.4 | J18: 6.7 | K18: 6.2 | L18: 871 | M18: 1013 | N18: 933 | O18: 937 | P18: 870 | Q18: 884 | R18: 976 | S18: 959 | T18: 1012 | U18: 977 | V18: 24-29天 | W18: - | X18: 5.8 | Y18: 6.6 | Z18: 6 | AA18: 5.6 | AB18: 6 | AC18: 6 | AD18: 6.6 | AE18: 6.5 | AF18: 6.8 | AG18: 6.4 | AH18: 903 | AI18: 1045 | AJ18: 938 | AK18: 937 | AL18: 933 | AM18: 941 | AN18: 1039 | AO18: 1022 | AP18: 1075 | AQ18: 1009 | AR18: 22-27天 | AS18: - | AT18: - | AU18: - | AV18: - | AW18: - | AX18: - | AY18: - | AZ18: - | BA18: - | BB18: - | BC18: - | BD18: - | BE18: - | BF18: - | BG18: - | BH18: - | BI18: - | BJ18: - | BK18: - | BL18: - | BM18: - | BN18: - | BO18: - | BP18: - | BQ18: - | BR18: - | BS18: - | BT18: - | BU18: - | BV18: - | BW18: - | BX18: - | BY18: - | BZ18: - | CA18: - | CB18: - | CC18: - | CD18: - | CE18: - | CF18: - | CG18: - | CH18: - | CI18: - | CJ18: - | CK18: -
